Workbook

Sheet サマリー
B1: 充填機導入 投資回収計画（白鳥惣菜）
B2: 48期（製造PL 17期）下期・2027年2月1日導入 ／ 減価償却10年・投資回収5年以内の基準で試算
B4: ■ 投資概要
B5: 導入機械 | C5: 充填機（AC200V 0.4kW サーボ／ホッパー15ℓ）
B6: 台数 | C6: =前提条件!C6 -> 2
B7: 充填機本体（取得価額） | C7: =前提条件!C8 -> 4500000
B8: 対象商品 | C8: カスタード＆ホイップシュー／ふんわりバナナロール
B9: 導入日 | C9: =前提条件!C11 -> 46419
B10: 減価償却（機械） | C10: =前提条件!C10 -> 37500
B11: 電気・付帯工事費 | C11: =前提条件!C85 -> 500000
B12: 電気・付帯工事の会計処理 | C12: =前提条件!C87 -> 機械の付随費用として資産計上（機械と同じ10年償却）
B13: 総投資額（機械＋電気・付帯工事） | C13: =前提条件!C94 -> 5000000
B15: ■ 結論（月平均）
B16: 月平均 投資効果（償却前） | C16: =前提条件!C76 -> 163928.33 | D16: 人件費・絞り袋の削減 − 電気・洗浄・保守
B17: 月額 減価償却費 | C17: =前提条件!C10+前提条件!C90 -> 41666.667 | D17: 機械（取得価額÷120か月）＋電気・付帯工事（資産計上時）
B18: 月平均 利益改善額（償却後） | C18: =前提条件!C79 -> 122261.67 | D18: 償却費を差し引いても毎月プラス
B19: 投資回収期間 | C19: =投資回収_月次!D4 -> 31
B20: 回収年月 | C20: =投資回収_月次!G4 -> 47331
B21: 回収基準（5年以内） | C21: =投資回収_月次!K4 -> ◎ 5年以内に回収
B22: 48期（2〜6月）経常利益の予算比 | C22: =白鳥惣菜PL_導入効果!P154*1000 -> 599566.67 | D22: 導入後PLの下期計 − 予算下期計
B23: 10年累計 利益改善額（償却後） | C23: =年度別_償却!I16 -> 14688308
B24: 損益分岐の効果発現率 | C24: =前提条件!C82 -> 0.31242531 | D24: 効果がこの割合まで落ちても赤字にならない
B26: ■ 1日当たりの効果
B27: 削減人時 | C27: =前提条件!C63 -> 3.8333333 | D27: ="現行 "&TEXT(前提条件!G46/60,"0.0")&"h → 導入後 "&TEXT(前提条件!G59/60,"0.0")&"h（壁崩し工程が不要に）" -> 現行 9.6h → 導入後 5.8h（壁崩し工程が不要に）
B28: 人件費削減 | C28: =前提条件!C64 -> 5750 | D28: 時給1,500円
B29: 絞り袋削減 | C29: =前提条件!C65 -> 96 | D29: 16円×6枚
B30: 電気代・洗浄費（増） | C30: =-(前提条件!C66+前提条件!C67) -> -210 | D30: 0.4kW×2台×2.5h＋洗浄
B31: 純効果 | C31: =前提条件!C68 -> 5636
B33: ■ 48期 下期の経常利益（千円） 予算 vs 導入後
C34: 1月 | D34: 2月 | E34: 3月 | F34: 4月 | G34: 5月 | H34: 6月 | I34: 下期計
B35: 予算 | C35: =白鳥惣菜PL_導入効果!I152 -> -2319.8961 | D35: =白鳥惣菜PL_導入効果!J152 -> -2565.4817 | E35: =白鳥惣菜PL_導入効果!K152 -> 3454.5383 | F35: =白鳥惣菜PL_導入効果!L152 -> 3740.4383 | G35: =白鳥惣菜PL_導入効果!M152 -> 2410.4383 | H35: =白鳥惣菜PL_導入効果!N152 -> -3722.2931 | I35: =白鳥惣菜PL_導入効果!P152 -> 997.744
B36: 導入後 | C36: =白鳥惣菜PL_導入効果!I153 -> -2319.8961 | D36: =白鳥惣菜PL_導入効果!J153 -> -2456.8404 | E36: =白鳥惣菜PL_導入効果!K153 -> 3580.0876 | F36: =白鳥惣菜PL_導入効果!L153 -> 3860.3516 | G36: =白鳥惣菜PL_導入効果!M153 -> 2535.9876 | H36: =白鳥惣菜PL_導入効果!N153 -> -3602.3798 | I36: =白鳥惣菜PL_導入効果!P153 -> 1597.3107
B37: 差額 | C37: =白鳥惣菜PL_導入効果!I154 -> 0 | D37: =白鳥惣菜PL_導入効果!J154 -> 108.64133 | E37: =白鳥惣菜PL_導入効果!K154 -> 125.54933 | F37: =白鳥惣菜PL_導入効果!L154 -> 119.91333 | G37: =白鳥惣菜PL_導入効果!M154 -> 125.54933 | H37: =白鳥惣菜PL_導入効果!N154 -> 119.91333 | I37: =白鳥惣菜PL_導入効果!P154 -> 599.56667
B38: 判定 | C38: =白鳥惣菜PL_導入効果!I155 -> 予算通り | D38: =白鳥惣菜PL_導入効果!J155 -> 予算超 | E38: =白鳥惣菜PL_導入効果!K155 -> 予算超 | F38: =白鳥惣菜PL_導入効果!L155 -> 予算超 | G38: =白鳥惣菜PL_導入効果!M155 -> 予算超 | H38: =白鳥惣菜PL_導入効果!N155 -> 予算超 | I38: =白鳥惣菜PL_導入効果!P155 -> 予算超
B40: ■ 定性効果（金額には未算入＝上振れ要因）
B41: ・充填重量の精度向上 → 充填後の計量を「全量計量」から「抜き打ち計量」へ（計量工数の削減）
B42: ・クリームの充填量ばらつき・絞り残しの減少 → 原材料ロスの削減
B43: ・絞り袋への手詰め（1kgずつ）がホッパー10ℓ一括投入に → 充填回数・手作業の削減、衛生面の向上
B44: ・生産能力 約3,000個/時（2口）→ 増産・新商品への対応余力
B46: ■ 前提・留意点
B47: ・投資額450万円は暫定値。見積確定後に「前提条件」シートを更新すれば全シートが連動します。
B48: ・人件費削減は、削減人時分のパートシフトを実際に減らす（または他工程へ再配置し残業・派遣を減らす）ことが前提です。
B49: ・稼働日数は年365日（暦日）、電力単価30円/kWh、洗浄費150円/日、保守部品費は取得価額の2%/年を想定しています。
B50: ・法定福利費の削減は含めず、電気代は定格出力×通電時間で計上し、保守的に試算しています。
B51: ・予算額は「経広_製造PL_17通期予算_2026.0618up エリア人件費修正.xls」のライン月別PL（白鳥惣菜）から転記しています。
B52: ・電気・付帯工事費50万円は機械の付随費用として取得価額に含め、機械と同じ10年で償却（区分1）。変更は「前提条件」下部で入力すると全シートに反映されます。
B54: ■ 電気・付帯工事費が発生した場合のPL影響（試算）
B55: 電気・付帯工事なしの場合の予算差（円） 2月： | C55: =投資回収_月次!J8-投資回収_月次!M8 -> 112808 | D55: 下期計： | E55: =SUMIFS(投資回収_月次!$J$8:$J$127,投資回収_月次!$C$8:$C$127,48)-SUMIFS(投資回収_月次!$M$8:$M$127,投資回収_月次!$C$8:$C$127,48) -> 620400 | F55: 48期の月数： | G55: =COUNTIF(投資回収_月次!$C$8:$C$127,48) -> 5
B56: 電気・付帯工事費（円） ※青字は変更可 | C56: 区分1 機械に含める 月額償却増 | D56: 区分1 2月 予算差 | E56: 区分1 下期計 予算差 | F56: 区分2 建物附属設備 月額償却増 | G56: 区分2 下期計 予算差 | H56: 区分3 一括費用 2月 予算差 | I56: 区分3 下期計 予算差 | J56: 回収月数 （目安）
B57: 100000 | C57: =B57/(前提条件!$C$9*12) -> 833.33333 | D57: =$C$55-C57 -> 111974.67 | E57: =$E$55-C57*$G$55 -> 616233.33 | F57: =B57/(前提条件!$C$88*12) -> 555.55556 | G57: =$E$55-F57*$G$55 -> 617622.22 | H57: =$C$55-B57 -> 12808 | I57: =$E$55-B57 -> 520400 | J57: =ROUNDUP((前提条件!$C$8+B57)/前提条件!$C$76,0) -> 29
B58: 300000 | C58: =B58/(前提条件!$C$9*12) -> 2500 | D58: =$C$55-C58 -> 110308 | E58: =$E$55-C58*$G$55 -> 607900 | F58: =B58/(前提条件!$C$88*12) -> 1666.6667 | G58: =$E$55-F58*$G$55 -> 612066.67 | H58: =$C$55-B58 -> -187192 | I58: =$E$55-B58 -> 320400 | J58: =ROUNDUP((前提条件!$C$8+B58)/前提条件!$C$76,0) -> 30
B59: 500000 | C59: =B59/(前提条件!$C$9*12) -> 4166.6667 | D59: =$C$55-C59 -> 108641.33 | E59: =$E$55-C59*$G$55 -> 599566.67 | F59: =B59/(前提条件!$C$88*12) -> 2777.7778 | G59: =$E$55-F59*$G$55 -> 606511.11 | H59: =$C$55-B59 -> -387192 | I59: =$E$55-B59 -> 120400 | J59: =ROUNDUP((前提条件!$C$8+B59)/前提条件!$C$76,0) -> 31
B60: 1000000 | C60: =B60/(前提条件!$C$9*12) -> 8333.3333 | D60: =$C$55-C60 -> 104474.67 | E60: =$E$55-C60*$G$55 -> 578733.33 | F60: =B60/(前提条件!$C$88*12) -> 5555.5556 | G60: =$E$55-F60*$G$55 -> 592622.22 | H60: =$C$55-B60 -> -887192 | I60: =$E$55-B60 -> -379600 | J60: =ROUNDUP((前提条件!$C$8+B60)/前提条件!$C$76,0) -> 34
B61: ・予算差＝導入後の経常利益 − 予算（プラスなら予算超）。赤色＝その月（期間）は予算を下回る。
B62: ・区分1・2は支払いが一括でもPLは月割りの減価償却。区分3は導入月（2月）に全額を修繕費で計上するため、2月単月が予算を下回りやすい。
B63: ・実際の工事費は「前提条件」の電気・付帯工事費・処理区分に入力すると、PL・投資回収の各シートに反映されます。

Sheet 説明用要約
B1: 説明用要約（製造部長向け・社長向け）
B2: 数値は各計算シートと連動しています。印刷する場合は「印刷用_製造部長」「印刷用_社長」シート（A4・1枚）を使用してください。
B4: ■ 製造部長向け（予算修正が不要であることの説明）
B5: ="【一言で】下期予算の修正は不要です。2月に導入しても、2〜6月の全月で白鳥惣菜の経常利益は予算を上回ります（下期計 +"&TEXT(白鳥惣菜PL_導入効果!$P$154*1000/10000,"0")&"万円）。" -> 【一言で】下期予算の修正は不要です。2月に導入しても、2〜6月の全月で白鳥惣菜の経常利益は予算を上回ります（下期計 +60万円）。
B6: ="・お願い：充填機2台（総投資"&TEXT(前提条件!$C$94/10000,"#,##0")&"万円）を2027年2月1日に導入したい。予算額はそのままで構いません。" -> ・お願い：充填機2台（総投資500万円）を2027年2月1日に導入したい。予算額はそのままで構いません。
B7: ="・増える費用：減価償却費 月"&TEXT((前提条件!$C$10+前提条件!$C$90)/10000,"0.0")&"万円／電気・洗浄・保守 月"&TEXT(((前提条件!$C$73+前提条件!$C$74)/12)/10000,"0.0")&"万円" -> ・増える費用：減価償却費 月4.2万円／電気・洗浄・保守 月1.4万円
B8: ="・減る費用：雑給 月"&TEXT((前提条件!$C$71/12)/10000,"0.0")&"万円（1日"&TEXT(前提条件!$C$63,"0.0")&"時間分の作業減）／絞り袋 月"&TEXT((前提条件!$C$72/12)/10000,"0.0")&"万円" -> ・減る費用：雑給 月17.5万円（1日3.8時間分の作業減）／絞り袋 月0.3万円
B9: ="・差し引き：毎月 約"&TEXT(前提条件!$C$79/10000,"0.0")&"万円、予算より利益が増える" -> ・差し引き：毎月 約12.2万円、予算より利益が増える
B10: ="・現場：作業人時 "&TEXT((前提条件!$G$46/60),"0.0")&"h → "&TEXT((前提条件!$G$59/60),"0.0")&"h。手詰め・壁崩しがなくなり、組立（2名×20分）・洗浄（2名×20分）が加わる" -> ・現場：作業人時 9.6h → 5.8h。手詰め・壁崩しがなくなり、組立（2名×20分）・洗浄（2名×20分）が加わる
B11: ="・条件：減った"&TEXT(前提条件!$C$63,"0.0")&"時間分のパートシフトを実際に調整すること" -> ・条件：減った3.8時間分のパートシフトを実際に調整すること
B13: ■ 社長向け（投資判断）
B14: ="【結論】充填機2台に"&TEXT(前提条件!$C$94/10000,"#,##0")&"万円を投資。月"&TEXT(前提条件!$C$79/10000,"0.0")&"万円の利益改善で"&投資回収_月次!$D$4&"か月（"&YEAR(投資回収_月次!$G$4)&"年"&MONTH(投資回収_月次!$G$4)&"月"&"）で回収し、5年以内の基準を満たす。期中導入でも48期の経常利益予算は下回らない。" -> 【結論】充填機2台に500万円を投資。月12.2万円の利益改善で31か月（2029年8月）で回収し、5年以内の基準を満たす。期中導入でも48期の経常利益予算は下回らない。
B15: ="・投資内容：本体"&TEXT(前提条件!$C$5/10000,"#,##0")&"万円（暫定）＋電気・付帯工事"&TEXT(前提条件!$C$85/10000,"#,##0")&"万円。2027年2月1日導入、"&前提条件!$C$9&"年償却" -> ・投資内容：本体450万円（暫定）＋電気・付帯工事50万円。2027年2月1日導入、10年償却
B16: ="・効果（月平均）：投資効果 償却前 約"&TEXT(前提条件!$C$76/10000,"0.0")&"万円 − 減価償却 "&TEXT((前提条件!$C$10+前提条件!$C$90)/10000,"0.0")&"万円 ＝ 利益改善 約"&TEXT(前提条件!$C$79/10000,"0.0")&"万円" -> ・効果（月平均）：投資効果 償却前 約16.4万円 − 減価償却 4.2万円 ＝ 利益改善 約12.2万円
B17: ="・48期（2〜6月）の経常利益：予算比 +"&TEXT(白鳥惣菜PL_導入効果!$P$154*1000/10000,"0")&"万円、全月で予算超" -> ・48期（2〜6月）の経常利益：予算比 +60万円、全月で予算超
B18: ="・10年累計の利益改善（償却後）：約"&TEXT(年度別_償却!$I$16/10000,"#,##0")&"万円" -> ・10年累計の利益改善（償却後）：約1,469万円
B19: ="・損益分岐：効果が見込みの"&TEXT(前提条件!$C$82,"0%")&"程度まで下がっても赤字にならない" -> ・損益分岐：効果が見込みの31%程度まで下がっても赤字にならない
B20: ・金額外の効果：計量の抜き打ち化、クリームロス削減、衛生面の向上、生産能力 約3,000個/時の増産余力
B21: ・前提とリスク：投資額は暫定（見積確定後に更新）。人件費削減はシフト調整の実行が前提。法定福利費の削減は含めず控えめに試算。

Sheet 印刷用_社長
B1: 充填機導入 投資判断資料（白鳥惣菜）
B2: 48期（製造PL 17期）下期・2027年2月1日導入 ／ 減価償却10年・投資回収5年以内の基準
B4: ="充填機2台に"&TEXT(前提条件!$C$94/10000,"#,##0")&"万円を投資。月"&TEXT(前提条件!$C$79/10000,"0.0")&"万円の利益改善で"&投資回収_月次!$D$4&"か月（"&YEAR(投資回収_月次!$G$4)&"年"&MONTH(投資回収_月次!$G$4)&"月"&"）で回収し、5年以内の基準を満たします。期中導入でも48期の経常利益予算は下回りません。" -> 充填機2台に500万円を投資。月12.2万円の利益改善で31か月（2029年8月）で回収し、5年以内の基準を満たします。期中導入でも48期の経常利益予算は下回りません。
B7: 総投資額 | D7: 投資回収 | F7: 月の利益改善（償却後） | H7: 48期下期 予算比
B8: =前提条件!$C$94 -> 5000000 | D8: =投資回収_月次!$D$4 -> 31 | F8: =前提条件!$C$79 -> 122261.67 | H8: =白鳥惣菜PL_導入効果!$P$154*1000 -> 599566.67
B10: ■ 投資の内容
B11: ="・充填機2台：本体"&TEXT(前提条件!$C$5/10000,"#,##0")&"万円（暫定）＋電気・付帯工事"&TEXT(前提条件!$C$85/10000,"#,##0")&"万円＝"&TEXT(前提条件!$C$94/10000,"#,##0")&"万円" -> ・充填機2台：本体450万円（暫定）＋電気・付帯工事50万円＝500万円
B12: ="・2027年2月1日導入。電気・付帯工事は"&前提条件!$C$87 -> ・2027年2月1日導入。電気・付帯工事は機械の付随費用として資産計上（機械と同じ10年償却）
B13: ・対象商品：カスタード＆ホイップシュー、ふんわりバナナロール（生産能力 約3,000個/時）
B15: ■ 効果（月平均）
B16: 項目 | D16: 金額（円/月） | F16: 内容
B17: 作業人時の削減 | D17: =(前提条件!$C$71/12) -> 174895.83 | F17: ="1日 "&TEXT(前提条件!$C$63,"0.0")&"時間（"&TEXT((前提条件!$G$46/60),"0.0")&"h→"&TEXT((前提条件!$G$59/60),"0.0")&"h）" -> 1日 3.8時間（9.6h→5.8h）
B18: 絞り袋の削減 | D18: =(前提条件!$C$72/12) -> 2920 | F18: 手詰め工程の廃止
B19: 電気・洗浄・保守部品 | D19: =-((前提条件!$C$73+前提条件!$C$74)/12) -> -13887.5 | F19: ランニングコスト
B20: 投資効果（償却前） | D20: =前提条件!$C$76 -> 163928.33 | F20: キャッシュの手残り＝投資回収の原資
B21: 減価償却費 | D21: =-(前提条件!$C$10+前提条件!$C$90) -> -41666.667 | F21: ="総投資を"&前提条件!$C$9&"年で償却" -> 総投資を10年で償却
B22: 利益改善（償却後） | D22: =前提条件!$C$79 -> 122261.67 | F22: 経常利益への影響
B24: ■ 48期 下期の経常利益（白鳥惣菜PL）
B25: 経常利益（千円） | C25: 2月 | D25: 3月 | E25: 4月 | F25: 5月 | G25: 6月 | H25: 下期計(1〜6月) | I25: 判定
B26: 予算 | C26: =白鳥惣菜PL_導入効果!J152 -> -2565.4817 | D26: =白鳥惣菜PL_導入効果!K152 -> 3454.5383 | E26: =白鳥惣菜PL_導入効果!L152 -> 3740.4383 | F26: =白鳥惣菜PL_導入効果!M152 -> 2410.4383 | G26: =白鳥惣菜PL_導入効果!N152 -> -3722.2931 | H26: =白鳥惣菜PL_導入効果!P152 -> 997.744
B27: 導入後 | C27: =白鳥惣菜PL_導入効果!J153 -> -2456.8404 | D27: =白鳥惣菜PL_導入効果!K153 -> 3580.0876 | E27: =白鳥惣菜PL_導入効果!L153 -> 3860.3516 | F27: =白鳥惣菜PL_導入効果!M153 -> 2535.9876 | G27: =白鳥惣菜PL_導入効果!N153 -> -3602.3798 | H27: =白鳥惣菜PL_導入効果!P153 -> 1597.3107
B28: 差額（導入後−予算） | C28: =白鳥惣菜PL_導入効果!J154 -> 108.64133 | D28: =白鳥惣菜PL_導入効果!K154 -> 125.54933 | E28: =白鳥惣菜PL_導入効果!L154 -> 119.91333 | F28: =白鳥惣菜PL_導入効果!M154 -> 125.54933 | G28: =白鳥惣菜PL_導入効果!N154 -> 119.91333 | H28: =白鳥惣菜PL_導入効果!P154 -> 599.56667 | I28: =白鳥惣菜PL_導入効果!P155 -> 予算超
B30: ■ 判断材料
B31: ="・10年間の累計利益改善（償却後）：約"&TEXT(年度別_償却!$I$16/10000,"#,##0")&"万円" -> ・10年間の累計利益改善（償却後）：約1,469万円
B32: ="・効果が見込みの"&TEXT(前提条件!$C$82,"0%")&"程度まで下がっても赤字にならない（損益分岐）" -> ・効果が見込みの31%程度まで下がっても赤字にならない（損益分岐）
B33: ・金額に入れていない効果：計量の抜き打ち化、クリームロス削減、衛生面の向上、増産余力
B35: ■ 前提とリスク
B36: ・投資額450万円は暫定。見積確定後に更新します。
B37: ・人件費削減は、削減時間分のシフト調整を実行することが前提です。
B38: ="・年"&前提条件!$C$26&"日稼働・時給"&TEXT(前提条件!$C$25,"#,##0")&"円で試算。法定福利費の削減は含めず、控えめに見積もっています。" -> ・年365日稼働・時給1,500円で試算。法定福利費の削減は含めず、控えめに見積もっています。

Sheet 印刷用_製造部長
B1: 充填機導入について（製造部長ご説明資料）
B2: 白鳥惣菜 48期（製造PL 17期）下期・2027年2月1日導入
B4: ="下期予算の修正は不要です。充填機を2月に導入しても、2〜6月の全月で白鳥惣菜の経常利益は予算を上回ります（下期計 +"&TEXT(白鳥惣菜PL_導入効果!$P$154*1000/10000,"0")&"万円）。" -> 下期予算の修正は不要です。充填機を2月に導入しても、2〜6月の全月で白鳥惣菜の経常利益は予算を上回ります（下期計 +60万円）。
B7: ■ お願いしたいこと
B8: ="・充填機2台（本体"&TEXT(前提条件!$C$5/10000,"#,##0")&"万円＋電気・付帯工事"&TEXT(前提条件!$C$85/10000,"#,##0")&"万円＝"&TEXT(前提条件!$C$94/10000,"#,##0")&"万円）を2027年2月1日に導入したい" -> ・充填機2台（本体450万円＋電気・付帯工事50万円＝500万円）を2027年2月1日に導入したい
B9: ・下期の予算額はそのままで構いません（予算修正のお願いではありません）
B11: ■ 予算を下回らない理由（月平均）
B12: 項目 | D12: 金額（円/月） | F12: 内容
B13: 減る費用：雑給（パート） | D13: =(前提条件!$C$71/12) -> 174895.83 | F13: ="1日 "&TEXT(前提条件!$C$63,"0.0")&"時間分の作業が減る（時給"&TEXT(前提条件!$C$25,"#,##0")&"円）" -> 1日 3.8時間分の作業が減る（時給1,500円）
B14: 減る費用：絞り袋 | D14: =(前提条件!$C$72/12) -> 2920 | F14: 手詰めが不要になる
B15: 増える費用：電気・洗浄・保守部品 | D15: =-((前提条件!$C$73+前提条件!$C$74)/12) -> -13887.5 | F15: 0.4kW×2台の電気代、洗浄水・洗剤、パッキン等
B16: 増える費用：減価償却費 | D16: =-(前提条件!$C$10+前提条件!$C$90) -> -41666.667 | F16: ="総投資"&TEXT(前提条件!$C$94/10000,"#,##0")&"万円を"&前提条件!$C$9&"年で償却" -> 総投資500万円を10年で償却
B17: 差し引き（利益が増える額） | D17: =前提条件!$C$79 -> 122261.67 | F17: 毎月この金額だけ予算より利益が増える
B19: ■ 月別の経常利益（白鳥惣菜PL）
B20: 経常利益（千円） | C20: 2月 | D20: 3月 | E20: 4月 | F20: 5月 | G20: 6月 | H20: 下期計(1〜6月) | I20: 判定
B21: 予算 | C21: =白鳥惣菜PL_導入効果!J152 -> -2565.4817 | D21: =白鳥惣菜PL_導入効果!K152 -> 3454.5383 | E21: =白鳥惣菜PL_導入効果!L152 -> 3740.4383 | F21: =白鳥惣菜PL_導入効果!M152 -> 2410.4383 | G21: =白鳥惣菜PL_導入効果!N152 -> -3722.2931 | H21: =白鳥惣菜PL_導入効果!P152 -> 997.744
B22: 導入後 | C22: =白鳥惣菜PL_導入効果!J153 -> -2456.8404 | D22: =白鳥惣菜PL_導入効果!K153 -> 3580.0876 | E22: =白鳥惣菜PL_導入効果!L153 -> 3860.3516 | F22: =白鳥惣菜PL_導入効果!M153 -> 2535.9876 | G22: =白鳥惣菜PL_導入効果!N153 -> -3602.3798 | H22: =白鳥惣菜PL_導入効果!P153 -> 1597.3107
B23: 差額（導入後−予算） | C23: =白鳥惣菜PL_導入効果!J154 -> 108.64133 | D23: =白鳥惣菜PL_導入効果!K154 -> 125.54933 | E23: =白鳥惣菜PL_導入効果!L154 -> 119.91333 | F23: =白鳥惣菜PL_導入効果!M154 -> 125.54933 | G23: =白鳥惣菜PL_導入効果!N154 -> 119.91333 | H23: =白鳥惣菜PL_導入効果!P154 -> 599.56667 | I23: =白鳥惣菜PL_導入効果!P155 -> 予算超
B24: ※2月・6月は元々予算上の赤字月ですが、導入後は赤字が縮小します。
B26: ■ 現場で変わること
B27: ="・1日の作業人時："&TEXT((前提条件!$G$46/60),"0.0")&"時間 → "&TEXT((前提条件!$G$59/60),"0.0")&"時間（▲"&TEXT(前提条件!$C$63,"0.0")&"時間）" -> ・1日の作業人時：9.6時間 → 5.8時間（▲3.8時間）
B28: ・なくなる作業：絞り袋への手詰め（カスタード・生クリーム）、シュー生地内の壁崩し
B29: ・増える作業：充填機の組立（2名×20分）、充填機の洗浄（2名×20分）
B30: ・クリームはホッパー（10ℓ）に一括投入。充填重量が安定し、計量は全量から抜き打ちへ
B32: ■ 効果を出すための条件
B33: ="・減った"&TEXT(前提条件!$C$63,"0.0")&"時間分のパートシフトを実際に調整する（または他工程へ再配置し残業・派遣を削減）" -> ・減った3.8時間分のパートシフトを実際に調整する（または他工程へ再配置し残業・派遣を削減）
B34: ="・効果が見込みの"&TEXT(前提条件!$C$82,"0%")&"程度まで下がっても、償却後の利益はマイナスになりません" -> ・効果が見込みの31%程度まで下がっても、償却後の利益はマイナスになりません

Sheet 前提条件
B1: 前提条件（入力シート）
B2: 青字・黄色セル＝入力値（変更すると全シートが再計算されます） 黒字＝計算式 緑字＝他シート参照
B4: ■ 投資条件
B5: 充填機本体（2台・暫定） | C5: 4500000 | D5: 円 | H5: 出典：現場資料「450万（暫定）」。見積確定後に更新
B6: 台数 | C6: 2 | D6: 台 | H6: 出典：現場資料「充填機・・・2台」
B7: 電気・付帯工事費 | C7: =C85 -> 500000 | D7: 円 | H7: 電源・配線、搬入・設置・試運転をまとめて下部「■ 電気・付帯工事費」で入力
B8: 機械本体の取得価額（償却対象） | C8: =C5 -> 4500000 | D8: 円 | H8: 電気・付帯工事分の償却は下部の処理区分に従い別計算
B9: 耐用年数（減価償却・定額法） | C9: 10 | D9: 年 | H9: 指示値：10年
B10: 月額減価償却費 | C10: =C8/(C9*12) -> 37500 | D10: 円/月 | H10: 取得価額÷耐用年数÷12（残存価額0で計算）
B11: 導入日（事業供用開始） | C11: 46419 | H11: 48期（製造PL 17期）下期・2月1日導入
B12: 投資回収の目標 | C12: 5 | D12: 年以内 | H12: 指示値：5年以内
B13: 総投資額（機械本体＋電気・付帯工事）→ | C13: =C94 -> 5000000
B14: ■ 機械仕様（カタログ値）
B15: 電源 | C15: AC200V 0.4kW（サーボモーター使用）
B16: ポンプ回転数 | C16: 1〜150rpm
B17: ポンプ吐出量 | C17: 60〜9,000cc/分
B18: 充填容量 | C18: 5〜9,999cc/回
B19: ホッパー容量 | C19: 15ℓ（標準）
B20: 総重量 | C20: 29kg（標準ポンプホッパー装着時）
B21: 生産能力 | C21: シュークリーム50g注入時 2口合計 約3,000個/時
B22: 外形寸法 | C22: 本体 W350×D400×H265mm／ホッパー装着時 H580mm
B24: ■ 単価・稼働条件
B25: 時給（パート） | C25: 1500 | D25: 円/h | H25: 出典：現場資料「時給1,500円」。法定福利費は含めず保守的に試算
B26: 年間稼働日数 | C26: 365 | D26: 日 | H26: 毎日生産を想定。休業日がある場合は修正（月の稼働日数は暦日で按分）
B27: 電力単価 | C27: 30 | D27: 円/kWh | H27: 想定値（高圧電力の目安）。工場の実単価に置換推奨
B28: 消費電力（1台） | C28: 0.4 | D28: kW | H28: カタログ値
B29: 1日の電源ON時間 | C29: =(MAX(D50:D58)-MIN(C50:C58))*24 -> 2.5 | D29: h | H29: 導入後工程の組立開始〜洗浄終了（定格出力で通電し続ける前提＝保守的）
B30: 洗浄費（水道・洗剤） | C30: 150 | D30: 円/日 | H30: 想定値（2台分）
B31: 保守部品費（年率） | C31: 0.02 | D31: 取得価額比 | H31: パッキン・ノズル等の交換。想定値
B32: 絞り袋単価 | C32: 16 | D32: 円/枚 | H32: 出典：現場資料「16円/枚」
B33: 絞り袋使用枚数（カスタード＆ホイップシュー） | C33: 4 | D33: 枚/日 | H33: 出典：現場資料
B34: 絞り袋使用枚数（ふんわりバナナロール） | C34: 2 | D34: 枚/日 | H34: 出典：現場資料
B36: ■ 工程比較① 現行（絞り袋手詰め）
B37: 工程 | C37: 開始 | D37: 終了 | E37: 時間(分) | F37: 人数 | G37: 人時(分)
B38: 材料運搬 | C38: 0.54166667 | D38: 0.54861111 | E38: =ROUND((D38-C38)*1440,0) -> 10 | F38: 2 | G38: =E38*F38 -> 20 | H38: 出典：現場資料の工程表（開始・終了・人数）※2026/10/29修正版
B39: カスタードクリーム絞り袋充填 | C39: 0.54861111 | D39: 0.64583333 | E39: =ROUND((D39-C39)*1440,0) -> 140 | F39: 0.5 | G39: =E39*F39 -> 70
B40: 生クリーム絞り袋充填 | C40: 0.54861111 | D40: 0.64583333 | E40: =ROUND((D40-C40)*1440,0) -> 140 | F40: 0.5 | G40: =E40*F40 -> 70
B41: シュー生地内の壁崩し | C41: 0.54166667 | D41: 0.58333333 | E41: =ROUND((D41-C41)*1440,0) -> 60 | F41: 1 | G41: =E41*F41 -> 60
B42: カスタードクリーム注入 | C42: 0.55208333 | D42: 0.61458333 | E42: =ROUND((D42-C42)*1440,0) -> 90 | F42: 1 | G42: =E42*F42 -> 90
B43: 生クリーム注入 | C43: 0.55208333 | D43: 0.61458333 | E43: =ROUND((D43-C43)*1440,0) -> 90 | F43: 1 | G43: =E43*F43 -> 90
B44: 粉糖掛け | C44: 0.55555556 | D44: 0.61805556 | E44: =ROUND((D44-C44)*1440,0) -> 90 | F44: 1 | G44: =E44*F44 -> 90
B45: 包材入れ（蓋閉め込み） | C45: 0.55902778 | D45: 0.61805556 | E45: =ROUND((D45-C45)*1440,0) -> 85 | F45: 1 | G45: =E45*F45 -> 85
B46: 合計 | G46: =SUM(G38:G45) -> 575
B48: ■ 工程比較② 充填機導入後
B49: 工程 | C49: 開始 | D49: 終了 | E49: 時間(分) | F49: 人数 | G49: 人時(分)
B50: 材料運搬 | C50: 0.54166667 | D50: 0.55555556 | E50: =ROUND((D50-C50)*1440,0) -> 20 | F50: 1 | G50: =E50*F50 -> 20 | H50: 壁崩し工程は充填機ノズル注入により不要（現場資料の導入後工程に記載なし）
B51: 充填機組み立て | C51: 0.54166667 | D51: 0.55555556 | E51: =ROUND((D51-C51)*1440,0) -> 20 | F51: 2 | G51: =E51*F51 -> 40
B52: カスタードクリーム充填機充填 | C52: 0.55555556 | D52: 0.58333333 | E52: =ROUND((D52-C52)*1440,0) -> 40 | F52: 0.5 | G52: =E52*F52 -> 20
B53: 生クリーム充填機充填 | C53: 0.55555556 | D53: 0.58333333 | E53: =ROUND((D53-C53)*1440,0) -> 40 | F53: 0.5 | G53: =E53*F53 -> 20
B54: カスタードクリーム注入 | C54: 0.55555556 | D54: 0.59027778 | E54: =ROUND((D54-C54)*1440,0) -> 50 | F54: 1 | G54: =E54*F54 -> 50
B55: 生クリーム注入 | C55: 0.55555556 | D55: 0.59027778 | E55: =ROUND((D55-C55)*1440,0) -> 50 | F55: 1 | G55: =E55*F55 -> 50
B56: 粉糖掛け | C56: 0.55555556 | D56: 0.59375 | E56: =ROUND((D56-C56)*1440,0) -> 55 | F56: 1 | G56: =E56*F56 -> 55
B57: 包材入れ（蓋閉め込み） | C57: 0.55902778 | D57: 0.59375 | E57: =ROUND((D57-C57)*1440,0) -> 50 | F57: 1 | G57: =E57*F57 -> 50
B58: 充填機洗浄 | C58: 0.63194444 | D58: 0.64583333 | E58: =ROUND((D58-C58)*1440,0) -> 20 | F58: 2 | G58: =E58*F58 -> 40
B59: 合計 | G59: =SUM(G50:G58) -> 345
B61: ■ 1日当たりの効果
B62: 削減人時（分） | C62: =G46-G59 -> 230 | D62: 分/日 | H62: 現行人時 − 導入後人時
B63: 削減人時（時間） | C63: =C62/60 -> 3.8333333 | D63: h/日
B64: ① 人件費削減 | C64: =C63*C25 -> 5750 | D64: 円/日 | H64: 削減人時 × 時給
B65: ② 消耗品費削減（絞り袋） | C65: =C32*(C33+C34) -> 96 | D65: 円/日 | H65: 絞り袋が不要になる
B66: ③ 電気代（増加） | C66: =C28*C6*C29*C27 -> 60 | D66: 円/日 | H66: kW × 台数 × 電源ON時間 × 電力単価
B67: ④ 洗浄費（増加） | C67: =C30 -> 150 | D67: 円/日
B68: 1日当たり純効果（①+②−③−④） | C68: =C64+C65-C66-C67 -> 5636 | D68: 円/日
B70: ■ 年間・月平均（投資回収の基礎数値）
B71: 年間 人件費削減 | C71: =C64*C26 -> 2098750 | D71: 円/年
B72: 年間 消耗品費削減 | C72: =C65*C26 -> 35040 | D72: 円/年
B73: 年間 ランニングコスト（電気・洗浄） | C73: =(C66+C67)*C26 -> 76650 | D73: 円/年
B74: 年間 保守部品費 | C74: =C8*C31 -> 90000 | D74: 円/年
B75: 年間 純効果（キャッシュ） | C75: =C71+C72-C73-C74 -> 1967140 | D75: 円/年 | H75: 減価償却前の手残り
B76: 月平均 純効果（キャッシュ） | C76: =C75/12 -> 163928.33 | D76: 円/月
B77: 年間 減価償却費（機械＋電気・付帯工事） | C77: =(C10+C90)*12 -> 500000 | D77: 円/年 | H77: 電気・付帯工事を一括費用にした場合は導入月のみ別途計上
B78: 年間 利益改善額（減価償却後） | C78: =C75-C77 -> 1467140 | D78: 円/年 | H78: PL上の経常利益への影響
B79: 月平均 利益改善額（減価償却後） | C79: =C78/12 -> 122261.67 | D79: 円/月
B80: 単純投資回収期間（か月） | C80: =IF(C76>0,C94/C76,0) -> 30.501134 | D80: か月 | H80: 総投資額（機械＋電気・付帯工事）÷ 月平均純効果
B81: 単純投資回収期間（年） | C81: =C80/12 -> 2.5417611 | D81: 年
B82: 損益分岐の効果発現率 | C82: =IF((C71+C72)>0,(C73+C74+C77)/(C71+C72),0) -> 0.31242531 | H82: 削減効果がこの割合を下回らない限り、償却後も利益はプラス
B84: ■ 電気・付帯工事費（AC200V電源・配線、搬入・設置・試運転）
B85: 電気・付帯工事費（税抜） | C85: 500000 | D85: 円 | H85: 指示値：50万円（電気・付帯工事＋付帯工事の合計・区分1）。0円にすると全シートで影響なし
B86: 会計処理区分（1〜3を選択） | C86: 1 | D86: 区分 | H86: 1:機械の取得価額に含める（10年償却）／2:建物附属設備（電気設備15年償却）／3:一括費用（修繕費）
B87: 処理の内容 | C87: =CHOOSE(C86,"機械の付随費用として資産計上（機械と同じ10年償却）","建物附属設備（電気設備）として資産計上（15年償却）","一括費用処理（導入月に修繕費で全額計上）") -> 機械の付随費用として資産計上（機械と同じ10年償却）
B88: 建物附属設備（電気設備）の耐用年数 | C88: 15 | D88: 年 | H88: 法定耐用年数：電気設備（照明設備を含む）その他のもの15年
B89: 適用する償却年数 | C89: =CHOOSE(C86,C9,C88,0) -> 10 | D89: 年
B90: 電気・付帯工事 月額減価償却費 | C90: =IF(C89>0,C85/(C89*12),0) -> 4166.6667 | D90: 円/月
B91: 電気・付帯工事 一括費用計上額（導入月） | C91: =IF(C86=3,C85,0) -> 0 | D91: 円 | H91: 区分3のときのみ
B92: PL計上科目 | C92: =CHOOSE(C86,"一般管理費＞減価償却費（月割）","一般管理費＞減価償却費（月割）","一般管理費＞修繕費（導入月に一括）") -> 一般管理費＞減価償却費（月割）
B93: 支払方法 | C93: 工事完了後に一括払い | H93: 支払は一括でも、資産計上ならPLは償却で月割り。回収計算では導入月に全額支出として扱う
B94: 総投資額（機械＋電気・付帯工事） | C94: =C8+C85 -> 5000000 | D94: 円 | H94: 投資回収の判定はこの金額で行う

Sheet 投資回収_月次
A1: 投資回収計画（月次） 充填機2台／白鳥惣菜
A2: 単位：円 導入月から耐用年数10年（120か月）まで表示。効果発現率（E列・青字）は月ごとに変更可
B4: 投資回収月数 | D4: =IF(MAX(K8:K127)>=前提条件!$C$94,COUNTIF(K8:K127,"<"&前提条件!$C$94)+1,"回収不可") -> 31 | F4: 回収年月 | G4: =IF(ISNUMBER(D4),EDATE(前提条件!$C$11,D4-1),"-") -> 47331 | I4: 5年以内判定 | K4: =IF(ISNUMBER(D4),IF(D4<=前提条件!$C$12*12,"◎ 5年以内に回収","× 5年超"),"× 回収不可") -> ◎ 5年以内に回収 | M4: 5年間累計CF | O4: =K67 -> 9841336
A7: No | B7: 年月 | C7: 期 | D7: 稼働日数 | E7: 効果発現率 | F7: ①人件費削減 | G7: ②消耗品削減 | H7: ③電気・洗浄費 | I7: ④保守部品費 | J7: 純効果(CF) ①+②−③−④ | K7: 累計CF | L7: 未回収残高 | M7: 減価償却費 (機械) | N7: 利益影響 (CF−償却等) | O7: 累計利益影響 | P7: 期末簿価 | Q7: 回収判定 | R7: 電気・付帯工事 減価償却費 | S7: 電気・付帯工事 一括費用
A8: 1 | B8: =EDATE(前提条件!$C$11,A8-1) -> 46419 | C8: =YEAR(B8)+IF(MONTH(B8)>=7,1,0)-2027+48 -> 48 | D8: =前提条件!$C$26/365*DAY(EOMONTH(B8,0)) -> 28 | E8: 1 | F8: =前提条件!$C$64*D8*E8 -> 161000 | G8: =前提条件!$C$65*D8*E8 -> 2688 | H8: =(前提条件!$C$66+前提条件!$C$67)*D8 -> 5880 | I8: =前提条件!$C$74/12 -> 7500 | J8: =F8+G8-H8-I8 -> 150308 | K8: =J8 -> 150308 | L8: =MAX(前提条件!$C$94-K8,0) -> 4849692 | M8: =前提条件!$C$10 -> 37500 | N8: =J8-M8-R8-S8 -> 108641.33 | O8: =N8 -> 108641.33 | P8: =前提条件!$C$8-SUM(M$8:M8)+IF(前提条件!$C$86<3,前提条件!$C$85-SUM(R$8:R8),0) -> 4958333.3 | Q8: =IF(AND(K8>=前提条件!$C$94,0<前提条件!$C$94),"◀投資回収","") | R8: =IF(A8<=前提条件!$C$89*12,前提条件!$C$90,0) -> 4166.6667 | S8: =IF(A8=1,前提条件!$C$91,0) -> 0
A9: 2 | B9: =EDATE(前提条件!$C$11,A9-1) -> 46447 | C9: =YEAR(B9)+IF(MONTH(B9)>=7,1,0)-2027+48 -> 48 | D9: =前提条件!$C$26/365*DAY(EOMONTH(B9,0)) -> 31 | E9: 1 | F9: =前提条件!$C$64*D9*E9 -> 178250 | G9: =前提条件!$C$65*D9*E9 -> 2976 | H9: =(前提条件!$C$66+前提条件!$C$67)*D9 -> 6510 | I9: =前提条件!$C$74/12 -> 7500 | J9: =F9+G9-H9-I9 -> 167216 | K9: =K8+J9 -> 317524 | L9: =MAX(前提条件!$C$94-K9,0) -> 4682476 | M9: =前提条件!$C$10 -> 37500 | N9: =J9-M9-R9-S9 -> 125549.33 | O9: =O8+N9 -> 234190.67 | P9: =前提条件!$C$8-SUM(M$8:M9)+IF(前提条件!$C$86<3,前提条件!$C$85-SUM(R$8:R9),0) -> 4916666.7 | Q9: =IF(AND(K9>=前提条件!$C$94,K8<前提条件!$C$94),"◀投資回収","") | R9: =IF(A9<=前提条件!$C$89*12,前提条件!$C$90,0) -> 4166.6667 | S9: =IF(A9=1,前提条件!$C$91,0) -> 0
A10: 3 | B10: =EDATE(前提条件!$C$11,A10-1) -> 46478 | C10: =YEAR(B10)+IF(MONTH(B10)>=7,1,0)-2027+48 -> 48 | D10: =前提条件!$C$26/365*DAY(EOMONTH(B10,0)) -> 30 | E10: 1 | F10: =前提条件!$C$64*D10*E10 -> 172500 | G10: =前提条件!$C$65*D10*E10 -> 2880 | H10: =(前提条件!$C$66+前提条件!$C$67)*D10 -> 6300 | I10: =前提条件!$C$74/12 -> 7500 | J10: =F10+G10-H10-I10 -> 161580 | K10: =K9+J10 -> 479104 | L10: =MAX(前提条件!$C$94-K10,0) -> 4520896 | M10: =前提条件!$C$10 -> 37500 | N10: =J10-M10-R10-S10 -> 119913.33 | O10: =O9+N10 -> 354104 | P10: =前提条件!$C$8-SUM(M$8:M10)+IF(前提条件!$C$86<3,前提条件!$C$85-SUM(R$8:R10),0) -> 4875000 | Q10: =IF(AND(K10>=前提条件!$C$94,K9<前提条件!$C$94),"◀投資回収","") | R10: =IF(A10<=前提条件!$C$89*12,前提条件!$C$90,0) -> 4166.6667 | S10: =IF(A10=1,前提条件!$C$91,0) -> 0
A11: 4 | B11: =EDATE(前提条件!$C$11,A11-1) -> 46508 | C11: =YEAR(B11)+IF(MONTH(B11)>=7,1,0)-2027+48 -> 48 | D11: =前提条件!$C$26/365*DAY(EOMONTH(B11,0)) -> 31 | E11: 1 | F11: =前提条件!$C$64*D11*E11 -> 178250 | G11: =前提条件!$C$65*D11*E11 -> 2976 | H11: =(前提条件!$C$66+前提条件!$C$67)*D11 -> 6510 | I11: =前提条件!$C$74/12 -> 7500 | J11: =F11+G11-H11-I11 -> 167216 | K11: =K10+J11 -> 646320 | L11: =MAX(前提条件!$C$94-K11,0) -> 4353680 | M11: =前提条件!$C$10 -> 37500 | N11: =J11-M11-R11-S11 -> 125549.33 | O11: =O10+N11 -> 479653.33 | P11: =前提条件!$C$8-SUM(M$8:M11)+IF(前提条件!$C$86<3,前提条件!$C$85-SUM(R$8:R11),0) -> 4833333.3 | Q11: =IF(AND(K11>=前提条件!$C$94,K10<前提条件!$C$94),"◀投資回収","") | R11: =IF(A11<=前提条件!$C$89*12,前提条件!$C$90,0) -> 4166.6667 | S11: =IF(A11=1,前提条件!$C$91,0) -> 0
A12: 5 | B12: =EDATE(前提条件!$C$11,A12-1) -> 46539 | C12: =YEAR(B12)+IF(MONTH(B12)>=7,1,0)-2027+48 -> 48 | D12: =前提条件!$C$26/365*DAY(EOMONTH(B12,0)) -> 30 | E12: 1 | F12: =前提条件!$C$64*D12*E12 -> 172500 | G12: =前提条件!$C$65*D12*E12 -> 2880 | H12: =(前提条件!$C$66+前提条件!$C$67)*D12 -> 6300 | I12: =前提条件!$C$74/12 -> 7500 | J12: =F12+G12-H12-I12 -> 161580 | K12: =K11+J12 -> 807900 | L12: =MAX(前提条件!$C$94-K12,0) -> 4192100 | M12: =前提条件!$C$10 -> 37500 | N12: =J12-M12-R12-S12 -> 119913.33 | O12: =O11+N12 -> 599566.67 | P12: =前提条件!$C$8-SUM(M$8:M12)+IF(前提条件!$C$86<3,前提条件!$C$85-SUM(R$8:R12),0) -> 4791666.7 | Q12: =IF(AND(K12>=前提条件!$C$94,K11<前提条件!$C$94),"◀投資回収","") | R12: =IF(A12<=前提条件!$C$89*12,前提条件!$C$90,0) -> 4166.6667 | S12: =IF(A12=1,前提条件!$C$91,0) -> 0
A13: 6 | B13: =EDATE(前提条件!$C$11,A13-1) -> 46569 | C13: =YEAR(B13)+IF(MONTH(B13)>=7,1,0)-2027+48 -> 49 | D13: =前提条件!$C$26/365*DAY(EOMONTH(B13,0)) -> 31 | E13: 1 | F13: =前提条件!$C$64*D13*E13 -> 178250 | G13: =前提条件!$C$65*D13*E13 -> 2976 | H13: =(前提条件!$C$66+前提条件!$C$67)*D13 -> 6510 | I13: =前提条件!$C$74/12 -> 7500 | J13: =F13+G13-H13-I13 -> 167216 | K13: =K12+J13 -> 975116 | L13: =MAX(前提条件!$C$94-K13,0) -> 4024884 | M13: =前提条件!$C$10 -> 37500 | N13: =J13-M13-R13-S13 -> 125549.33 | O13: =O12+N13 -> 725116 | P13: =前提条件!$C$8-SUM(M$8:M13)+IF(前提条件!$C$86<3,前提条件!$C$85-SUM(R$8:R13),0) -> 4750000 | Q13: =IF(AND(K13>=前提条件!$C$94,K12<前提条件!$C$94),"◀投資回収","") | R13: =IF(A13<=前提条件!$C$89*12,前提条件!$C$90,0) -> 4166.6667 | S13: =IF(A13=1,前提条件!$C$91,0) -> 0
A14: 7 | B14: =EDATE(前提条件!$C$11,A14-1) -> 46600 | C14: =YEAR(B14)+IF(MONTH(B14)>=7,1,0)-2027+48 -> 49 | D14: =前提条件!$C$26/365*DAY(EOMONTH(B14,0)) -> 31 | E14: 1 | F14: =前提条件!$C$64*D14*E14 -> 178250 | G14: =前提条件!$C$65*D14*E14 -> 2976 | H14: =(前提条件!$C$66+前提条件!$C$67)*D14 -> 6510 | I14: =前提条件!$C$74/12 -> 7500 | J14: =F14+G14-H14-I14 -> 167216 | K14: =K13+J14 -> 1142332 | L14: =MAX(前提条件!$C$94-K14,0) -> 3857668 | M14: =前提条件!$C$10 -> 37500 | N14: =J14-M14-R14-S14 -> 125549.33 | O14: =O13+N14 -> 850665.33 | P14: =前提条件!$C$8-SUM(M$8:M14)+IF(前提条件!$C$86<3,前提条件!$C$85-SUM(R$8:R14),0) -> 4708333.3 | Q14: =IF(AND(K14>=前提条件!$C$94,K13<前提条件!$C$94),"◀投資回収","") | R14: =IF(A14<=前提条件!$C$89*12,前提条件!$C$90,0) -> 4166.6667 | S14: =IF(A14=1,前提条件!$C$91,0) -> 0
A15: 8 | B15: =EDATE(前提条件!$C$11,A15-1) -> 46631 | C15: =YEAR(B15)+IF(MONTH(B15)>=7,1,0)-2027+48 -> 49 | D15: =前提条件!$C$26/365*DAY(EOMONTH(B15,0)) -> 30 | E15: 1 | F15: =前提条件!$C$64*D15*E15 -> 172500 | G15: =前提条件!$C$65*D15*E15 -> 2880 | H15: =(前提条件!$C$66+前提条件!$C$67)*D15 -> 6300 | I15: =前提条件!$C$74/12 -> 7500 | J15: =F15+G15-H15-I15 -> 161580 | K15: =K14+J15 -> 1303912 | L15: =MAX(前提条件!$C$94-K15,0) -> 3696088 | M15: =前提条件!$C$10 -> 37500 | N15: =J15-M15-R15-S15 -> 119913.33 | O15: =O14+N15 -> 970578.67 | P15: =前提条件!$C$8-SUM(M$8:M15)+IF(前提条件!$C$86<3,前提条件!$C$85-SUM(R$8:R15),0) -> 4666666.7 | Q15: =IF(AND(K15>=前提条件!$C$94,K14<前提条件!$C$94),"◀投資回収","") | R15: =IF(A15<=前提条件!$C$89*12,前提条件!$C$90,0) -> 4166.6667 | S15: =IF(A15=1,前提条件!$C$91,0) -> 0
A16: 9 | B16: =EDATE(前提条件!$C$11,A16-1) -> 46661 | C16: =YEAR(B16)+IF(MONTH(B16)>=7,1,0)-2027+48 -> 49 | D16: =前提条件!$C$26/365*DAY(EOMONTH(B16,0)) -> 31 | E16: 1 | F16: =前提条件!$C$64*D16*E16 -> 178250 | G16: =前提条件!$C$65*D16*E16 -> 2976 | H16: =(前提条件!$C$66+前提条件!$C$67)*D16 -> 6510 | I16: =前提条件!$C$74/12 -> 7500 | J16: =F16+G16-H16-I16 -> 167216 | K16: =K15+J16 -> 1471128 | L16: =MAX(前提条件!$C$94-K16,0) -> 3528872 | M16: =前提条件!$C$10 -> 37500 | N16: =J16-M16-R16-S16 -> 125549.33 | O16: =O15+N16 -> 1096128 | P16: =前提条件!$C$8-SUM(M$8:M16)+IF(前提条件!$C$86<3,前提条件!$C$85-SUM(R$8:R16),0) -> 4625000 | Q16: =IF(AND(K16>=前提条件!$C$94,K15<前提条件!$C$94),"◀投資回収","") | R16: =IF(A16<=前提条件!$C$89*12,前提条件!$C$90,0) -> 4166.6667 | S16: =IF(A16=1,前提条件!$C$91,0) -> 0
A17: 10 | B17: =EDATE(前提条件!$C$11,A17-1) -> 46692 | C17: =YEAR(B17)+IF(MONTH(B17)>=7,1,0)-2027+48 -> 49 | D17: =前提条件!$C$26/365*DAY(EOMONTH(B17,0)) -> 30 | E17: 1 | F17: =前提条件!$C$64*D17*E17 -> 172500 | G17: =前提条件!$C$65*D17*E17 -> 2880 | H17: =(前提条件!$C$66+前提条件!$C$67)*D17 -> 6300 | I17: =前提条件!$C$74/12 -> 7500 | J17: =F17+G17-H17-I17 -> 161580 | K17: =K16+J17 -> 1632708 | L17: =MAX(前提条件!$C$94-K17,0) -> 3367292 | M17: =前提条件!$C$10 -> 37500 | N17: =J17-M17-R17-S17 -> 119913.33 | O17: =O16+N17 -> 1216041.3 | P17: =前提条件!$C$8-SUM(M$8:M17)+IF(前提条件!$C$86<3,前提条件!$C$85-SUM(R$8:R17),0) -> 4583333.3 | Q17: =IF(AND(K17>=前提条件!$C$94,K16<前提条件!$C$94),"◀投資回収","") | R17: =IF(A17<=前提条件!$C$89*12,前提条件!$C$90,0) -> 4166.6667 | S17: =IF(A17=1,前提条件!$C$91,0) -> 0
A18: 11 | B18: =EDATE(前提条件!$C$11,A18-1) -> 46722 | C18: =YEAR(B18)+IF(MONTH(B18)>=7,1,0)-2027+48 -> 49 | D18: =前提条件!$C$26/365*DAY(EOMONTH(B18,0)) -> 31 | E18: 1 | F18: =前提条件!$C$64*D18*E18 -> 178250 | G18: =前提条件!$C$65*D18*E18 -> 2976 | H18: =(前提条件!$C$66+前提条件!$C$67)*D18 -> 6510 | I18: =前提条件!$C$74/12 -> 7500 | J18: =F18+G18-H18-I18 -> 167216 | K18: =K17+J18 -> 1799924 | L18: =MAX(前提条件!$C$94-K18,0) -> 3200076 | M18: =前提条件!$C$10 -> 37500 | N18: =J18-M18-R18-S18 -> 125549.33 | O18: =O17+N18 -> 1341590.7 | P18: =前提条件!$C$8-SUM(M$8:M18)+IF(前提条件!$C$86<3,前提条件!$C$85-SUM(R$8:R18),0) -> 4541666.7 | Q18: =IF(AND(K18>=前提条件!$C$94,K17<前提条件!$C$94),"◀投資回収","") | R18: =IF(A18<=前提条件!$C$89*12,前提条件!$C$90,0) -> 4166.6667 | S18: =IF(A18=1,前提条件!$C$91,0) -> 0
A19: 12 | B19: =EDATE(前提条件!$C$11,A19-1) -> 46753 | C19: =YEAR(B19)+IF(MONTH(B19)>=7,1,0)-2027+48 -> 49 | D19: =前提条件!$C$26/365*DAY(EOMONTH(B19,0)) -> 31 | E19: 1 | F19: =前提条件!$C$64*D19*E19 -> 178250 | G19: =前提条件!$C$65*D19*E19 -> 2976 | H19: =(前提条件!$C$66+前提条件!$C$67)*D19 -> 6510 | I19: =前提条件!$C$74/12 -> 7500 | J19: =F19+G19-H19-I19 -> 167216 | K19: =K18+J19 -> 1967140 | L19: =MAX(前提条件!$C$94-K19,0) -> 3032860 | M19: =前提条件!$C$10 -> 37500 | N19: =J19-M19-R19-S19 -> 125549.33 | O19: =O18+N19 -> 1467140 | P19: =前提条件!$C$8-SUM(M$8:M19)+IF(前提条件!$C$86<3,前提条件!$C$85-SUM(R$8:R19),0) -> 4500000 | Q19: =IF(AND(K19>=前提条件!$C$94,K18<前提条件!$C$94),"◀投資回収","") | R19: =IF(A19<=前提条件!$C$89*12,前提条件!$C$90,0) -> 4166.6667 | S19: =IF(A19=1,前提条件!$C$91,0) -> 0
A20: 13 | B20: =EDATE(前提条件!$C$11,A20-1) -> 46784 | C20: =YEAR(B20)+IF(MONTH(B20)>=7,1,0)-2027+48 -> 49 | D20: =前提条件!$C$26/365*DAY(EOMONTH(B20,0)) -> 29 | E20: 1 | F20: =前提条件!$C$64*D20*E20 -> 166750 | G20: =前提条件!$C$65*D20*E20 -> 2784 | H20: =(前提条件!$C$66+前提条件!$C$67)*D20 -> 6090 | I20: =前提条件!$C$74/12 -> 7500 | J20: =F20+G20-H20-I20 -> 155944 | K20: =K19+J20 -> 2123084 | L20: =MAX(前提条件!$C$94-K20,0) -> 2876916 | M20: =前提条件!$C$10 -> 37500 | N20: =J20-M20-R20-S20 -> 114277.33 | O20: =O19+N20 -> 1581417.3 | P20: =前提条件!$C$8-SUM(M$8:M20)+IF(前提条件!$C$86<3,前提条件!$C$85-SUM(R$8:R20),0) -> 4458333.3 | Q20: =IF(AND(K20>=前提条件!$C$94,K19<前提条件!$C$94),"◀投資回収","") | R20: =IF(A20<=前提条件!$C$89*12,前提条件!$C$90,0) -> 4166.6667 | S20: =IF(A20=1,前提条件!$C$91,0) -> 0
... A127: 120 | B127: =EDATE(前提条件!$C$11,A127-1) -> 50041 | C127: =YEAR(B127)+IF(MONTH(B127)>=7,1,0)-2027+48 -> 58 | D127: =前提条件!$C$26/365*DAY(EOMONTH(B127,0)) -> 31 | E127: 1 | F127: =前提条件!$C$64*D127*E127 -> 178250 | G127: =前提条件!$C$65*D127*E127 -> 2976 | H127: =(前提条件!$C$66+前提条件!$C$67)*D127 -> 6510 | I127: =前提条件!$C$74/12 -> 7500 | J127: =F127+G127-H127-I127 -> 167216 | K127: =K126+J127 -> 19688308 | L127: =MAX(前提条件!$C$94-K127,0) -> 0 | M127: =前提条件!$C$10 -> 37500 | N127: =J127-M127-R127-S127 -> 125549.33 | O127: =O126+N127 -> 14688308 | P127: =前提条件!$C$8-SUM(M$8:M127)+IF(前提条件!$C$86<3,前提条件!$C$85-SUM(R$8:R127),0) -> 0 | Q127: =IF(AND(K127>=前提条件!$C$94,K126<前提条件!$C$94),"◀投資回収","") | R127: =IF(A127<=前提条件!$C$89*12,前提条件!$C$90,0) -> 4166.6667 | S127: =IF(A127=1,前提条件!$C$91,0) -> 0

Sheet 年度別_償却
B1: 投資回収・減価償却 期別推移（10年）
B2: 単位：円 期＝7月〜翌6月。48期は2027年2月〜6月の5か月分。電気・付帯工事費は「前提条件」下部で入力
B4: 期 | C4: 期間 | D4: 月数 | E4: 純効果(CF) | F4: 減価償却費 (機械) | G4: 減価償却費 (電気・付帯工事) | H4: 一括費用 (電気・付帯工事) | I4: 利益影響 (償却後) | J4: 累計CF | K4: 未回収残高 | L4: 期末簿価 | M4: 累計利益影響
B5: 48 | C5: ="2026年7月〜2027年6月" -> 2026年7月〜2027年6月 | D5: =COUNTIF(投資回収_月次!$C$8:$C$127,B5) -> 5 | E5: =SUMIFS(投資回収_月次!$J$8:$J$127,投資回収_月次!$C$8:$C$127,B5) -> 807900 | F5: =SUMIFS(投資回収_月次!$M$8:$M$127,投資回収_月次!$C$8:$C$127,B5) -> 187500 | G5: =SUMIFS(投資回収_月次!$R$8:$R$127,投資回収_月次!$C$8:$C$127,B5) -> 20833.333 | H5: =SUMIFS(投資回収_月次!$S$8:$S$127,投資回収_月次!$C$8:$C$127,B5) -> 0 | I5: =E5-F5-G5-H5 -> 599566.67 | J5: =SUM(E$5:E5) -> 807900 | K5: =MAX(前提条件!$C$94-J5,0) -> 4192100 | L5: =前提条件!$C$8-SUM(F$5:F5)+IF(前提条件!$C$86<3,前提条件!$C$85-SUM(G$5:G5),0) -> 4791666.7 | M5: =SUM(I$5:I5) -> 599566.67
B6: 49 | C6: ="2027年7月〜2028年6月" -> 2027年7月〜2028年6月 | D6: =COUNTIF(投資回収_月次!$C$8:$C$127,B6) -> 12 | E6: =SUMIFS(投資回収_月次!$J$8:$J$127,投資回収_月次!$C$8:$C$127,B6) -> 1972776 | F6: =SUMIFS(投資回収_月次!$M$8:$M$127,投資回収_月次!$C$8:$C$127,B6) -> 450000 | G6: =SUMIFS(投資回収_月次!$R$8:$R$127,投資回収_月次!$C$8:$C$127,B6) -> 50000 | H6: =SUMIFS(投資回収_月次!$S$8:$S$127,投資回収_月次!$C$8:$C$127,B6) -> 0 | I6: =E6-F6-G6-H6 -> 1472776 | J6: =SUM(E$5:E6) -> 2780676 | K6: =MAX(前提条件!$C$94-J6,0) -> 2219324 | L6: =前提条件!$C$8-SUM(F$5:F6)+IF(前提条件!$C$86<3,前提条件!$C$85-SUM(G$5:G6),0) -> 4291666.7 | M6: =SUM(I$5:I6) -> 2072342.7
B7: 50 | C7: ="2028年7月〜2029年6月" -> 2028年7月〜2029年6月 | D7: =COUNTIF(投資回収_月次!$C$8:$C$127,B7) -> 12 | E7: =SUMIFS(投資回収_月次!$J$8:$J$127,投資回収_月次!$C$8:$C$127,B7) -> 1967140 | F7: =SUMIFS(投資回収_月次!$M$8:$M$127,投資回収_月次!$C$8:$C$127,B7) -> 450000 | G7: =SUMIFS(投資回収_月次!$R$8:$R$127,投資回収_月次!$C$8:$C$127,B7) -> 50000 | H7: =SUMIFS(投資回収_月次!$S$8:$S$127,投資回収_月次!$C$8:$C$127,B7) -> 0 | I7: =E7-F7-G7-H7 -> 1467140 | J7: =SUM(E$5:E7) -> 4747816 | K7: =MAX(前提条件!$C$94-J7,0) -> 252184 | L7: =前提条件!$C$8-SUM(F$5:F7)+IF(前提条件!$C$86<3,前提条件!$C$85-SUM(G$5:G7),0) -> 3791666.7 | M7: =SUM(I$5:I7) -> 3539482.7
B8: 51 | C8: ="2029年7月〜2030年6月" -> 2029年7月〜2030年6月 | D8: =COUNTIF(投資回収_月次!$C$8:$C$127,B8) -> 12 | E8: =SUMIFS(投資回収_月次!$J$8:$J$127,投資回収_月次!$C$8:$C$127,B8) -> 1967140 | F8: =SUMIFS(投資回収_月次!$M$8:$M$127,投資回収_月次!$C$8:$C$127,B8) -> 450000 | G8: =SUMIFS(投資回収_月次!$R$8:$R$127,投資回収_月次!$C$8:$C$127,B8) -> 50000 | H8: =SUMIFS(投資回収_月次!$S$8:$S$127,投資回収_月次!$C$8:$C$127,B8) -> 0 | I8: =E8-F8-G8-H8 -> 1467140 | J8: =SUM(E$5:E8) -> 6714956 | K8: =MAX(前提条件!$C$94-J8,0) -> 0 | L8: =前提条件!$C$8-SUM(F$5:F8)+IF(前提条件!$C$86<3,前提条件!$C$85-SUM(G$5:G8),0) -> 3291666.7 | M8: =SUM(I$5:I8) -> 5006622.7
B9: 52 | C9: ="2030年7月〜2031年6月" -> 2030年7月〜2031年6月 | D9: =COUNTIF(投資回収_月次!$C$8:$C$127,B9) -> 12 | E9: =SUMIFS(投資回収_月次!$J$8:$J$127,投資回収_月次!$C$8:$C$127,B9) -> 1967140 | F9: =SUMIFS(投資回収_月次!$M$8:$M$127,投資回収_月次!$C$8:$C$127,B9) -> 450000 | G9: =SUMIFS(投資回収_月次!$R$8:$R$127,投資回収_月次!$C$8:$C$127,B9) -> 50000 | H9: =SUMIFS(投資回収_月次!$S$8:$S$127,投資回収_月次!$C$8:$C$127,B9) -> 0 | I9: =E9-F9-G9-H9 -> 1467140 | J9: =SUM(E$5:E9) -> 8682096 | K9: =MAX(前提条件!$C$94-J9,0) -> 0 | L9: =前提条件!$C$8-SUM(F$5:F9)+IF(前提条件!$C$86<3,前提条件!$C$85-SUM(G$5:G9),0) -> 2791666.7 | M9: =SUM(I$5:I9) -> 6473762.7
B10: 53 | C10: ="2031年7月〜2032年6月" -> 2031年7月〜2032年6月 | D10: =COUNTIF(投資回収_月次!$C$8:$C$127,B10) -> 12 | E10: =SUMIFS(投資回収_月次!$J$8:$J$127,投資回収_月次!$C$8:$C$127,B10) -> 1972776 | F10: =SUMIFS(投資回収_月次!$M$8:$M$127,投資回収_月次!$C$8:$C$127,B10) -> 450000 | G10: =SUMIFS(投資回収_月次!$R$8:$R$127,投資回収_月次!$C$8:$C$127,B10) -> 50000 | H10: =SUMIFS(投資回収_月次!$S$8:$S$127,投資回収_月次!$C$8:$C$127,B10) -> 0 | I10: =E10-F10-G10-H10 -> 1472776 | J10: =SUM(E$5:E10) -> 10654872 | K10: =MAX(前提条件!$C$94-J10,0) -> 0 | L10: =前提条件!$C$8-SUM(F$5:F10)+IF(前提条件!$C$86<3,前提条件!$C$85-SUM(G$5:G10),0) -> 2291666.7 | M10: =SUM(I$5:I10) -> 7946538.7
B11: 54 | C11: ="2032年7月〜2033年6月" -> 2032年7月〜2033年6月 | D11: =COUNTIF(投資回収_月次!$C$8:$C$127,B11) -> 12 | E11: =SUMIFS(投資回収_月次!$J$8:$J$127,投資回収_月次!$C$8:$C$127,B11) -> 1967140 | F11: =SUMIFS(投資回収_月次!$M$8:$M$127,投資回収_月次!$C$8:$C$127,B11) -> 450000 | G11: =SUMIFS(投資回収_月次!$R$8:$R$127,投資回収_月次!$C$8:$C$127,B11) -> 50000 | H11: =SUMIFS(投資回収_月次!$S$8:$S$127,投資回収_月次!$C$8:$C$127,B11) -> 0 | I11: =E11-F11-G11-H11 -> 1467140 | J11: =SUM(E$5:E11) -> 12622012 | K11: =MAX(前提条件!$C$94-J11,0) -> 0 | L11: =前提条件!$C$8-SUM(F$5:F11)+IF(前提条件!$C$86<3,前提条件!$C$85-SUM(G$5:G11),0) -> 1791666.7 | M11: =SUM(I$5:I11) -> 9413678.7
B12: 55 | C12: ="2033年7月〜2034年6月" -> 2033年7月〜2034年6月 | D12: =COUNTIF(投資回収_月次!$C$8:$C$127,B12) -> 12 | E12: =SUMIFS(投資回収_月次!$J$8:$J$127,投資回収_月次!$C$8:$C$127,B12) -> 1967140 | F12: =SUMIFS(投資回収_月次!$M$8:$M$127,投資回収_月次!$C$8:$C$127,B12) -> 450000 | G12: =SUMIFS(投資回収_月次!$R$8:$R$127,投資回収_月次!$C$8:$C$127,B12) -> 50000 | H12: =SUMIFS(投資回収_月次!$S$8:$S$127,投資回収_月次!$C$8:$C$127,B12) -> 0 | I12: =E12-F12-G12-H12 -> 1467140 | J12: =SUM(E$5:E12) -> 14589152 | K12: =MAX(前提条件!$C$94-J12,0) -> 0 | L12: =前提条件!$C$8-SUM(F$5:F12)+IF(前提条件!$C$86<3,前提条件!$C$85-SUM(G$5:G12),0) -> 1291666.7 | M12: =SUM(I$5:I12) -> 10880819
B13: 56 | C13: ="2034年7月〜2035年6月" -> 2034年7月〜2035年6月 | D13: =COUNTIF(投資回収_月次!$C$8:$C$127,B13) -> 12 | E13: =SUMIFS(投資回収_月次!$J$8:$J$127,投資回収_月次!$C$8:$C$127,B13) -> 1967140 | F13: =SUMIFS(投資回収_月次!$M$8:$M$127,投資回収_月次!$C$8:$C$127,B13) -> 450000 | G13: =SUMIFS(投資回収_月次!$R$8:$R$127,投資回収_月次!$C$8:$C$127,B13) -> 50000 | H13: =SUMIFS(投資回収_月次!$S$8:$S$127,投資回収_月次!$C$8:$C$127,B13) -> 0 | I13: =E13-F13-G13-H13 -> 1467140 | J13: =SUM(E$5:E13) -> 16556292 | K13: =MAX(前提条件!$C$94-J13,0) -> 0 | L13: =前提条件!$C$8-SUM(F$5:F13)+IF(前提条件!$C$86<3,前提条件!$C$85-SUM(G$5:G13),0) -> 791666.67 | M13: =SUM(I$5:I13) -> 12347959
B14: 57 | C14: ="2035年7月〜2036年6月" -> 2035年7月〜2036年6月 | D14: =COUNTIF(投資回収_月次!$C$8:$C$127,B14) -> 12 | E14: =SUMIFS(投資回収_月次!$J$8:$J$127,投資回収_月次!$C$8:$C$127,B14) -> 1972776 | F14: =SUMIFS(投資回収_月次!$M$8:$M$127,投資回収_月次!$C$8:$C$127,B14) -> 450000 | G14: =SUMIFS(投資回収_月次!$R$8:$R$127,投資回収_月次!$C$8:$C$127,B14) -> 50000 | H14: =SUMIFS(投資回収_月次!$S$8:$S$127,投資回収_月次!$C$8:$C$127,B14) -> 0 | I14: =E14-F14-G14-H14 -> 1472776 | J14: =SUM(E$5:E14) -> 18529068 | K14: =MAX(前提条件!$C$94-J14,0) -> 0 | L14: =前提条件!$C$8-SUM(F$5:F14)+IF(前提条件!$C$86<3,前提条件!$C$85-SUM(G$5:G14),0) -> 291666.67 | M14: =SUM(I$5:I14) -> 13820735
B15: 58 | C15: ="2036年7月〜2037年6月" -> 2036年7月〜2037年6月 | D15: =COUNTIF(投資回収_月次!$C$8:$C$127,B15) -> 7 | E15: =SUMIFS(投資回収_月次!$J$8:$J$127,投資回収_月次!$C$8:$C$127,B15) -> 1159240 | F15: =SUMIFS(投資回収_月次!$M$8:$M$127,投資回収_月次!$C$8:$C$127,B15) -> 262500 | G15: =SUMIFS(投資回収_月次!$R$8:$R$127,投資回収_月次!$C$8:$C$127,B15) -> 29166.667 | H15: =SUMIFS(投資回収_月次!$S$8:$S$127,投資回収_月次!$C$8:$C$127,B15) -> 0 | I15: =E15-F15-G15-H15 -> 867573.33 | J15: =SUM(E$5:E15) -> 19688308 | K15: =MAX(前提条件!$C$94-J15,0) -> 0 | L15: =前提条件!$C$8-SUM(F$5:F15)+IF(前提条件!$C$86<3,前提条件!$C$85-SUM(G$5:G15),0) -> 0 | M15: =SUM(I$5:I15) -> 14688308
B16: 合計 | D16: =SUM(D5:D15) -> 120 | E16: =SUM(E5:E15) -> 19688308 | F16: =SUM(F5:F15) -> 4500000 | G16: =SUM(G5:G15) -> 500000 | H16: =SUM(H5:H15) -> 0 | I16: =SUM(I5:I15) -> 14688308
B18: 見方
B19: ・純効果(CF)＝人件費・絞り袋の削減額から電気・洗浄・保守部品費を差し引いた手残り（減価償却前）。投資回収はこの累計と総投資額（機械＋電気・付帯工事）で判定。
B20: ・利益影響＝純効果 − 減価償却費（機械・電気・付帯工事）− 電気・付帯工事の一括費用。PL（経常利益）に表れる金額。
B21: ・黄色の行＝投資額を回収し終える期。電気・付帯工事が15年償却（区分2）の場合、10年経過後も簿価が残ります。

Sheet 予算原本_白鳥惣菜
A1: 白鳥惣菜 ライン月別PL（17期予算）原本値
A2: 出典：経広_製造PL_17通期予算_2026.0618up エリア人件費修正.xls ／「ライン月別PL」シート（白鳥惣菜）。単位：千円。値を転記（編集しない）
A3: 科目 | B3: 7月 | C3: 8月 | D3: 9月 | E3: 10月 | F3: 11月 | G3: 12月 | H3: 1月 | I3: 2月 | J3: 3月 | K3: 4月 | L3: 5月 | M3: 6月 | N3: 17期合計
A4: 売 上 高 | B4: 787800 | C4: 836803.38 | D4: 747600 | E4: 772524.47 | F4: 750295.52 | G4: 847205.75 | H4: 770219.86 | I4: 729600 | J4: 826500 | K4: 792000 | L4: 802000 | M4: 777000 | N4: 9439549
A5: 売上総利益 | B5: 224170 | C5: 237991.38 | D5: 212690 | E5: 219664.47 | F5: 213231.52 | G5: 240495.75 | H5: 218795.86 | I5: 207111.4 | J5: 234509 | K5: 224780 | L5: 227600 | M5: 219247.27 | N5: 2680286.7
A6: 荒利率 | B6: 0.28455192 | C6: 0.28440538 | D6: 0.28449706 | E6: 0.28434629 | F6: 0.28419671 | G6: 0.28386936 | H6: 0.28406936 | I6: 0.28386979 | J6: 0.28373745 | K6: 0.28381313 | L6: 0.28379052 | M6: 0.28217152 | N6: 0.28394224
A7: 商品卸売上高 | B7: 785000 | C7: 834000 | D7: 745000 | E7: 770000 | F7: 748000 | G7: 845000 | H7: 768000 | I7: 727700 | J7: 824500 | K7: 790000 | L7: 800000 | M7: 775000 | N7: 9412200
A8: 荒利益高 | B8: 213520 | C8: 226848 | D8: 202640 | E8: 209440 | F8: 203456 | G8: 229840 | H8: 208896 | I8: 197934.4 | J8: 224264 | K8: 214880 | L8: 217600 | M8: 210800 | N8: 2560118.4
A9: 荒利率 | B9: 0.272 | C9: 0.272 | D9: 0.272 | E9: 0.272 | F9: 0.272 | G9: 0.272 | H9: 0.272 | I9: 0.272 | J9: 0.272 | K9: 0.272 | L9: 0.272 | M9: 0.272 | N9: 0.272
A10: 物流フィ高 | B10: 2800 | C10: 2803.384 | D10: 2600 | E10: 2524.471 | F10: 2295.52 | G10: 2205.75 | H10: 2219.863 | I10: 1900 | J10: 2000 | K10: 2000 | L10: 2000 | M10: 2000 | N10: 27348.988
A11: 物流フィ高及びサービスリサイクル料等 | B11: 2800 | C11: 2803.384 | D11: 2600 | E11: 2524.471 | F11: 2295.52 | G11: 2205.75 | H11: 2219.863 | I11: 1900 | J11: 2000 | K11: 2000 | L11: 2000 | M11: 2000 | N11: 27348.988
A12: 荒利率 | B12: 1 | C12: 1 | D12: 1 | E12: 1 | F12: 1 | G12: 1 | H12: 1 | I12: 1 | J12: 1 | K12: 1 | L12: 1 | M12: 1 | N12: 1
A13: 手数料等売上高 | B13: 0 | C13: 0 | D13: 0 | E13: 0 | F13: 0 | G13: 0 | H13: 0 | I13: 0 | J13: 0 | K13: 0 | L13: 0 | M13: 0 | N13: 0
A14: 手数料等 | B14: 0 | C14: 0 | D14: 0 | E14: 0 | F14: 0 | G14: 0 | H14: 0 | I14: 0 | J14: 0 | K14: 0 | L14: 0 | M14: 0 | N14: 0
A15: 荒利率 | B15: 0 | C15: 0 | D15: 0 | E15: 0 | F15: 0 | G15: 0 | H15: 0 | I15: 0 | J15: 0 | K15: 0 | L15: 0 | M15: 0 | N15: 0
... A66: 経常利益 | B66: 4992.2533 | C66: 11406.008 | D66: -2807.815 | E66: 1098.9632 | F66: 4249.4476 | G66: 8054.2711 | H66: -2319.8961 | I66: -2565.4817 | J66: 3454.5383 | K66: 3740.4383 | L66: 2410.4383 | M66: -3722.2931 | N66: 27990.872
A67: 経営効率(前期) | B67: 7月 | C67: 8月 | D67: 9月 | E67: 10月 | F67: 11月 | G67: 12月 | H67: 1月 | I67: 2月 | J67: 3月 | K67: 4月 | L67: 5月 | M67: 6月 | N67: 17期合計
A68: 労働分配率 | B68: 0.6132578 | C68: 0.58259672 | D68: 0.66670741 | E68: 0.6396073 | F68: 0.62629577 | G68: 0.60218112 | H68: 0.6614019 | I68: 0.65182795 | J68: 0.61271849 | K68: 0.6199217 | L68: 0.63422671 | M68: 0.65044368 | N68: 0.62922412
A69: 運賃分配率 | B69: 0.16938912 | C69: 0.1694764 | D69: 0.16942179 | E69: 0.16951162 | F69: 0.16960084 | G69: 0.16979642 | H69: 0.16967687 | I69: 0.16979616 | J69: 0.16987536 | K69: 0.16983006 | L69: 0.16984359 | M69: 0.17081809 | N69: 0.16975284
A70: 物流機能分配率 | B70: 0 | C70: 0 | D70: 0 | E70: 0 | F70: 0 | G70: 0 | H70: 0 | I70: 0 | J70: 0 | K70: 0 | L70: 0 | M70: 0 | N70: 0
A71: 設備分配率 | B71: 0.057776628 | C71: 0.054701364 | D71: 0.067005948 | E71: 0.065986221 | F71: 0.071494253 | G71: 0.063735686 | H71: 0.070056908 | I71: 0.075216341 | J71: 0.066428844 | K71: 0.069304038 | L71: 0.06844535 | M71: 0.071052934 | N71: 0.066600534
A72: 荒利率 | B72: 0.28455192 | C72: 0.28440538 | D72: 0.28449706 | E72: 0.28434629 | F72: 0.28419671 | G72: 0.28386936 | H72: 0.28406936 | I72: 0.28386979 | J72: 0.28373745 | K72: 0.28381313 | L72: 0.28379052 | M72: 0.28217152 | N72: 0.28394224
A73: 人件費率 | B73: 0.17450368 | C73: 0.16569364 | D73: 0.1896763 | E73: 0.18186997 | F73: 0.1779912 | G73: 0.17094077 | H73: 0.18788401 | I73: 0.18503427 | J73: 0.17385118 | K73: 0.17594192 | L73: 0.17998753 | M73: 0.18353668 | N73: 0.1786633
A74: 運賃費率 | B74: 0.0482 | C74: 0.0482 | D74: 0.0482 | E74: 0.0482 | F74: 0.0482 | G74: 0.0482 | H74: 0.0482 | I74: 0.0482 | J74: 0.0482 | K74: 0.0482 | L74: 0.0482 | M74: 0.0482 | N74: 0.0482
A75: 物流機能率 | B75: 0 | C75: 0 | D75: 0 | E75: 0 | F75: 0 | G75: 0 | H75: 0 | I75: 0 | J75: 0 | K75: 0 | L75: 0 | M75: 0 | N75: 0
A76: 設備費率 | B76: 0.01644045 | C76: 0.015557362 | D76: 0.019062995 | E76: 0.018762937 | F76: 0.020318432 | G76: 0.018092608 | H76: 0.019901021 | I76: 0.021351647 | J76: 0.018848351 | K76: 0.019669396 | L76: 0.019424142 | M76: 0.020049114 | N76: 0.018910705
A77: 売上対経常利益率 | B77: 0.0063369552 | C77: 0.013630451 | D77: -0.0037557718 | E77: 0.001422561 | F77: 0.0056636985 | G77: 0.0095068655 | H77: -0.003011992 | I77: -0.0035162852 | J77: 0.0041797197 | K77: 0.0047227756 | L77: 0.003005534 | M77: -0.004790596 | N77: 0.0029652764
A78: 売上対経費率 | B78: 0.27821496 | C78: 0.27077493 | D78: 0.28825283 | E78: 0.28292373 | F78: 0.27853301 | G78: 0.27436249 | H78: 0.28708135 | I78: 0.28738608 | J78: 0.27955773 | K78: 0.27909036 | L78: 0.28078499 | M78: 0.28696211 | N78: 0.28097696

Sheet 実績原本_白鳥惣菜_7-9月
A1: 白鳥惣菜 ライン月別PL（17期実績 7〜9月）原本値
A2: 出典：■CRAST_Line_PL17_9-1Q.xls ／「ライン月別PL」シート（白鳥惣菜）製造PL 17期 7〜9月実績。単位：千円。値を転記（編集しない）
A3: 科目 | B3: 7月 | C3: 8月 | D3: 9月 | E3: 7〜9月計
A4: 売 上 高 | B4: 859016.86 | C4: 980922.58 | D4: 810842.5 | E4: =SUM(B4:D4) -> 2650781.9
A5: 売上総利益 | B5: 243490.3 | C5: 282030.26 | D5: 246956.76 | E5: =SUM(B5:D5) -> 772477.31
A6: 荒利率 | B6: 0.28345229 | C6: 0.28751531 | D6: 0.3045681
A7: 商品卸売上高 | B7: 856552.1 | C7: 978185.97 | D7: 808524.62 | E7: =SUM(B7:D7) -> 2643262.7
A8: 荒利益高 | B8: 231367.24 | C8: 268948.59 | D8: 235658.63 | E8: =SUM(B8:D8) -> 735974.45
A9: 荒利率 | B9: 0.27011461 | C9: 0.27494627 | D9: 0.29146748
A10: 物流フィ高 | B10: 2464.763 | C10: 2736.609 | D10: 2317.878 | E10: =SUM(B10:D10) -> 7519.25
A11: 物流フィ高及びサービスリサイクル料等 | B11: 2464.763 | C11: 2736.609 | D11: 2317.878 | E11: =SUM(B11:D11) -> 7519.25
A12: 荒利率 | B12: 1 | C12: 1 | D12: 1
A13: 手数料等売上高 | B13: 0 | C13: 0 | D13: 0 | E13: =SUM(B13:D13) -> 0
A14: 手数料等 | B14: 0 | C14: 0 | D14: 0 | E14: =SUM(B14:D14) -> 0
A15: 荒利率 | B15: 0 | C15: 0 | D15: 0
A16: ④その他売上高 | B16: 0 | C16: 0 | D16: 0 | E16: =SUM(B16:D16) -> 0
A17: 販売奨励金 | B17: 9658.3004 | C17: 10345.059 | D17: 8980.2514 | E17: =SUM(B17:D17) -> 28983.611
A18: 荒利率 | B18: 0 | C18: 0 | D18: 0
A19: 人件費 | B19: 159123.95 | C19: 163148.19 | D19: 164121.69 | E19: =SUM(B19:D19) -> 486393.83
A20: 社員給与 | B20: 103680.97 | C20: 118115.4 | D20: 112717.35 | E20: =SUM(B20:D20) -> 334513.72
A21: 契約社員人件費 | B21: 0 | C21: 0 | D21: 0 | E21: =SUM(B21:D21) -> 0
A22: 雑給 | B22: 19396.332 | C22: 19221.482 | D22: 17675.614 | E22: =SUM(B22:D22) -> 56293.428
A23: 派遣代 | B23: 9197.121 | C23: -1271.735 | D23: 5864.168 | E23: =SUM(B23:D23) -> 13789.554
A24: 賞与 | B24: 5160 | C24: 5160 | D24: 5160 | E24: =SUM(B24:D24) -> 15480
A25: 法定福利費 | B25: 19189.69 | C25: 19595.368 | D25: 19894.275 | E25: =SUM(B25:D25) -> 58679.333
A26: 福利厚生費 | B26: 2499.8363 | C26: 2327.673 | D26: 2810.286 | E26: =SUM(B26:D26) -> 7637.7953
A27: 按分対象者人件費 | B27: 0 | C27: 0 | D27: 0 | E27: =SUM(B27:D27) -> 0
A28: 採用教育・退職金 | B28: 0 | C28: 0 | D28: 0 | E28: =SUM(B28:D28) -> 0
A29: 広告・販促費 | B29: 0 | C29: 0 | D29: 0 | E29: =SUM(B29:D29) -> 0
A30: 広告費 | B30: 0 | C30: 0 | D30: 0 | E30: =SUM(B30:D30) -> 0
... A66: 経常利益高 | B66: -21486.83 | C66: 21609.749 | D66: -1617.3532 | E66: =SUM(B66:D66) -> -1494.4344

Sheet 白鳥惣菜PL_導入効果
B1: 白鳥惣菜 ライン月別PL（48期＝製造PL 17期予算） 充填機導入（2027年2月1日）効果
B2: 単位：千円 ①予算は製造PL原本値、②は投資回収シートの月次効果を千円換算、③＝①＋②の影響
B4: 科目 | C4: 7月 | D4: 8月 | E4: 9月 | F4: 10月 | G4: 11月 | H4: 12月 | I4: 1月 | J4: 2月 | K4: 3月 | L4: 4月 | M4: 5月 | N4: 6月 | O4: 17期合計 | P4: 下期計 (1〜6月)
B5: （月度） | C5: =DATE(2026,7+0,1) -> 46204 | D5: =DATE(2026,7+1,1) -> 46235 | E5: =DATE(2026,7+2,1) -> 46266 | F5: =DATE(2026,7+3,1) -> 46296 | G5: =DATE(2026,7+4,1) -> 46327 | H5: =DATE(2026,7+5,1) -> 46357 | I5: =DATE(2026,7+6,1) -> 46388 | J5: =DATE(2026,7+7,1) -> 46419 | K5: =DATE(2026,7+8,1) -> 46447 | L5: =DATE(2026,7+9,1) -> 46478 | M5: =DATE(2026,7+10,1) -> 46508 | N5: =DATE(2026,7+11,1) -> 46539
B7: ① 17期予算（現行・製造部予算）
B8: 売 上 高 | C8: =予算原本_白鳥惣菜!B4 -> 787800 | D8: =予算原本_白鳥惣菜!C4 -> 836803.38 | E8: =予算原本_白鳥惣菜!D4 -> 747600 | F8: =予算原本_白鳥惣菜!E4 -> 772524.47 | G8: =予算原本_白鳥惣菜!F4 -> 750295.52 | H8: =予算原本_白鳥惣菜!G4 -> 847205.75 | I8: =予算原本_白鳥惣菜!H4 -> 770219.86 | J8: =予算原本_白鳥惣菜!I4 -> 729600 | ... N8: =予算原本_白鳥惣菜!M4 -> 777000 | O8: =SUM(C8:N8) -> 9439549 | P8: =SUM(I8:N8) -> 4697319.9
B9: 売上総利益 | C9: =予算原本_白鳥惣菜!B5 -> 224170 | D9: =予算原本_白鳥惣菜!C5 -> 237991.38 | E9: =予算原本_白鳥惣菜!D5 -> 212690 | F9: =予算原本_白鳥惣菜!E5 -> 219664.47 | G9: =予算原本_白鳥惣菜!F5 -> 213231.52 | H9: =予算原本_白鳥惣菜!G5 -> 240495.75 | I9: =予算原本_白鳥惣菜!H5 -> 218795.86 | J9: =予算原本_白鳥惣菜!I5 -> 207111.4 | ... N9: =予算原本_白鳥惣菜!M5 -> 219247.27 | O9: =SUM(C9:N9) -> 2680286.7 | P9: =SUM(I9:N9) -> 1332043.5
B10: 荒利率 | C10: =予算原本_白鳥惣菜!B6 -> 0.28455192 | D10: =予算原本_白鳥惣菜!C6 -> 0.28440538 | E10: =予算原本_白鳥惣菜!D6 -> 0.28449706 | F10: =予算原本_白鳥惣菜!E6 -> 0.28434629 | G10: =予算原本_白鳥惣菜!F6 -> 0.28419671 | H10: =予算原本_白鳥惣菜!G6 -> 0.28386936 | I10: =予算原本_白鳥惣菜!H6 -> 0.28406936 | J10: =予算原本_白鳥惣菜!I6 -> 0.28386979 | ... N10: =予算原本_白鳥惣菜!M6 -> 0.28217152 | O10: =IF(O8=0,0,O9/O8) -> 0.28394224 | P10: =IF(P8=0,0,P9/P8) -> 0.28357522
B11: 商品卸売上高 | C11: =予算原本_白鳥惣菜!B7 -> 785000 | D11: =予算原本_白鳥惣菜!C7 -> 834000 | E11: =予算原本_白鳥惣菜!D7 -> 745000 | F11: =予算原本_白鳥惣菜!E7 -> 770000 | G11: =予算原本_白鳥惣菜!F7 -> 748000 | H11: =予算原本_白鳥惣菜!G7 -> 845000 | I11: =予算原本_白鳥惣菜!H7 -> 768000 | J11: =予算原本_白鳥惣菜!I7 -> 727700 | ... N11: =予算原本_白鳥惣菜!M7 -> 775000 | O11: =SUM(C11:N11) -> 9412200 | P11: =SUM(I11:N11) -> 4685200
B12: 荒利益高 | C12: =予算原本_白鳥惣菜!B8 -> 213520 | D12: =予算原本_白鳥惣菜!C8 -> 226848 | E12: =予算原本_白鳥惣菜!D8 -> 202640 | F12: =予算原本_白鳥惣菜!E8 -> 209440 | G12: =予算原本_白鳥惣菜!F8 -> 203456 | H12: =予算原本_白鳥惣菜!G8 -> 229840 | I12: =予算原本_白鳥惣菜!H8 -> 208896 | J12: =予算原本_白鳥惣菜!I8 -> 197934.4 | ... N12: =予算原本_白鳥惣菜!M8 -> 210800 | O12: =SUM(C12:N12) -> 2560118.4 | P12: =SUM(I12:N12) -> 1274374.4
B13: 荒利率 | C13: =予算原本_白鳥惣菜!B9 -> 0.272 | D13: =予算原本_白鳥惣菜!C9 -> 0.272 | E13: =予算原本_白鳥惣菜!D9 -> 0.272 | F13: =予算原本_白鳥惣菜!E9 -> 0.272 | G13: =予算原本_白鳥惣菜!F9 -> 0.272 | H13: =予算原本_白鳥惣菜!G9 -> 0.272 | I13: =予算原本_白鳥惣菜!H9 -> 0.272 | J13: =予算原本_白鳥惣菜!I9 -> 0.272 | ... N13: =予算原本_白鳥惣菜!M9 -> 0.272 | O13: =IF(O11=0,0,O12/O11) -> 0.272 | P13: =IF(P11=0,0,P12/P11) -> 0.272
B14: 物流フィ高 | C14: =予算原本_白鳥惣菜!B10 -> 2800 | D14: =予算原本_白鳥惣菜!C10 -> 2803.384 | E14: =予算原本_白鳥惣菜!D10 -> 2600 | F14: =予算原本_白鳥惣菜!E10 -> 2524.471 | G14: =予算原本_白鳥惣菜!F10 -> 2295.52 | H14: =予算原本_白鳥惣菜!G10 -> 2205.75 | I14: =予算原本_白鳥惣菜!H10 -> 2219.863 | J14: =予算原本_白鳥惣菜!I10 -> 1900 | ... N14: =予算原本_白鳥惣菜!M10 -> 2000 | O14: =SUM(C14:N14) -> 27348.988 | P14: =SUM(I14:N14) -> 12119.863
B15: 物流フィ高及びサービスリサイクル料等 | C15: =予算原本_白鳥惣菜!B11 -> 2800 | D15: =予算原本_白鳥惣菜!C11 -> 2803.384 | E15: =予算原本_白鳥惣菜!D11 -> 2600 | F15: =予算原本_白鳥惣菜!E11 -> 2524.471 | G15: =予算原本_白鳥惣菜!F11 -> 2295.52 | H15: =予算原本_白鳥惣菜!G11 -> 2205.75 | I15: =予算原本_白鳥惣菜!H11 -> 2219.863 | J15: =予算原本_白鳥惣菜!I11 -> 1900 | ... N15: =予算原本_白鳥惣菜!M11 -> 2000 | O15: =SUM(C15:N15) -> 27348.988 | P15: =SUM(I15:N15) -> 12119.863
B16: 荒利率 | C16: =予算原本_白鳥惣菜!B12 -> 1 | D16: =予算原本_白鳥惣菜!C12 -> 1 | E16: =予算原本_白鳥惣菜!D12 -> 1 | F16: =予算原本_白鳥惣菜!E12 -> 1 | G16: =予算原本_白鳥惣菜!F12 -> 1 | H16: =予算原本_白鳥惣菜!G12 -> 1 | I16: =予算原本_白鳥惣菜!H12 -> 1 | J16: =予算原本_白鳥惣菜!I12 -> 1 | ... N16: =予算原本_白鳥惣菜!M12 -> 1 | O16: =IF(O14=0,0,O15/O14) -> 1 | P16: =IF(P14=0,0,P15/P14) -> 1
B17: 手数料等売上高 | C17: =予算原本_白鳥惣菜!B13 -> 0 | D17: =予算原本_白鳥惣菜!C13 -> 0 | E17: =予算原本_白鳥惣菜!D13 -> 0 | F17: =予算原本_白鳥惣菜!E13 -> 0 | G17: =予算原本_白鳥惣菜!F13 -> 0 | H17: =予算原本_白鳥惣菜!G13 -> 0 | I17: =予算原本_白鳥惣菜!H13 -> 0 | J17: =予算原本_白鳥惣菜!I13 -> 0 | ... N17: =予算原本_白鳥惣菜!M13 -> 0 | O17: =SUM(C17:N17) -> 0 | P17: =SUM(I17:N17) -> 0
B18: 手数料等 | C18: =予算原本_白鳥惣菜!B14 -> 0 | D18: =予算原本_白鳥惣菜!C14 -> 0 | E18: =予算原本_白鳥惣菜!D14 -> 0 | F18: =予算原本_白鳥惣菜!E14 -> 0 | G18: =予算原本_白鳥惣菜!F14 -> 0 | H18: =予算原本_白鳥惣菜!G14 -> 0 | I18: =予算原本_白鳥惣菜!H14 -> 0 | J18: =予算原本_白鳥惣菜!I14 -> 0 | ... N18: =予算原本_白鳥惣菜!M14 -> 0 | O18: =SUM(C18:N18) -> 0 | P18: =SUM(I18:N18) -> 0
B19: 荒利率 | C19: =予算原本_白鳥惣菜!B15 -> 0 | D19: =予算原本_白鳥惣菜!C15 -> 0 | E19: =予算原本_白鳥惣菜!D15 -> 0 | F19: =予算原本_白鳥惣菜!E15 -> 0 | G19: =予算原本_白鳥惣菜!F15 -> 0 | H19: =予算原本_白鳥惣菜!G15 -> 0 | I19: =予算原本_白鳥惣菜!H15 -> 0 | J19: =予算原本_白鳥惣菜!I15 -> 0 | ... N19: =予算原本_白鳥惣菜!M15 -> 0 | O19: =IF(O17=0,0,O18/O17) -> 0 | P19: =IF(P17=0,0,P18/P17) -> 0
B20: ④その他売上高 | C20: =予算原本_白鳥惣菜!B16 -> 0 | D20: =予算原本_白鳥惣菜!C16 -> 0 | E20: =予算原本_白鳥惣菜!D16 -> 0 | F20: =予算原本_白鳥惣菜!E16 -> 0 | G20: =予算原本_白鳥惣菜!F16 -> 0 | H20: =予算原本_白鳥惣菜!G16 -> 0 | I20: =予算原本_白鳥惣菜!H16 -> 0 | J20: =予算原本_白鳥惣菜!I16 -> 0 | ... N20: =予算原本_白鳥惣菜!M16 -> 0 | O20: =SUM(C20:N20) -> 0 | P20: =SUM(I20:N20) -> 0
B21: 販売奨励金 | C21: =予算原本_白鳥惣菜!B17 -> 7850 | D21: =予算原本_白鳥惣菜!C17 -> 8340 | E21: =予算原本_白鳥惣菜!D17 -> 7450 | F21: =予算原本_白鳥惣菜!E17 -> 7700 | G21: =予算原本_白鳥惣菜!F17 -> 7480 | H21: =予算原本_白鳥惣菜!G17 -> 8450 | I21: =予算原本_白鳥惣菜!H17 -> 7680 | J21: =予算原本_白鳥惣菜!I17 -> 7277 | ... N21: =予算原本_白鳥惣菜!M17 -> 6447.2686 | O21: =SUM(C21:N21) -> 92819.269 | P21: =SUM(I21:N21) -> 45549.269
B22: 荒利率 | C22: =予算原本_白鳥惣菜!B18 -> 0 | D22: =予算原本_白鳥惣菜!C18 -> 0 | E22: =予算原本_白鳥惣菜!D18 -> 0 | F22: =予算原本_白鳥惣菜!E18 -> 0 | G22: =予算原本_白鳥惣菜!F18 -> 0 | H22: =予算原本_白鳥惣菜!G18 -> 0 | I22: =予算原本_白鳥惣菜!H18 -> 0 | J22: =予算原本_白鳥惣菜!I18 -> 0 | ... N22: =予算原本_白鳥惣菜!M18 -> 0 | O22: =IF(O20=0,0,O21/O20) -> 0 | P22: =IF(P20=0,0,P21/P20) -> 0
B23: 人件費 | C23: =予算原本_白鳥惣菜!B19 -> 137474 | D23: =予算原本_白鳥惣菜!C19 -> 138653 | E23: =予算原本_白鳥惣菜!D19 -> 141802 | F23: =予算原本_白鳥惣菜!E19 -> 140499 | G23: =予算原本_白鳥惣菜!F19 -> 133546 | H23: =予算原本_白鳥惣菜!G19 -> 144822 | I23: =予算原本_白鳥惣菜!H19 -> 144712 | J23: =予算原本_白鳥惣菜!I19 -> 135001 | ... N23: =予算原本_白鳥惣菜!M19 -> 142608 | O23: =SUM(C23:N23) -> 1686501 | P23: =SUM(I23:N23) -> 849705
B24: 社員給与 | C24: =予算原本_白鳥惣菜!B20 -> 89240 | D24: =予算原本_白鳥惣菜!C20 -> 91540 | E24: =予算原本_白鳥惣菜!D20 -> 97500 | F24: =予算原本_白鳥惣菜!E20 -> 96250 | G24: =予算原本_白鳥惣菜!F20 -> 86900 | H24: =予算原本_白鳥惣菜!G20 -> 94800 | I24: =予算原本_白鳥惣菜!H20 -> 99450 | J24: =予算原本_白鳥惣菜!I20 -> 90475 | ... N24: =予算原本_白鳥惣菜!M20 -> 97500 | O24: =SUM(C24:N24) -> 1129905 | P24: =SUM(I24:N24) -> 573675
B25: 契約社員人件費 | C25: =予算原本_白鳥惣菜!B21 -> 0 | D25: =予算原本_白鳥惣菜!C21 -> 0 | E25: =予算原本_白鳥惣菜!D21 -> 0 | F25: =予算原本_白鳥惣菜!E21 -> 0 | G25: =予算原本_白鳥惣菜!F21 -> 0 | H25: =予算原本_白鳥惣菜!G21 -> 0 | I25: =予算原本_白鳥惣菜!H21 -> 0 | J25: =予算原本_白鳥惣菜!I21 -> 0 | ... N25: =予算原本_白鳥惣菜!M21 -> 0 | O25: =SUM(C25:N25) -> 0 | P25: =SUM(I25:N25) -> 0
B26: 雑 給 | C26: =予算原本_白鳥惣菜!B22 -> 18960 | D26: =予算原本_白鳥惣菜!C22 -> 19440 | E26: =予算原本_白鳥惣菜!D22 -> 18000 | F26: =予算原本_白鳥惣菜!E22 -> 18120 | G26: =予算原本_白鳥惣菜!F22 -> 18724 | H26: =予算原本_白鳥惣菜!G22 -> 20336 | I26: =予算原本_白鳥惣菜!H22 -> 18600 | J26: =予算原本_白鳥惣菜!I22 -> 18450 | ... N26: =予算原本_白鳥惣菜!M22 -> 18724 | O26: =SUM(C26:N26) -> 227386 | P26: =SUM(I26:N26) -> 113806
B27: 派遣代 | C27: =予算原本_白鳥惣菜!B23 -> 1000 | D27: =予算原本_白鳥惣菜!C23 -> 2000 | E27: =予算原本_白鳥惣菜!D23 -> 100 | F27: =予算原本_白鳥惣菜!E23 -> 100 | G27: =予算原本_白鳥惣菜!F23 -> 100 | H27: =予算原本_白鳥惣菜!G23 -> 3500 | I27: =予算原本_白鳥惣菜!H23 -> 100 | J27: =予算原本_白鳥惣菜!I23 -> 1000 | ... N27: =予算原本_白鳥惣菜!M23 -> 100 | O27: =SUM(C27:N27) -> 10600 | P27: =SUM(I27:N27) -> 3800
B28: 賞 与 | C28: =予算原本_白鳥惣菜!B24 -> 5160 | D28: =予算原本_白鳥惣菜!C24 -> 5160 | E28: =予算原本_白鳥惣菜!D24 -> 5160 | F28: =予算原本_白鳥惣菜!E24 -> 5160 | G28: =予算原本_白鳥惣菜!F24 -> 5160 | H28: =予算原本_白鳥惣菜!G24 -> 5160 | I28: =予算原本_白鳥惣菜!H24 -> 5160 | J28: =予算原本_白鳥惣菜!I24 -> 5160 | ... N28: =予算原本_白鳥惣菜!M24 -> 5160 | O28: =SUM(C28:N28) -> 61920 | P28: =SUM(I28:N28) -> 30960
B29: 法定福利費 | C29: =予算原本_白鳥惣菜!B25 -> 16269 | D29: =予算原本_白鳥惣菜!C25 -> 16668 | E29: =予算原本_白鳥惣菜!D25 -> 17397 | F29: =予算原本_白鳥惣菜!E25 -> 17224 | G29: =予算原本_白鳥惣菜!F25 -> 15892 | H29: =予算原本_白鳥惣菜!G25 -> 17256 | I29: =予算原本_白鳥惣菜!H25 -> 17757 | J29: =予算原本_白鳥惣菜!I25 -> 16396 | ... N29: =予算原本_白鳥惣菜!M25 -> 17479 | O29: =SUM(C29:N29) -> 204050 | P29: =SUM(I29:N29) -> 103344
B30: 福利厚生費 | C30: =予算原本_白鳥惣菜!B26 -> 6835 | D30: =予算原本_白鳥惣菜!C26 -> 3835 | E30: =予算原本_白鳥惣菜!D26 -> 3635 | F30: =予算原本_白鳥惣菜!E26 -> 3635 | G30: =予算原本_白鳥惣菜!F26 -> 6760 | H30: =予算原本_白鳥惣菜!G26 -> 3760 | I30: =予算原本_白鳥惣菜!H26 -> 3635 | J30: =予算原本_白鳥惣菜!I26 -> 3510 | ... N30: =予算原本_白鳥惣菜!M26 -> 3635 | O30: =SUM(C30:N30) -> 52520 | P30: =SUM(I30:N30) -> 24060
B31: 按分対象者人件費 | C31: =予算原本_白鳥惣菜!B27 -> 0 | D31: =予算原本_白鳥惣菜!C27 -> 0 | E31: =予算原本_白鳥惣菜!D27 -> 0 | F31: =予算原本_白鳥惣菜!E27 -> 0 | G31: =予算原本_白鳥惣菜!F27 -> 0 | H31: =予算原本_白鳥惣菜!G27 -> 0 | I31: =予算原本_白鳥惣菜!H27 -> 0 | J31: =予算原本_白鳥惣菜!I27 -> 0 | ... N31: =予算原本_白鳥惣菜!M27 -> 0 | O31: =SUM(C31:N31) -> 0 | P31: =SUM(I31:N31) -> 0
B32: 採用教育・退職金 | C32: =予算原本_白鳥惣菜!B28 -> 10 | D32: =予算原本_白鳥惣菜!C28 -> 10 | E32: =予算原本_白鳥惣菜!D28 -> 10 | F32: =予算原本_白鳥惣菜!E28 -> 10 | G32: =予算原本_白鳥惣菜!F28 -> 10 | H32: =予算原本_白鳥惣菜!G28 -> 10 | I32: =予算原本_白鳥惣菜!H28 -> 10 | J32: =予算原本_白鳥惣菜!I28 -> 10 | ... N32: =予算原本_白鳥惣菜!M28 -> 10 | O32: =SUM(C32:N32) -> 120 | P32: =SUM(I32:N32) -> 60
B33: 広告・販促費 | C33: =予算原本_白鳥惣菜!B29 -> 0 | D33: =予算原本_白鳥惣菜!C29 -> 0 | E33: =予算原本_白鳥惣菜!D29 -> 0 | F33: =予算原本_白鳥惣菜!E29 -> 0 | G33: =予算原本_白鳥惣菜!F29 -> 0 | H33: =予算原本_白鳥惣菜!G29 -> 0 | I33: =予算原本_白鳥惣菜!H29 -> 0 | J33: =予算原本_白鳥惣菜!I29 -> 0 | ... N33: =予算原本_白鳥惣菜!M29 -> 0 | O33: =SUM(C33:N33) -> 0 | P33: =SUM(I33:N33) -> 0
B34: 広告費 | C34: =予算原本_白鳥惣菜!B30 -> 0 | D34: =予算原本_白鳥惣菜!C30 -> 0 | E34: =予算原本_白鳥惣菜!D30 -> 0 | F34: =予算原本_白鳥惣菜!E30 -> 0 | G34: =予算原本_白鳥惣菜!F30 -> 0 | H34: =予算原本_白鳥惣菜!G30 -> 0 | I34: =予算原本_白鳥惣菜!H30 -> 0 | J34: =予算原本_白鳥惣菜!I30 -> 0 | ... N34: =予算原本_白鳥惣菜!M30 -> 0 | O34: =SUM(C34:N34) -> 0 | P34: =SUM(I34:N34) -> 0
... B50: 発送配達費（運賃） | C50: =予算原本_白鳥惣菜!B46 -> 37971.96 | D50: =予算原本_白鳥惣菜!C46 -> 40333.923 | E50: =予算原本_白鳥惣菜!D46 -> 36034.32 | F50: =予算原本_白鳥惣菜!E46 -> 37235.679 | G50: =予算原本_白鳥惣菜!F46 -> 36164.244 | H50: =予算原本_白鳥惣菜!G46 -> 40835.317 | I50: =予算原本_白鳥惣菜!H46 -> 37124.597 | J50: =予算原本_白鳥惣菜!I46 -> 35166.72 | ... N50: =予算原本_白鳥惣菜!M46 -> 37451.4 | O50: =SUM(C50:N50) -> 454986.26 | P50: =SUM(I50:N50) -> 226410.82
B51: 物流費（料率） | C51: =予算原本_白鳥惣菜!B47 -> 0 | D51: =予算原本_白鳥惣菜!C47 -> 0 | E51: =予算原本_白鳥惣菜!D47 -> 0 | F51: =予算原本_白鳥惣菜!E47 -> 0 | G51: =予算原本_白鳥惣菜!F47 -> 0 | H51: =予算原本_白鳥惣菜!G47 -> 0 | I51: =予算原本_白鳥惣菜!H47 -> 0 | J51: =予算原本_白鳥惣菜!I47 -> 0 | ... N51: =予算原本_白鳥惣菜!M47 -> 0 | O51: =IF(O49=0,0,O50/O49) -> 0 | P51: =IF(P49=0,0,P50/P49) -> 0
B52: 物流費（料率外） | C52: =予算原本_白鳥惣菜!B48 -> 0 | D52: =予算原本_白鳥惣菜!C48 -> 0 | E52: =予算原本_白鳥惣菜!D48 -> 0 | F52: =予算原本_白鳥惣菜!E48 -> 0 | G52: =予算原本_白鳥惣菜!F48 -> 0 | H52: =予算原本_白鳥惣菜!G48 -> 0 | I52: =予算原本_白鳥惣菜!H48 -> 0 | J52: =予算原本_白鳥惣菜!I48 -> 0 | ... N52: =予算原本_白鳥惣菜!M48 -> 0 | O52: =IF(O50=0,0,O51/O50) -> 0 | P52: =IF(P50=0,0,P51/P50) -> 0
B53: 支払手数料 | C53: =予算原本_白鳥惣菜!B49 -> 8837 | D53: =予算原本_白鳥惣菜!C49 -> 8837 | E53: =予算原本_白鳥惣菜!D49 -> 8837 | F53: =予算原本_白鳥惣菜!E49 -> 8837 | G53: =予算原本_白鳥惣菜!F49 -> 8962 | H53: =予算原本_白鳥惣菜!G49 -> 8962 | I53: =予算原本_白鳥惣菜!H49 -> 8837 | J53: =予算原本_白鳥惣菜!I49 -> 8812 | ... N53: =予算原本_白鳥惣菜!M49 -> 8962 | O53: =SUM(C53:N53) -> 106319 | P53: =SUM(I53:N53) -> 53047
B54: 車両費 | C54: =予算原本_白鳥惣菜!B50 -> 0 | D54: =予算原本_白鳥惣菜!C50 -> 0 | E54: =予算原本_白鳥惣菜!D50 -> 0 | F54: =予算原本_白鳥惣菜!E50 -> 0 | G54: =予算原本_白鳥惣菜!F50 -> 0 | H54: =予算原本_白鳥惣菜!G50 -> 0 | I54: =予算原本_白鳥惣菜!H50 -> 0 | J54: =予算原本_白鳥惣菜!I50 -> 0 | ... N54: =予算原本_白鳥惣菜!M50 -> 0 | O54: =SUM(C54:N54) -> 0 | P54: =SUM(I54:N54) -> 0
B55: 新聞図書費 | C55: =予算原本_白鳥惣菜!B51 -> 0 | D55: =予算原本_白鳥惣菜!C51 -> 0 | E55: =予算原本_白鳥惣菜!D51 -> 0 | F55: =予算原本_白鳥惣菜!E51 -> 0 | G55: =予算原本_白鳥惣菜!F51 -> 0 | H55: =予算原本_白鳥惣菜!G51 -> 0 | I55: =予算原本_白鳥惣菜!H51 -> 0 | J55: =予算原本_白鳥惣菜!I51 -> 0 | ... N55: =予算原本_白鳥惣菜!M51 -> 0 | O55: =SUM(C55:N55) -> 0 | P55: =SUM(I55:N55) -> 0
B56: リース料 | C56: =予算原本_白鳥惣菜!B52 -> 1032 | D56: =予算原本_白鳥惣菜!C52 -> 1032 | E56: =予算原本_白鳥惣菜!D52 -> 1032 | F56: =予算原本_白鳥惣菜!E52 -> 1032 | G56: =予算原本_白鳥惣菜!F52 -> 1032 | H56: =予算原本_白鳥惣菜!G52 -> 1032 | I56: =予算原本_白鳥惣菜!H52 -> 1032 | J56: =予算原本_白鳥惣菜!I52 -> 1032 | ... N56: =予算原本_白鳥惣菜!M52 -> 1032 | O56: =SUM(C56:N56) -> 12384 | P56: =SUM(I56:N56) -> 6192
B57: 顧問料 | C57: =予算原本_白鳥惣菜!B53 -> 0 | D57: =予算原本_白鳥惣菜!C53 -> 0 | E57: =予算原本_白鳥惣菜!D53 -> 0 | F57: =予算原本_白鳥惣菜!E53 -> 0 | G57: =予算原本_白鳥惣菜!F53 -> 0 | H57: =予算原本_白鳥惣菜!G53 -> 0 | I57: =予算原本_白鳥惣菜!H53 -> 0 | J57: =予算原本_白鳥惣菜!I53 -> 0 | ... N57: =予算原本_白鳥惣菜!M53 -> 0 | O57: =SUM(C57:N57) -> 0 | P57: =SUM(I57:N57) -> 0
B58: 雑 費 | C58: =予算原本_白鳥惣菜!B54 -> 10 | D58: =予算原本_白鳥惣菜!C54 -> 10 | E58: =予算原本_白鳥惣菜!D54 -> 10 | F58: =予算原本_白鳥惣菜!E54 -> 10 | G58: =予算原本_白鳥惣菜!F54 -> 10 | H58: =予算原本_白鳥惣菜!G54 -> 10 | I58: =予算原本_白鳥惣菜!H54 -> 10 | J58: =予算原本_白鳥惣菜!I54 -> 10 | ... N58: =予算原本_白鳥惣菜!M54 -> 10 | O58: =SUM(C58:N58) -> 120 | P58: =SUM(I58:N58) -> 60
B59: 減価償却費 | C59: =予算原本_白鳥惣菜!B55 -> 9850.1867 | D59: =予算原本_白鳥惣菜!C55 -> 9916.8533 | E59: =予算原本_白鳥惣菜!D55 -> 11149.895 | F59: =予算原本_白鳥惣菜!E55 -> 11393.228 | G59: =予算原本_白鳥惣菜!F55 -> 12143.228 | H59: =予算原本_白鳥惣菜!G55 -> 12226.562 | I59: =予算原本_白鳥惣菜!H55 -> 12226.562 | J59: =予算原本_白鳥惣菜!I55 -> 12476.562 | ... N59: =予算原本_白鳥惣菜!M55 -> 12476.562 | O59: =SUM(C59:N59) -> 141289.32 | P59: =SUM(I59:N59) -> 74609.37
B60: 保守契約料 | C60: =予算原本_白鳥惣菜!B56 -> 984 | D60: =予算原本_白鳥惣菜!C56 -> 984 | E60: =予算原本_白鳥惣菜!D56 -> 1014 | F60: =予算原本_白鳥惣菜!E56 -> 1160 | G60: =予算原本_白鳥惣菜!F56 -> 1506 | H60: =予算原本_白鳥惣菜!G56 -> 1605 | I60: =予算原本_白鳥惣菜!H56 -> 1285 | J60: =予算原本_白鳥惣菜!I56 -> 1160 | ... N60: =予算原本_白鳥惣菜!M56 -> 1741 | O60: =SUM(C60:N60) -> 15113 | P60: =SUM(I60:N60) -> 7860
B61: 外注費（派遣など） | C61: =予算原本_白鳥惣菜!B57 -> 300 | D61: =予算原本_白鳥惣菜!C57 -> 300 | E61: =予算原本_白鳥惣菜!D57 -> 300 | F61: =予算原本_白鳥惣菜!E57 -> 300 | G61: =予算原本_白鳥惣菜!F57 -> 300 | H61: =予算原本_白鳥惣菜!G57 -> 300 | I61: =予算原本_白鳥惣菜!H57 -> 300 | J61: =予算原本_白鳥惣菜!I57 -> 300 | ... N61: =予算原本_白鳥惣菜!M57 -> 300 | O61: =SUM(C61:N61) -> 3600 | P61: =SUM(I61:N61) -> 1800
B62: 経費合計 | C62: =予算原本_白鳥惣菜!B58 -> 219177.75 | D62: =予算原本_白鳥惣菜!C58 -> 226585.38 | E62: =予算原本_白鳥惣菜!D58 -> 215497.82 | F62: =予算原本_白鳥惣菜!E58 -> 218565.51 | G62: =予算原本_白鳥惣菜!F58 -> 208982.07 | H62: =予算原本_白鳥惣菜!G58 -> 232441.48 | I62: =予算原本_白鳥惣菜!H58 -> 221115.76 | J62: =予算原本_白鳥惣菜!I58 -> 209676.88 | ... N62: =予算原本_白鳥惣菜!M58 -> 222969.56 | O62: =SUM(C62:N62) -> 2652295.8 | P62: =SUM(I62:N62) -> 1331045.8
B63: 受取家賃 | C63: =予算原本_白鳥惣菜!B59 -> 0 | D63: =予算原本_白鳥惣菜!C59 -> 0 | E63: =予算原本_白鳥惣菜!D59 -> 0 | F63: =予算原本_白鳥惣菜!E59 -> 0 | G63: =予算原本_白鳥惣菜!F59 -> 0 | H63: =予算原本_白鳥惣菜!G59 -> 0 | I63: =予算原本_白鳥惣菜!H59 -> 0 | J63: =予算原本_白鳥惣菜!I59 -> 0 | ... N63: =予算原本_白鳥惣菜!M59 -> 0 | O63: =SUM(C63:N63) -> 0 | P63: =SUM(I63:N63) -> 0
B64: 営業利益高 | C64: =予算原本_白鳥惣菜!B60 -> 4992.2533 | D64: =予算原本_白鳥惣菜!C60 -> 11406.008 | E64: =予算原本_白鳥惣菜!D60 -> -2807.815 | F64: =予算原本_白鳥惣菜!E60 -> 1098.9632 | G64: =予算原本_白鳥惣菜!F60 -> 4249.4476 | H64: =予算原本_白鳥惣菜!G60 -> 8054.2711 | I64: =予算原本_白鳥惣菜!H60 -> -2319.8961 | J64: =予算原本_白鳥惣菜!I60 -> -2565.4817 | ... N64: =予算原本_白鳥惣菜!M60 -> -3722.2931 | O64: =SUM(C64:N64) -> 27990.872 | P64: =SUM(I64:N64) -> 997.744
... B70: 経常利益 | C70: =予算原本_白鳥惣菜!B66 -> 4992.2533 | D70: =予算原本_白鳥惣菜!C66 -> 11406.008 | E70: =予算原本_白鳥惣菜!D66 -> -2807.815 | F70: =予算原本_白鳥惣菜!E66 -> 1098.9632 | G70: =予算原本_白鳥惣菜!F66 -> 4249.4476 | H70: =予算原本_白鳥惣菜!G66 -> 8054.2711 | I70: =予算原本_白鳥惣菜!H66 -> -2319.8961 | J70: =予算原本_白鳥惣菜!I66 -> -2565.4817 | ... N70: =予算原本_白鳥惣菜!M66 -> -3722.2931 | O70: =SUM(C70:N70) -> 27990.872 | P70: =SUM(I70:N70) -> 997.744
B72: ② 充填機導入による増減（経費のプラスは費用増、マイナスは費用減）
B73: 稼働日数（日） | C73: =SUMIFS(投資回収_月次!$D$8:$D$127,投資回収_月次!$B$8:$B$127,C$5) -> 0 | D73: =SUMIFS(投資回収_月次!$D$8:$D$127,投資回収_月次!$B$8:$B$127,D$5) -> 0 | E73: =SUMIFS(投資回収_月次!$D$8:$D$127,投資回収_月次!$B$8:$B$127,E$5) -> 0 | F73: =SUMIFS(投資回収_月次!$D$8:$D$127,投資回収_月次!$B$8:$B$127,F$5) -> 0 | G73: =SUMIFS(投資回収_月次!$D$8:$D$127,投資回収_月次!$B$8:$B$127,G$5) -> 0 | H73: =SUMIFS(投資回収_月次!$D$8:$D$127,投資回収_月次!$B$8:$B$127,H$5) -> 0 | I73: =SUMIFS(投資回収_月次!$D$8:$D$127,投資回収_月次!$B$8:$B$127,I$5) -> 0 | J73: =SUMIFS(投資回収_月次!$D$8:$D$127,投資回収_月次!$B$8:$B$127,J$5) -> 28 | ... N73: =SUMIFS(投資回収_月次!$D$8:$D$127,投資回収_月次!$B$8:$B$127,N$5) -> 30 | O73: =SUM(C73:N73) -> 150 | P73: =SUM(I73:N73) -> 150
B74: 雑給（人件費削減） | C74: =-SUMIFS(投資回収_月次!$F$8:$F$127,投資回収_月次!$B$8:$B$127,C$5)/1000 -> 0 | D74: =-SUMIFS(投資回収_月次!$F$8:$F$127,投資回収_月次!$B$8:$B$127,D$5)/1000 -> 0 | E74: =-SUMIFS(投資回収_月次!$F$8:$F$127,投資回収_月次!$B$8:$B$127,E$5)/1000 -> 0 | F74: =-SUMIFS(投資回収_月次!$F$8:$F$127,投資回収_月次!$B$8:$B$127,F$5)/1000 -> 0 | G74: =-SUMIFS(投資回収_月次!$F$8:$F$127,投資回収_月次!$B$8:$B$127,G$5)/1000 -> 0 | H74: =-SUMIFS(投資回収_月次!$F$8:$F$127,投資回収_月次!$B$8:$B$127,H$5)/1000 -> 0 | I74: =-SUMIFS(投資回収_月次!$F$8:$F$127,投資回収_月次!$B$8:$B$127,I$5)/1000 -> 0 | J74: =-SUMIFS(投資回収_月次!$F$8:$F$127,投資回収_月次!$B$8:$B$127,J$5)/1000 -> -161 | ... N74: =-SUMIFS(投資回収_月次!$F$8:$F$127,投資回収_月次!$B$8:$B$127,N$5)/1000 -> -172.5 | O74: =SUM(C74:N74) -> -862.5 | P74: =SUM(I74:N74) -> -862.5 | Q74: 手詰め・壁崩し工程の削減人時 × 時給
B75: 消耗品費（絞り袋削減） | C75: =-SUMIFS(投資回収_月次!$G$8:$G$127,投資回収_月次!$B$8:$B$127,C$5)/1000 -> 0 | D75: =-SUMIFS(投資回収_月次!$G$8:$G$127,投資回収_月次!$B$8:$B$127,D$5)/1000 -> 0 | E75: =-SUMIFS(投資回収_月次!$G$8:$G$127,投資回収_月次!$B$8:$B$127,E$5)/1000 -> 0 | F75: =-SUMIFS(投資回収_月次!$G$8:$G$127,投資回収_月次!$B$8:$B$127,F$5)/1000 -> 0 | G75: =-SUMIFS(投資回収_月次!$G$8:$G$127,投資回収_月次!$B$8:$B$127,G$5)/1000 -> 0 | H75: =-SUMIFS(投資回収_月次!$G$8:$G$127,投資回収_月次!$B$8:$B$127,H$5)/1000 -> 0 | I75: =-SUMIFS(投資回収_月次!$G$8:$G$127,投資回収_月次!$B$8:$B$127,I$5)/1000 -> 0 | J75: =-SUMIFS(投資回収_月次!$G$8:$G$127,投資回収_月次!$B$8:$B$127,J$5)/1000 -> -2.688 | ... N75: =-SUMIFS(投資回収_月次!$G$8:$G$127,投資回収_月次!$B$8:$B$127,N$5)/1000 -> -2.88 | O75: =SUM(C75:N75) -> -14.4 | P75: =SUM(I75:N75) -> -14.4 | Q75: 絞り袋 16円×6枚/日が不要
B76: 水道光熱費（電気・洗浄水） | C76: =SUMIFS(投資回収_月次!$H$8:$H$127,投資回収_月次!$B$8:$B$127,C$5)/1000 -> 0 | D76: =SUMIFS(投資回収_月次!$H$8:$H$127,投資回収_月次!$B$8:$B$127,D$5)/1000 -> 0 | E76: =SUMIFS(投資回収_月次!$H$8:$H$127,投資回収_月次!$B$8:$B$127,E$5)/1000 -> 0 | F76: =SUMIFS(投資回収_月次!$H$8:$H$127,投資回収_月次!$B$8:$B$127,F$5)/1000 -> 0 | G76: =SUMIFS(投資回収_月次!$H$8:$H$127,投資回収_月次!$B$8:$B$127,G$5)/1000 -> 0 | H76: =SUMIFS(投資回収_月次!$H$8:$H$127,投資回収_月次!$B$8:$B$127,H$5)/1000 -> 0 | I76: =SUMIFS(投資回収_月次!$H$8:$H$127,投資回収_月次!$B$8:$B$127,I$5)/1000 -> 0 | J76: =SUMIFS(投資回収_月次!$H$8:$H$127,投資回収_月次!$B$8:$B$127,J$5)/1000 -> 5.88 | ... N76: =SUMIFS(投資回収_月次!$H$8:$H$127,投資回収_月次!$B$8:$B$127,N$5)/1000 -> 6.3 | O76: =SUM(C76:N76) -> 31.5 | P76: =SUM(I76:N76) -> 31.5 | Q76: 0.4kW×2台の電気代＋洗浄水・洗剤
B77: 修繕費（保守部品） | C77: =SUMIFS(投資回収_月次!$I$8:$I$127,投資回収_月次!$B$8:$B$127,C$5)/1000 -> 0 | D77: =SUMIFS(投資回収_月次!$I$8:$I$127,投資回収_月次!$B$8:$B$127,D$5)/1000 -> 0 | E77: =SUMIFS(投資回収_月次!$I$8:$I$127,投資回収_月次!$B$8:$B$127,E$5)/1000 -> 0 | F77: =SUMIFS(投資回収_月次!$I$8:$I$127,投資回収_月次!$B$8:$B$127,F$5)/1000 -> 0 | G77: =SUMIFS(投資回収_月次!$I$8:$I$127,投資回収_月次!$B$8:$B$127,G$5)/1000 -> 0 | H77: =SUMIFS(投資回収_月次!$I$8:$I$127,投資回収_月次!$B$8:$B$127,H$5)/1000 -> 0 | I77: =SUMIFS(投資回収_月次!$I$8:$I$127,投資回収_月次!$B$8:$B$127,I$5)/1000 -> 0 | J77: =SUMIFS(投資回収_月次!$I$8:$I$127,投資回収_月次!$B$8:$B$127,J$5)/1000 -> 7.5 | ... N77: =SUMIFS(投資回収_月次!$I$8:$I$127,投資回収_月次!$B$8:$B$127,N$5)/1000 -> 7.5 | O77: =SUM(C77:N77) -> 37.5 | P77: =SUM(I77:N77) -> 37.5 | Q77: 取得価額×2%/年
B78: 減価償却費（機械・10年定額） | C78: =SUMIFS(投資回収_月次!$M$8:$M$127,投資回収_月次!$B$8:$B$127,C$5)/1000 -> 0 | D78: =SUMIFS(投資回収_月次!$M$8:$M$127,投資回収_月次!$B$8:$B$127,D$5)/1000 -> 0 | E78: =SUMIFS(投資回収_月次!$M$8:$M$127,投資回収_月次!$B$8:$B$127,E$5)/1000 -> 0 | F78: =SUMIFS(投資回収_月次!$M$8:$M$127,投資回収_月次!$B$8:$B$127,F$5)/1000 -> 0 | G78: =SUMIFS(投資回収_月次!$M$8:$M$127,投資回収_月次!$B$8:$B$127,G$5)/1000 -> 0 | H78: =SUMIFS(投資回収_月次!$M$8:$M$127,投資回収_月次!$B$8:$B$127,H$5)/1000 -> 0 | I78: =SUMIFS(投資回収_月次!$M$8:$M$127,投資回収_月次!$B$8:$B$127,I$5)/1000 -> 0 | J78: =SUMIFS(投資回収_月次!$M$8:$M$127,投資回収_月次!$B$8:$B$127,J$5)/1000 -> 37.5 | ... N78: =SUMIFS(投資回収_月次!$M$8:$M$127,投資回収_月次!$B$8:$B$127,N$5)/1000 -> 37.5 | O78: =SUM(C78:N78) -> 187.5 | P78: =SUM(I78:N78) -> 187.5 | Q78: 機械 取得価額÷120か月
B79: 減価償却費（電気・付帯工事） | C79: =SUMIFS(投資回収_月次!$R$8:$R$127,投資回収_月次!$B$8:$B$127,C$5)/1000 -> 0 | D79: =SUMIFS(投資回収_月次!$R$8:$R$127,投資回収_月次!$B$8:$B$127,D$5)/1000 -> 0 | E79: =SUMIFS(投資回収_月次!$R$8:$R$127,投資回収_月次!$B$8:$B$127,E$5)/1000 -> 0 | F79: =SUMIFS(投資回収_月次!$R$8:$R$127,投資回収_月次!$B$8:$B$127,F$5)/1000 -> 0 | G79: =SUMIFS(投資回収_月次!$R$8:$R$127,投資回収_月次!$B$8:$B$127,G$5)/1000 -> 0 | H79: =SUMIFS(投資回収_月次!$R$8:$R$127,投資回収_月次!$B$8:$B$127,H$5)/1000 -> 0 | I79: =SUMIFS(投資回収_月次!$R$8:$R$127,投資回収_月次!$B$8:$B$127,I$5)/1000 -> 0 | J79: =SUMIFS(投資回収_月次!$R$8:$R$127,投資回収_月次!$B$8:$B$127,J$5)/1000 -> 4.1666667 | ... N79: =SUMIFS(投資回収_月次!$R$8:$R$127,投資回収_月次!$B$8:$B$127,N$5)/1000 -> 4.1666667 | O79: =SUM(C79:N79) -> 20.833333 | P79: =SUM(I79:N79) -> 20.833333 | Q79: 電気・付帯工事を資産計上（区分1:10年／区分2:15年）した場合の月割償却
B80: 修繕費（電気・付帯工事・一括費用） | C80: =SUMIFS(投資回収_月次!$S$8:$S$127,投資回収_月次!$B$8:$B$127,C$5)/1000 -> 0 | D80: =SUMIFS(投資回収_月次!$S$8:$S$127,投資回収_月次!$B$8:$B$127,D$5)/1000 -> 0 | E80: =SUMIFS(投資回収_月次!$S$8:$S$127,投資回収_月次!$B$8:$B$127,E$5)/1000 -> 0 | F80: =SUMIFS(投資回収_月次!$S$8:$S$127,投資回収_月次!$B$8:$B$127,F$5)/1000 -> 0 | G80: =SUMIFS(投資回収_月次!$S$8:$S$127,投資回収_月次!$B$8:$B$127,G$5)/1000 -> 0 | H80: =SUMIFS(投資回収_月次!$S$8:$S$127,投資回収_月次!$B$8:$B$127,H$5)/1000 -> 0 | I80: =SUMIFS(投資回収_月次!$S$8:$S$127,投資回収_月次!$B$8:$B$127,I$5)/1000 -> 0 | J80: =SUMIFS(投資回収_月次!$S$8:$S$127,投資回収_月次!$B$8:$B$127,J$5)/1000 -> 0 | ... N80: =SUMIFS(投資回収_月次!$S$8:$S$127,投資回収_月次!$B$8:$B$127,N$5)/1000 -> 0 | O80: =SUM(C80:N80) -> 0 | P80: =SUM(I80:N80) -> 0 | Q80: 区分3：導入月（2月）に全額費用計上
B81: 経費増減 合計 | C81: =SUM(C74:C80) -> 0 | D81: =SUM(D74:D80) -> 0 | E81: =SUM(E74:E80) -> 0 | F81: =SUM(F74:F80) -> 0 | G81: =SUM(G74:G80) -> 0 | H81: =SUM(H74:H80) -> 0 | I81: =SUM(I74:I80) -> 0 | J81: =SUM(J74:J80) -> -108.64133 | ... P81: =SUM(P74:P80) -> -599.56667
B82: 経常利益への影響 | C82: =-C81 -> 0 | D82: =-D81 -> 0 | E82: =-E81 -> 0 | F82: =-F81 -> 0 | G82: =-G81 -> 0 | H82: =-H81 -> 0 | I82: =-I81 -> 0 | J82: =-J81 -> 108.64133 | ... P82: =-P81 -> 599.56667
B83: （参考）償却前の投資効果額 | C83: =-SUM(C74:C77) -> 0 | D83: =-SUM(D74:D77) -> 0 | E83: =-SUM(E74:E77) -> 0 | F83: =-SUM(F74:F77) -> 0 | G83: =-SUM(G74:G77) -> 0 | H83: =-SUM(H74:H77) -> 0 | I83: =-SUM(I74:I77) -> 0 | J83: =-SUM(J74:J77) -> 150.308 | ... P83: =-SUM(P74:P77) -> 807.9
B84: （参考）効果額 ÷ 減価償却費 | C84: =IF((C78+C79)=0,"-",C83/(C78+C79)) -> - | D84: =IF((D78+D79)=0,"-",D83/(D78+D79)) -> - | E84: =IF((E78+E79)=0,"-",E83/(E78+E79)) -> - | F84: =IF((F78+F79)=0,"-",F83/(F78+F79)) -> - | G84: =IF((G78+G79)=0,"-",G83/(G78+G79)) -> - | H84: =IF((H78+H79)=0,"-",H83/(H78+H79)) -> - | I84: =IF((I78+I79)=0,"-",I83/(I78+I79)) -> - | J84: =IF((J78+J79)=0,"-",J83/(J78+J79)) -> 3.607392 | ... P84: =IF((P78+P79)=0,"-",P83/(P78+P79)) -> 3.87792 | Q84: 償却費を何倍の効果で相殺しているか
B86: ③ 充填機導入後 PL（①＋②） ※黄色行＝充填機導入で変動する科目
B87: 売 上 高 | C87: =C8 -> 787800 | D87: =D8 -> 836803.38 | E87: =E8 -> 747600 | F87: =F8 -> 772524.47 | G87: =G8 -> 750295.52 | H87: =H8 -> 847205.75 | I87: =I8 -> 770219.86 | J87: =J8 -> 729600 | ... N87: =N8 -> 777000 | O87: =SUM(C87:N87) -> 9439549 | P87: =SUM(I87:N87) -> 4697319.9
B88: 売上総利益 | C88: =C9 -> 224170 | D88: =D9 -> 237991.38 | E88: =E9 -> 212690 | F88: =F9 -> 219664.47 | G88: =G9 -> 213231.52 | H88: =H9 -> 240495.75 | I88: =I9 -> 218795.86 | J88: =J9 -> 207111.4 | ... N88: =N9 -> 219247.27 | O88: =SUM(C88:N88) -> 2680286.7 | P88: =SUM(I88:N88) -> 1332043.5
B89: 荒利率 | C89: =IF(C87=0,0,C88/C87) -> 0.28455192 | D89: =IF(D87=0,0,D88/D87) -> 0.28440538 | E89: =IF(E87=0,0,E88/E87) -> 0.28449706 | F89: =IF(F87=0,0,F88/F87) -> 0.28434629 | G89: =IF(G87=0,0,G88/G87) -> 0.28419671 | H89: =IF(H87=0,0,H88/H87) -> 0.28386936 | I89: =IF(I87=0,0,I88/I87) -> 0.28406936 | J89: =IF(J87=0,0,J88/J87) -> 0.28386979 | ... P89: =IF(P87=0,0,P88/P87) -> 0.28357522
B90: 商品卸売上高 | C90: =C11 -> 785000 | D90: =D11 -> 834000 | E90: =E11 -> 745000 | F90: =F11 -> 770000 | G90: =G11 -> 748000 | H90: =H11 -> 845000 | I90: =I11 -> 768000 | J90: =J11 -> 727700 | ... N90: =N11 -> 775000 | O90: =SUM(C90:N90) -> 9412200 | P90: =SUM(I90:N90) -> 4685200
B91: 荒利益高 | C91: =C12 -> 213520 | D91: =D12 -> 226848 | E91: =E12 -> 202640 | F91: =F12 -> 209440 | G91: =G12 -> 203456 | H91: =H12 -> 229840 | I91: =I12 -> 208896 | J91: =J12 -> 197934.4 | ... N91: =N12 -> 210800 | O91: =SUM(C91:N91) -> 2560118.4 | P91: =SUM(I91:N91) -> 1274374.4
B92: 荒利率 | C92: =IF(C90=0,0,C91/C90) -> 0.272 | D92: =IF(D90=0,0,D91/D90) -> 0.272 | E92: =IF(E90=0,0,E91/E90) -> 0.272 | F92: =IF(F90=0,0,F91/F90) -> 0.272 | G92: =IF(G90=0,0,G91/G90) -> 0.272 | H92: =IF(H90=0,0,H91/H90) -> 0.272 | I92: =IF(I90=0,0,I91/I90) -> 0.272 | J92: =IF(J90=0,0,J91/J90) -> 0.272 | ... P92: =IF(P90=0,0,P91/P90) -> 0.272
B93: 物流フィ高 | C93: =C14 -> 2800 | D93: =D14 -> 2803.384 | E93: =E14 -> 2600 | F93: =F14 -> 2524.471 | G93: =G14 -> 2295.52 | H93: =H14 -> 2205.75 | I93: =I14 -> 2219.863 | J93: =J14 -> 1900 | ... N93: =N14 -> 2000 | O93: =SUM(C93:N93) -> 27348.988 | P93: =SUM(I93:N93) -> 12119.863
B94: 物流フィ高及びサービスリサイクル料等 | C94: =C15 -> 2800 | D94: =D15 -> 2803.384 | E94: =E15 -> 2600 | F94: =F15 -> 2524.471 | G94: =G15 -> 2295.52 | H94: =H15 -> 2205.75 | I94: =I15 -> 2219.863 | J94: =J15 -> 1900 | ... N94: =N15 -> 2000 | O94: =SUM(C94:N94) -> 27348.988 | P94: =SUM(I94:N94) -> 12119.863
B95: 荒利率 | C95: =IF(C93=0,0,C94/C93) -> 1 | D95: =IF(D93=0,0,D94/D93) -> 1 | E95: =IF(E93=0,0,E94/E93) -> 1 | F95: =IF(F93=0,0,F94/F93) -> 1 | G95: =IF(G93=0,0,G94/G93) -> 1 | H95: =IF(H93=0,0,H94/H93) -> 1 | I95: =IF(I93=0,0,I94/I93) -> 1 | J95: =IF(J93=0,0,J94/J93) -> 1 | ... P95: =IF(P93=0,0,P94/P93) -> 1
B96: 手数料等売上高 | C96: =C17 -> 0 | D96: =D17 -> 0 | E96: =E17 -> 0 | F96: =F17 -> 0 | G96: =G17 -> 0 | H96: =H17 -> 0 | I96: =I17 -> 0 | J96: =J17 -> 0 | ... N96: =N17 -> 0 | O96: =SUM(C96:N96) -> 0 | P96: =SUM(I96:N96) -> 0
B97: 手数料等 | C97: =C18 -> 0 | D97: =D18 -> 0 | E97: =E18 -> 0 | F97: =F18 -> 0 | G97: =G18 -> 0 | H97: =H18 -> 0 | I97: =I18 -> 0 | J97: =J18 -> 0 | ... N97: =N18 -> 0 | O97: =SUM(C97:N97) -> 0 | P97: =SUM(I97:N97) -> 0
B98: 荒利率 | C98: =IF(C96=0,0,C97/C96) -> 0 | D98: =IF(D96=0,0,D97/D96) -> 0 | E98: =IF(E96=0,0,E97/E96) -> 0 | F98: =IF(F96=0,0,F97/F96) -> 0 | G98: =IF(G96=0,0,G97/G96) -> 0 | H98: =IF(H96=0,0,H97/H96) -> 0 | I98: =IF(I96=0,0,I97/I96) -> 0 | J98: =IF(J96=0,0,J97/J96) -> 0 | ... P98: =IF(P96=0,0,P97/P96) -> 0
B99: ④その他売上高 | C99: =C20 -> 0 | D99: =D20 -> 0 | E99: =E20 -> 0 | F99: =F20 -> 0 | G99: =G20 -> 0 | H99: =H20 -> 0 | I99: =I20 -> 0 | J99: =J20 -> 0 | ... N99: =N20 -> 0 | O99: =SUM(C99:N99) -> 0 | P99: =SUM(I99:N99) -> 0
B100: 販売奨励金 | C100: =C21 -> 7850 | D100: =D21 -> 8340 | E100: =E21 -> 7450 | F100: =F21 -> 7700 | G100: =G21 -> 7480 | H100: =H21 -> 8450 | I100: =I21 -> 7680 | J100: =J21 -> 7277 | ... N100: =N21 -> 6447.2686 | O100: =SUM(C100:N100) -> 92819.269 | P100: =SUM(I100:N100) -> 45549.269
B101: 荒利率 | C101: =IF(C99=0,0,C100/C99) -> 0 | D101: =IF(D99=0,0,D100/D99) -> 0 | E101: =IF(E99=0,0,E100/E99) -> 0 | F101: =IF(F99=0,0,F100/F99) -> 0 | G101: =IF(G99=0,0,G100/G99) -> 0 | H101: =IF(H99=0,0,H100/H99) -> 0 | I101: =IF(I99=0,0,I100/I99) -> 0 | J101: =IF(J99=0,0,J100/J99) -> 0 | ... P101: =IF(P99=0,0,P100/P99) -> 0
B102: 人件費 | C102: =SUM(C103:C111) -> 137474 | D102: =SUM(D103:D111) -> 138653 | E102: =SUM(E103:E111) -> 141802 | F102: =SUM(F103:F111) -> 140499 | G102: =SUM(G103:G111) -> 133546 | H102: =SUM(H103:H111) -> 144822 | I102: =SUM(I103:I111) -> 144712 | J102: =SUM(J103:J111) -> 134840 | ... N102: =SUM(N103:N111) -> 142435.5 | O102: =SUM(C102:N102) -> 1685638.5 | P102: =SUM(I102:N102) -> 848842.5 | Q102: ← 明細の合計（再計算）
B103: 社員給与 | C103: =C24 -> 89240 | D103: =D24 -> 91540 | E103: =E24 -> 97500 | F103: =F24 -> 96250 | G103: =G24 -> 86900 | H103: =H24 -> 94800 | I103: =I24 -> 99450 | J103: =J24 -> 90475 | ... N103: =N24 -> 97500 | O103: =SUM(C103:N103) -> 1129905 | P103: =SUM(I103:N103) -> 573675
B104: 契約社員人件費 | C104: =C25 -> 0 | D104: =D25 -> 0 | E104: =E25 -> 0 | F104: =F25 -> 0 | G104: =G25 -> 0 | H104: =H25 -> 0 | I104: =I25 -> 0 | J104: =J25 -> 0 | ... N104: =N25 -> 0 | O104: =SUM(C104:N104) -> 0 | P104: =SUM(I104:N104) -> 0
B105: 雑 給 | C105: =C26+C74 -> 18960 | D105: =D26+D74 -> 19440 | E105: =E26+E74 -> 18000 | F105: =F26+F74 -> 18120 | G105: =G26+G74 -> 18724 | H105: =H26+H74 -> 20336 | I105: =I26+I74 -> 18600 | J105: =J26+J74 -> 18289 | ... N105: =N26+N74 -> 18551.5 | O105: =SUM(C105:N105) -> 226523.5 | P105: =SUM(I105:N105) -> 112943.5 | Q105: ← 充填機導入による増減を反映
B106: 派遣代 | C106: =C27 -> 1000 | D106: =D27 -> 2000 | E106: =E27 -> 100 | F106: =F27 -> 100 | G106: =G27 -> 100 | H106: =H27 -> 3500 | I106: =I27 -> 100 | J106: =J27 -> 1000 | ... N106: =N27 -> 100 | O106: =SUM(C106:N106) -> 10600 | P106: =SUM(I106:N106) -> 3800
B107: 賞 与 | C107: =C28 -> 5160 | D107: =D28 -> 5160 | E107: =E28 -> 5160 | F107: =F28 -> 5160 | G107: =G28 -> 5160 | H107: =H28 -> 5160 | I107: =I28 -> 5160 | J107: =J28 -> 5160 | ... N107: =N28 -> 5160 | O107: =SUM(C107:N107) -> 61920 | P107: =SUM(I107:N107) -> 30960
B108: 法定福利費 | C108: =C29 -> 16269 | D108: =D29 -> 16668 | E108: =E29 -> 17397 | F108: =F29 -> 17224 | G108: =G29 -> 15892 | H108: =H29 -> 17256 | I108: =I29 -> 17757 | J108: =J29 -> 16396 | ... N108: =N29 -> 17479 | O108: =SUM(C108:N108) -> 204050 | P108: =SUM(I108:N108) -> 103344
B109: 福利厚生費 | C109: =C30 -> 6835 | D109: =D30 -> 3835 | E109: =E30 -> 3635 | F109: =F30 -> 3635 | G109: =G30 -> 6760 | H109: =H30 -> 3760 | I109: =I30 -> 3635 | J109: =J30 -> 3510 | ... N109: =N30 -> 3635 | O109: =SUM(C109:N109) -> 52520 | P109: =SUM(I109:N109) -> 24060
B110: 按分対象者人件費 | C110: =C31 -> 0 | D110: =D31 -> 0 | E110: =E31 -> 0 | F110: =F31 -> 0 | G110: =G31 -> 0 | H110: =H31 -> 0 | I110: =I31 -> 0 | J110: =J31 -> 0 | ... N110: =N31 -> 0 | O110: =SUM(C110:N110) -> 0 | P110: =SUM(I110:N110) -> 0
B111: 採用教育・退職金 | C111: =C32 -> 10 | D111: =D32 -> 10 | E111: =E32 -> 10 | F111: =F32 -> 10 | G111: =G32 -> 10 | H111: =H32 -> 10 | I111: =I32 -> 10 | J111: =J32 -> 10 | ... N111: =N32 -> 10 | O111: =SUM(C111:N111) -> 120 | P111: =SUM(I111:N111) -> 60
B112: 広告・販促費 | C112: =SUM(C113:C114) -> 0 | D112: =SUM(D113:D114) -> 0 | E112: =SUM(E113:E114) -> 0 | F112: =SUM(F113:F114) -> 0 | G112: =SUM(G113:G114) -> 0 | H112: =SUM(H113:H114) -> 0 | I112: =SUM(I113:I114) -> 0 | J112: =SUM(J113:J114) -> 0 | ... N112: =SUM(N113:N114) -> 0 | O112: =SUM(C112:N112) -> 0 | P112: =SUM(I112:N112) -> 0
B113: 広告費 | C113: =C34 -> 0 | D113: =D34 -> 0 | E113: =E34 -> 0 | F113: =F34 -> 0 | G113: =G34 -> 0 | H113: =H34 -> 0 | I113: =I34 -> 0 | J113: =J34 -> 0 | ... N113: =N34 -> 0 | O113: =SUM(C113:N113) -> 0 | P113: =SUM(I113:N113) -> 0
B114: 販売促進費 | C114: =C35 -> 0 | D114: =D35 -> 0 | E114: =E35 -> 0 | F114: =F35 -> 0 | G114: =G35 -> 0 | H114: =H35 -> 0 | I114: =I35 -> 0 | J114: =J35 -> 0 | ... N114: =N35 -> 0 | O114: =SUM(C114:N114) -> 0 | P114: =SUM(I114:N114) -> 0
B115: 不動産費 | C115: =SUM(C116:C118) -> 2069.6 | D115: =SUM(D116:D118) -> 2069.6 | E115: =SUM(E116:E118) -> 2069.6 | F115: =SUM(F116:F118) -> 2069.6 | G115: =SUM(G116:G118) -> 2069.6 | H115: =SUM(H116:H118) -> 2069.6 | I115: =SUM(I116:I118) -> 2069.6 | J115: =SUM(J116:J118) -> 2069.6 | ... N115: =SUM(N116:N118) -> 2069.6 | O115: =SUM(C115:N115) -> 24835.2 | P115: =SUM(I115:N115) -> 12417.6
B116: 地 代 | C116: =C37 -> 0 | D116: =D37 -> 0 | E116: =E37 -> 0 | F116: =F37 -> 0 | G116: =G37 -> 0 | H116: =H37 -> 0 | I116: =I37 -> 0 | J116: =J37 -> 0 | ... N116: =N37 -> 0 | O116: =SUM(C116:N116) -> 0 | P116: =SUM(I116:N116) -> 0
B117: 減価償却相当分設備費 | C117: =C38 -> 632 | D117: =D38 -> 632 | E117: =E38 -> 632 | F117: =F38 -> 632 | G117: =G38 -> 632 | H117: =H38 -> 632 | I117: =I38 -> 632 | J117: =J38 -> 632 | ... N117: =N38 -> 632 | O117: =SUM(C117:N117) -> 7584 | P117: =SUM(I117:N117) -> 3792
B118: 家 賃 | C118: =C39 -> 1437.6 | D118: =D39 -> 1437.6 | E118: =E39 -> 1437.6 | F118: =F39 -> 1437.6 | G118: =G39 -> 1437.6 | H118: =H39 -> 1437.6 | I118: =I39 -> 1437.6 | J118: =J39 -> 1437.6 | ... N118: =N39 -> 1437.6 | O118: =SUM(C118:N118) -> 17251.2 | P118: =SUM(I118:N118) -> 8625.6
B119: 一般管理費 | C119: =SUM(C120:C140) -> 79634.147 | D119: =SUM(D120:D140) -> 85862.776 | E119: =SUM(E120:E140) -> 71626.215 | F119: =SUM(F120:F140) -> 75996.908 | G119: =SUM(G120:G140) -> 73366.472 | H119: =SUM(H120:H140) -> 85549.879 | I119: =SUM(I120:I140) -> 74334.159 | J119: =SUM(J120:J140) -> 72658.64 | ... N119: =SUM(N120:N140) -> 78344.548 | O119: =SUM(C119:N119) -> 941222.52 | P119: =SUM(I119:N119) -> 469186.12 | Q119: ← 明細の合計（再計算）
B120: 消耗品費 | C120: =C41+C75 -> 7500 | D120: =D41+D75 -> 8000 | E120: =E41+E75 -> 1500 | F120: =F41+F75 -> 3650 | G120: =G41+G75 -> 1000 | H120: =H41+H75 -> 7500 | I120: =I41+I75 -> 1500 | J120: =J41+J75 -> 1997.312 | ... N120: =N41+N75 -> 4247.12 | O120: =SUM(C120:N120) -> 55885.6 | P120: =SUM(I120:N120) -> 26735.6 | Q120: ← 充填機導入による増減を反映
B121: 保険料 | C121: =C42 -> 0 | D121: =D42 -> 0 | E121: =E42 -> 0 | F121: =F42 -> 0 | G121: =G42 -> 0 | H121: =H42 -> 0 | I121: =I42 -> 0 | J121: =J42 -> 0 | ... N121: =N42 -> 0 | O121: =SUM(C121:N121) -> 0 | P121: =SUM(I121:N121) -> 0
B122: 修繕費 | C122: =C43+C77+C80 -> 2000 | D122: =D43+D77+D80 -> 4800 | E122: =E43+E77+E80 -> 600 | F122: =F43+F77+F80 -> 1230 | G122: =G43+G77+G80 -> 600 | H122: =H43+H77+H80 -> 1230 | I122: =I43+I77+I80 -> 370 | J122: =J43+J77+J80 -> 507.5 | ... N122: =N43+N77+N80 -> 767.5 | O122: =SUM(C122:N122) -> 14607.5 | P122: =SUM(I122:N122) -> 4147.5 | Q122: ← 充填機導入による増減を反映
B123: 租税公課 | C123: =C44 -> 0 | D123: =D44 -> 0 | E123: =E44 -> 0 | F123: =F44 -> 0 | G123: =G44 -> 0 | H123: =H44 -> 0 | I123: =I44 -> 0 | J123: =J44 -> 0 | ... N123: =N44 -> 0 | O123: =SUM(C123:N123) -> 0 | P123: =SUM(I123:N123) -> 0
B124: 燃料費（租税） | C124: =C45 -> 0 | D124: =D45 -> 0 | E124: =E45 -> 0 | F124: =F45 -> 0 | G124: =G45 -> 0 | H124: =H45 -> 0 | I124: =I45 -> 0 | J124: =J45 -> 0 | ... N124: =N45 -> 0 | O124: =SUM(C124:N124) -> 0 | P124: =SUM(I124:N124) -> 0
...

Sheet 白鳥惣菜PL_実績見込_導入効果
B1: 白鳥惣菜 ライン月別PL（17期 実績＋予算見込） 充填機導入（2027年2月1日）効果
B2: 単位：千円 7〜9月＝実績、10月〜6月＝17期予算（見込）。②は「白鳥惣菜PL_導入効果」シートの増減を参照
B4: 科目 | C4: 7月 | D4: 8月 | E4: 9月 | F4: 10月 | G4: 11月 | H4: 12月 | I4: 1月 | J4: 2月 | K4: 3月 | L4: 4月 | M4: 5月 | N4: 6月 | O4: 17期合計 (実績+見込) | P4: 下期計 (1〜6月)
B5: （区分） | C5: 実績 | D5: 実績 | E5: 実績 | F5: 予算 | G5: 予算 | H5: 予算 | I5: 予算 | J5: 予算 | K5: 予算 | L5: 予算 | M5: 予算 | N5: 予算
B7: ① 17期 実績（7〜9月）＋予算見込（10〜6月） ※充填機導入前
B8: 売 上 高 | C8: ='実績原本_白鳥惣菜_7-9月'!B4 -> 859016.86 | D8: ='実績原本_白鳥惣菜_7-9月'!C4 -> 980922.58 | E8: ='実績原本_白鳥惣菜_7-9月'!D4 -> 810842.5 | F8: =予算原本_白鳥惣菜!E4 -> 772524.47 | G8: =予算原本_白鳥惣菜!F4 -> 750295.52 | H8: =予算原本_白鳥惣菜!G4 -> 847205.75 | I8: =予算原本_白鳥惣菜!H4 -> 770219.86 | J8: =予算原本_白鳥惣菜!I4 -> 729600 | K8: =予算原本_白鳥惣菜!J4 -> 826500 | L8: =予算原本_白鳥惣菜!K4 -> 792000 | M8: =予算原本_白鳥惣菜!L4 -> 802000 | N8: =予算原本_白鳥惣菜!M4 -> 777000 | O8: =SUM(C8:N8) -> 9718127.5 | P8: =SUM(I8:N8) -> 4697319.9
B9: 売上総利益 | C9: ='実績原本_白鳥惣菜_7-9月'!B5 -> 243490.3 | D9: ='実績原本_白鳥惣菜_7-9月'!C5 -> 282030.26 | E9: ='実績原本_白鳥惣菜_7-9月'!D5 -> 246956.76 | F9: =予算原本_白鳥惣菜!E5 -> 219664.47 | G9: =予算原本_白鳥惣菜!F5 -> 213231.52 | H9: =予算原本_白鳥惣菜!G5 -> 240495.75 | I9: =予算原本_白鳥惣菜!H5 -> 218795.86 | J9: =予算原本_白鳥惣菜!I5 -> 207111.4 | K9: =予算原本_白鳥惣菜!J5 -> 234509 | L9: =予算原本_白鳥惣菜!K5 -> 224780 | M9: =予算原本_白鳥惣菜!L5 -> 227600 | N9: =予算原本_白鳥惣菜!M5 -> 219247.27 | O9: =SUM(C9:N9) -> 2777912.6 | P9: =SUM(I9:N9) -> 1332043.5
B10: 荒利率 | C10: ='実績原本_白鳥惣菜_7-9月'!B6 -> 0.28345229 | D10: ='実績原本_白鳥惣菜_7-9月'!C6 -> 0.28751531 | E10: ='実績原本_白鳥惣菜_7-9月'!D6 -> 0.3045681 | F10: =予算原本_白鳥惣菜!E6 -> 0.28434629 | G10: =予算原本_白鳥惣菜!F6 -> 0.28419671 | H10: =予算原本_白鳥惣菜!G6 -> 0.28386936 | I10: =予算原本_白鳥惣菜!H6 -> 0.28406936 | J10: =予算原本_白鳥惣菜!I6 -> 0.28386979 | K10: =予算原本_白鳥惣菜!J6 -> 0.28373745 | L10: =予算原本_白鳥惣菜!K6 -> 0.28381313 | M10: =予算原本_白鳥惣菜!L6 -> 0.28379052 | N10: =予算原本_白鳥惣菜!M6 -> 0.28217152 | O10: =IF(O8=0,0,O9/O8) -> 0.28584854 | P10: =IF(P8=0,0,P9/P8) -> 0.28357522
B11: 商品卸売上高 | C11: ='実績原本_白鳥惣菜_7-9月'!B7 -> 856552.1 | D11: ='実績原本_白鳥惣菜_7-9月'!C7 -> 978185.97 | E11: ='実績原本_白鳥惣菜_7-9月'!D7 -> 808524.62 | F11: =予算原本_白鳥惣菜!E7 -> 770000 | G11: =予算原本_白鳥惣菜!F7 -> 748000 | H11: =予算原本_白鳥惣菜!G7 -> 845000 | I11: =予算原本_白鳥惣菜!H7 -> 768000 | J11: =予算原本_白鳥惣菜!I7 -> 727700 | K11: =予算原本_白鳥惣菜!J7 -> 824500 | L11: =予算原本_白鳥惣菜!K7 -> 790000 | M11: =予算原本_白鳥惣菜!L7 -> 800000 | N11: =予算原本_白鳥惣菜!M7 -> 775000 | O11: =SUM(C11:N11) -> 9691462.7 | P11: =SUM(I11:N11) -> 4685200
B12: 荒利益高 | C12: ='実績原本_白鳥惣菜_7-9月'!B8 -> 231367.24 | D12: ='実績原本_白鳥惣菜_7-9月'!C8 -> 268948.59 | E12: ='実績原本_白鳥惣菜_7-9月'!D8 -> 235658.63 | F12: =予算原本_白鳥惣菜!E8 -> 209440 | G12: =予算原本_白鳥惣菜!F8 -> 203456 | H12: =予算原本_白鳥惣菜!G8 -> 229840 | I12: =予算原本_白鳥惣菜!H8 -> 208896 | J12: =予算原本_白鳥惣菜!I8 -> 197934.4 | K12: =予算原本_白鳥惣菜!J8 -> 224264 | L12: =予算原本_白鳥惣菜!K8 -> 214880 | M12: =予算原本_白鳥惣菜!L8 -> 217600 | N12: =予算原本_白鳥惣菜!M8 -> 210800 | O12: =SUM(C12:N12) -> 2653084.9 | P12: =SUM(I12:N12) -> 1274374.4
B13: 荒利率 | C13: ='実績原本_白鳥惣菜_7-9月'!B9 -> 0.27011461 | D13: ='実績原本_白鳥惣菜_7-9月'!C9 -> 0.27494627 | E13: ='実績原本_白鳥惣菜_7-9月'!D9 -> 0.29146748 | F13: =予算原本_白鳥惣菜!E9 -> 0.272 | G13: =予算原本_白鳥惣菜!F9 -> 0.272 | H13: =予算原本_白鳥惣菜!G9 -> 0.272 | I13: =予算原本_白鳥惣菜!H9 -> 0.272 | J13: =予算原本_白鳥惣菜!I9 -> 0.272 | K13: =予算原本_白鳥惣菜!J9 -> 0.272 | L13: =予算原本_白鳥惣菜!K9 -> 0.272 | M13: =予算原本_白鳥惣菜!L9 -> 0.272 | N13: =予算原本_白鳥惣菜!M9 -> 0.272 | O13: =IF(O11=0,0,O12/O11) -> 0.27375484 | P13: =IF(P11=0,0,P12/P11) -> 0.272
B14: 物流フィ高 | C14: ='実績原本_白鳥惣菜_7-9月'!B10 -> 2464.763 | D14: ='実績原本_白鳥惣菜_7-9月'!C10 -> 2736.609 | E14: ='実績原本_白鳥惣菜_7-9月'!D10 -> 2317.878 | F14: =予算原本_白鳥惣菜!E10 -> 2524.471 | G14: =予算原本_白鳥惣菜!F10 -> 2295.52 | H14: =予算原本_白鳥惣菜!G10 -> 2205.75 | I14: =予算原本_白鳥惣菜!H10 -> 2219.863 | J14: =予算原本_白鳥惣菜!I10 -> 1900 | K14: =予算原本_白鳥惣菜!J10 -> 2000 | L14: =予算原本_白鳥惣菜!K10 -> 2000 | M14: =予算原本_白鳥惣菜!L10 -> 2000 | N14: =予算原本_白鳥惣菜!M10 -> 2000 | O14: =SUM(C14:N14) -> 26664.854 | P14: =SUM(I14:N14) -> 12119.863
B15: 物流フィ高及びサービスリサイクル料等 | C15: ='実績原本_白鳥惣菜_7-9月'!B11 -> 2464.763 | D15: ='実績原本_白鳥惣菜_7-9月'!C11 -> 2736.609 | E15: ='実績原本_白鳥惣菜_7-9月'!D11 -> 2317.878 | F15: =予算原本_白鳥惣菜!E11 -> 2524.471 | G15: =予算原本_白鳥惣菜!F11 -> 2295.52 | H15: =予算原本_白鳥惣菜!G11 -> 2205.75 | I15: =予算原本_白鳥惣菜!H11 -> 2219.863 | J15: =予算原本_白鳥惣菜!I11 -> 1900 | K15: =予算原本_白鳥惣菜!J11 -> 2000 | L15: =予算原本_白鳥惣菜!K11 -> 2000 | M15: =予算原本_白鳥惣菜!L11 -> 2000 | N15: =予算原本_白鳥惣菜!M11 -> 2000 | O15: =SUM(C15:N15) -> 26664.854 | P15: =SUM(I15:N15) -> 12119.863
B16: 荒利率 | C16: ='実績原本_白鳥惣菜_7-9月'!B12 -> 1 | D16: ='実績原本_白鳥惣菜_7-9月'!C12 -> 1 | E16: ='実績原本_白鳥惣菜_7-9月'!D12 -> 1 | F16: =予算原本_白鳥惣菜!E12 -> 1 | G16: =予算原本_白鳥惣菜!F12 -> 1 | H16: =予算原本_白鳥惣菜!G12 -> 1 | I16: =予算原本_白鳥惣菜!H12 -> 1 | J16: =予算原本_白鳥惣菜!I12 -> 1 | K16: =予算原本_白鳥惣菜!J12 -> 1 | L16: =予算原本_白鳥惣菜!K12 -> 1 | M16: =予算原本_白鳥惣菜!L12 -> 1 | N16: =予算原本_白鳥惣菜!M12 -> 1 | O16: =IF(O14=0,0,O15/O14) -> 1 | P16: =IF(P14=0,0,P15/P14) -> 1
B17: 手数料等売上高 | C17: ='実績原本_白鳥惣菜_7-9月'!B13 -> 0 | D17: ='実績原本_白鳥惣菜_7-9月'!C13 -> 0 | E17: ='実績原本_白鳥惣菜_7-9月'!D13 -> 0 | F17: =予算原本_白鳥惣菜!E13 -> 0 | G17: =予算原本_白鳥惣菜!F13 -> 0 | H17: =予算原本_白鳥惣菜!G13 -> 0 | I17: =予算原本_白鳥惣菜!H13 -> 0 | J17: =予算原本_白鳥惣菜!I13 -> 0 | K17: =予算原本_白鳥惣菜!J13 -> 0 | L17: =予算原本_白鳥惣菜!K13 -> 0 | M17: =予算原本_白鳥惣菜!L13 -> 0 | N17: =予算原本_白鳥惣菜!M13 -> 0 | O17: =SUM(C17:N17) -> 0 | P17: =SUM(I17:N17) -> 0
B18: 手数料等 | C18: ='実績原本_白鳥惣菜_7-9月'!B14 -> 0 | D18: ='実績原本_白鳥惣菜_7-9月'!C14 -> 0 | E18: ='実績原本_白鳥惣菜_7-9月'!D14 -> 0 | F18: =予算原本_白鳥惣菜!E14 -> 0 | G18: =予算原本_白鳥惣菜!F14 -> 0 | H18: =予算原本_白鳥惣菜!G14 -> 0 | I18: =予算原本_白鳥惣菜!H14 -> 0 | J18: =予算原本_白鳥惣菜!I14 -> 0 | K18: =予算原本_白鳥惣菜!J14 -> 0 | L18: =予算原本_白鳥惣菜!K14 -> 0 | M18: =予算原本_白鳥惣菜!L14 -> 0 | N18: =予算原本_白鳥惣菜!M14 -> 0 | O18: =SUM(C18:N18) -> 0 | P18: =SUM(I18:N18) -> 0
B19: 荒利率 | C19: ='実績原本_白鳥惣菜_7-9月'!B15 -> 0 | D19: ='実績原本_白鳥惣菜_7-9月'!C15 -> 0 | E19: ='実績原本_白鳥惣菜_7-9月'!D15 -> 0 | F19: =予算原本_白鳥惣菜!E15 -> 0 | G19: =予算原本_白鳥惣菜!F15 -> 0 | H19: =予算原本_白鳥惣菜!G15 -> 0 | I19: =予算原本_白鳥惣菜!H15 -> 0 | J19: =予算原本_白鳥惣菜!I15 -> 0 | K19: =予算原本_白鳥惣菜!J15 -> 0 | L19: =予算原本_白鳥惣菜!K15 -> 0 | M19: =予算原本_白鳥惣菜!L15 -> 0 | N19: =予算原本_白鳥惣菜!M15 -> 0 | O19: =IF(O17=0,0,O18/O17) -> 0 | P19: =IF(P17=0,0,P18/P17) -> 0
B20: ④その他売上高 | C20: ='実績原本_白鳥惣菜_7-9月'!B16 -> 0 | D20: ='実績原本_白鳥惣菜_7-9月'!C16 -> 0 | E20: ='実績原本_白鳥惣菜_7-9月'!D16 -> 0 | F20: =予算原本_白鳥惣菜!E16 -> 0 | G20: =予算原本_白鳥惣菜!F16 -> 0 | H20: =予算原本_白鳥惣菜!G16 -> 0 | I20: =予算原本_白鳥惣菜!H16 -> 0 | J20: =予算原本_白鳥惣菜!I16 -> 0 | K20: =予算原本_白鳥惣菜!J16 -> 0 | L20: =予算原本_白鳥惣菜!K16 -> 0 | M20: =予算原本_白鳥惣菜!L16 -> 0 | N20: =予算原本_白鳥惣菜!M16 -> 0 | O20: =SUM(C20:N20) -> 0 | P20: =SUM(I20:N20) -> 0
B21: 販売奨励金 | C21: ='実績原本_白鳥惣菜_7-9月'!B17 -> 9658.3004 | D21: ='実績原本_白鳥惣菜_7-9月'!C17 -> 10345.059 | E21: ='実績原本_白鳥惣菜_7-9月'!D17 -> 8980.2514 | F21: =予算原本_白鳥惣菜!E17 -> 7700 | G21: =予算原本_白鳥惣菜!F17 -> 7480 | H21: =予算原本_白鳥惣菜!G17 -> 8450 | I21: =予算原本_白鳥惣菜!H17 -> 7680 | J21: =予算原本_白鳥惣菜!I17 -> 7277 | K21: =予算原本_白鳥惣菜!J17 -> 8245 | L21: =予算原本_白鳥惣菜!K17 -> 7900 | M21: =予算原本_白鳥惣菜!L17 -> 8000 | N21: =予算原本_白鳥惣菜!M17 -> 6447.2686 | O21: =SUM(C21:N21) -> 98162.879 | P21: =SUM(I21:N21) -> 45549.269
B22: 荒利率 | C22: ='実績原本_白鳥惣菜_7-9月'!B18 -> 0 | D22: ='実績原本_白鳥惣菜_7-9月'!C18 -> 0 | E22: ='実績原本_白鳥惣菜_7-9月'!D18 -> 0 | F22: =予算原本_白鳥惣菜!E18 -> 0 | G22: =予算原本_白鳥惣菜!F18 -> 0 | H22: =予算原本_白鳥惣菜!G18 -> 0 | I22: =予算原本_白鳥惣菜!H18 -> 0 | J22: =予算原本_白鳥惣菜!I18 -> 0 | K22: =予算原本_白鳥惣菜!J18 -> 0 | L22: =予算原本_白鳥惣菜!K18 -> 0 | M22: =予算原本_白鳥惣菜!L18 -> 0 | N22: =予算原本_白鳥惣菜!M18 -> 0 | O22: =IF(O20=0,0,O21/O20) -> 0 | P22: =IF(P20=0,0,P21/P20) -> 0
B23: 人件費 | C23: ='実績原本_白鳥惣菜_7-9月'!B19 -> 159123.95 | D23: ='実績原本_白鳥惣菜_7-9月'!C19 -> 163148.19 | E23: ='実績原本_白鳥惣菜_7-9月'!D19 -> 164121.69 | F23: =予算原本_白鳥惣菜!E19 -> 140499 | G23: =予算原本_白鳥惣菜!F19 -> 133546 | H23: =予算原本_白鳥惣菜!G19 -> 144822 | I23: =予算原本_白鳥惣菜!H19 -> 144712 | J23: =予算原本_白鳥惣菜!I19 -> 135001 | K23: =予算原本_白鳥惣菜!J19 -> 143688 | L23: =予算原本_白鳥惣菜!K19 -> 139346 | M23: =予算原本_白鳥惣菜!L19 -> 144350 | N23: =予算原本_白鳥惣菜!M19 -> 142608 | O23: =SUM(C23:N23) -> 1754965.8 | P23: =SUM(I23:N23) -> 849705
B24: 社員給与 | C24: ='実績原本_白鳥惣菜_7-9月'!B20 -> 103680.97 | D24: ='実績原本_白鳥惣菜_7-9月'!C20 -> 118115.4 | E24: ='実績原本_白鳥惣菜_7-9月'!D20 -> 112717.35 | F24: =予算原本_白鳥惣菜!E20 -> 96250 | G24: =予算原本_白鳥惣菜!F20 -> 86900 | H24: =予算原本_白鳥惣菜!G20 -> 94800 | I24: =予算原本_白鳥惣菜!H20 -> 99450 | J24: =予算原本_白鳥惣菜!I20 -> 90475 | K24: =予算原本_白鳥惣菜!J20 -> 96250 | L24: =予算原本_白鳥惣菜!K20 -> 95000 | M24: =予算原本_白鳥惣菜!L20 -> 95000 | N24: =予算原本_白鳥惣菜!M20 -> 97500 | O24: =SUM(C24:N24) -> 1186138.7 | P24: =SUM(I24:N24) -> 573675
B25: 契約社員人件費 | C25: ='実績原本_白鳥惣菜_7-9月'!B21 -> 0 | D25: ='実績原本_白鳥惣菜_7-9月'!C21 -> 0 | E25: ='実績原本_白鳥惣菜_7-9月'!D21 -> 0 | F25: =予算原本_白鳥惣菜!E21 -> 0 | G25: =予算原本_白鳥惣菜!F21 -> 0 | H25: =予算原本_白鳥惣菜!G21 -> 0 | I25: =予算原本_白鳥惣菜!H21 -> 0 | J25: =予算原本_白鳥惣菜!I21 -> 0 | K25: =予算原本_白鳥惣菜!J21 -> 0 | L25: =予算原本_白鳥惣菜!K21 -> 0 | M25: =予算原本_白鳥惣菜!L21 -> 0 | N25: =予算原本_白鳥惣菜!M21 -> 0 | O25: =SUM(C25:N25) -> 0 | P25: =SUM(I25:N25) -> 0
B26: 雑 給 | C26: ='実績原本_白鳥惣菜_7-9月'!B22 -> 19396.332 | D26: ='実績原本_白鳥惣菜_7-9月'!C22 -> 19221.482 | E26: ='実績原本_白鳥惣菜_7-9月'!D22 -> 17675.614 | F26: =予算原本_白鳥惣菜!E22 -> 18120 | G26: =予算原本_白鳥惣菜!F22 -> 18724 | H26: =予算原本_白鳥惣菜!G22 -> 20336 | I26: =予算原本_白鳥惣菜!H22 -> 18600 | J26: =予算原本_白鳥惣菜!I22 -> 18450 | K26: =予算原本_白鳥惣菜!J22 -> 19840 | L26: =予算原本_白鳥惣菜!K22 -> 18600 | M26: =予算原本_白鳥惣菜!L22 -> 19592 | N26: =予算原本_白鳥惣菜!M22 -> 18724 | O26: =SUM(C26:N26) -> 227279.43 | P26: =SUM(I26:N26) -> 113806
B27: 派遣代 | C27: ='実績原本_白鳥惣菜_7-9月'!B23 -> 9197.121 | D27: ='実績原本_白鳥惣菜_7-9月'!C23 -> -1271.735 | E27: ='実績原本_白鳥惣菜_7-9月'!D23 -> 5864.168 | F27: =予算原本_白鳥惣菜!E23 -> 100 | G27: =予算原本_白鳥惣菜!F23 -> 100 | H27: =予算原本_白鳥惣菜!G23 -> 3500 | I27: =予算原本_白鳥惣菜!H23 -> 100 | J27: =予算原本_白鳥惣菜!I23 -> 1000 | K27: =予算原本_白鳥惣菜!J23 -> 1500 | L27: =予算原本_白鳥惣菜!K23 -> 100 | M27: =予算原本_白鳥惣菜!L23 -> 1000 | N27: =予算原本_白鳥惣菜!M23 -> 100 | O27: =SUM(C27:N27) -> 21289.554 | P27: =SUM(I27:N27) -> 3800
B28: 賞 与 | C28: ='実績原本_白鳥惣菜_7-9月'!B24 -> 5160 | D28: ='実績原本_白鳥惣菜_7-9月'!C24 -> 5160 | E28: ='実績原本_白鳥惣菜_7-9月'!D24 -> 5160 | F28: =予算原本_白鳥惣菜!E24 -> 5160 | G28: =予算原本_白鳥惣菜!F24 -> 5160 | H28: =予算原本_白鳥惣菜!G24 -> 5160 | I28: =予算原本_白鳥惣菜!H24 -> 5160 | J28: =予算原本_白鳥惣菜!I24 -> 5160 | K28: =予算原本_白鳥惣菜!J24 -> 5160 | L28: =予算原本_白鳥惣菜!K24 -> 5160 | M28: =予算原本_白鳥惣菜!L24 -> 5160 | N28: =予算原本_白鳥惣菜!M24 -> 5160 | O28: =SUM(C28:N28) -> 61920 | P28: =SUM(I28:N28) -> 30960
B29: 法定福利費 | C29: ='実績原本_白鳥惣菜_7-9月'!B25 -> 19189.69 | D29: ='実績原本_白鳥惣菜_7-9月'!C25 -> 19595.368 | E29: ='実績原本_白鳥惣菜_7-9月'!D25 -> 19894.275 | F29: =予算原本_白鳥惣菜!E25 -> 17224 | G29: =予算原本_白鳥惣菜!F25 -> 15892 | H29: =予算原本_白鳥惣菜!G25 -> 17256 | I29: =予算原本_白鳥惣菜!H25 -> 17757 | J29: =予算原本_白鳥惣菜!I25 -> 16396 | K29: =予算原本_白鳥惣菜!J25 -> 17418 | L29: =予算原本_白鳥惣菜!K25 -> 17091 | M29: =予算原本_白鳥惣菜!L25 -> 17203 | N29: =予算原本_白鳥惣菜!M25 -> 17479 | O29: =SUM(C29:N29) -> 212395.33 | P29: =SUM(I29:N29) -> 103344
B30: 福利厚生費 | C30: ='実績原本_白鳥惣菜_7-9月'!B26 -> 2499.8363 | D30: ='実績原本_白鳥惣菜_7-9月'!C26 -> 2327.673 | E30: ='実績原本_白鳥惣菜_7-9月'!D26 -> 2810.286 | F30: =予算原本_白鳥惣菜!E26 -> 3635 | G30: =予算原本_白鳥惣菜!F26 -> 6760 | H30: =予算原本_白鳥惣菜!G26 -> 3760 | I30: =予算原本_白鳥惣菜!H26 -> 3635 | J30: =予算原本_白鳥惣菜!I26 -> 3510 | K30: =予算原本_白鳥惣菜!J26 -> 3510 | L30: =予算原本_白鳥惣菜!K26 -> 3385 | M30: =予算原本_白鳥惣菜!L26 -> 6385 | N30: =予算原本_白鳥惣菜!M26 -> 3635 | O30: =SUM(C30:N30) -> 45852.795 | P30: =SUM(I30:N30) -> 24060
B31: 按分対象者人件費 | C31: ='実績原本_白鳥惣菜_7-9月'!B27 -> 0 | D31: ='実績原本_白鳥惣菜_7-9月'!C27 -> 0 | E31: ='実績原本_白鳥惣菜_7-9月'!D27 -> 0 | F31: =予算原本_白鳥惣菜!E27 -> 0 | G31: =予算原本_白鳥惣菜!F27 -> 0 | H31: =予算原本_白鳥惣菜!G27 -> 0 | I31: =予算原本_白鳥惣菜!H27 -> 0 | J31: =予算原本_白鳥惣菜!I27 -> 0 | K31: =予算原本_白鳥惣菜!J27 -> 0 | L31: =予算原本_白鳥惣菜!K27 -> 0 | M31: =予算原本_白鳥惣菜!L27 -> 0 | N31: =予算原本_白鳥惣菜!M27 -> 0 | O31: =SUM(C31:N31) -> 0 | P31: =SUM(I31:N31) -> 0
B32: 採用教育・退職金 | C32: ='実績原本_白鳥惣菜_7-9月'!B28 -> 0 | D32: ='実績原本_白鳥惣菜_7-9月'!C28 -> 0 | E32: ='実績原本_白鳥惣菜_7-9月'!D28 -> 0 | F32: =予算原本_白鳥惣菜!E28 -> 10 | G32: =予算原本_白鳥惣菜!F28 -> 10 | H32: =予算原本_白鳥惣菜!G28 -> 10 | I32: =予算原本_白鳥惣菜!H28 -> 10 | J32: =予算原本_白鳥惣菜!I28 -> 10 | K32: =予算原本_白鳥惣菜!J28 -> 10 | L32: =予算原本_白鳥惣菜!K28 -> 10 | M32: =予算原本_白鳥惣菜!L28 -> 10 | N32: =予算原本_白鳥惣菜!M28 -> 10 | O32: =SUM(C32:N32) -> 90 | P32: =SUM(I32:N32) -> 60
B33: 広告・販促費 | C33: ='実績原本_白鳥惣菜_7-9月'!B29 -> 0 | D33: ='実績原本_白鳥惣菜_7-9月'!C29 -> 0 | E33: ='実績原本_白鳥惣菜_7-9月'!D29 -> 0 | F33: =予算原本_白鳥惣菜!E29 -> 0 | G33: =予算原本_白鳥惣菜!F29 -> 0 | H33: =予算原本_白鳥惣菜!G29 -> 0 | I33: =予算原本_白鳥惣菜!H29 -> 0 | J33: =予算原本_白鳥惣菜!I29 -> 0 | K33: =予算原本_白鳥惣菜!J29 -> 0 | L33: =予算原本_白鳥惣菜!K29 -> 0 | M33: =予算原本_白鳥惣菜!L29 -> 0 | N33: =予算原本_白鳥惣菜!M29 -> 0 | O33: =SUM(C33:N33) -> 0 | P33: =SUM(I33:N33) -> 0
B34: 広告費 | C34: ='実績原本_白鳥惣菜_7-9月'!B30 -> 0 | D34: ='実績原本_白鳥惣菜_7-9月'!C30 -> 0 | E34: ='実績原本_白鳥惣菜_7-9月'!D30 -> 0 | F34: =予算原本_白鳥惣菜!E30 -> 0 | G34: =予算原本_白鳥惣菜!F30 -> 0 | H34: =予算原本_白鳥惣菜!G30 -> 0 | I34: =予算原本_白鳥惣菜!H30 -> 0 | J34: =予算原本_白鳥惣菜!I30 -> 0 | K34: =予算原本_白鳥惣菜!J30 -> 0 | L34: =予算原本_白鳥惣菜!K30 -> 0 | M34: =予算原本_白鳥惣菜!L30 -> 0 | N34: =予算原本_白鳥惣菜!M30 -> 0 | O34: =SUM(C34:N34) -> 0 | P34: =SUM(I34:N34) -> 0
... B50: 発送配達費（運賃） | C50: ='実績原本_白鳥惣菜_7-9月'!B46 -> 48160.854 | D50: ='実績原本_白鳥惣菜_7-9月'!C46 -> 46164.248 | E50: ='実績原本_白鳥惣菜_7-9月'!D46 -> 43385.615 | F50: =予算原本_白鳥惣菜!E46 -> 37235.679 | G50: =予算原本_白鳥惣菜!F46 -> 36164.244 | H50: =予算原本_白鳥惣菜!G46 -> 40835.317 | I50: =予算原本_白鳥惣菜!H46 -> 37124.597 | J50: =予算原本_白鳥惣菜!I46 -> 35166.72 | K50: =予算原本_白鳥惣菜!J46 -> 39837.3 | L50: =予算原本_白鳥惣菜!K46 -> 38174.4 | M50: =予算原本_白鳥惣菜!L46 -> 38656.4 | N50: =予算原本_白鳥惣菜!M46 -> 37451.4 | O50: =SUM(C50:N50) -> 478356.77 | P50: =SUM(I50:N50) -> 226410.82
B51: 物流費（料率） | C51: ='実績原本_白鳥惣菜_7-9月'!B47 -> 0 | D51: ='実績原本_白鳥惣菜_7-9月'!C47 -> 0 | E51: ='実績原本_白鳥惣菜_7-9月'!D47 -> 0 | F51: =予算原本_白鳥惣菜!E47 -> 0 | G51: =予算原本_白鳥惣菜!F47 -> 0 | H51: =予算原本_白鳥惣菜!G47 -> 0 | I51: =予算原本_白鳥惣菜!H47 -> 0 | J51: =予算原本_白鳥惣菜!I47 -> 0 | K51: =予算原本_白鳥惣菜!J47 -> 0 | L51: =予算原本_白鳥惣菜!K47 -> 0 | M51: =予算原本_白鳥惣菜!L47 -> 0 | N51: =予算原本_白鳥惣菜!M47 -> 0 | O51: =IF(O49=0,0,O50/O49) -> 0 | P51: =IF(P49=0,0,P50/P49) -> 0
B52: 物流費（料率外） | C52: ='実績原本_白鳥惣菜_7-9月'!B48 -> 0 | D52: ='実績原本_白鳥惣菜_7-9月'!C48 -> 0 | E52: ='実績原本_白鳥惣菜_7-9月'!D48 -> 0 | F52: =予算原本_白鳥惣菜!E48 -> 0 | G52: =予算原本_白鳥惣菜!F48 -> 0 | H52: =予算原本_白鳥惣菜!G48 -> 0 | I52: =予算原本_白鳥惣菜!H48 -> 0 | J52: =予算原本_白鳥惣菜!I48 -> 0 | K52: =予算原本_白鳥惣菜!J48 -> 0 | L52: =予算原本_白鳥惣菜!K48 -> 0 | M52: =予算原本_白鳥惣菜!L48 -> 0 | N52: =予算原本_白鳥惣菜!M48 -> 0 | O52: =IF(O50=0,0,O51/O50) -> 0 | P52: =IF(P50=0,0,P51/P50) -> 0
B53: 支払手数料 | C53: ='実績原本_白鳥惣菜_7-9月'!B49 -> 7878.869 | D53: ='実績原本_白鳥惣菜_7-9月'!C49 -> 7542.759 | E53: ='実績原本_白鳥惣菜_7-9月'!D49 -> 8222.931 | F53: =予算原本_白鳥惣菜!E49 -> 8837 | G53: =予算原本_白鳥惣菜!F49 -> 8962 | H53: =予算原本_白鳥惣菜!G49 -> 8962 | I53: =予算原本_白鳥惣菜!H49 -> 8837 | J53: =予算原本_白鳥惣菜!I49 -> 8812 | K53: =予算原本_白鳥惣菜!J49 -> 8812 | L53: =予算原本_白鳥惣菜!K49 -> 8812 | M53: =予算原本_白鳥惣菜!L49 -> 8812 | N53: =予算原本_白鳥惣菜!M49 -> 8962 | O53: =SUM(C53:N53) -> 103452.56 | P53: =SUM(I53:N53) -> 53047
B54: 車両費 | C54: ='実績原本_白鳥惣菜_7-9月'!B50 -> 0 | D54: ='実績原本_白鳥惣菜_7-9月'!C50 -> 0 | E54: ='実績原本_白鳥惣菜_7-9月'!D50 -> 0 | F54: =予算原本_白鳥惣菜!E50 -> 0 | G54: =予算原本_白鳥惣菜!F50 -> 0 | H54: =予算原本_白鳥惣菜!G50 -> 0 | I54: =予算原本_白鳥惣菜!H50 -> 0 | J54: =予算原本_白鳥惣菜!I50 -> 0 | K54: =予算原本_白鳥惣菜!J50 -> 0 | L54: =予算原本_白鳥惣菜!K50 -> 0 | M54: =予算原本_白鳥惣菜!L50 -> 0 | N54: =予算原本_白鳥惣菜!M50 -> 0 | O54: =SUM(C54:N54) -> 0 | P54: =SUM(I54:N54) -> 0
B55: 新聞図書費 | C55: ='実績原本_白鳥惣菜_7-9月'!B51 -> 0 | D55: ='実績原本_白鳥惣菜_7-9月'!C51 -> 0 | E55: ='実績原本_白鳥惣菜_7-9月'!D51 -> 0 | F55: =予算原本_白鳥惣菜!E51 -> 0 | G55: =予算原本_白鳥惣菜!F51 -> 0 | H55: =予算原本_白鳥惣菜!G51 -> 0 | I55: =予算原本_白鳥惣菜!H51 -> 0 | J55: =予算原本_白鳥惣菜!I51 -> 0 | K55: =予算原本_白鳥惣菜!J51 -> 0 | L55: =予算原本_白鳥惣菜!K51 -> 0 | M55: =予算原本_白鳥惣菜!L51 -> 0 | N55: =予算原本_白鳥惣菜!M51 -> 0 | O55: =SUM(C55:N55) -> 0 | P55: =SUM(I55:N55) -> 0
B56: リース料 | C56: ='実績原本_白鳥惣菜_7-9月'!B52 -> 1059.403 | D56: ='実績原本_白鳥惣菜_7-9月'!C52 -> 1061.529 | E56: ='実績原本_白鳥惣菜_7-9月'!D52 -> 1062.592 | F56: =予算原本_白鳥惣菜!E52 -> 1032 | G56: =予算原本_白鳥惣菜!F52 -> 1032 | H56: =予算原本_白鳥惣菜!G52 -> 1032 | I56: =予算原本_白鳥惣菜!H52 -> 1032 | J56: =予算原本_白鳥惣菜!I52 -> 1032 | K56: =予算原本_白鳥惣菜!J52 -> 1032 | L56: =予算原本_白鳥惣菜!K52 -> 1032 | M56: =予算原本_白鳥惣菜!L52 -> 1032 | N56: =予算原本_白鳥惣菜!M52 -> 1032 | O56: =SUM(C56:N56) -> 12471.524 | P56: =SUM(I56:N56) -> 6192
B57: 顧問料 | C57: ='実績原本_白鳥惣菜_7-9月'!B53 -> 0 | D57: ='実績原本_白鳥惣菜_7-9月'!C53 -> 0 | E57: ='実績原本_白鳥惣菜_7-9月'!D53 -> 0 | F57: =予算原本_白鳥惣菜!E53 -> 0 | G57: =予算原本_白鳥惣菜!F53 -> 0 | H57: =予算原本_白鳥惣菜!G53 -> 0 | I57: =予算原本_白鳥惣菜!H53 -> 0 | J57: =予算原本_白鳥惣菜!I53 -> 0 | K57: =予算原本_白鳥惣菜!J53 -> 0 | L57: =予算原本_白鳥惣菜!K53 -> 0 | M57: =予算原本_白鳥惣菜!L53 -> 0 | N57: =予算原本_白鳥惣菜!M53 -> 0 | O57: =SUM(C57:N57) -> 0 | P57: =SUM(I57:N57) -> 0
B58: 雑 費 | C58: ='実績原本_白鳥惣菜_7-9月'!B54 -> 0 | D58: ='実績原本_白鳥惣菜_7-9月'!C54 -> 0 | E58: ='実績原本_白鳥惣菜_7-9月'!D54 -> 0 | F58: =予算原本_白鳥惣菜!E54 -> 10 | G58: =予算原本_白鳥惣菜!F54 -> 10 | H58: =予算原本_白鳥惣菜!G54 -> 10 | I58: =予算原本_白鳥惣菜!H54 -> 10 | J58: =予算原本_白鳥惣菜!I54 -> 10 | K58: =予算原本_白鳥惣菜!J54 -> 10 | L58: =予算原本_白鳥惣菜!K54 -> 10 | M58: =予算原本_白鳥惣菜!L54 -> 10 | N58: =予算原本_白鳥惣菜!M54 -> 10 | O58: =SUM(C58:N58) -> 90 | P58: =SUM(I58:N58) -> 60
B59: 減価償却費 | C59: ='実績原本_白鳥惣菜_7-9月'!B55 -> 7403.246 | D59: ='実績原本_白鳥惣菜_7-9月'!C55 -> 7403.24 | E59: ='実績原本_白鳥惣菜_7-9月'!D55 -> 7403.251 | F59: =予算原本_白鳥惣菜!E55 -> 11393.228 | G59: =予算原本_白鳥惣菜!F55 -> 12143.228 | H59: =予算原本_白鳥惣菜!G55 -> 12226.562 | I59: =予算原本_白鳥惣菜!H55 -> 12226.562 | J59: =予算原本_白鳥惣菜!I55 -> 12476.562 | K59: =予算原本_白鳥惣菜!J55 -> 12476.562 | L59: =予算原本_白鳥惣菜!K55 -> 12476.562 | M59: =予算原本_白鳥惣菜!L55 -> 12476.562 | N59: =予算原本_白鳥惣菜!M55 -> 12476.562 | O59: =SUM(C59:N59) -> 132582.13 | P59: =SUM(I59:N59) -> 74609.37
B60: 保守契約料 | C60: ='実績原本_白鳥惣菜_7-9月'!B56 -> 2135.419 | D60: ='実績原本_白鳥惣菜_7-9月'!C56 -> 5352.7387 | E60: ='実績原本_白鳥惣菜_7-9月'!D56 -> 1958.1627 | F60: =予算原本_白鳥惣菜!E56 -> 1160 | G60: =予算原本_白鳥惣菜!F56 -> 1506 | H60: =予算原本_白鳥惣菜!G56 -> 1605 | I60: =予算原本_白鳥惣菜!H56 -> 1285 | J60: =予算原本_白鳥惣菜!I56 -> 1160 | K60: =予算原本_白鳥惣菜!J56 -> 1190 | L60: =予算原本_白鳥惣菜!K56 -> 1160 | M60: =予算原本_白鳥惣菜!L56 -> 1324 | N60: =予算原本_白鳥惣菜!M56 -> 1741 | O60: =SUM(C60:N60) -> 21577.32 | P60: =SUM(I60:N60) -> 7860
B61: 外注費（派遣など） | C61: ='実績原本_白鳥惣菜_7-9月'!B57 -> 3202.859 | D61: ='実績原本_白鳥惣菜_7-9月'!C57 -> 3019.609 | E61: ='実績原本_白鳥惣菜_7-9月'!D57 -> -3869.555 | F61: =予算原本_白鳥惣菜!E57 -> 300 | G61: =予算原本_白鳥惣菜!F57 -> 300 | H61: =予算原本_白鳥惣菜!G57 -> 300 | I61: =予算原本_白鳥惣菜!H57 -> 300 | J61: =予算原本_白鳥惣菜!I57 -> 300 | K61: =予算原本_白鳥惣菜!J57 -> 300 | L61: =予算原本_白鳥惣菜!K57 -> 300 | M61: =予算原本_白鳥惣菜!L57 -> 300 | N61: =予算原本_白鳥惣菜!M57 -> 300 | O61: =SUM(C61:N61) -> 5052.913 | P61: =SUM(I61:N61) -> 1800
B62: 経費合計 | C62: ='実績原本_白鳥惣菜_7-9月'!B58 -> 264977.19 | D62: ='実績原本_白鳥惣菜_7-9月'!C58 -> 260436.33 | E62: ='実績原本_白鳥惣菜_7-9月'!D58 -> 248574.11 | F62: =予算原本_白鳥惣菜!E58 -> 218565.51 | G62: =予算原本_白鳥惣菜!F58 -> 208982.07 | H62: =予算原本_白鳥惣菜!G58 -> 232441.48 | I62: =予算原本_白鳥惣菜!H58 -> 221115.76 | J62: =予算原本_白鳥惣菜!I58 -> 209676.88 | K62: =予算原本_白鳥惣菜!J58 -> 231054.46 | L62: =予算原本_白鳥惣菜!K58 -> 221039.56 | M62: =予算原本_白鳥惣菜!L58 -> 225189.56 | N62: =予算原本_白鳥惣菜!M58 -> 222969.56 | O62: =SUM(C62:N62) -> 2765022.5 | P62: =SUM(I62:N62) -> 1331045.8
B63: 受取家賃 | C63: ='実績原本_白鳥惣菜_7-9月'!B59 -> 0 | D63: ='実績原本_白鳥惣菜_7-9月'!C59 -> 0 | E63: ='実績原本_白鳥惣菜_7-9月'!D59 -> 0 | F63: =予算原本_白鳥惣菜!E59 -> 0 | G63: =予算原本_白鳥惣菜!F59 -> 0 | H63: =予算原本_白鳥惣菜!G59 -> 0 | I63: =予算原本_白鳥惣菜!H59 -> 0 | J63: =予算原本_白鳥惣菜!I59 -> 0 | K63: =予算原本_白鳥惣菜!J59 -> 0 | L63: =予算原本_白鳥惣菜!K59 -> 0 | M63: =予算原本_白鳥惣菜!L59 -> 0 | N63: =予算原本_白鳥惣菜!M59 -> 0 | O63: =SUM(C63:N63) -> 0 | P63: =SUM(I63:N63) -> 0
B64: 営業利益高 | C64: ='実績原本_白鳥惣菜_7-9月'!B60 -> -21486.888 | D64: ='実績原本_白鳥惣菜_7-9月'!C60 -> 21593.929 | E64: ='実績原本_白鳥惣菜_7-9月'!D60 -> -1617.3532 | F64: =予算原本_白鳥惣菜!E60 -> 1098.9632 | G64: =予算原本_白鳥惣菜!F60 -> 4249.4476 | H64: =予算原本_白鳥惣菜!G60 -> 8054.2711 | I64: =予算原本_白鳥惣菜!H60 -> -2319.8961 | J64: =予算原本_白鳥惣菜!I60 -> -2565.4817 | K64: =予算原本_白鳥惣菜!J60 -> 3454.5383 | L64: =予算原本_白鳥惣菜!K60 -> 3740.4383 | M64: =予算原本_白鳥惣菜!L60 -> 2410.4383 | N64: =予算原本_白鳥惣菜!M60 -> -3722.2931 | O64: =SUM(C64:N64) -> 12890.114 | P64: =SUM(I64:N64) -> 997.744
... B70: 経常利益 | C70: ='実績原本_白鳥惣菜_7-9月'!B66 -> -21486.83 | D70: ='実績原本_白鳥惣菜_7-9月'!C66 -> 21609.749 | E70: ='実績原本_白鳥惣菜_7-9月'!D66 -> -1617.3532 | F70: =予算原本_白鳥惣菜!E66 -> 1098.9632 | G70: =予算原本_白鳥惣菜!F66 -> 4249.4476 | H70: =予算原本_白鳥惣菜!G66 -> 8054.2711 | I70: =予算原本_白鳥惣菜!H66 -> -2319.8961 | J70: =予算原本_白鳥惣菜!I66 -> -2565.4817 | K70: =予算原本_白鳥惣菜!J66 -> 3454.5383 | L70: =予算原本_白鳥惣菜!K66 -> 3740.4383 | M70: =予算原本_白鳥惣菜!L66 -> 2410.4383 | N70: =予算原本_白鳥惣菜!M66 -> -3722.2931 | O70: =SUM(C70:N70) -> 12905.992 | P70: =SUM(I70:N70) -> 997.744
B72: ② 充填機導入による増減（「白鳥惣菜PL_導入効果」シート②と同じ）
B73: 雑給（人件費削減） | C73: =白鳥惣菜PL_導入効果!C74 -> 0 | D73: =白鳥惣菜PL_導入効果!D74 -> 0 | E73: =白鳥惣菜PL_導入効果!E74 -> 0 | F73: =白鳥惣菜PL_導入効果!F74 -> 0 | G73: =白鳥惣菜PL_導入効果!G74 -> 0 | H73: =白鳥惣菜PL_導入効果!H74 -> 0 | I73: =白鳥惣菜PL_導入効果!I74 -> 0 | J73: =白鳥惣菜PL_導入効果!J74 -> -161 | ... P73: =白鳥惣菜PL_導入効果!P74 -> -862.5
B74: 消耗品費（絞り袋削減） | C74: =白鳥惣菜PL_導入効果!C75 -> 0 | D74: =白鳥惣菜PL_導入効果!D75 -> 0 | E74: =白鳥惣菜PL_導入効果!E75 -> 0 | F74: =白鳥惣菜PL_導入効果!F75 -> 0 | G74: =白鳥惣菜PL_導入効果!G75 -> 0 | H74: =白鳥惣菜PL_導入効果!H75 -> 0 | I74: =白鳥惣菜PL_導入効果!I75 -> 0 | J74: =白鳥惣菜PL_導入効果!J75 -> -2.688 | ... P74: =白鳥惣菜PL_導入効果!P75 -> -14.4
B75: 水道光熱費（電気・洗浄水） | C75: =白鳥惣菜PL_導入効果!C76 -> 0 | D75: =白鳥惣菜PL_導入効果!D76 -> 0 | E75: =白鳥惣菜PL_導入効果!E76 -> 0 | F75: =白鳥惣菜PL_導入効果!F76 -> 0 | G75: =白鳥惣菜PL_導入効果!G76 -> 0 | H75: =白鳥惣菜PL_導入効果!H76 -> 0 | I75: =白鳥惣菜PL_導入効果!I76 -> 0 | J75: =白鳥惣菜PL_導入効果!J76 -> 5.88 | ... P75: =白鳥惣菜PL_導入効果!P76 -> 31.5
B76: 修繕費（保守部品） | C76: =白鳥惣菜PL_導入効果!C77 -> 0 | D76: =白鳥惣菜PL_導入効果!D77 -> 0 | E76: =白鳥惣菜PL_導入効果!E77 -> 0 | F76: =白鳥惣菜PL_導入効果!F77 -> 0 | G76: =白鳥惣菜PL_導入効果!G77 -> 0 | H76: =白鳥惣菜PL_導入効果!H77 -> 0 | I76: =白鳥惣菜PL_導入効果!I77 -> 0 | J76: =白鳥惣菜PL_導入効果!J77 -> 7.5 | ... P76: =白鳥惣菜PL_導入効果!P77 -> 37.5
B77: 減価償却費（機械・10年定額） | C77: =白鳥惣菜PL_導入効果!C78 -> 0 | D77: =白鳥惣菜PL_導入効果!D78 -> 0 | E77: =白鳥惣菜PL_導入効果!E78 -> 0 | F77: =白鳥惣菜PL_導入効果!F78 -> 0 | G77: =白鳥惣菜PL_導入効果!G78 -> 0 | H77: =白鳥惣菜PL_導入効果!H78 -> 0 | I77: =白鳥惣菜PL_導入効果!I78 -> 0 | J77: =白鳥惣菜PL_導入効果!J78 -> 37.5 | ... P77: =白鳥惣菜PL_導入効果!P78 -> 187.5
B78: 減価償却費（電気・付帯工事） | C78: =白鳥惣菜PL_導入効果!C79 -> 0 | D78: =白鳥惣菜PL_導入効果!D79 -> 0 | E78: =白鳥惣菜PL_導入効果!E79 -> 0 | F78: =白鳥惣菜PL_導入効果!F79 -> 0 | G78: =白鳥惣菜PL_導入効果!G79 -> 0 | H78: =白鳥惣菜PL_導入効果!H79 -> 0 | I78: =白鳥惣菜PL_導入効果!I79 -> 0 | J78: =白鳥惣菜PL_導入効果!J79 -> 4.1666667 | ... P78: =白鳥惣菜PL_導入効果!P79 -> 20.833333
B79: 修繕費（電気・付帯工事・一括費用） | C79: =白鳥惣菜PL_導入効果!C80 -> 0 | D79: =白鳥惣菜PL_導入効果!D80 -> 0 | E79: =白鳥惣菜PL_導入効果!E80 -> 0 | F79: =白鳥惣菜PL_導入効果!F80 -> 0 | G79: =白鳥惣菜PL_導入効果!G80 -> 0 | H79: =白鳥惣菜PL_導入効果!H80 -> 0 | I79: =白鳥惣菜PL_導入効果!I80 -> 0 | J79: =白鳥惣菜PL_導入効果!J80 -> 0 | ... P79: =白鳥惣菜PL_導入効果!P80 -> 0
B80: 経費増減 合計 | C80: =白鳥惣菜PL_導入効果!C81 -> 0 | D80: =白鳥惣菜PL_導入効果!D81 -> 0 | E80: =白鳥惣菜PL_導入効果!E81 -> 0 | F80: =白鳥惣菜PL_導入効果!F81 -> 0 | G80: =白鳥惣菜PL_導入効果!G81 -> 0 | H80: =白鳥惣菜PL_導入効果!H81 -> 0 | I80: =白鳥惣菜PL_導入効果!I81 -> 0 | J80: =白鳥惣菜PL_導入効果!J81 -> -108.64133 | ... P80: =白鳥惣菜PL_導入効果!P81 -> -599.56667
B81: 経常利益への影響 | C81: =白鳥惣菜PL_導入効果!C82 -> 0 | D81: =白鳥惣菜PL_導入効果!D82 -> 0 | E81: =白鳥惣菜PL_導入効果!E82 -> 0 | F81: =白鳥惣菜PL_導入効果!F82 -> 0 | G81: =白鳥惣菜PL_導入効果!G82 -> 0 | H81: =白鳥惣菜PL_導入効果!H82 -> 0 | I81: =白鳥惣菜PL_導入効果!I82 -> 0 | J81: =白鳥惣菜PL_導入効果!J82 -> 108.64133 | ... P81: =白鳥惣菜PL_導入効果!P82 -> 599.56667
B83: ③ 充填機導入後 PL（実績＋予算見込＋②） ※黄色行＝充填機導入で変動する科目
B84: 売 上 高 | C84: =C8 -> 859016.86 | D84: =D8 -> 980922.58 | E84: =E8 -> 810842.5 | F84: =F8 -> 772524.47 | G84: =G8 -> 750295.52 | H84: =H8 -> 847205.75 | I84: =I8 -> 770219.86 | J84: =J8 -> 729600 | ... N84: =N8 -> 777000 | O84: =SUM(C84:N84) -> 9718127.5 | P84: =SUM(I84:N84) -> 4697319.9
B85: 売上総利益 | C85: =C9 -> 243490.3 | D85: =D9 -> 282030.26 | E85: =E9 -> 246956.76 | F85: =F9 -> 219664.47 | G85: =G9 -> 213231.52 | H85: =H9 -> 240495.75 | I85: =I9 -> 218795.86 | J85: =J9 -> 207111.4 | ... N85: =N9 -> 219247.27 | O85: =SUM(C85:N85) -> 2777912.6 | P85: =SUM(I85:N85) -> 1332043.5
B86: 荒利率 | C86: =IF(C84=0,0,C85/C84) -> 0.28345229 | D86: =IF(D84=0,0,D85/D84) -> 0.28751531 | E86: =IF(E84=0,0,E85/E84) -> 0.3045681 | F86: =IF(F84=0,0,F85/F84) -> 0.28434629 | G86: =IF(G84=0,0,G85/G84) -> 0.28419671 | H86: =IF(H84=0,0,H85/H84) -> 0.28386936 | I86: =IF(I84=0,0,I85/I84) -> 0.28406936 | J86: =IF(J84=0,0,J85/J84) -> 0.28386979 | ... P86: =IF(P84=0,0,P85/P84) -> 0.28357522
B87: 商品卸売上高 | C87: =C11 -> 856552.1 | D87: =D11 -> 978185.97 | E87: =E11 -> 808524.62 | F87: =F11 -> 770000 | G87: =G11 -> 748000 | H87: =H11 -> 845000 | I87: =I11 -> 768000 | J87: =J11 -> 727700 | ... N87: =N11 -> 775000 | O87: =SUM(C87:N87) -> 9691462.7 | P87: =SUM(I87:N87) -> 4685200
B88: 荒利益高 | C88: =C12 -> 231367.24 | D88: =D12 -> 268948.59 | E88: =E12 -> 235658.63 | F88: =F12 -> 209440 | G88: =G12 -> 203456 | H88: =H12 -> 229840 | I88: =I12 -> 208896 | J88: =J12 -> 197934.4 | ... N88: =N12 -> 210800 | O88: =SUM(C88:N88) -> 2653084.9 | P88: =SUM(I88:N88) -> 1274374.4
B89: 荒利率 | C89: =IF(C87=0,0,C88/C87) -> 0.27011461 | D89: =IF(D87=0,0,D88/D87) -> 0.27494627 | E89: =IF(E87=0,0,E88/E87) -> 0.29146748 | F89: =IF(F87=0,0,F88/F87) -> 0.272 | G89: =IF(G87=0,0,G88/G87) -> 0.272 | H89: =IF(H87=0,0,H88/H87) -> 0.272 | I89: =IF(I87=0,0,I88/I87) -> 0.272 | J89: =IF(J87=0,0,J88/J87) -> 0.272 | ... P89: =IF(P87=0,0,P88/P87) -> 0.272
B90: 物流フィ高 | C90: =C14 -> 2464.763 | D90: =D14 -> 2736.609 | E90: =E14 -> 2317.878 | F90: =F14 -> 2524.471 | G90: =G14 -> 2295.52 | H90: =H14 -> 2205.75 | I90: =I14 -> 2219.863 | J90: =J14 -> 1900 | ... N90: =N14 -> 2000 | O90: =SUM(C90:N90) -> 26664.854 | P90: =SUM(I90:N90) -> 12119.863
B91: 物流フィ高及びサービスリサイクル料等 | C91: =C15 -> 2464.763 | D91: =D15 -> 2736.609 | E91: =E15 -> 2317.878 | F91: =F15 -> 2524.471 | G91: =G15 -> 2295.52 | H91: =H15 -> 2205.75 | I91: =I15 -> 2219.863 | J91: =J15 -> 1900 | ... N91: =N15 -> 2000 | O91: =SUM(C91:N91) -> 26664.854 | P91: =SUM(I91:N91) -> 12119.863
B92: 荒利率 | C92: =IF(C90=0,0,C91/C90) -> 1 | D92: =IF(D90=0,0,D91/D90) -> 1 | E92: =IF(E90=0,0,E91/E90) -> 1 | F92: =IF(F90=0,0,F91/F90) -> 1 | G92: =IF(G90=0,0,G91/G90) -> 1 | H92: =IF(H90=0,0,H91/H90) -> 1 | I92: =IF(I90=0,0,I91/I90) -> 1 | J92: =IF(J90=0,0,J91/J90) -> 1 | ... P92: =IF(P90=0,0,P91/P90) -> 1
B93: 手数料等売上高 | C93: =C17 -> 0 | D93: =D17 -> 0 | E93: =E17 -> 0 | F93: =F17 -> 0 | G93: =G17 -> 0 | H93: =H17 -> 0 | I93: =I17 -> 0 | J93: =J17 -> 0 | ... N93: =N17 -> 0 | O93: =SUM(C93:N93) -> 0 | P93: =SUM(I93:N93) -> 0
B94: 手数料等 | C94: =C18 -> 0 | D94: =D18 -> 0 | E94: =E18 -> 0 | F94: =F18 -> 0 | G94: =G18 -> 0 | H94: =H18 -> 0 | I94: =I18 -> 0 | J94: =J18 -> 0 | ... N94: =N18 -> 0 | O94: =SUM(C94:N94) -> 0 | P94: =SUM(I94:N94) -> 0
B95: 荒利率 | C95: =IF(C93=0,0,C94/C93) -> 0 | D95: =IF(D93=0,0,D94/D93) -> 0 | E95: =IF(E93=0,0,E94/E93) -> 0 | F95: =IF(F93=0,0,F94/F93) -> 0 | G95: =IF(G93=0,0,G94/G93) -> 0 | H95: =IF(H93=0,0,H94/H93) -> 0 | I95: =IF(I93=0,0,I94/I93) -> 0 | J95: =IF(J93=0,0,J94/J93) -> 0 | ... P95: =IF(P93=0,0,P94/P93) -> 0
B96: ④その他売上高 | C96: =C20 -> 0 | D96: =D20 -> 0 | E96: =E20 -> 0 | F96: =F20 -> 0 | G96: =G20 -> 0 | H96: =H20 -> 0 | I96: =I20 -> 0 | J96: =J20 -> 0 | ... N96: =N20 -> 0 | O96: =SUM(C96:N96) -> 0 | P96: =SUM(I96:N96) -> 0
B97: 販売奨励金 | C97: =C21 -> 9658.3004 | D97: =D21 -> 10345.059 | E97: =E21 -> 8980.2514 | F97: =F21 -> 7700 | G97: =G21 -> 7480 | H97: =H21 -> 8450 | I97: =I21 -> 7680 | J97: =J21 -> 7277 | ... N97: =N21 -> 6447.2686 | O97: =SUM(C97:N97) -> 98162.879 | P97: =SUM(I97:N97) -> 45549.269
B98: 荒利率 | C98: =IF(C96=0,0,C97/C96) -> 0 | D98: =IF(D96=0,0,D97/D96) -> 0 | E98: =IF(E96=0,0,E97/E96) -> 0 | F98: =IF(F96=0,0,F97/F96) -> 0 | G98: =IF(G96=0,0,G97/G96) -> 0 | H98: =IF(H96=0,0,H97/H96) -> 0 | I98: =IF(I96=0,0,I97/I96) -> 0 | J98: =IF(J96=0,0,J97/J96) -> 0 | ... P98: =IF(P96=0,0,P97/P96) -> 0
B99: 人件費 | C99: =SUM(C100:C108) -> 159123.95 | D99: =SUM(D100:D108) -> 163148.19 | E99: =SUM(E100:E108) -> 164121.69 | F99: =SUM(F100:F108) -> 140499 | G99: =SUM(G100:G108) -> 133546 | H99: =SUM(H100:H108) -> 144822 | I99: =SUM(I100:I108) -> 144712 | J99: =SUM(J100:J108) -> 134840 | ... N99: =SUM(N100:N108) -> 142435.5 | O99: =SUM(C99:N99) -> 1754103.3 | P99: =SUM(I99:N99) -> 848842.5
B100: 社員給与 | C100: =C24 -> 103680.97 | D100: =D24 -> 118115.4 | E100: =E24 -> 112717.35 | F100: =F24 -> 96250 | G100: =G24 -> 86900 | H100: =H24 -> 94800 | I100: =I24 -> 99450 | J100: =J24 -> 90475 | ... N100: =N24 -> 97500 | O100: =SUM(C100:N100) -> 1186138.7 | P100: =SUM(I100:N100) -> 573675
B101: 契約社員人件費 | C101: =C25 -> 0 | D101: =D25 -> 0 | E101: =E25 -> 0 | F101: =F25 -> 0 | G101: =G25 -> 0 | H101: =H25 -> 0 | I101: =I25 -> 0 | J101: =J25 -> 0 | ... N101: =N25 -> 0 | O101: =SUM(C101:N101) -> 0 | P101: =SUM(I101:N101) -> 0
B102: 雑 給 | C102: =C26+C73 -> 19396.332 | D102: =D26+D73 -> 19221.482 | E102: =E26+E73 -> 17675.614 | F102: =F26+F73 -> 18120 | G102: =G26+G73 -> 18724 | H102: =H26+H73 -> 20336 | I102: =I26+I73 -> 18600 | J102: =J26+J73 -> 18289 | ... N102: =N26+N73 -> 18551.5 | O102: =SUM(C102:N102) -> 226416.93 | P102: =SUM(I102:N102) -> 112943.5 | Q102: ← 充填機導入による増減を反映
B103: 派遣代 | C103: =C27 -> 9197.121 | D103: =D27 -> -1271.735 | E103: =E27 -> 5864.168 | F103: =F27 -> 100 | G103: =G27 -> 100 | H103: =H27 -> 3500 | I103: =I27 -> 100 | J103: =J27 -> 1000 | ... N103: =N27 -> 100 | O103: =SUM(C103:N103) -> 21289.554 | P103: =SUM(I103:N103) -> 3800
B104: 賞 与 | C104: =C28 -> 5160 | D104: =D28 -> 5160 | E104: =E28 -> 5160 | F104: =F28 -> 5160 | G104: =G28 -> 5160 | H104: =H28 -> 5160 | I104: =I28 -> 5160 | J104: =J28 -> 5160 | ... N104: =N28 -> 5160 | O104: =SUM(C104:N104) -> 61920 | P104: =SUM(I104:N104) -> 30960
B105: 法定福利費 | C105: =C29 -> 19189.69 | D105: =D29 -> 19595.368 | E105: =E29 -> 19894.275 | F105: =F29 -> 17224 | G105: =G29 -> 15892 | H105: =H29 -> 17256 | I105: =I29 -> 17757 | J105: =J29 -> 16396 | ... N105: =N29 -> 17479 | O105: =SUM(C105:N105) -> 212395.33 | P105: =SUM(I105:N105) -> 103344
B106: 福利厚生費 | C106: =C30 -> 2499.8363 | D106: =D30 -> 2327.673 | E106: =E30 -> 2810.286 | F106: =F30 -> 3635 | G106: =G30 -> 6760 | H106: =H30 -> 3760 | I106: =I30 -> 3635 | J106: =J30 -> 3510 | ... N106: =N30 -> 3635 | O106: =SUM(C106:N106) -> 45852.795 | P106: =SUM(I106:N106) -> 24060
B107: 按分対象者人件費 | C107: =C31 -> 0 | D107: =D31 -> 0 | E107: =E31 -> 0 | F107: =F31 -> 0 | G107: =G31 -> 0 | H107: =H31 -> 0 | I107: =I31 -> 0 | J107: =J31 -> 0 | ... N107: =N31 -> 0 | O107: =SUM(C107:N107) -> 0 | P107: =SUM(I107:N107) -> 0
B108: 採用教育・退職金 | C108: =C32 -> 0 | D108: =D32 -> 0 | E108: =E32 -> 0 | F108: =F32 -> 10 | G108: =G32 -> 10 | H108: =H32 -> 10 | I108: =I32 -> 10 | J108: =J32 -> 10 | ... N108: =N32 -> 10 | O108: =SUM(C108:N108) -> 90 | P108: =SUM(I108:N108) -> 60
B109: 広告・販促費 | C109: =SUM(C110:C111) -> 0 | D109: =SUM(D110:D111) -> 0 | E109: =SUM(E110:E111) -> 0 | F109: =SUM(F110:F111) -> 0 | G109: =SUM(G110:G111) -> 0 | H109: =SUM(H110:H111) -> 0 | I109: =SUM(I110:I111) -> 0 | J109: =SUM(J110:J111) -> 0 | ... N109: =SUM(N110:N111) -> 0 | O109: =SUM(C109:N109) -> 0 | P109: =SUM(I109:N109) -> 0
B110: 広告費 | C110: =C34 -> 0 | D110: =D34 -> 0 | E110: =E34 -> 0 | F110: =F34 -> 0 | G110: =G34 -> 0 | H110: =H34 -> 0 | I110: =I34 -> 0 | J110: =J34 -> 0 | ... N110: =N34 -> 0 | O110: =SUM(C110:N110) -> 0 | P110: =SUM(I110:N110) -> 0
B111: 販売促進費 | C111: =C35 -> 0 | D111: =D35 -> 0 | E111: =E35 -> 0 | F111: =F35 -> 0 | G111: =G35 -> 0 | H111: =H35 -> 0 | I111: =I35 -> 0 | J111: =J35 -> 0 | ... N111: =N35 -> 0 | O111: =SUM(C111:N111) -> 0 | P111: =SUM(I111:N111) -> 0
B112: 不動産費 | C112: =SUM(C113:C115) -> 4654.458 | D112: =SUM(D113:D115) -> 4650.976 | E112: =SUM(E113:E115) -> 4649.648 | F112: =SUM(F113:F115) -> 2069.6 | G112: =SUM(G113:G115) -> 2069.6 | H112: =SUM(H113:H115) -> 2069.6 | I112: =SUM(I113:I115) -> 2069.6 | J112: =SUM(J113:J115) -> 2069.6 | ... N112: =SUM(N113:N115) -> 2069.6 | O112: =SUM(C112:N112) -> 32581.482 | P112: =SUM(I112:N112) -> 12417.6
B113: 地 代 | C113: =C37 -> 0 | D113: =D37 -> 0 | E113: =E37 -> 0 | F113: =F37 -> 0 | G113: =G37 -> 0 | H113: =H37 -> 0 | I113: =I37 -> 0 | J113: =J37 -> 0 | ... N113: =N37 -> 0 | O113: =SUM(C113:N113) -> 0 | P113: =SUM(I113:N113) -> 0
B114: 減価償却相当分設備費 | C114: =C38 -> 3216.858 | D114: =D38 -> 3213.376 | E114: =E38 -> 3212.048 | F114: =F38 -> 632 | G114: =G38 -> 632 | H114: =H38 -> 632 | I114: =I38 -> 632 | J114: =J38 -> 632 | ... N114: =N38 -> 632 | O114: =SUM(C114:N114) -> 15330.282 | P114: =SUM(I114:N114) -> 3792
B115: 家 賃 | C115: =C39 -> 1437.6 | D115: =D39 -> 1437.6 | E115: =E39 -> 1437.6 | F115: =F39 -> 1437.6 | G115: =G39 -> 1437.6 | H115: =H39 -> 1437.6 | I115: =I39 -> 1437.6 | J115: =J39 -> 1437.6 | ... N115: =N39 -> 1437.6 | O115: =SUM(C115:N115) -> 17251.2 | P115: =SUM(I115:N115) -> 8625.6
B116: 一般管理費 | C116: =SUM(C117:C137) -> 101198.78 | D116: =SUM(D117:D137) -> 92637.161 | E116: =SUM(E117:E137) -> 79802.776 | F116: =SUM(F117:F137) -> 75996.908 | G116: =SUM(G117:G137) -> 73366.472 | H116: =SUM(H117:H137) -> 85549.879 | I116: =SUM(I117:I137) -> 74334.159 | J116: =SUM(J117:J137) -> 72658.64 | ... N116: =SUM(N117:N137) -> 78344.548 | O116: =SUM(C116:N116) -> 977738.09 | P116: =SUM(I116:N116) -> 469186.12
B117: 消耗品費 | C117: =C41+C74 -> 16456.422 | D117: =D41+D74 -> 8596.9369 | E117: =E41+E74 -> 4820.7976 | F117: =F41+F74 -> 3650 | G117: =G41+G74 -> 1000 | H117: =H41+H74 -> 7500 | I117: =I41+I74 -> 1500 | J117: =J41+J74 -> 1997.312 | ... N117: =N41+N74 -> 4247.12 | O117: =SUM(C117:N117) -> 68759.757 | P117: =SUM(I117:N117) -> 26735.6 | Q117: ← 充填機導入による増減を反映
B118: 保険料 | C118: =C42 -> 0 | D118: =D42 -> 0 | E118: =E42 -> 0 | F118: =F42 -> 0 | G118: =G42 -> 0 | H118: =H42 -> 0 | I118: =I42 -> 0 | J118: =J42 -> 0 | ... N118: =N42 -> 0 | O118: =SUM(C118:N118) -> 0 | P118: =SUM(I118:N118) -> 0
B119: 修繕費 | C119: =C43+C76+C79 -> 250.3 | D119: =D43+D76+D79 -> 964.2 | E119: =E43+E76+E79 -> 2554.4 | F119: =F43+F76+F79 -> 1230 | G119: =G43+G76+G79 -> 600 | H119: =H43+H76+H79 -> 1230 | I119: =I43+I76+I79 -> 370 | J119: =J43+J76+J79 -> 507.5 | ... N119: =N43+N76+N79 -> 767.5 | O119: =SUM(C119:N119) -> 10976.4 | P119: =SUM(I119:N119) -> 4147.5 | Q119: ← 充填機導入による増減を反映
B120: 租税公課 | C120: =C44 -> 370.75533 | D120: =D44 -> 324.74967 | E120: =E44 -> 361.24967 | F120: =F44 -> 0 | G120: =G44 -> 0 | H120: =H44 -> 0 | I120: =I44 -> 0 | J120: =J44 -> 0 | ... N120: =N44 -> 0 | O120: =SUM(C120:N120) -> 1056.7547 | P120: =SUM(I120:N120) -> 0
B121: 燃料費（租税） | C121: =C45 -> 0 | D121: =D45 -> 0 | E121: =E45 -> 0 | F121: =F45 -> 0 | G121: =G45 -> 0 | H121: =H45 -> 0 | I121: =I45 -> 0 | J121: =J45 -> 0 | ... N121: =N45 -> 0 | O121: =SUM(C121:N121) -> 0 | P121: =SUM(I121:N121) -> 0
B122: 旅費交通費 | C122: =C46 -> 1.44 | D122: =D46 -> 9.433 | E122: =E46 -> 54.403 | F122: =F46 -> 90 | G122: =G46 -> 90 | H122: =H46 -> 90 | I122: =I46 -> 90 | J122: =J46 -> 90 | ... N122: =N46 -> 250 | O122: =SUM(C122:N122) -> 1065.276 | P122: =SUM(I122:N122) -> 730
B123: 通信費 | C123: =C47 -> 240.71333 | D123: =D47 -> 122.218 | E123: =E47 -> 115.669 | F123: =F47 -> 126 | G123: =G47 -> 126 | H123: =H47 -> 126 | I123: =I47 -> 126 | J123: =J47 -> 126 | ... N123: =N47 -> 126 | O123: =SUM(C123:N123) -> 1612.6003 | P123: =SUM(I123:N123) -> 756
B124: 水道光熱費重油ガス代 | C124: =C48+C75 -> 14038.497 | D124: =D48+D75 -> 12075.499 | E124: =E48+E75 -> 13733.26 | F124: =F48+F75 -> 10933 | G124: =G48+G75 -> 11433 | H124: =H48+H75 -> 11633 | I124: =I48+I75 -> 11433 | J124: =J48+J75 -> 10938.88 | ... N124: =N48+N75 -> 10939.3 | O124: =SUM(C124:N124) -> 140475.76 | P124: =SUM(I124:N124) -> 66629.5 | Q124: ← 充填機導入による増減を反映
...
