Workbook

Sheet ①使い方・更新手順
A1: 益子工場 生産性管理ファイル 使い方
A3: ■ ファイル構成
A4: ② 釜工程入力 …釜①〜⑤の全工程。黄色セル（商品名・重量・実作業時間）を毎週更新する
A5: ③ スチコン工程入力 …スチコン①〜⑤の全工程。同じく黄色セルを毎週更新する
A6: ④ 前提設定 …時給・固定費等。変更すると全シートに反映
A7: ⑤ 中間品別損益 …自動集計。原材料費を入力すると粗利が算出される
A8: ⑥ 機器別サマリー …釜＋スチコン10機器の生産性比較（自動更新）
A9: ⑦ 釜タイムライン …時間帯別の全釜稼働状況（参考）
A11: ■ 毎週の更新手順（所要時間：約15分）
A12: STEP 1 ②「釜工程入力」シートを開く
A13: → 商品名・開始・終了・重量kgの黄色セルを今週のデータに更新する（追加・削除もOK）
A14: STEP 2 ③「スチコン工程入力」シートも同様に更新
... A35: ■ 追加工程シート一覧（盛り込み・フライヤー・ジェット・カット・製菓）
A36: ⑩盛付梱包工程入力 | B36: 食数・人数・生産性（個/h）を入力
A37: ⑪ZEN工程入力 | B37: 重量・生産性（kg/h）を入力
A38: ⑫ミキサー工程入力 | B38: 重量・生産性（kg/h）を入力
A39: ⑬計量工程入力 | B39: 重量・生産性（kg/h）を入力
A40: ⑭手動工程入力 | B40: 食数・人数・生産性（個/h）を入力
A42: 更新のポイント | B42: 商品名★・食数★・人数★・実作業分★・重量★の黄色セルを毎週入力 → 生産性・労務費が自動計算

Sheet ②釜工程入力
A1: 釜工程入力台帳 毎週更新 | 黄色セル＝入力（商品名・重量・実作業分を更新）
A2: ● 青字・黄背景 = 毎週更新するセル 黒字・グレー = 自動計算（変更不要） | ★R列で中間品名を選ぶと、中間品JAN（S列）で⑱〜⑳に労務費がひもづきます
A4: No. | B4: 釜 | C4: 商品名★ | D4: 開始★ | E4: 終了★ | F4: 稼働(分) | G4: 実作業(分)★ | H4: 人数★ | I4: 重量kg★ | J4: 個数(個)★ 個入力欄 | K4: 生産性 (kg/h) | L4: 生産性 (個/h) | M4: 労務費 (円) | N4: 円/kg | O4: 円/個 | P4: 区分 | Q4: 備考 | R4: ★商品名① | S4: ★商品名② | T4: ★商品名③ | U4: ★商品名④ | V4: ★商品名⑤ | W4: ★商品名⑥ | X4: 振り分け数 自動 | Y4: 1商品あたり 労務費(等分・参考) | Z4: ひもづけ確認 | AA4: 選んだ商品の 食数合計 | AB4: 労務費(数値) | AD4: 配分額① (自動) | AE4: 配分額② (自動) | AF4: 配分額③ (自動) | AG4: 配分額④ (自動) | AH4: 配分額⑤ (自動) | AI4: 配分額⑥ (自動)
A5: 1 | B5: 釜製造 | C5: プリンロール液 | D5: 0.0069444444 | E5: 0.020833333 | F5: 20 | G5: 15 | H5: 1 | I5: 120 | K5: =IF(F5>0,I5/(F5/60),0) | L5: =IF(AND(ISNUMBER(F5),J5>0),J5/(F5/60),"") | M5: =IF(OR(ISNUMBER(SEARCH("サニテーション",C5)),ISNUMBER(SEARCH("客注",C5)),ISNUMBER(SEARCH("切り替え",C5)),ISNUMBER(SEARCH("切替",C5)),NOT(ISNUMBER(H5))),"",IF(ISNUMBER(G5),G5/60*H5*④前提設定!$B$4,IF(AND(G5="",ISNUMBER(F5)),F5/60*H5*④前提設定!$B$4,""))) | N5: =IF(I5>0,M5/I5,"") | O5: =IF(AND(J5>0,ISNUMBER(M5)),M5/J5,"") | R5: 自社製ホイップの卵プリン | X5: =COUNTA(R5:W5) | Y5: =IF(AND($X5>0,ISNUMBER($M5)),$M5/$X5,"") | Z5: =IF($X5=0,"",IF(COUNTIF(⑳商品別1食労務費!$C$5:$C$124,$R5)+COUNTIF(⑳商品別1食労務費!$C$5:$C$124,$S5)+COUNTIF(⑳商品別1食労務費!$C$5:$C$124,$T5)+COUNTIF(⑳商品別1食労務費!$C$5:$C$124,$U5)+COUNTIF(⑳商品別1食労務費!$C$5:$C$124,$V5)+COUNTIF(⑳商品別1食労務費!$C$5:$C$124,$W5)=$X5,"OK","⑳に無い商品名")) | AA5: =SUMIF(⑳商品別1食労務費!$C$5:$C$124,$R5,⑳商品別1食労務費!$F$5:$F$124)+SUMIF(⑳商品別1食労務費!$C$5:$C$124,$S5,⑳商品別1食労務費!$F$5:$F$124)+SUMIF(⑳商品別1食労務費!$C$5:$C$124,$T5,⑳商品別1食労務費!$F$5:$F$124)+SUMIF(⑳商品別1食労務費!$C$5:$C$124,$U5,⑳商品別1食労務費!$F$5:$F$124)+SUMIF(⑳商品別1食労務費!$C$5:$C$124,$V5,⑳商品別1食労務費!$F$5:$F$124)+SUMIF(⑳商品別1食労務費!$C$5:$C$124,$W5,⑳商品別1食労務費!$F$5:$F$124) | AB5: =IF(ISNUMBER($M5),$M5,0) | AD5: =IF($R5="",0,IF($AA5>0,$AB5*SUMIF(⑳商品別1食労務費!$C$5:$C$124,$R5,⑳商品別1食労務費!$F$5:$F$124)/$AA5,$AB5/$X5)) | AE5: =IF($S5="",0,IF($AA5>0,$AB5*SUMIF(⑳商品別1食労務費!$C$5:$C$124,$S5,⑳商品別1食労務費!$F$5:$F$124)/$AA5,$AB5/$X5)) | AF5: =IF($T5="",0,IF($AA5>0,$AB5*SUMIF(⑳商品別1食労務費!$C$5:$C$124,$T5,⑳商品別1食労務費!$F$5:$F$124)/$AA5,$AB5/$X5)) | AG5: =IF($U5="",0,IF($AA5>0,$AB5*SUMIF(⑳商品別1食労務費!$C$5:$C$124,$U5,⑳商品別1食労務費!$F$5:$F$124)/$AA5,$AB5/$X5)) | AH5: =IF($V5="",0,IF($AA5>0,$AB5*SUMIF(⑳商品別1食労務費!$C$5:$C$124,$V5,⑳商品別1食労務費!$F$5:$F$124)/$AA5,$AB5/$X5)) | AI5: =IF($W5="",0,IF($AA5>0,$AB5*SUMIF(⑳商品別1食労務費!$C$5:$C$124,$W5,⑳商品別1食労務費!$F$5:$F$124)/$AA5,$AB5/$X5))
A6: 2 | B6: 釜製造 | C6: あんこ | D6: 0.024305556 | E6: 0.11458333 | F6: 130 | G6: 100 | H6: 1 | I6: 120 | K6: =IF(F6>0,I6/(F6/60),0) | L6: =IF(AND(ISNUMBER(F6),J6>0),J6/(F6/60),"") | M6: =IF(OR(ISNUMBER(SEARCH("サニテーション",C6)),ISNUMBER(SEARCH("客注",C6)),ISNUMBER(SEARCH("切り替え",C6)),ISNUMBER(SEARCH("切替",C6)),NOT(ISNUMBER(H6))),"",IF(ISNUMBER(G6),G6/60*H6*④前提設定!$B$4,IF(AND(G6="",ISNUMBER(F6)),F6/60*H6*④前提設定!$B$4,""))) | N6: =IF(I6>0,M6/I6,"") | O6: =IF(AND(J6>0,ISNUMBER(M6)),M6/J6,"") | Q6: あんこ→おはぎ・どら焼き・あんこＫＩＴに使用（食数の比で配分。⑳で食数を入れてください） | R6: おはぎ | S6: どら焼き | T6: あんこＫＩＴ １ｋｇ | X6: =COUNTA(R6:W6) | Y6: =IF(AND($X6>0,ISNUMBER($M6)),$M6/$X6,"") | Z6: =IF($X6=0,"",IF(COUNTIF(⑳商品別1食労務費!$C$5:$C$124,$R6)+COUNTIF(⑳商品別1食労務費!$C$5:$C$124,$S6)+COUNTIF(⑳商品別1食労務費!$C$5:$C$124,$T6)+COUNTIF(⑳商品別1食労務費!$C$5:$C$124,$U6)+COUNTIF(⑳商品別1食労務費!$C$5:$C$124,$V6)+COUNTIF(⑳商品別1食労務費!$C$5:$C$124,$W6)=$X6,"OK","⑳に無い商品名")) | AA6: =SUMIF(⑳商品別1食労務費!$C$5:$C$124,$R6,⑳商品別1食労務費!$F$5:$F$124)+SUMIF(⑳商品別1食労務費!$C$5:$C$124,$S6,⑳商品別1食労務費!$F$5:$F$124)+SUMIF(⑳商品別1食労務費!$C$5:$C$124,$T6,⑳商品別1食労務費!$F$5:$F$124)+SUMIF(⑳商品別1食労務費!$C$5:$C$124,$U6,⑳商品別1食労務費!$F$5:$F$124)+SUMIF(⑳商品別1食労務費!$C$5:$C$124,$V6,⑳商品別1食労務費!$F$5:$F$124)+SUMIF(⑳商品別1食労務費!$C$5:$C$124,$W6,⑳商品別1食労務費!$F$5:$F$124) | AB6: =IF(ISNUMBER($M6),$M6,0) | AD6: =IF($R6="",0,IF($AA6>0,$AB6*SUMIF(⑳商品別1食労務費!$C$5:$C$124,$R6,⑳商品別1食労務費!$F$5:$F$124)/$AA6,$AB6/$X6)) | AE6: =IF($S6="",0,IF($AA6>0,$AB6*SUMIF(⑳商品別1食労務費!$C$5:$C$124,$S6,⑳商品別1食労務費!$F$5:$F$124)/$AA6,$AB6/$X6)) | AF6: =IF($T6="",0,IF($AA6>0,$AB6*SUMIF(⑳商品別1食労務費!$C$5:$C$124,$T6,⑳商品別1食労務費!$F$5:$F$124)/$AA6,$AB6/$X6)) | AG6: =IF($U6="",0,IF($AA6>0,$AB6*SUMIF(⑳商品別1食労務費!$C$5:$C$124,$U6,⑳商品別1食労務費!$F$5:$F$124)/$AA6,$AB6/$X6)) | AH6: =IF($V6="",0,IF($AA6>0,$AB6*SUMIF(⑳商品別1食労務費!$C$5:$C$124,$V6,⑳商品別1食労務費!$F$5:$F$124)/$AA6,$AB6/$X6)) | AI6: =IF($W6="",0,IF($AA6>0,$AB6*SUMIF(⑳商品別1食労務費!$C$5:$C$124,$W6,⑳商品別1食労務費!$F$5:$F$124)/$AA6,$AB6/$X6))
A7: 3 | B7: 釜製造 | C7: あんこ | F7: 130 | G7: 100 | H7: 1 | I7: 120 | K7: =IF(F7>0,I7/(F7/60),0) | L7: =IF(AND(ISNUMBER(F7),J7>0),J7/(F7/60),"") | M7: =IF(OR(ISNUMBER(SEARCH("サニテーション",C7)),ISNUMBER(SEARCH("客注",C7)),ISNUMBER(SEARCH("切り替え",C7)),ISNUMBER(SEARCH("切替",C7)),NOT(ISNUMBER(H7))),"",IF(ISNUMBER(G7),G7/60*H7*④前提設定!$B$4,IF(AND(G7="",ISNUMBER(F7)),F7/60*H7*④前提設定!$B$4,""))) | N7: =IF(I7>0,M7/I7,"") | O7: =IF(AND(J7>0,ISNUMBER(M7)),M7/J7,"") | Q7: あんこ→おはぎ・どら焼き・あんこＫＩＴに使用（食数の比で配分。⑳で食数を入れてください） | R7: おはぎ | S7: どら焼き | T7: あんこＫＩＴ １ｋｇ | X7: =COUNTA(R7:W7) | Y7: =IF(AND($X7>0,ISNUMBER($M7)),$M7/$X7,"") | Z7: =IF($X7=0,"",IF(COUNTIF(⑳商品別1食労務費!$C$5:$C$124,$R7)+COUNTIF(⑳商品別1食労務費!$C$5:$C$124,$S7)+COUNTIF(⑳商品別1食労務費!$C$5:$C$124,$T7)+COUNTIF(⑳商品別1食労務費!$C$5:$C$124,$U7)+COUNTIF(⑳商品別1食労務費!$C$5:$C$124,$V7)+COUNTIF(⑳商品別1食労務費!$C$5:$C$124,$W7)=$X7,"OK","⑳に無い商品名")) | AA7: =SUMIF(⑳商品別1食労務費!$C$5:$C$124,$R7,⑳商品別1食労務費!$F$5:$F$124)+SUMIF(⑳商品別1食労務費!$C$5:$C$124,$S7,⑳商品別1食労務費!$F$5:$F$124)+SUMIF(⑳商品別1食労務費!$C$5:$C$124,$T7,⑳商品別1食労務費!$F$5:$F$124)+SUMIF(⑳商品別1食労務費!$C$5:$C$124,$U7,⑳商品別1食労務費!$F$5:$F$124)+SUMIF(⑳商品別1食労務費!$C$5:$C$124,$V7,⑳商品別1食労務費!$F$5:$F$124)+SUMIF(⑳商品別1食労務費!$C$5:$C$124,$W7,⑳商品別1食労務費!$F$5:$F$124) | AB7: =IF(ISNUMBER($M7),$M7,0) | AD7: =IF($R7="",0,IF($AA7>0,$AB7*SUMIF(⑳商品別1食労務費!$C$5:$C$124,$R7,⑳商品別1食労務費!$F$5:$F$124)/$AA7,$AB7/$X7)) | AE7: =IF($S7="",0,IF($AA7>0,$AB7*SUMIF(⑳商品別1食労務費!$C$5:$C$124,$S7,⑳商品別1食労務費!$F$5:$F$124)/$AA7,$AB7/$X7)) | AF7: =IF($T7="",0,IF($AA7>0,$AB7*SUMIF(⑳商品別1食労務費!$C$5:$C$124,$T7,⑳商品別1食労務費!$F$5:$F$124)/$AA7,$AB7/$X7)) | AG7: =IF($U7="",0,IF($AA7>0,$AB7*SUMIF(⑳商品別1食労務費!$C$5:$C$124,$U7,⑳商品別1食労務費!$F$5:$F$124)/$AA7,$AB7/$X7)) | AH7: =IF($V7="",0,IF($AA7>0,$AB7*SUMIF(⑳商品別1食労務費!$C$5:$C$124,$V7,⑳商品別1食労務費!$F$5:$F$124)/$AA7,$AB7/$X7)) | AI7: =IF($W7="",0,IF($AA7>0,$AB7*SUMIF(⑳商品別1食労務費!$C$5:$C$124,$W7,⑳商品別1食労務費!$F$5:$F$124)/$AA7,$AB7/$X7))
A8: 4 | B8: 釜製造 | C8: まっしろミルクプリン液 | D8: 0.12152778 | E8: 0.14583333 | F8: 35 | G8: 30 | H8: 1 | I8: 120 | K8: =IF(F8>0,I8/(F8/60),0) | L8: =IF(AND(ISNUMBER(F8),J8>0),J8/(F8/60),"") | M8: =IF(OR(ISNUMBER(SEARCH("サニテーション",C8)),ISNUMBER(SEARCH("客注",C8)),ISNUMBER(SEARCH("切り替え",C8)),ISNUMBER(SEARCH("切替",C8)),NOT(ISNUMBER(H8))),"",IF(ISNUMBER(G8),G8/60*H8*④前提設定!$B$4,IF(AND(G8="",ISNUMBER(F8)),F8/60*H8*④前提設定!$B$4,""))) | N8: =IF(I8>0,M8/I8,"") | O8: =IF(AND(J8>0,ISNUMBER(M8)),M8/J8,"") | R8: まっしろミルクプリン３ | S8: Ｓまっしろミルクプリン小３ | X8: =COUNTA(R8:W8) | Y8: =IF(AND($X8>0,ISNUMBER($M8)),$M8/$X8,"") | Z8: =IF($X8=0,"",IF(COUNTIF(⑳商品別1食労務費!$C$5:$C$124,$R8)+COUNTIF(⑳商品別1食労務費!$C$5:$C$124,$S8)+COUNTIF(⑳商品別1食労務費!$C$5:$C$124,$T8)+COUNTIF(⑳商品別1食労務費!$C$5:$C$124,$U8)+COUNTIF(⑳商品別1食労務費!$C$5:$C$124,$V8)+COUNTIF(⑳商品別1食労務費!$C$5:$C$124,$W8)=$X8,"OK","⑳に無い商品名")) | AA8: =SUMIF(⑳商品別1食労務費!$C$5:$C$124,$R8,⑳商品別1食労務費!$F$5:$F$124)+SUMIF(⑳商品別1食労務費!$C$5:$C$124,$S8,⑳商品別1食労務費!$F$5:$F$124)+SUMIF(⑳商品別1食労務費!$C$5:$C$124,$T8,⑳商品別1食労務費!$F$5:$F$124)+SUMIF(⑳商品別1食労務費!$C$5:$C$124,$U8,⑳商品別1食労務費!$F$5:$F$124)+SUMIF(⑳商品別1食労務費!$C$5:$C$124,$V8,⑳商品別1食労務費!$F$5:$F$124)+SUMIF(⑳商品別1食労務費!$C$5:$C$124,$W8,⑳商品別1食労務費!$F$5:$F$124) | AB8: =IF(ISNUMBER($M8),$M8,0) | AD8: =IF($R8="",0,IF($AA8>0,$AB8*SUMIF(⑳商品別1食労務費!$C$5:$C$124,$R8,⑳商品別1食労務費!$F$5:$F$124)/$AA8,$AB8/$X8)) | AE8: =IF($S8="",0,IF($AA8>0,$AB8*SUMIF(⑳商品別1食労務費!$C$5:$C$124,$S8,⑳商品別1食労務費!$F$5:$F$124)/$AA8,$AB8/$X8)) | AF8: =IF($T8="",0,IF($AA8>0,$AB8*SUMIF(⑳商品別1食労務費!$C$5:$C$124,$T8,⑳商品別1食労務費!$F$5:$F$124)/$AA8,$AB8/$X8)) | AG8: =IF($U8="",0,IF($AA8>0,$AB8*SUMIF(⑳商品別1食労務費!$C$5:$C$124,$U8,⑳商品別1食労務費!$F$5:$F$124)/$AA8,$AB8/$X8)) | AH8: =IF($V8="",0,IF($AA8>0,$AB8*SUMIF(⑳商品別1食労務費!$C$5:$C$124,$V8,⑳商品別1食労務費!$F$5:$F$124)/$AA8,$AB8/$X8)) | AI8: =IF($W8="",0,IF($AA8>0,$AB8*SUMIF(⑳商品別1食労務費!$C$5:$C$124,$W8,⑳商品別1食労務費!$F$5:$F$124)/$AA8,$AB8/$X8))
A9: 5 | B9: 釜製造 | C9: まっしろミルクプリン液 | F9: 35 | G9: 30 | H9: 1 | I9: 120 | K9: =IF(F9>0,I9/(F9/60),0) | L9: =IF(AND(ISNUMBER(F9),J9>0),J9/(F9/60),"") | M9: =IF(OR(ISNUMBER(SEARCH("サニテーション",C9)),ISNUMBER(SEARCH("客注",C9)),ISNUMBER(SEARCH("切り替え",C9)),ISNUMBER(SEARCH("切替",C9)),NOT(ISNUMBER(H9))),"",IF(ISNUMBER(G9),G9/60*H9*④前提設定!$B$4,IF(AND(G9="",ISNUMBER(F9)),F9/60*H9*④前提設定!$B$4,""))) | N9: =IF(I9>0,M9/I9,"") | O9: =IF(AND(J9>0,ISNUMBER(M9)),M9/J9,"") | R9: まっしろミルクプリン３ | S9: Ｓまっしろミルクプリン小３ | X9: =COUNTA(R9:W9) | Y9: =IF(AND($X9>0,ISNUMBER($M9)),$M9/$X9,"") | Z9: =IF($X9=0,"",IF(COUNTIF(⑳商品別1食労務費!$C$5:$C$124,$R9)+COUNTIF(⑳商品別1食労務費!$C$5:$C$124,$S9)+COUNTIF(⑳商品別1食労務費!$C$5:$C$124,$T9)+COUNTIF(⑳商品別1食労務費!$C$5:$C$124,$U9)+COUNTIF(⑳商品別1食労務費!$C$5:$C$124,$V9)+COUNTIF(⑳商品別1食労務費!$C$5:$C$124,$W9)=$X9,"OK","⑳に無い商品名")) | AA9: =SUMIF(⑳商品別1食労務費!$C$5:$C$124,$R9,⑳商品別1食労務費!$F$5:$F$124)+SUMIF(⑳商品別1食労務費!$C$5:$C$124,$S9,⑳商品別1食労務費!$F$5:$F$124)+SUMIF(⑳商品別1食労務費!$C$5:$C$124,$T9,⑳商品別1食労務費!$F$5:$F$124)+SUMIF(⑳商品別1食労務費!$C$5:$C$124,$U9,⑳商品別1食労務費!$F$5:$F$124)+SUMIF(⑳商品別1食労務費!$C$5:$C$124,$V9,⑳商品別1食労務費!$F$5:$F$124)+SUMIF(⑳商品別1食労務費!$C$5:$C$124,$W9,⑳商品別1食労務費!$F$5:$F$124) | AB9: =IF(ISNUMBER($M9),$M9,0) | AD9: =IF($R9="",0,IF($AA9>0,$AB9*SUMIF(⑳商品別1食労務費!$C$5:$C$124,$R9,⑳商品別1食労務費!$F$5:$F$124)/$AA9,$AB9/$X9)) | AE9: =IF($S9="",0,IF($AA9>0,$AB9*SUMIF(⑳商品別1食労務費!$C$5:$C$124,$S9,⑳商品別1食労務費!$F$5:$F$124)/$AA9,$AB9/$X9)) | AF9: =IF($T9="",0,IF($AA9>0,$AB9*SUMIF(⑳商品別1食労務費!$C$5:$C$124,$T9,⑳商品別1食労務費!$F$5:$F$124)/$AA9,$AB9/$X9)) | AG9: =IF($U9="",0,IF($AA9>0,$AB9*SUMIF(⑳商品別1食労務費!$C$5:$C$124,$U9,⑳商品別1食労務費!$F$5:$F$124)/$AA9,$AB9/$X9)) | AH9: =IF($V9="",0,IF($AA9>0,$AB9*SUMIF(⑳商品別1食労務費!$C$5:$C$124,$V9,⑳商品別1食労務費!$F$5:$F$124)/$AA9,$AB9/$X9)) | AI9: =IF($W9="",0,IF($AA9>0,$AB9*SUMIF(⑳商品別1食労務費!$C$5:$C$124,$W9,⑳商品別1食労務費!$F$5:$F$124)/$AA9,$AB9/$X9))
A10: 6 | B10: 釜製造 | C10: みかん牛乳寒天 | D10: 0.14930556 | E10: 0.19444444 | F10: 65 | G10: 40 | H10: 1 | I10: 120 | K10: =IF(F10>0,I10/(F10/60),0) | L10: =IF(AND(ISNUMBER(F10),J10>0),J10/(F10/60),"") | M10: =IF(OR(ISNUMBER(SEARCH("サニテーション",C10)),ISNUMBER(SEARCH("客注",C10)),ISNUMBER(SEARCH("切り替え",C10)),ISNUMBER(SEARCH("切替",C10)),NOT(ISNUMBER(H10))),"",IF(ISNUMBER(G10),G10/60*H10*④前提設定!$B$4,IF(AND(G10="",ISNUMBER(F10)),F10/60*H10*④前提設定!$B$4,""))) | N10: =IF(I10>0,M10/I10,"") | O10: =IF(AND(J10>0,ISNUMBER(M10)),M10/J10,"") | R10: みかんの牛乳寒天２ | S10: みかんの牛乳寒天 小 | T10: Ｓみかんの牛乳寒天 小 | X10: =COUNTA(R10:W10) | Y10: =IF(AND($X10>0,ISNUMBER($M10)),$M10/$X10,"") | Z10: =IF($X10=0,"",IF(COUNTIF(⑳商品別1食労務費!$C$5:$C$124,$R10)+COUNTIF(⑳商品別1食労務費!$C$5:$C$124,$S10)+COUNTIF(⑳商品別1食労務費!$C$5:$C$124,$T10)+COUNTIF(⑳商品別1食労務費!$C$5:$C$124,$U10)+COUNTIF(⑳商品別1食労務費!$C$5:$C$124,$V10)+COUNTIF(⑳商品別1食労務費!$C$5:$C$124,$W10)=$X10,"OK","⑳に無い商品名")) | AA10: =SUMIF(⑳商品別1食労務費!$C$5:$C$124,$R10,⑳商品別1食労務費!$F$5:$F$124)+SUMIF(⑳商品別1食労務費!$C$5:$C$124,$S10,⑳商品別1食労務費!$F$5:$F$124)+SUMIF(⑳商品別1食労務費!$C$5:$C$124,$T10,⑳商品別1食労務費!$F$5:$F$124)+SUMIF(⑳商品別1食労務費!$C$5:$C$124,$U10,⑳商品別1食労務費!$F$5:$F$124)+SUMIF(⑳商品別1食労務費!$C$5:$C$124,$V10,⑳商品別1食労務費!$F$5:$F$124)+SUMIF(⑳商品別1食労務費!$C$5:$C$124,$W10,⑳商品別1食労務費!$F$5:$F$124) | AB10: =IF(ISNUMBER($M10),$M10,0) | AD10: =IF($R10="",0,IF($AA10>0,$AB10*SUMIF(⑳商品別1食労務費!$C$5:$C$124,$R10,⑳商品別1食労務費!$F$5:$F$124)/$AA10,$AB10/$X10)) | AE10: =IF($S10="",0,IF($AA10>0,$AB10*SUMIF(⑳商品別1食労務費!$C$5:$C$124,$S10,⑳商品別1食労務費!$F$5:$F$124)/$AA10,$AB10/$X10)) | AF10: =IF($T10="",0,IF($AA10>0,$AB10*SUMIF(⑳商品別1食労務費!$C$5:$C$124,$T10,⑳商品別1食労務費!$F$5:$F$124)/$AA10,$AB10/$X10)) | AG10: =IF($U10="",0,IF($AA10>0,$AB10*SUMIF(⑳商品別1食労務費!$C$5:$C$124,$U10,⑳商品別1食労務費!$F$5:$F$124)/$AA10,$AB10/$X10)) | AH10: =IF($V10="",0,IF($AA10>0,$AB10*SUMIF(⑳商品別1食労務費!$C$5:$C$124,$V10,⑳商品別1食労務費!$F$5:$F$124)/$AA10,$AB10/$X10)) | AI10: =IF($W10="",0,IF($AA10>0,$AB10*SUMIF(⑳商品別1食労務費!$C$5:$C$124,$W10,⑳商品別1食労務費!$F$5:$F$124)/$AA10,$AB10/$X10))
A11: 7 | B11: 釜製造 | C11: コーヒーゼリー液 | D11: 0.20138889 | E11: 0.33680556 | F11: 195 | G11: 100 | H11: 1 | I11: 120 | K11: =IF(F11>0,I11/(F11/60),0) | L11: =IF(AND(ISNUMBER(F11),J11>0),J11/(F11/60),"") | M11: =IF(OR(ISNUMBER(SEARCH("サニテーション",C11)),ISNUMBER(SEARCH("客注",C11)),ISNUMBER(SEARCH("切り替え",C11)),ISNUMBER(SEARCH("切替",C11)),NOT(ISNUMBER(H11))),"",IF(ISNUMBER(G11),G11/60*H11*④前提設定!$B$4,IF(AND(G11="",ISNUMBER(F11)),F11/60*H11*④前提設定!$B$4,""))) | N11: =IF(I11>0,M11/I11,"") | O11: =IF(AND(J11>0,ISNUMBER(M11)),M11/J11,"") | R11: 大人のコーヒーゼリー４ | S11: Ｓ大人のコーヒーゼリー４ | T11: 大人のコーヒーゼリー小４ | U11: Ｓ大人のコーヒーゼリー小４ | X11: =COUNTA(R11:W11) | Y11: =IF(AND($X11>0,ISNUMBER($M11)),$M11/$X11,"") | Z11: =IF($X11=0,"",IF(COUNTIF(⑳商品別1食労務費!$C$5:$C$124,$R11)+COUNTIF(⑳商品別1食労務費!$C$5:$C$124,$S11)+COUNTIF(⑳商品別1食労務費!$C$5:$C$124,$T11)+COUNTIF(⑳商品別1食労務費!$C$5:$C$124,$U11)+COUNTIF(⑳商品別1食労務費!$C$5:$C$124,$V11)+COUNTIF(⑳商品別1食労務費!$C$5:$C$124,$W11)=$X11,"OK","⑳に無い商品名")) | AA11: =SUMIF(⑳商品別1食労務費!$C$5:$C$124,$R11,⑳商品別1食労務費!$F$5:$F$124)+SUMIF(⑳商品別1食労務費!$C$5:$C$124,$S11,⑳商品別1食労務費!$F$5:$F$124)+SUMIF(⑳商品別1食労務費!$C$5:$C$124,$T11,⑳商品別1食労務費!$F$5:$F$124)+SUMIF(⑳商品別1食労務費!$C$5:$C$124,$U11,⑳商品別1食労務費!$F$5:$F$124)+SUMIF(⑳商品別1食労務費!$C$5:$C$124,$V11,⑳商品別1食労務費!$F$5:$F$124)+SUMIF(⑳商品別1食労務費!$C$5:$C$124,$W11,⑳商品別1食労務費!$F$5:$F$124) | AB11: =IF(ISNUMBER($M11),$M11,0) | AD11: =IF($R11="",0,IF($AA11>0,$AB11*SUMIF(⑳商品別1食労務費!$C$5:$C$124,$R11,⑳商品別1食労務費!$F$5:$F$124)/$AA11,$AB11/$X11)) | AE11: =IF($S11="",0,IF($AA11>0,$AB11*SUMIF(⑳商品別1食労務費!$C$5:$C$124,$S11,⑳商品別1食労務費!$F$5:$F$124)/$AA11,$AB11/$X11)) | AF11: =IF($T11="",0,IF($AA11>0,$AB11*SUMIF(⑳商品別1食労務費!$C$5:$C$124,$T11,⑳商品別1食労務費!$F$5:$F$124)/$AA11,$AB11/$X11)) | AG11: =IF($U11="",0,IF($AA11>0,$AB11*SUMIF(⑳商品別1食労務費!$C$5:$C$124,$U11,⑳商品別1食労務費!$F$5:$F$124)/$AA11,$AB11/$X11)) | AH11: =IF($V11="",0,IF($AA11>0,$AB11*SUMIF(⑳商品別1食労務費!$C$5:$C$124,$V11,⑳商品別1食労務費!$F$5:$F$124)/$AA11,$AB11/$X11)) | AI11: =IF($W11="",0,IF($AA11>0,$AB11*SUMIF(⑳商品別1食労務費!$C$5:$C$124,$W11,⑳商品別1食労務費!$F$5:$F$124)/$AA11,$AB11/$X11))
A12: 8 | B12: 釜製造 | C12: コーヒーゼリー液 | F12: 195 | G12: 100 | H12: 1 | I12: 120 | K12: =IF(F12>0,I12/(F12/60),0) | L12: =IF(AND(ISNUMBER(F12),J12>0),J12/(F12/60),"") | M12: =IF(OR(ISNUMBER(SEARCH("サニテーション",C12)),ISNUMBER(SEARCH("客注",C12)),ISNUMBER(SEARCH("切り替え",C12)),ISNUMBER(SEARCH("切替",C12)),NOT(ISNUMBER(H12))),"",IF(ISNUMBER(G12),G12/60*H12*④前提設定!$B$4,IF(AND(G12="",ISNUMBER(F12)),F12/60*H12*④前提設定!$B$4,""))) | N12: =IF(I12>0,M12/I12,"") | O12: =IF(AND(J12>0,ISNUMBER(M12)),M12/J12,"") | R12: 大人のコーヒーゼリー４ | S12: Ｓ大人のコーヒーゼリー４ | T12: 大人のコーヒーゼリー小４ | U12: Ｓ大人のコーヒーゼリー小４ | X12: =COUNTA(R12:W12) | Y12: =IF(AND($X12>0,ISNUMBER($M12)),$M12/$X12,"") | Z12: =IF($X12=0,"",IF(COUNTIF(⑳商品別1食労務費!$C$5:$C$124,$R12)+COUNTIF(⑳商品別1食労務費!$C$5:$C$124,$S12)+COUNTIF(⑳商品別1食労務費!$C$5:$C$124,$T12)+COUNTIF(⑳商品別1食労務費!$C$5:$C$124,$U12)+COUNTIF(⑳商品別1食労務費!$C$5:$C$124,$V12)+COUNTIF(⑳商品別1食労務費!$C$5:$C$124,$W12)=$X12,"OK","⑳に無い商品名")) | AA12: =SUMIF(⑳商品別1食労務費!$C$5:$C$124,$R12,⑳商品別1食労務費!$F$5:$F$124)+SUMIF(⑳商品別1食労務費!$C$5:$C$124,$S12,⑳商品別1食労務費!$F$5:$F$124)+SUMIF(⑳商品別1食労務費!$C$5:$C$124,$T12,⑳商品別1食労務費!$F$5:$F$124)+SUMIF(⑳商品別1食労務費!$C$5:$C$124,$U12,⑳商品別1食労務費!$F$5:$F$124)+SUMIF(⑳商品別1食労務費!$C$5:$C$124,$V12,⑳商品別1食労務費!$F$5:$F$124)+SUMIF(⑳商品別1食労務費!$C$5:$C$124,$W12,⑳商品別1食労務費!$F$5:$F$124) | AB12: =IF(ISNUMBER($M12),$M12,0) | AD12: =IF($R12="",0,IF($AA12>0,$AB12*SUMIF(⑳商品別1食労務費!$C$5:$C$124,$R12,⑳商品別1食労務費!$F$5:$F$124)/$AA12,$AB12/$X12)) | AE12: =IF($S12="",0,IF($AA12>0,$AB12*SUMIF(⑳商品別1食労務費!$C$5:$C$124,$S12,⑳商品別1食労務費!$F$5:$F$124)/$AA12,$AB12/$X12)) | AF12: =IF($T12="",0,IF($AA12>0,$AB12*SUMIF(⑳商品別1食労務費!$C$5:$C$124,$T12,⑳商品別1食労務費!$F$5:$F$124)/$AA12,$AB12/$X12)) | AG12: =IF($U12="",0,IF($AA12>0,$AB12*SUMIF(⑳商品別1食労務費!$C$5:$C$124,$U12,⑳商品別1食労務費!$F$5:$F$124)/$AA12,$AB12/$X12)) | AH12: =IF($V12="",0,IF($AA12>0,$AB12*SUMIF(⑳商品別1食労務費!$C$5:$C$124,$V12,⑳商品別1食労務費!$F$5:$F$124)/$AA12,$AB12/$X12)) | AI12: =IF($W12="",0,IF($AA12>0,$AB12*SUMIF(⑳商品別1食労務費!$C$5:$C$124,$W12,⑳商品別1食労務費!$F$5:$F$124)/$AA12,$AB12/$X12))
A13: 9 | B13: 釜製造 | C13: コーヒーゼリー液 | F13: 195 | G13: 100 | H13: 1 | I13: 120 | K13: =IF(F13>0,I13/(F13/60),0) | L13: =IF(AND(ISNUMBER(F13),J13>0),J13/(F13/60),"") | M13: =IF(OR(ISNUMBER(SEARCH("サニテーション",C13)),ISNUMBER(SEARCH("客注",C13)),ISNUMBER(SEARCH("切り替え",C13)),ISNUMBER(SEARCH("切替",C13)),NOT(ISNUMBER(H13))),"",IF(ISNUMBER(G13),G13/60*H13*④前提設定!$B$4,IF(AND(G13="",ISNUMBER(F13)),F13/60*H13*④前提設定!$B$4,""))) | N13: =IF(I13>0,M13/I13,"") | O13: =IF(AND(J13>0,ISNUMBER(M13)),M13/J13,"") | R13: 大人のコーヒーゼリー４ | S13: Ｓ大人のコーヒーゼリー４ | T13: 大人のコーヒーゼリー小４ | U13: Ｓ大人のコーヒーゼリー小４ | X13: =COUNTA(R13:W13) | Y13: =IF(AND($X13>0,ISNUMBER($M13)),$M13/$X13,"") | Z13: =IF($X13=0,"",IF(COUNTIF(⑳商品別1食労務費!$C$5:$C$124,$R13)+COUNTIF(⑳商品別1食労務費!$C$5:$C$124,$S13)+COUNTIF(⑳商品別1食労務費!$C$5:$C$124,$T13)+COUNTIF(⑳商品別1食労務費!$C$5:$C$124,$U13)+COUNTIF(⑳商品別1食労務費!$C$5:$C$124,$V13)+COUNTIF(⑳商品別1食労務費!$C$5:$C$124,$W13)=$X13,"OK","⑳に無い商品名")) | AA13: =SUMIF(⑳商品別1食労務費!$C$5:$C$124,$R13,⑳商品別1食労務費!$F$5:$F$124)+SUMIF(⑳商品別1食労務費!$C$5:$C$124,$S13,⑳商品別1食労務費!$F$5:$F$124)+SUMIF(⑳商品別1食労務費!$C$5:$C$124,$T13,⑳商品別1食労務費!$F$5:$F$124)+SUMIF(⑳商品別1食労務費!$C$5:$C$124,$U13,⑳商品別1食労務費!$F$5:$F$124)+SUMIF(⑳商品別1食労務費!$C$5:$C$124,$V13,⑳商品別1食労務費!$F$5:$F$124)+SUMIF(⑳商品別1食労務費!$C$5:$C$124,$W13,⑳商品別1食労務費!$F$5:$F$124) | AB13: =IF(ISNUMBER($M13),$M13,0) | AD13: =IF($R13="",0,IF($AA13>0,$AB13*SUMIF(⑳商品別1食労務費!$C$5:$C$124,$R13,⑳商品別1食労務費!$F$5:$F$124)/$AA13,$AB13/$X13)) | AE13: =IF($S13="",0,IF($AA13>0,$AB13*SUMIF(⑳商品別1食労務費!$C$5:$C$124,$S13,⑳商品別1食労務費!$F$5:$F$124)/$AA13,$AB13/$X13)) | AF13: =IF($T13="",0,IF($AA13>0,$AB13*SUMIF(⑳商品別1食労務費!$C$5:$C$124,$T13,⑳商品別1食労務費!$F$5:$F$124)/$AA13,$AB13/$X13)) | AG13: =IF($U13="",0,IF($AA13>0,$AB13*SUMIF(⑳商品別1食労務費!$C$5:$C$124,$U13,⑳商品別1食労務費!$F$5:$F$124)/$AA13,$AB13/$X13)) | AH13: =IF($V13="",0,IF($AA13>0,$AB13*SUMIF(⑳商品別1食労務費!$C$5:$C$124,$V13,⑳商品別1食労務費!$F$5:$F$124)/$AA13,$AB13/$X13)) | AI13: =IF($W13="",0,IF($AA13>0,$AB13*SUMIF(⑳商品別1食労務費!$C$5:$C$124,$W13,⑳商品別1食労務費!$F$5:$F$124)/$AA13,$AB13/$X13))
A14: 10 | B14: 釜製造 | C14: ブルーベリーソース | D14: 0.45138889 | E14: 0.46180556 | F14: 15 | G14: 10 | H14: 1 | I14: 30 | K14: =IF(F14>0,I14/(F14/60),0) | L14: =IF(AND(ISNUMBER(F14),J14>0),J14/(F14/60),"") | M14: =IF(OR(ISNUMBER(SEARCH("サニテーション",C14)),ISNUMBER(SEARCH("客注",C14)),ISNUMBER(SEARCH("切り替え",C14)),ISNUMBER(SEARCH("切替",C14)),NOT(ISNUMBER(H14))),"",IF(ISNUMBER(G14),G14/60*H14*④前提設定!$B$4,IF(AND(G14="",ISNUMBER(F14)),F14/60*H14*④前提設定!$B$4,""))) | N14: =IF(I14>0,M14/I14,"") | O14: =IF(AND(J14>0,ISNUMBER(M14)),M14/J14,"") | R14: Ｓ２層仕立てのチーズケーキ | S14: ２層仕立てのチーズケーキ | X14: =COUNTA(R14:W14) | Y14: =IF(AND($X14>0,ISNUMBER($M14)),$M14/$X14,"") | Z14: =IF($X14=0,"",IF(COUNTIF(⑳商品別1食労務費!$C$5:$C$124,$R14)+COUNTIF(⑳商品別1食労務費!$C$5:$C$124,$S14)+COUNTIF(⑳商品別1食労務費!$C$5:$C$124,$T14)+COUNTIF(⑳商品別1食労務費!$C$5:$C$124,$U14)+COUNTIF(⑳商品別1食労務費!$C$5:$C$124,$V14)+COUNTIF(⑳商品別1食労務費!$C$5:$C$124,$W14)=$X14,"OK","⑳に無い商品名")) | AA14: =SUMIF(⑳商品別1食労務費!$C$5:$C$124,$R14,⑳商品別1食労務費!$F$5:$F$124)+SUMIF(⑳商品別1食労務費!$C$5:$C$124,$S14,⑳商品別1食労務費!$F$5:$F$124)+SUMIF(⑳商品別1食労務費!$C$5:$C$124,$T14,⑳商品別1食労務費!$F$5:$F$124)+SUMIF(⑳商品別1食労務費!$C$5:$C$124,$U14,⑳商品別1食労務費!$F$5:$F$124)+SUMIF(⑳商品別1食労務費!$C$5:$C$124,$V14,⑳商品別1食労務費!$F$5:$F$124)+SUMIF(⑳商品別1食労務費!$C$5:$C$124,$W14,⑳商品別1食労務費!$F$5:$F$124) | AB14: =IF(ISNUMBER($M14),$M14,0) | AD14: =IF($R14="",0,IF($AA14>0,$AB14*SUMIF(⑳商品別1食労務費!$C$5:$C$124,$R14,⑳商品別1食労務費!$F$5:$F$124)/$AA14,$AB14/$X14)) | AE14: =IF($S14="",0,IF($AA14>0,$AB14*SUMIF(⑳商品別1食労務費!$C$5:$C$124,$S14,⑳商品別1食労務費!$F$5:$F$124)/$AA14,$AB14/$X14)) | AF14: =IF($T14="",0,IF($AA14>0,$AB14*SUMIF(⑳商品別1食労務費!$C$5:$C$124,$T14,⑳商品別1食労務費!$F$5:$F$124)/$AA14,$AB14/$X14)) | AG14: =IF($U14="",0,IF($AA14>0,$AB14*SUMIF(⑳商品別1食労務費!$C$5:$C$124,$U14,⑳商品別1食労務費!$F$5:$F$124)/$AA14,$AB14/$X14)) | AH14: =IF($V14="",0,IF($AA14>0,$AB14*SUMIF(⑳商品別1食労務費!$C$5:$C$124,$V14,⑳商品別1食労務費!$F$5:$F$124)/$AA14,$AB14/$X14)) | AI14: =IF($W14="",0,IF($AA14>0,$AB14*SUMIF(⑳商品別1食労務費!$C$5:$C$124,$W14,⑳商品別1食労務費!$F$5:$F$124)/$AA14,$AB14/$X14))
A15: 11 | B15: 釜製造 | C15: ブルーベリーソース | F15: 15 | G15: 10 | H15: 1 | I15: 30 | K15: =IF(F15>0,I15/(F15/60),0) | L15: =IF(AND(ISNUMBER(F15),J15>0),J15/(F15/60),"") | M15: =IF(OR(ISNUMBER(SEARCH("サニテーション",C15)),ISNUMBER(SEARCH("客注",C15)),ISNUMBER(SEARCH("切り替え",C15)),ISNUMBER(SEARCH("切替",C15)),NOT(ISNUMBER(H15))),"",IF(ISNUMBER(G15),G15/60*H15*④前提設定!$B$4,IF(AND(G15="",ISNUMBER(F15)),F15/60*H15*④前提設定!$B$4,""))) | N15: =IF(I15>0,M15/I15,"") | O15: =IF(AND(J15>0,ISNUMBER(M15)),M15/J15,"") | R15: Ｓ２層仕立てのチーズケーキ | S15: ２層仕立てのチーズケーキ | X15: =COUNTA(R15:W15) | Y15: =IF(AND($X15>0,ISNUMBER($M15)),$M15/$X15,"") | Z15: =IF($X15=0,"",IF(COUNTIF(⑳商品別1食労務費!$C$5:$C$124,$R15)+COUNTIF(⑳商品別1食労務費!$C$5:$C$124,$S15)+COUNTIF(⑳商品別1食労務費!$C$5:$C$124,$T15)+COUNTIF(⑳商品別1食労務費!$C$5:$C$124,$U15)+COUNTIF(⑳商品別1食労務費!$C$5:$C$124,$V15)+COUNTIF(⑳商品別1食労務費!$C$5:$C$124,$W15)=$X15,"OK","⑳に無い商品名")) | AA15: =SUMIF(⑳商品別1食労務費!$C$5:$C$124,$R15,⑳商品別1食労務費!$F$5:$F$124)+SUMIF(⑳商品別1食労務費!$C$5:$C$124,$S15,⑳商品別1食労務費!$F$5:$F$124)+SUMIF(⑳商品別1食労務費!$C$5:$C$124,$T15,⑳商品別1食労務費!$F$5:$F$124)+SUMIF(⑳商品別1食労務費!$C$5:$C$124,$U15,⑳商品別1食労務費!$F$5:$F$124)+SUMIF(⑳商品別1食労務費!$C$5:$C$124,$V15,⑳商品別1食労務費!$F$5:$F$124)+SUMIF(⑳商品別1食労務費!$C$5:$C$124,$W15,⑳商品別1食労務費!$F$5:$F$124) | AB15: =IF(ISNUMBER($M15),$M15,0) | AD15: =IF($R15="",0,IF($AA15>0,$AB15*SUMIF(⑳商品別1食労務費!$C$5:$C$124,$R15,⑳商品別1食労務費!$F$5:$F$124)/$AA15,$AB15/$X15)) | AE15: =IF($S15="",0,IF($AA15>0,$AB15*SUMIF(⑳商品別1食労務費!$C$5:$C$124,$S15,⑳商品別1食労務費!$F$5:$F$124)/$AA15,$AB15/$X15)) | AF15: =IF($T15="",0,IF($AA15>0,$AB15*SUMIF(⑳商品別1食労務費!$C$5:$C$124,$T15,⑳商品別1食労務費!$F$5:$F$124)/$AA15,$AB15/$X15)) | AG15: =IF($U15="",0,IF($AA15>0,$AB15*SUMIF(⑳商品別1食労務費!$C$5:$C$124,$U15,⑳商品別1食労務費!$F$5:$F$124)/$AA15,$AB15/$X15)) | AH15: =IF($V15="",0,IF($AA15>0,$AB15*SUMIF(⑳商品別1食労務費!$C$5:$C$124,$V15,⑳商品別1食労務費!$F$5:$F$124)/$AA15,$AB15/$X15)) | AI15: =IF($W15="",0,IF($AA15>0,$AB15*SUMIF(⑳商品別1食労務費!$C$5:$C$124,$W15,⑳商品別1食労務費!$F$5:$F$124)/$AA15,$AB15/$X15))
A16: 12 | B16: 釜製造 | C16: 自社製ホイップの卵プリン | D16: 0.49305556 | E16: 0.56944444 | F16: 110 | G16: 90 | H16: 2 | I16: 120 | K16: =IF(F16>0,I16/(F16/60),0) | L16: =IF(AND(ISNUMBER(F16),J16>0),J16/(F16/60),"") | M16: =IF(OR(ISNUMBER(SEARCH("サニテーション",C16)),ISNUMBER(SEARCH("客注",C16)),ISNUMBER(SEARCH("切り替え",C16)),ISNUMBER(SEARCH("切替",C16)),NOT(ISNUMBER(H16))),"",IF(ISNUMBER(G16),G16/60*H16*④前提設定!$B$4,IF(AND(G16="",ISNUMBER(F16)),F16/60*H16*④前提設定!$B$4,""))) | N16: =IF(I16>0,M16/I16,"") | O16: =IF(AND(J16>0,ISNUMBER(M16)),M16/J16,"") | R16: 自社製ホイップの卵プリン | S16: Ｓホイップの卵プリン | T16: ホイップの卵プリン | X16: =COUNTA(R16:W16) | Y16: =IF(AND($X16>0,ISNUMBER($M16)),$M16/$X16,"") | Z16: =IF($X16=0,"",IF(COUNTIF(⑳商品別1食労務費!$C$5:$C$124,$R16)+COUNTIF(⑳商品別1食労務費!$C$5:$C$124,$S16)+COUNTIF(⑳商品別1食労務費!$C$5:$C$124,$T16)+COUNTIF(⑳商品別1食労務費!$C$5:$C$124,$U16)+COUNTIF(⑳商品別1食労務費!$C$5:$C$124,$V16)+COUNTIF(⑳商品別1食労務費!$C$5:$C$124,$W16)=$X16,"OK","⑳に無い商品名")) | AA16: =SUMIF(⑳商品別1食労務費!$C$5:$C$124,$R16,⑳商品別1食労務費!$F$5:$F$124)+SUMIF(⑳商品別1食労務費!$C$5:$C$124,$S16,⑳商品別1食労務費!$F$5:$F$124)+SUMIF(⑳商品別1食労務費!$C$5:$C$124,$T16,⑳商品別1食労務費!$F$5:$F$124)+SUMIF(⑳商品別1食労務費!$C$5:$C$124,$U16,⑳商品別1食労務費!$F$5:$F$124)+SUMIF(⑳商品別1食労務費!$C$5:$C$124,$V16,⑳商品別1食労務費!$F$5:$F$124)+SUMIF(⑳商品別1食労務費!$C$5:$C$124,$W16,⑳商品別1食労務費!$F$5:$F$124) | AB16: =IF(ISNUMBER($M16),$M16,0) | AD16: =IF($R16="",0,IF($AA16>0,$AB16*SUMIF(⑳商品別1食労務費!$C$5:$C$124,$R16,⑳商品別1食労務費!$F$5:$F$124)/$AA16,$AB16/$X16)) | AE16: =IF($S16="",0,IF($AA16>0,$AB16*SUMIF(⑳商品別1食労務費!$C$5:$C$124,$S16,⑳商品別1食労務費!$F$5:$F$124)/$AA16,$AB16/$X16)) | AF16: =IF($T16="",0,IF($AA16>0,$AB16*SUMIF(⑳商品別1食労務費!$C$5:$C$124,$T16,⑳商品別1食労務費!$F$5:$F$124)/$AA16,$AB16/$X16)) | AG16: =IF($U16="",0,IF($AA16>0,$AB16*SUMIF(⑳商品別1食労務費!$C$5:$C$124,$U16,⑳商品別1食労務費!$F$5:$F$124)/$AA16,$AB16/$X16)) | AH16: =IF($V16="",0,IF($AA16>0,$AB16*SUMIF(⑳商品別1食労務費!$C$5:$C$124,$V16,⑳商品別1食労務費!$F$5:$F$124)/$AA16,$AB16/$X16)) | AI16: =IF($W16="",0,IF($AA16>0,$AB16*SUMIF(⑳商品別1食労務費!$C$5:$C$124,$W16,⑳商品別1食労務費!$F$5:$F$124)/$AA16,$AB16/$X16))
A17: 13 | B17: 釜製造 | C17: 自社製ホイップの卵プリン | F17: 110 | G17: 90 | H17: 2 | I17: 120 | K17: - | L17: =IF(AND(ISNUMBER(F17),J17>0),J17/(F17/60),"") | M17: =IF(OR(ISNUMBER(SEARCH("サニテーション",C17)),ISNUMBER(SEARCH("客注",C17)),ISNUMBER(SEARCH("切り替え",C17)),ISNUMBER(SEARCH("切替",C17)),NOT(ISNUMBER(H17))),"",IF(ISNUMBER(G17),G17/60*H17*④前提設定!$B$4,IF(AND(G17="",ISNUMBER(F17)),F17/60*H17*④前提設定!$B$4,""))) | N17: - | O17: =IF(AND(J17>0,ISNUMBER(M17)),M17/J17,"") | R17: 自社製ホイップの卵プリン | S17: Ｓホイップの卵プリン | T17: ホイップの卵プリン | X17: =COUNTA(R17:W17) | Y17: =IF(AND($X17>0,ISNUMBER($M17)),$M17/$X17,"") | Z17: =IF($X17=0,"",IF(COUNTIF(⑳商品別1食労務費!$C$5:$C$124,$R17)+COUNTIF(⑳商品別1食労務費!$C$5:$C$124,$S17)+COUNTIF(⑳商品別1食労務費!$C$5:$C$124,$T17)+COUNTIF(⑳商品別1食労務費!$C$5:$C$124,$U17)+COUNTIF(⑳商品別1食労務費!$C$5:$C$124,$V17)+COUNTIF(⑳商品別1食労務費!$C$5:$C$124,$W17)=$X17,"OK","⑳に無い商品名")) | AA17: =SUMIF(⑳商品別1食労務費!$C$5:$C$124,$R17,⑳商品別1食労務費!$F$5:$F$124)+SUMIF(⑳商品別1食労務費!$C$5:$C$124,$S17,⑳商品別1食労務費!$F$5:$F$124)+SUMIF(⑳商品別1食労務費!$C$5:$C$124,$T17,⑳商品別1食労務費!$F$5:$F$124)+SUMIF(⑳商品別1食労務費!$C$5:$C$124,$U17,⑳商品別1食労務費!$F$5:$F$124)+SUMIF(⑳商品別1食労務費!$C$5:$C$124,$V17,⑳商品別1食労務費!$F$5:$F$124)+SUMIF(⑳商品別1食労務費!$C$5:$C$124,$W17,⑳商品別1食労務費!$F$5:$F$124) | AB17: =IF(ISNUMBER($M17),$M17,0) | AD17: =IF($R17="",0,IF($AA17>0,$AB17*SUMIF(⑳商品別1食労務費!$C$5:$C$124,$R17,⑳商品別1食労務費!$F$5:$F$124)/$AA17,$AB17/$X17)) | AE17: =IF($S17="",0,IF($AA17>0,$AB17*SUMIF(⑳商品別1食労務費!$C$5:$C$124,$S17,⑳商品別1食労務費!$F$5:$F$124)/$AA17,$AB17/$X17)) | AF17: =IF($T17="",0,IF($AA17>0,$AB17*SUMIF(⑳商品別1食労務費!$C$5:$C$124,$T17,⑳商品別1食労務費!$F$5:$F$124)/$AA17,$AB17/$X17)) | AG17: =IF($U17="",0,IF($AA17>0,$AB17*SUMIF(⑳商品別1食労務費!$C$5:$C$124,$U17,⑳商品別1食労務費!$F$5:$F$124)/$AA17,$AB17/$X17)) | AH17: =IF($V17="",0,IF($AA17>0,$AB17*SUMIF(⑳商品別1食労務費!$C$5:$C$124,$V17,⑳商品別1食労務費!$F$5:$F$124)/$AA17,$AB17/$X17)) | AI17: =IF($W17="",0,IF($AA17>0,$AB17*SUMIF(⑳商品別1食労務費!$C$5:$C$124,$W17,⑳商品別1食労務費!$F$5:$F$124)/$AA17,$AB17/$X17))
A18: 14 | B18: 釜製造 | C18: 自社製ホイップの卵プリン | F18: 110 | G18: 90 | H18: 2 | I18: 120 | K18: =IF(F18>0,I18/(F18/60),0) | L18: =IF(AND(ISNUMBER(F18),J18>0),J18/(F18/60),"") | M18: =IF(OR(ISNUMBER(SEARCH("サニテーション",C18)),ISNUMBER(SEARCH("客注",C18)),ISNUMBER(SEARCH("切り替え",C18)),ISNUMBER(SEARCH("切替",C18)),NOT(ISNUMBER(H18))),"",IF(ISNUMBER(G18),G18/60*H18*④前提設定!$B$4,IF(AND(G18="",ISNUMBER(F18)),F18/60*H18*④前提設定!$B$4,""))) | N18: =IF(I18>0,M18/I18,"") | O18: =IF(AND(J18>0,ISNUMBER(M18)),M18/J18,"") | R18: 自社製ホイップの卵プリン | S18: Ｓホイップの卵プリン | T18: ホイップの卵プリン | X18: =COUNTA(R18:W18) | Y18: =IF(AND($X18>0,ISNUMBER($M18)),$M18/$X18,"") | Z18: =IF($X18=0,"",IF(COUNTIF(⑳商品別1食労務費!$C$5:$C$124,$R18)+COUNTIF(⑳商品別1食労務費!$C$5:$C$124,$S18)+COUNTIF(⑳商品別1食労務費!$C$5:$C$124,$T18)+COUNTIF(⑳商品別1食労務費!$C$5:$C$124,$U18)+COUNTIF(⑳商品別1食労務費!$C$5:$C$124,$V18)+COUNTIF(⑳商品別1食労務費!$C$5:$C$124,$W18)=$X18,"OK","⑳に無い商品名")) | AA18: =SUMIF(⑳商品別1食労務費!$C$5:$C$124,$R18,⑳商品別1食労務費!$F$5:$F$124)+SUMIF(⑳商品別1食労務費!$C$5:$C$124,$S18,⑳商品別1食労務費!$F$5:$F$124)+SUMIF(⑳商品別1食労務費!$C$5:$C$124,$T18,⑳商品別1食労務費!$F$5:$F$124)+SUMIF(⑳商品別1食労務費!$C$5:$C$124,$U18,⑳商品別1食労務費!$F$5:$F$124)+SUMIF(⑳商品別1食労務費!$C$5:$C$124,$V18,⑳商品別1食労務費!$F$5:$F$124)+SUMIF(⑳商品別1食労務費!$C$5:$C$124,$W18,⑳商品別1食労務費!$F$5:$F$124) | AB18: =IF(ISNUMBER($M18),$M18,0) | AD18: =IF($R18="",0,IF($AA18>0,$AB18*SUMIF(⑳商品別1食労務費!$C$5:$C$124,$R18,⑳商品別1食労務費!$F$5:$F$124)/$AA18,$AB18/$X18)) | AE18: =IF($S18="",0,IF($AA18>0,$AB18*SUMIF(⑳商品別1食労務費!$C$5:$C$124,$S18,⑳商品別1食労務費!$F$5:$F$124)/$AA18,$AB18/$X18)) | AF18: =IF($T18="",0,IF($AA18>0,$AB18*SUMIF(⑳商品別1食労務費!$C$5:$C$124,$T18,⑳商品別1食労務費!$F$5:$F$124)/$AA18,$AB18/$X18)) | AG18: =IF($U18="",0,IF($AA18>0,$AB18*SUMIF(⑳商品別1食労務費!$C$5:$C$124,$U18,⑳商品別1食労務費!$F$5:$F$124)/$AA18,$AB18/$X18)) | AH18: =IF($V18="",0,IF($AA18>0,$AB18*SUMIF(⑳商品別1食労務費!$C$5:$C$124,$V18,⑳商品別1食労務費!$F$5:$F$124)/$AA18,$AB18/$X18)) | AI18: =IF($W18="",0,IF($AA18>0,$AB18*SUMIF(⑳商品別1食労務費!$C$5:$C$124,$W18,⑳商品別1食労務費!$F$5:$F$124)/$AA18,$AB18/$X18))
A19: 15 | B19: 釜製造 | C19: ミキサー | K19: =IF(F19>0,I19/(F19/60),0) | L19: =IF(AND(ISNUMBER(F19),J19>0),J19/(F19/60),"") | M19: =IF(OR(ISNUMBER(SEARCH("サニテーション",C19)),ISNUMBER(SEARCH("客注",C19)),ISNUMBER(SEARCH("切り替え",C19)),ISNUMBER(SEARCH("切替",C19)),NOT(ISNUMBER(H19))),"",IF(ISNUMBER(G19),G19/60*H19*④前提設定!$B$4,IF(AND(G19="",ISNUMBER(F19)),F19/60*H19*④前提設定!$B$4,""))) | N19: =IF(I19>0,M19/I19,"") | O19: =IF(AND(J19>0,ISNUMBER(M19)),M19/J19,"") | X19: =COUNTA(R19:W19) | Y19: =IF(AND($X19>0,ISNUMBER($M19)),$M19/$X19,"") | Z19: =IF($X19=0,"",IF(COUNTIF(⑳商品別1食労務費!$C$5:$C$124,$R19)+COUNTIF(⑳商品別1食労務費!$C$5:$C$124,$S19)+COUNTIF(⑳商品別1食労務費!$C$5:$C$124,$T19)+COUNTIF(⑳商品別1食労務費!$C$5:$C$124,$U19)+COUNTIF(⑳商品別1食労務費!$C$5:$C$124,$V19)+COUNTIF(⑳商品別1食労務費!$C$5:$C$124,$W19)=$X19,"OK","⑳に無い商品名")) | AA19: =SUMIF(⑳商品別1食労務費!$C$5:$C$124,$R19,⑳商品別1食労務費!$F$5:$F$124)+SUMIF(⑳商品別1食労務費!$C$5:$C$124,$S19,⑳商品別1食労務費!$F$5:$F$124)+SUMIF(⑳商品別1食労務費!$C$5:$C$124,$T19,⑳商品別1食労務費!$F$5:$F$124)+SUMIF(⑳商品別1食労務費!$C$5:$C$124,$U19,⑳商品別1食労務費!$F$5:$F$124)+SUMIF(⑳商品別1食労務費!$C$5:$C$124,$V19,⑳商品別1食労務費!$F$5:$F$124)+SUMIF(⑳商品別1食労務費!$C$5:$C$124,$W19,⑳商品別1食労務費!$F$5:$F$124) | AB19: =IF(ISNUMBER($M19),$M19,0) | AD19: =IF($R19="",0,IF($AA19>0,$AB19*SUMIF(⑳商品別1食労務費!$C$5:$C$124,$R19,⑳商品別1食労務費!$F$5:$F$124)/$AA19,$AB19/$X19)) | AE19: =IF($S19="",0,IF($AA19>0,$AB19*SUMIF(⑳商品別1食労務費!$C$5:$C$124,$S19,⑳商品別1食労務費!$F$5:$F$124)/$AA19,$AB19/$X19)) | AF19: =IF($T19="",0,IF($AA19>0,$AB19*SUMIF(⑳商品別1食労務費!$C$5:$C$124,$T19,⑳商品別1食労務費!$F$5:$F$124)/$AA19,$AB19/$X19)) | AG19: =IF($U19="",0,IF($AA19>0,$AB19*SUMIF(⑳商品別1食労務費!$C$5:$C$124,$U19,⑳商品別1食労務費!$F$5:$F$124)/$AA19,$AB19/$X19)) | AH19: =IF($V19="",0,IF($AA19>0,$AB19*SUMIF(⑳商品別1食労務費!$C$5:$C$124,$V19,⑳商品別1食労務費!$F$5:$F$124)/$AA19,$AB19/$X19)) | AI19: =IF($W19="",0,IF($AA19>0,$AB19*SUMIF(⑳商品別1食労務費!$C$5:$C$124,$W19,⑳商品別1食労務費!$F$5:$F$124)/$AA19,$AB19/$X19))
A20: 16 | B20: 釜製造 | C20: 湯種ロールパン | D20: 0.025 | E20: 0.038888889 | F20: 5 | G20: 15 | H20: 1 | I20: 16 | K20: =IF(F20>0,I20/(F20/60),0) | L20: =IF(AND(ISNUMBER(F20),J20>0),J20/(F20/60),"") | M20: =IF(OR(ISNUMBER(SEARCH("サニテーション",C20)),ISNUMBER(SEARCH("客注",C20)),ISNUMBER(SEARCH("切り替え",C20)),ISNUMBER(SEARCH("切替",C20)),NOT(ISNUMBER(H20))),"",IF(ISNUMBER(G20),G20/60*H20*④前提設定!$B$4,IF(AND(G20="",ISNUMBER(F20)),F20/60*H20*④前提設定!$B$4,""))) | N20: =IF(I20>0,M20/I20,"") | O20: =IF(AND(J20>0,ISNUMBER(M20)),M20/J20,"") | R20: 全粒粉入り湯種ロール６個 | S20: 全粒粉入り湯種ロール３個 | T20: Ｓ全粒粉入り湯種ロール６個 | X20: =COUNTA(R20:W20) | Y20: =IF(AND($X20>0,ISNUMBER($M20)),$M20/$X20,"") | Z20: =IF($X20=0,"",IF(COUNTIF(⑳商品別1食労務費!$C$5:$C$124,$R20)+COUNTIF(⑳商品別1食労務費!$C$5:$C$124,$S20)+COUNTIF(⑳商品別1食労務費!$C$5:$C$124,$T20)+COUNTIF(⑳商品別1食労務費!$C$5:$C$124,$U20)+COUNTIF(⑳商品別1食労務費!$C$5:$C$124,$V20)+COUNTIF(⑳商品別1食労務費!$C$5:$C$124,$W20)=$X20,"OK","⑳に無い商品名")) | AA20: =SUMIF(⑳商品別1食労務費!$C$5:$C$124,$R20,⑳商品別1食労務費!$F$5:$F$124)+SUMIF(⑳商品別1食労務費!$C$5:$C$124,$S20,⑳商品別1食労務費!$F$5:$F$124)+SUMIF(⑳商品別1食労務費!$C$5:$C$124,$T20,⑳商品別1食労務費!$F$5:$F$124)+SUMIF(⑳商品別1食労務費!$C$5:$C$124,$U20,⑳商品別1食労務費!$F$5:$F$124)+SUMIF(⑳商品別1食労務費!$C$5:$C$124,$V20,⑳商品別1食労務費!$F$5:$F$124)+SUMIF(⑳商品別1食労務費!$C$5:$C$124,$W20,⑳商品別1食労務費!$F$5:$F$124) | AB20: =IF(ISNUMBER($M20),$M20,0) | AD20: =IF($R20="",0,IF($AA20>0,$AB20*SUMIF(⑳商品別1食労務費!$C$5:$C$124,$R20,⑳商品別1食労務費!$F$5:$F$124)/$AA20,$AB20/$X20)) | AE20: =IF($S20="",0,IF($AA20>0,$AB20*SUMIF(⑳商品別1食労務費!$C$5:$C$124,$S20,⑳商品別1食労務費!$F$5:$F$124)/$AA20,$AB20/$X20)) | AF20: =IF($T20="",0,IF($AA20>0,$AB20*SUMIF(⑳商品別1食労務費!$C$5:$C$124,$T20,⑳商品別1食労務費!$F$5:$F$124)/$AA20,$AB20/$X20)) | AG20: =IF($U20="",0,IF($AA20>0,$AB20*SUMIF(⑳商品別1食労務費!$C$5:$C$124,$U20,⑳商品別1食労務費!$F$5:$F$124)/$AA20,$AB20/$X20)) | AH20: =IF($V20="",0,IF($AA20>0,$AB20*SUMIF(⑳商品別1食労務費!$C$5:$C$124,$V20,⑳商品別1食労務費!$F$5:$F$124)/$AA20,$AB20/$X20)) | AI20: =IF($W20="",0,IF($AA20>0,$AB20*SUMIF(⑳商品別1食労務費!$C$5:$C$124,$W20,⑳商品別1食労務費!$F$5:$F$124)/$AA20,$AB20/$X20))
A21: 17 | B21: 釜製造 | C21: 湯種ロールパン | D21: 0.038888889 | E21: 0.052777778 | F21: 5 | G21: 15 | H21: 1 | I21: 16 | K21: =IF(F21>0,I21/(F21/60),0) | L21: =IF(AND(ISNUMBER(F21),J21>0),J21/(F21/60),"") | M21: =IF(OR(ISNUMBER(SEARCH("サニテーション",C21)),ISNUMBER(SEARCH("客注",C21)),ISNUMBER(SEARCH("切り替え",C21)),ISNUMBER(SEARCH("切替",C21)),NOT(ISNUMBER(H21))),"",IF(ISNUMBER(G21),G21/60*H21*④前提設定!$B$4,IF(AND(G21="",ISNUMBER(F21)),F21/60*H21*④前提設定!$B$4,""))) | N21: =IF(I21>0,M21/I21,"") | O21: =IF(AND(J21>0,ISNUMBER(M21)),M21/J21,"") | R21: 全粒粉入り湯種ロール６個 | S21: 全粒粉入り湯種ロール３個 | T21: Ｓ全粒粉入り湯種ロール６個 | X21: =COUNTA(R21:W21) | Y21: =IF(AND($X21>0,ISNUMBER($M21)),$M21/$X21,"") | Z21: =IF($X21=0,"",IF(COUNTIF(⑳商品別1食労務費!$C$5:$C$124,$R21)+COUNTIF(⑳商品別1食労務費!$C$5:$C$124,$S21)+COUNTIF(⑳商品別1食労務費!$C$5:$C$124,$T21)+COUNTIF(⑳商品別1食労務費!$C$5:$C$124,$U21)+COUNTIF(⑳商品別1食労務費!$C$5:$C$124,$V21)+COUNTIF(⑳商品別1食労務費!$C$5:$C$124,$W21)=$X21,"OK","⑳に無い商品名")) | AA21: =SUMIF(⑳商品別1食労務費!$C$5:$C$124,$R21,⑳商品別1食労務費!$F$5:$F$124)+SUMIF(⑳商品別1食労務費!$C$5:$C$124,$S21,⑳商品別1食労務費!$F$5:$F$124)+SUMIF(⑳商品別1食労務費!$C$5:$C$124,$T21,⑳商品別1食労務費!$F$5:$F$124)+SUMIF(⑳商品別1食労務費!$C$5:$C$124,$U21,⑳商品別1食労務費!$F$5:$F$124)+SUMIF(⑳商品別1食労務費!$C$5:$C$124,$V21,⑳商品別1食労務費!$F$5:$F$124)+SUMIF(⑳商品別1食労務費!$C$5:$C$124,$W21,⑳商品別1食労務費!$F$5:$F$124) | AB21: =IF(ISNUMBER($M21),$M21,0) | AD21: =IF($R21="",0,IF($AA21>0,$AB21*SUMIF(⑳商品別1食労務費!$C$5:$C$124,$R21,⑳商品別1食労務費!$F$5:$F$124)/$AA21,$AB21/$X21)) | AE21: =IF($S21="",0,IF($AA21>0,$AB21*SUMIF(⑳商品別1食労務費!$C$5:$C$124,$S21,⑳商品別1食労務費!$F$5:$F$124)/$AA21,$AB21/$X21)) | AF21: =IF($T21="",0,IF($AA21>0,$AB21*SUMIF(⑳商品別1食労務費!$C$5:$C$124,$T21,⑳商品別1食労務費!$F$5:$F$124)/$AA21,$AB21/$X21)) | AG21: =IF($U21="",0,IF($AA21>0,$AB21*SUMIF(⑳商品別1食労務費!$C$5:$C$124,$U21,⑳商品別1食労務費!$F$5:$F$124)/$AA21,$AB21/$X21)) | AH21: =IF($V21="",0,IF($AA21>0,$AB21*SUMIF(⑳商品別1食労務費!$C$5:$C$124,$V21,⑳商品別1食労務費!$F$5:$F$124)/$AA21,$AB21/$X21)) | AI21: =IF($W21="",0,IF($AA21>0,$AB21*SUMIF(⑳商品別1食労務費!$C$5:$C$124,$W21,⑳商品別1食労務費!$F$5:$F$124)/$AA21,$AB21/$X21))
A22: 18 | B22: 釜製造 | C22: 湯種ロールパン | D22: 0.052777778 | E22: 0.066666667 | F22: 5 | G22: 15 | H22: 1 | I22: 16 | K22: =IF(F22>0,I22/(F22/60),0) | L22: =IF(AND(ISNUMBER(F22),J22>0),J22/(F22/60),"") | M22: =IF(OR(ISNUMBER(SEARCH("サニテーション",C22)),ISNUMBER(SEARCH("客注",C22)),ISNUMBER(SEARCH("切り替え",C22)),ISNUMBER(SEARCH("切替",C22)),NOT(ISNUMBER(H22))),"",IF(ISNUMBER(G22),G22/60*H22*④前提設定!$B$4,IF(AND(G22="",ISNUMBER(F22)),F22/60*H22*④前提設定!$B$4,""))) | N22: =IF(I22>0,M22/I22,"") | O22: =IF(AND(J22>0,ISNUMBER(M22)),M22/J22,"") | R22: 全粒粉入り湯種ロール６個 | S22: 全粒粉入り湯種ロール３個 | T22: Ｓ全粒粉入り湯種ロール６個 | X22: =COUNTA(R22:W22) | Y22: =IF(AND($X22>0,ISNUMBER($M22)),$M22/$X22,"") | Z22: =IF($X22=0,"",IF(COUNTIF(⑳商品別1食労務費!$C$5:$C$124,$R22)+COUNTIF(⑳商品別1食労務費!$C$5:$C$124,$S22)+COUNTIF(⑳商品別1食労務費!$C$5:$C$124,$T22)+COUNTIF(⑳商品別1食労務費!$C$5:$C$124,$U22)+COUNTIF(⑳商品別1食労務費!$C$5:$C$124,$V22)+COUNTIF(⑳商品別1食労務費!$C$5:$C$124,$W22)=$X22,"OK","⑳に無い商品名")) | AA22: =SUMIF(⑳商品別1食労務費!$C$5:$C$124,$R22,⑳商品別1食労務費!$F$5:$F$124)+SUMIF(⑳商品別1食労務費!$C$5:$C$124,$S22,⑳商品別1食労務費!$F$5:$F$124)+SUMIF(⑳商品別1食労務費!$C$5:$C$124,$T22,⑳商品別1食労務費!$F$5:$F$124)+SUMIF(⑳商品別1食労務費!$C$5:$C$124,$U22,⑳商品別1食労務費!$F$5:$F$124)+SUMIF(⑳商品別1食労務費!$C$5:$C$124,$V22,⑳商品別1食労務費!$F$5:$F$124)+SUMIF(⑳商品別1食労務費!$C$5:$C$124,$W22,⑳商品別1食労務費!$F$5:$F$124) | AB22: =IF(ISNUMBER($M22),$M22,0) | AD22: =IF($R22="",0,IF($AA22>0,$AB22*SUMIF(⑳商品別1食労務費!$C$5:$C$124,$R22,⑳商品別1食労務費!$F$5:$F$124)/$AA22,$AB22/$X22)) | AE22: =IF($S22="",0,IF($AA22>0,$AB22*SUMIF(⑳商品別1食労務費!$C$5:$C$124,$S22,⑳商品別1食労務費!$F$5:$F$124)/$AA22,$AB22/$X22)) | AF22: =IF($T22="",0,IF($AA22>0,$AB22*SUMIF(⑳商品別1食労務費!$C$5:$C$124,$T22,⑳商品別1食労務費!$F$5:$F$124)/$AA22,$AB22/$X22)) | AG22: =IF($U22="",0,IF($AA22>0,$AB22*SUMIF(⑳商品別1食労務費!$C$5:$C$124,$U22,⑳商品別1食労務費!$F$5:$F$124)/$AA22,$AB22/$X22)) | AH22: =IF($V22="",0,IF($AA22>0,$AB22*SUMIF(⑳商品別1食労務費!$C$5:$C$124,$V22,⑳商品別1食労務費!$F$5:$F$124)/$AA22,$AB22/$X22)) | AI22: =IF($W22="",0,IF($AA22>0,$AB22*SUMIF(⑳商品別1食労務費!$C$5:$C$124,$W22,⑳商品別1食労務費!$F$5:$F$124)/$AA22,$AB22/$X22))
A23: 19 | B23: 釜製造 | C23: 湯種ロールパン | D23: 0.066666667 | E23: 0.080555556 | F23: 5 | G23: 15 | H23: 1 | I23: 16 | K23: =IF(F23>0,I23/(F23/60),0) | L23: =IF(AND(ISNUMBER(F23),J23>0),J23/(F23/60),"") | M23: =IF(OR(ISNUMBER(SEARCH("サニテーション",C23)),ISNUMBER(SEARCH("客注",C23)),ISNUMBER(SEARCH("切り替え",C23)),ISNUMBER(SEARCH("切替",C23)),NOT(ISNUMBER(H23))),"",IF(ISNUMBER(G23),G23/60*H23*④前提設定!$B$4,IF(AND(G23="",ISNUMBER(F23)),F23/60*H23*④前提設定!$B$4,""))) | N23: =IF(I23>0,M23/I23,"") | O23: =IF(AND(J23>0,ISNUMBER(M23)),M23/J23,"") | R23: 全粒粉入り湯種ロール６個 | S23: 全粒粉入り湯種ロール３個 | T23: Ｓ全粒粉入り湯種ロール６個 | X23: =COUNTA(R23:W23) | Y23: =IF(AND($X23>0,ISNUMBER($M23)),$M23/$X23,"") | Z23: =IF($X23=0,"",IF(COUNTIF(⑳商品別1食労務費!$C$5:$C$124,$R23)+COUNTIF(⑳商品別1食労務費!$C$5:$C$124,$S23)+COUNTIF(⑳商品別1食労務費!$C$5:$C$124,$T23)+COUNTIF(⑳商品別1食労務費!$C$5:$C$124,$U23)+COUNTIF(⑳商品別1食労務費!$C$5:$C$124,$V23)+COUNTIF(⑳商品別1食労務費!$C$5:$C$124,$W23)=$X23,"OK","⑳に無い商品名")) | AA23: =SUMIF(⑳商品別1食労務費!$C$5:$C$124,$R23,⑳商品別1食労務費!$F$5:$F$124)+SUMIF(⑳商品別1食労務費!$C$5:$C$124,$S23,⑳商品別1食労務費!$F$5:$F$124)+SUMIF(⑳商品別1食労務費!$C$5:$C$124,$T23,⑳商品別1食労務費!$F$5:$F$124)+SUMIF(⑳商品別1食労務費!$C$5:$C$124,$U23,⑳商品別1食労務費!$F$5:$F$124)+SUMIF(⑳商品別1食労務費!$C$5:$C$124,$V23,⑳商品別1食労務費!$F$5:$F$124)+SUMIF(⑳商品別1食労務費!$C$5:$C$124,$W23,⑳商品別1食労務費!$F$5:$F$124) | AB23: =IF(ISNUMBER($M23),$M23,0) | AD23: =IF($R23="",0,IF($AA23>0,$AB23*SUMIF(⑳商品別1食労務費!$C$5:$C$124,$R23,⑳商品別1食労務費!$F$5:$F$124)/$AA23,$AB23/$X23)) | AE23: =IF($S23="",0,IF($AA23>0,$AB23*SUMIF(⑳商品別1食労務費!$C$5:$C$124,$S23,⑳商品別1食労務費!$F$5:$F$124)/$AA23,$AB23/$X23)) | AF23: =IF($T23="",0,IF($AA23>0,$AB23*SUMIF(⑳商品別1食労務費!$C$5:$C$124,$T23,⑳商品別1食労務費!$F$5:$F$124)/$AA23,$AB23/$X23)) | AG23: =IF($U23="",0,IF($AA23>0,$AB23*SUMIF(⑳商品別1食労務費!$C$5:$C$124,$U23,⑳商品別1食労務費!$F$5:$F$124)/$AA23,$AB23/$X23)) | AH23: =IF($V23="",0,IF($AA23>0,$AB23*SUMIF(⑳商品別1食労務費!$C$5:$C$124,$V23,⑳商品別1食労務費!$F$5:$F$124)/$AA23,$AB23/$X23)) | AI23: =IF($W23="",0,IF($AA23>0,$AB23*SUMIF(⑳商品別1食労務費!$C$5:$C$124,$W23,⑳商品別1食労務費!$F$5:$F$124)/$AA23,$AB23/$X23))
A24: 20 | B24: 釜製造 | C24: 湯種ロールパン | D24: 0.080555556 | E24: 0.094444444 | F24: 5 | G24: 15 | H24: 1 | I24: 16 | K24: =IF(F24>0,I24/(F24/60),0) | L24: =IF(AND(ISNUMBER(F24),J24>0),J24/(F24/60),"") | M24: =IF(OR(ISNUMBER(SEARCH("サニテーション",C24)),ISNUMBER(SEARCH("客注",C24)),ISNUMBER(SEARCH("切り替え",C24)),ISNUMBER(SEARCH("切替",C24)),NOT(ISNUMBER(H24))),"",IF(ISNUMBER(G24),G24/60*H24*④前提設定!$B$4,IF(AND(G24="",ISNUMBER(F24)),F24/60*H24*④前提設定!$B$4,""))) | N24: =IF(I24>0,M24/I24,"") | O24: =IF(AND(J24>0,ISNUMBER(M24)),M24/J24,"") | R24: 全粒粉入り湯種ロール６個 | S24: 全粒粉入り湯種ロール３個 | T24: Ｓ全粒粉入り湯種ロール６個 | X24: =COUNTA(R24:W24) | Y24: =IF(AND($X24>0,ISNUMBER($M24)),$M24/$X24,"") | Z24: =IF($X24=0,"",IF(COUNTIF(⑳商品別1食労務費!$C$5:$C$124,$R24)+COUNTIF(⑳商品別1食労務費!$C$5:$C$124,$S24)+COUNTIF(⑳商品別1食労務費!$C$5:$C$124,$T24)+COUNTIF(⑳商品別1食労務費!$C$5:$C$124,$U24)+COUNTIF(⑳商品別1食労務費!$C$5:$C$124,$V24)+COUNTIF(⑳商品別1食労務費!$C$5:$C$124,$W24)=$X24,"OK","⑳に無い商品名")) | AA24: =SUMIF(⑳商品別1食労務費!$C$5:$C$124,$R24,⑳商品別1食労務費!$F$5:$F$124)+SUMIF(⑳商品別1食労務費!$C$5:$C$124,$S24,⑳商品別1食労務費!$F$5:$F$124)+SUMIF(⑳商品別1食労務費!$C$5:$C$124,$T24,⑳商品別1食労務費!$F$5:$F$124)+SUMIF(⑳商品別1食労務費!$C$5:$C$124,$U24,⑳商品別1食労務費!$F$5:$F$124)+SUMIF(⑳商品別1食労務費!$C$5:$C$124,$V24,⑳商品別1食労務費!$F$5:$F$124)+SUMIF(⑳商品別1食労務費!$C$5:$C$124,$W24,⑳商品別1食労務費!$F$5:$F$124) | AB24: =IF(ISNUMBER($M24),$M24,0) | AD24: =IF($R24="",0,IF($AA24>0,$AB24*SUMIF(⑳商品別1食労務費!$C$5:$C$124,$R24,⑳商品別1食労務費!$F$5:$F$124)/$AA24,$AB24/$X24)) | AE24: =IF($S24="",0,IF($AA24>0,$AB24*SUMIF(⑳商品別1食労務費!$C$5:$C$124,$S24,⑳商品別1食労務費!$F$5:$F$124)/$AA24,$AB24/$X24)) | AF24: =IF($T24="",0,IF($AA24>0,$AB24*SUMIF(⑳商品別1食労務費!$C$5:$C$124,$T24,⑳商品別1食労務費!$F$5:$F$124)/$AA24,$AB24/$X24)) | AG24: =IF($U24="",0,IF($AA24>0,$AB24*SUMIF(⑳商品別1食労務費!$C$5:$C$124,$U24,⑳商品別1食労務費!$F$5:$F$124)/$AA24,$AB24/$X24)) | AH24: =IF($V24="",0,IF($AA24>0,$AB24*SUMIF(⑳商品別1食労務費!$C$5:$C$124,$V24,⑳商品別1食労務費!$F$5:$F$124)/$AA24,$AB24/$X24)) | AI24: =IF($W24="",0,IF($AA24>0,$AB24*SUMIF(⑳商品別1食労務費!$C$5:$C$124,$W24,⑳商品別1食労務費!$F$5:$F$124)/$AA24,$AB24/$X24))
A25: 21 | B25: 釜製造 | C25: ホテルロール | D25: 0.094444444 | E25: 0.10833333 | F25: 5 | G25: 15 | H25: 1 | I25: 16 | K25: =IF(F25>0,I25/(F25/60),0) | L25: =IF(AND(ISNUMBER(F25),J25>0),J25/(F25/60),"") | M25: =IF(OR(ISNUMBER(SEARCH("サニテーション",C25)),ISNUMBER(SEARCH("客注",C25)),ISNUMBER(SEARCH("切り替え",C25)),ISNUMBER(SEARCH("切替",C25)),NOT(ISNUMBER(H25))),"",IF(ISNUMBER(G25),G25/60*H25*④前提設定!$B$4,IF(AND(G25="",ISNUMBER(F25)),F25/60*H25*④前提設定!$B$4,""))) | N25: =IF(I25>0,M25/I25,"") | O25: =IF(AND(J25>0,ISNUMBER(M25)),M25/J25,"") | R25: ふわもちホテルロール３個 | S25: ふわもちホテルロール８個入 | T25: ふわもちホテルロール１６個 | U25: Ｓふわもちホテルロール８個 | V25: Ｓふわもちホテルロール１６ | W25: ホテルロールＫＩＴ ４０個 | X25: =COUNTA(R25:W25) | Y25: =IF(AND($X25>0,ISNUMBER($M25)),$M25/$X25,"") | Z25: =IF($X25=0,"",IF(COUNTIF(⑳商品別1食労務費!$C$5:$C$124,$R25)+COUNTIF(⑳商品別1食労務費!$C$5:$C$124,$S25)+COUNTIF(⑳商品別1食労務費!$C$5:$C$124,$T25)+COUNTIF(⑳商品別1食労務費!$C$5:$C$124,$U25)+COUNTIF(⑳商品別1食労務費!$C$5:$C$124,$V25)+COUNTIF(⑳商品別1食労務費!$C$5:$C$124,$W25)=$X25,"OK","⑳に無い商品名")) | AA25: =SUMIF(⑳商品別1食労務費!$C$5:$C$124,$R25,⑳商品別1食労務費!$F$5:$F$124)+SUMIF(⑳商品別1食労務費!$C$5:$C$124,$S25,⑳商品別1食労務費!$F$5:$F$124)+SUMIF(⑳商品別1食労務費!$C$5:$C$124,$T25,⑳商品別1食労務費!$F$5:$F$124)+SUMIF(⑳商品別1食労務費!$C$5:$C$124,$U25,⑳商品別1食労務費!$F$5:$F$124)+SUMIF(⑳商品別1食労務費!$C$5:$C$124,$V25,⑳商品別1食労務費!$F$5:$F$124)+SUMIF(⑳商品別1食労務費!$C$5:$C$124,$W25,⑳商品別1食労務費!$F$5:$F$124) | AB25: =IF(ISNUMBER($M25),$M25,0) | AD25: =IF($R25="",0,IF($AA25>0,$AB25*SUMIF(⑳商品別1食労務費!$C$5:$C$124,$R25,⑳商品別1食労務費!$F$5:$F$124)/$AA25,$AB25/$X25)) | AE25: =IF($S25="",0,IF($AA25>0,$AB25*SUMIF(⑳商品別1食労務費!$C$5:$C$124,$S25,⑳商品別1食労務費!$F$5:$F$124)/$AA25,$AB25/$X25)) | AF25: =IF($T25="",0,IF($AA25>0,$AB25*SUMIF(⑳商品別1食労務費!$C$5:$C$124,$T25,⑳商品別1食労務費!$F$5:$F$124)/$AA25,$AB25/$X25)) | AG25: =IF($U25="",0,IF($AA25>0,$AB25*SUMIF(⑳商品別1食労務費!$C$5:$C$124,$U25,⑳商品別1食労務費!$F$5:$F$124)/$AA25,$AB25/$X25)) | AH25: =IF($V25="",0,IF($AA25>0,$AB25*SUMIF(⑳商品別1食労務費!$C$5:$C$124,$V25,⑳商品別1食労務費!$F$5:$F$124)/$AA25,$AB25/$X25)) | AI25: =IF($W25="",0,IF($AA25>0,$AB25*SUMIF(⑳商品別1食労務費!$C$5:$C$124,$W25,⑳商品別1食労務費!$F$5:$F$124)/$AA25,$AB25/$X25))
A26: 22 | B26: 釜製造 | C26: ホテルロール | D26: 0.10833333 | E26: 0.12222222 | F26: 5 | G26: 15 | H26: 1 | I26: 16 | K26: =IF(F26>0,I26/(F26/60),0) | L26: =IF(AND(ISNUMBER(F26),J26>0),J26/(F26/60),"") | M26: =IF(OR(ISNUMBER(SEARCH("サニテーション",C26)),ISNUMBER(SEARCH("客注",C26)),ISNUMBER(SEARCH("切り替え",C26)),ISNUMBER(SEARCH("切替",C26)),NOT(ISNUMBER(H26))),"",IF(ISNUMBER(G26),G26/60*H26*④前提設定!$B$4,IF(AND(G26="",ISNUMBER(F26)),F26/60*H26*④前提設定!$B$4,""))) | N26: =IF(I26>0,M26/I26,"") | O26: =IF(AND(J26>0,ISNUMBER(M26)),M26/J26,"") | R26: ふわもちホテルロール３個 | S26: ふわもちホテルロール８個入 | T26: ふわもちホテルロール１６個 | U26: Ｓふわもちホテルロール８個 | V26: Ｓふわもちホテルロール１６ | W26: ホテルロールＫＩＴ ４０個 | X26: =COUNTA(R26:W26) | Y26: =IF(AND($X26>0,ISNUMBER($M26)),$M26/$X26,"") | Z26: =IF($X26=0,"",IF(COUNTIF(⑳商品別1食労務費!$C$5:$C$124,$R26)+COUNTIF(⑳商品別1食労務費!$C$5:$C$124,$S26)+COUNTIF(⑳商品別1食労務費!$C$5:$C$124,$T26)+COUNTIF(⑳商品別1食労務費!$C$5:$C$124,$U26)+COUNTIF(⑳商品別1食労務費!$C$5:$C$124,$V26)+COUNTIF(⑳商品別1食労務費!$C$5:$C$124,$W26)=$X26,"OK","⑳に無い商品名")) | AA26: =SUMIF(⑳商品別1食労務費!$C$5:$C$124,$R26,⑳商品別1食労務費!$F$5:$F$124)+SUMIF(⑳商品別1食労務費!$C$5:$C$124,$S26,⑳商品別1食労務費!$F$5:$F$124)+SUMIF(⑳商品別1食労務費!$C$5:$C$124,$T26,⑳商品別1食労務費!$F$5:$F$124)+SUMIF(⑳商品別1食労務費!$C$5:$C$124,$U26,⑳商品別1食労務費!$F$5:$F$124)+SUMIF(⑳商品別1食労務費!$C$5:$C$124,$V26,⑳商品別1食労務費!$F$5:$F$124)+SUMIF(⑳商品別1食労務費!$C$5:$C$124,$W26,⑳商品別1食労務費!$F$5:$F$124) | AB26: =IF(ISNUMBER($M26),$M26,0) | AD26: =IF($R26="",0,IF($AA26>0,$AB26*SUMIF(⑳商品別1食労務費!$C$5:$C$124,$R26,⑳商品別1食労務費!$F$5:$F$124)/$AA26,$AB26/$X26)) | AE26: =IF($S26="",0,IF($AA26>0,$AB26*SUMIF(⑳商品別1食労務費!$C$5:$C$124,$S26,⑳商品別1食労務費!$F$5:$F$124)/$AA26,$AB26/$X26)) | AF26: =IF($T26="",0,IF($AA26>0,$AB26*SUMIF(⑳商品別1食労務費!$C$5:$C$124,$T26,⑳商品別1食労務費!$F$5:$F$124)/$AA26,$AB26/$X26)) | AG26: =IF($U26="",0,IF($AA26>0,$AB26*SUMIF(⑳商品別1食労務費!$C$5:$C$124,$U26,⑳商品別1食労務費!$F$5:$F$124)/$AA26,$AB26/$X26)) | AH26: =IF($V26="",0,IF($AA26>0,$AB26*SUMIF(⑳商品別1食労務費!$C$5:$C$124,$V26,⑳商品別1食労務費!$F$5:$F$124)/$AA26,$AB26/$X26)) | AI26: =IF($W26="",0,IF($AA26>0,$AB26*SUMIF(⑳商品別1食労務費!$C$5:$C$124,$W26,⑳商品別1食労務費!$F$5:$F$124)/$AA26,$AB26/$X26))
A27: 23 | B27: 釜製造 | C27: ホテルロール | D27: 0.12222222 | E27: 0.13611111 | F27: 5 | G27: 15 | H27: 1 | I27: 16 | K27: - | L27: =IF(AND(ISNUMBER(F27),J27>0),J27/(F27/60),"") | M27: =IF(OR(ISNUMBER(SEARCH("サニテーション",C27)),ISNUMBER(SEARCH("客注",C27)),ISNUMBER(SEARCH("切り替え",C27)),ISNUMBER(SEARCH("切替",C27)),NOT(ISNUMBER(H27))),"",IF(ISNUMBER(G27),G27/60*H27*④前提設定!$B$4,IF(AND(G27="",ISNUMBER(F27)),F27/60*H27*④前提設定!$B$4,""))) | N27: - | O27: =IF(AND(J27>0,ISNUMBER(M27)),M27/J27,"") | R27: ふわもちホテルロール３個 | S27: ふわもちホテルロール８個入 | T27: ふわもちホテルロール１６個 | U27: Ｓふわもちホテルロール８個 | V27: Ｓふわもちホテルロール１６ | W27: ホテルロールＫＩＴ ４０個 | X27: =COUNTA(R27:W27) | Y27: =IF(AND($X27>0,ISNUMBER($M27)),$M27/$X27,"") | Z27: =IF($X27=0,"",IF(COUNTIF(⑳商品別1食労務費!$C$5:$C$124,$R27)+COUNTIF(⑳商品別1食労務費!$C$5:$C$124,$S27)+COUNTIF(⑳商品別1食労務費!$C$5:$C$124,$T27)+COUNTIF(⑳商品別1食労務費!$C$5:$C$124,$U27)+COUNTIF(⑳商品別1食労務費!$C$5:$C$124,$V27)+COUNTIF(⑳商品別1食労務費!$C$5:$C$124,$W27)=$X27,"OK","⑳に無い商品名")) | AA27: =SUMIF(⑳商品別1食労務費!$C$5:$C$124,$R27,⑳商品別1食労務費!$F$5:$F$124)+SUMIF(⑳商品別1食労務費!$C$5:$C$124,$S27,⑳商品別1食労務費!$F$5:$F$124)+SUMIF(⑳商品別1食労務費!$C$5:$C$124,$T27,⑳商品別1食労務費!$F$5:$F$124)+SUMIF(⑳商品別1食労務費!$C$5:$C$124,$U27,⑳商品別1食労務費!$F$5:$F$124)+SUMIF(⑳商品別1食労務費!$C$5:$C$124,$V27,⑳商品別1食労務費!$F$5:$F$124)+SUMIF(⑳商品別1食労務費!$C$5:$C$124,$W27,⑳商品別1食労務費!$F$5:$F$124) | AB27: =IF(ISNUMBER($M27),$M27,0) | AD27: =IF($R27="",0,IF($AA27>0,$AB27*SUMIF(⑳商品別1食労務費!$C$5:$C$124,$R27,⑳商品別1食労務費!$F$5:$F$124)/$AA27,$AB27/$X27)) | AE27: =IF($S27="",0,IF($AA27>0,$AB27*SUMIF(⑳商品別1食労務費!$C$5:$C$124,$S27,⑳商品別1食労務費!$F$5:$F$124)/$AA27,$AB27/$X27)) | AF27: =IF($T27="",0,IF($AA27>0,$AB27*SUMIF(⑳商品別1食労務費!$C$5:$C$124,$T27,⑳商品別1食労務費!$F$5:$F$124)/$AA27,$AB27/$X27)) | AG27: =IF($U27="",0,IF($AA27>0,$AB27*SUMIF(⑳商品別1食労務費!$C$5:$C$124,$U27,⑳商品別1食労務費!$F$5:$F$124)/$AA27,$AB27/$X27)) | AH27: =IF($V27="",0,IF($AA27>0,$AB27*SUMIF(⑳商品別1食労務費!$C$5:$C$124,$V27,⑳商品別1食労務費!$F$5:$F$124)/$AA27,$AB27/$X27)) | AI27: =IF($W27="",0,IF($AA27>0,$AB27*SUMIF(⑳商品別1食労務費!$C$5:$C$124,$W27,⑳商品別1食労務費!$F$5:$F$124)/$AA27,$AB27/$X27))
A28: 24 | B28: 釜製造 | C28: ホテルロール | D28: 0.13611111 | E28: 0.15 | F28: 5 | G28: 15 | H28: 1 | I28: 16 | K28: =IF(F28>0,I28/(F28/60),0) | L28: =IF(AND(ISNUMBER(F28),J28>0),J28/(F28/60),"") | M28: =IF(OR(ISNUMBER(SEARCH("サニテーション",C28)),ISNUMBER(SEARCH("客注",C28)),ISNUMBER(SEARCH("切り替え",C28)),ISNUMBER(SEARCH("切替",C28)),NOT(ISNUMBER(H28))),"",IF(ISNUMBER(G28),G28/60*H28*④前提設定!$B$4,IF(AND(G28="",ISNUMBER(F28)),F28/60*H28*④前提設定!$B$4,""))) | N28: =IF(I28>0,M28/I28,"") | O28: =IF(AND(J28>0,ISNUMBER(M28)),M28/J28,"") | R28: ふわもちホテルロール３個 | S28: ふわもちホテルロール８個入 | T28: ふわもちホテルロール１６個 | U28: Ｓふわもちホテルロール８個 | V28: Ｓふわもちホテルロール１６ | W28: ホテルロールＫＩＴ ４０個 | X28: =COUNTA(R28:W28) | Y28: =IF(AND($X28>0,ISNUMBER($M28)),$M28/$X28,"") | Z28: =IF($X28=0,"",IF(COUNTIF(⑳商品別1食労務費!$C$5:$C$124,$R28)+COUNTIF(⑳商品別1食労務費!$C$5:$C$124,$S28)+COUNTIF(⑳商品別1食労務費!$C$5:$C$124,$T28)+COUNTIF(⑳商品別1食労務費!$C$5:$C$124,$U28)+COUNTIF(⑳商品別1食労務費!$C$5:$C$124,$V28)+COUNTIF(⑳商品別1食労務費!$C$5:$C$124,$W28)=$X28,"OK","⑳に無い商品名")) | AA28: =SUMIF(⑳商品別1食労務費!$C$5:$C$124,$R28,⑳商品別1食労務費!$F$5:$F$124)+SUMIF(⑳商品別1食労務費!$C$5:$C$124,$S28,⑳商品別1食労務費!$F$5:$F$124)+SUMIF(⑳商品別1食労務費!$C$5:$C$124,$T28,⑳商品別1食労務費!$F$5:$F$124)+SUMIF(⑳商品別1食労務費!$C$5:$C$124,$U28,⑳商品別1食労務費!$F$5:$F$124)+SUMIF(⑳商品別1食労務費!$C$5:$C$124,$V28,⑳商品別1食労務費!$F$5:$F$124)+SUMIF(⑳商品別1食労務費!$C$5:$C$124,$W28,⑳商品別1食労務費!$F$5:$F$124) | AB28: =IF(ISNUMBER($M28),$M28,0) | AD28: =IF($R28="",0,IF($AA28>0,$AB28*SUMIF(⑳商品別1食労務費!$C$5:$C$124,$R28,⑳商品別1食労務費!$F$5:$F$124)/$AA28,$AB28/$X28)) | AE28: =IF($S28="",0,IF($AA28>0,$AB28*SUMIF(⑳商品別1食労務費!$C$5:$C$124,$S28,⑳商品別1食労務費!$F$5:$F$124)/$AA28,$AB28/$X28)) | AF28: =IF($T28="",0,IF($AA28>0,$AB28*SUMIF(⑳商品別1食労務費!$C$5:$C$124,$T28,⑳商品別1食労務費!$F$5:$F$124)/$AA28,$AB28/$X28)) | AG28: =IF($U28="",0,IF($AA28>0,$AB28*SUMIF(⑳商品別1食労務費!$C$5:$C$124,$U28,⑳商品別1食労務費!$F$5:$F$124)/$AA28,$AB28/$X28)) | AH28: =IF($V28="",0,IF($AA28>0,$AB28*SUMIF(⑳商品別1食労務費!$C$5:$C$124,$V28,⑳商品別1食労務費!$F$5:$F$124)/$AA28,$AB28/$X28)) | AI28: =IF($W28="",0,IF($AA28>0,$AB28*SUMIF(⑳商品別1食労務費!$C$5:$C$124,$W28,⑳商品別1食労務費!$F$5:$F$124)/$AA28,$AB28/$X28))
A29: 25 | B29: 釜製造 | C29: ホテルロール | D29: 0.15 | E29: 0.16388889 | F29: 5 | G29: 15 | H29: 1 | I29: 16 | K29: =IF(F29>0,I29/(F29/60),0) | L29: =IF(AND(ISNUMBER(F29),J29>0),J29/(F29/60),"") | M29: =IF(OR(ISNUMBER(SEARCH("サニテーション",C29)),ISNUMBER(SEARCH("客注",C29)),ISNUMBER(SEARCH("切り替え",C29)),ISNUMBER(SEARCH("切替",C29)),NOT(ISNUMBER(H29))),"",IF(ISNUMBER(G29),G29/60*H29*④前提設定!$B$4,IF(AND(G29="",ISNUMBER(F29)),F29/60*H29*④前提設定!$B$4,""))) | N29: =IF(I29>0,M29/I29,"") | O29: =IF(AND(J29>0,ISNUMBER(M29)),M29/J29,"") | R29: ふわもちホテルロール３個 | S29: ふわもちホテルロール８個入 | T29: ふわもちホテルロール１６個 | U29: Ｓふわもちホテルロール８個 | V29: Ｓふわもちホテルロール１６ | W29: ホテルロールＫＩＴ ４０個 | X29: =COUNTA(R29:W29) | Y29: =IF(AND($X29>0,ISNUMBER($M29)),$M29/$X29,"") | Z29: =IF($X29=0,"",IF(COUNTIF(⑳商品別1食労務費!$C$5:$C$124,$R29)+COUNTIF(⑳商品別1食労務費!$C$5:$C$124,$S29)+COUNTIF(⑳商品別1食労務費!$C$5:$C$124,$T29)+COUNTIF(⑳商品別1食労務費!$C$5:$C$124,$U29)+COUNTIF(⑳商品別1食労務費!$C$5:$C$124,$V29)+COUNTIF(⑳商品別1食労務費!$C$5:$C$124,$W29)=$X29,"OK","⑳に無い商品名")) | AA29: =SUMIF(⑳商品別1食労務費!$C$5:$C$124,$R29,⑳商品別1食労務費!$F$5:$F$124)+SUMIF(⑳商品別1食労務費!$C$5:$C$124,$S29,⑳商品別1食労務費!$F$5:$F$124)+SUMIF(⑳商品別1食労務費!$C$5:$C$124,$T29,⑳商品別1食労務費!$F$5:$F$124)+SUMIF(⑳商品別1食労務費!$C$5:$C$124,$U29,⑳商品別1食労務費!$F$5:$F$124)+SUMIF(⑳商品別1食労務費!$C$5:$C$124,$V29,⑳商品別1食労務費!$F$5:$F$124)+SUMIF(⑳商品別1食労務費!$C$5:$C$124,$W29,⑳商品別1食労務費!$F$5:$F$124) | AB29: =IF(ISNUMBER($M29),$M29,0) | AD29: =IF($R29="",0,IF($AA29>0,$AB29*SUMIF(⑳商品別1食労務費!$C$5:$C$124,$R29,⑳商品別1食労務費!$F$5:$F$124)/$AA29,$AB29/$X29)) | AE29: =IF($S29="",0,IF($AA29>0,$AB29*SUMIF(⑳商品別1食労務費!$C$5:$C$124,$S29,⑳商品別1食労務費!$F$5:$F$124)/$AA29,$AB29/$X29)) | AF29: =IF($T29="",0,IF($AA29>0,$AB29*SUMIF(⑳商品別1食労務費!$C$5:$C$124,$T29,⑳商品別1食労務費!$F$5:$F$124)/$AA29,$AB29/$X29)) | AG29: =IF($U29="",0,IF($AA29>0,$AB29*SUMIF(⑳商品別1食労務費!$C$5:$C$124,$U29,⑳商品別1食労務費!$F$5:$F$124)/$AA29,$AB29/$X29)) | AH29: =IF($V29="",0,IF($AA29>0,$AB29*SUMIF(⑳商品別1食労務費!$C$5:$C$124,$V29,⑳商品別1食労務費!$F$5:$F$124)/$AA29,$AB29/$X29)) | AI29: =IF($W29="",0,IF($AA29>0,$AB29*SUMIF(⑳商品別1食労務費!$C$5:$C$124,$W29,⑳商品別1食労務費!$F$5:$F$124)/$AA29,$AB29/$X29))
A30: 26 | B30: 釜製造 | C30: ホテルロール | D30: 0.16388889 | E30: 0.17777778 | F30: 5 | G30: 15 | H30: 1 | I30: 16 | K30: =IF(F30>0,I30/(F30/60),0) | L30: =IF(AND(ISNUMBER(F30),J30>0),J30/(F30/60),"") | M30: =IF(OR(ISNUMBER(SEARCH("サニテーション",C30)),ISNUMBER(SEARCH("客注",C30)),ISNUMBER(SEARCH("切り替え",C30)),ISNUMBER(SEARCH("切替",C30)),NOT(ISNUMBER(H30))),"",IF(ISNUMBER(G30),G30/60*H30*④前提設定!$B$4,IF(AND(G30="",ISNUMBER(F30)),F30/60*H30*④前提設定!$B$4,""))) | N30: =IF(I30>0,M30/I30,"") | O30: =IF(AND(J30>0,ISNUMBER(M30)),M30/J30,"") | R30: ふわもちホテルロール３個 | S30: ふわもちホテルロール８個入 | T30: ふわもちホテルロール１６個 | U30: Ｓふわもちホテルロール８個 | V30: Ｓふわもちホテルロール１６ | W30: ホテルロールＫＩＴ ４０個 | X30: =COUNTA(R30:W30) | Y30: =IF(AND($X30>0,ISNUMBER($M30)),$M30/$X30,"") | Z30: =IF($X30=0,"",IF(COUNTIF(⑳商品別1食労務費!$C$5:$C$124,$R30)+COUNTIF(⑳商品別1食労務費!$C$5:$C$124,$S30)+COUNTIF(⑳商品別1食労務費!$C$5:$C$124,$T30)+COUNTIF(⑳商品別1食労務費!$C$5:$C$124,$U30)+COUNTIF(⑳商品別1食労務費!$C$5:$C$124,$V30)+COUNTIF(⑳商品別1食労務費!$C$5:$C$124,$W30)=$X30,"OK","⑳に無い商品名")) | AA30: =SUMIF(⑳商品別1食労務費!$C$5:$C$124,$R30,⑳商品別1食労務費!$F$5:$F$124)+SUMIF(⑳商品別1食労務費!$C$5:$C$124,$S30,⑳商品別1食労務費!$F$5:$F$124)+SUMIF(⑳商品別1食労務費!$C$5:$C$124,$T30,⑳商品別1食労務費!$F$5:$F$124)+SUMIF(⑳商品別1食労務費!$C$5:$C$124,$U30,⑳商品別1食労務費!$F$5:$F$124)+SUMIF(⑳商品別1食労務費!$C$5:$C$124,$V30,⑳商品別1食労務費!$F$5:$F$124)+SUMIF(⑳商品別1食労務費!$C$5:$C$124,$W30,⑳商品別1食労務費!$F$5:$F$124) | AB30: =IF(ISNUMBER($M30),$M30,0) | AD30: =IF($R30="",0,IF($AA30>0,$AB30*SUMIF(⑳商品別1食労務費!$C$5:$C$124,$R30,⑳商品別1食労務費!$F$5:$F$124)/$AA30,$AB30/$X30)) | AE30: =IF($S30="",0,IF($AA30>0,$AB30*SUMIF(⑳商品別1食労務費!$C$5:$C$124,$S30,⑳商品別1食労務費!$F$5:$F$124)/$AA30,$AB30/$X30)) | AF30: =IF($T30="",0,IF($AA30>0,$AB30*SUMIF(⑳商品別1食労務費!$C$5:$C$124,$T30,⑳商品別1食労務費!$F$5:$F$124)/$AA30,$AB30/$X30)) | AG30: =IF($U30="",0,IF($AA30>0,$AB30*SUMIF(⑳商品別1食労務費!$C$5:$C$124,$U30,⑳商品別1食労務費!$F$5:$F$124)/$AA30,$AB30/$X30)) | AH30: =IF($V30="",0,IF($AA30>0,$AB30*SUMIF(⑳商品別1食労務費!$C$5:$C$124,$V30,⑳商品別1食労務費!$F$5:$F$124)/$AA30,$AB30/$X30)) | AI30: =IF($W30="",0,IF($AA30>0,$AB30*SUMIF(⑳商品別1食労務費!$C$5:$C$124,$W30,⑳商品別1食労務費!$F$5:$F$124)/$AA30,$AB30/$X30))
A31: 27 | B31: 釜製造 | C31: ホテルロール | D31: 0.17777778 | E31: 0.19166667 | F31: 5 | G31: 15 | H31: 1 | I31: 16 | K31: =IF(F31>0,I31/(F31/60),0) | L31: =IF(AND(ISNUMBER(F31),J31>0),J31/(F31/60),"") | M31: =IF(OR(ISNUMBER(SEARCH("サニテーション",C31)),ISNUMBER(SEARCH("客注",C31)),ISNUMBER(SEARCH("切り替え",C31)),ISNUMBER(SEARCH("切替",C31)),NOT(ISNUMBER(H31))),"",IF(ISNUMBER(G31),G31/60*H31*④前提設定!$B$4,IF(AND(G31="",ISNUMBER(F31)),F31/60*H31*④前提設定!$B$4,""))) | N31: =IF(I31>0,M31/I31,"") | O31: =IF(AND(J31>0,ISNUMBER(M31)),M31/J31,"") | R31: ふわもちホテルロール３個 | S31: ふわもちホテルロール８個入 | T31: ふわもちホテルロール１６個 | U31: Ｓふわもちホテルロール８個 | V31: Ｓふわもちホテルロール１６ | W31: ホテルロールＫＩＴ ４０個 | X31: =COUNTA(R31:W31) | Y31: =IF(AND($X31>0,ISNUMBER($M31)),$M31/$X31,"") | Z31: =IF($X31=0,"",IF(COUNTIF(⑳商品別1食労務費!$C$5:$C$124,$R31)+COUNTIF(⑳商品別1食労務費!$C$5:$C$124,$S31)+COUNTIF(⑳商品別1食労務費!$C$5:$C$124,$T31)+COUNTIF(⑳商品別1食労務費!$C$5:$C$124,$U31)+COUNTIF(⑳商品別1食労務費!$C$5:$C$124,$V31)+COUNTIF(⑳商品別1食労務費!$C$5:$C$124,$W31)=$X31,"OK","⑳に無い商品名")) | AA31: =SUMIF(⑳商品別1食労務費!$C$5:$C$124,$R31,⑳商品別1食労務費!$F$5:$F$124)+SUMIF(⑳商品別1食労務費!$C$5:$C$124,$S31,⑳商品別1食労務費!$F$5:$F$124)+SUMIF(⑳商品別1食労務費!$C$5:$C$124,$T31,⑳商品別1食労務費!$F$5:$F$124)+SUMIF(⑳商品別1食労務費!$C$5:$C$124,$U31,⑳商品別1食労務費!$F$5:$F$124)+SUMIF(⑳商品別1食労務費!$C$5:$C$124,$V31,⑳商品別1食労務費!$F$5:$F$124)+SUMIF(⑳商品別1食労務費!$C$5:$C$124,$W31,⑳商品別1食労務費!$F$5:$F$124) | AB31: =IF(ISNUMBER($M31),$M31,0) | AD31: =IF($R31="",0,IF($AA31>0,$AB31*SUMIF(⑳商品別1食労務費!$C$5:$C$124,$R31,⑳商品別1食労務費!$F$5:$F$124)/$AA31,$AB31/$X31)) | AE31: =IF($S31="",0,IF($AA31>0,$AB31*SUMIF(⑳商品別1食労務費!$C$5:$C$124,$S31,⑳商品別1食労務費!$F$5:$F$124)/$AA31,$AB31/$X31)) | AF31: =IF($T31="",0,IF($AA31>0,$AB31*SUMIF(⑳商品別1食労務費!$C$5:$C$124,$T31,⑳商品別1食労務費!$F$5:$F$124)/$AA31,$AB31/$X31)) | AG31: =IF($U31="",0,IF($AA31>0,$AB31*SUMIF(⑳商品別1食労務費!$C$5:$C$124,$U31,⑳商品別1食労務費!$F$5:$F$124)/$AA31,$AB31/$X31)) | AH31: =IF($V31="",0,IF($AA31>0,$AB31*SUMIF(⑳商品別1食労務費!$C$5:$C$124,$V31,⑳商品別1食労務費!$F$5:$F$124)/$AA31,$AB31/$X31)) | AI31: =IF($W31="",0,IF($AA31>0,$AB31*SUMIF(⑳商品別1食労務費!$C$5:$C$124,$W31,⑳商品別1食労務費!$F$5:$F$124)/$AA31,$AB31/$X31))
A32: 28 | B32: 釜製造 | C32: ホテルロール | D32: 0.19166667 | E32: 0.20555556 | F32: 5 | G32: 15 | H32: 1 | I32: 16 | K32: =IF(F32>0,I32/(F32/60),0) | L32: =IF(AND(ISNUMBER(F32),J32>0),J32/(F32/60),"") | M32: =IF(OR(ISNUMBER(SEARCH("サニテーション",C32)),ISNUMBER(SEARCH("客注",C32)),ISNUMBER(SEARCH("切り替え",C32)),ISNUMBER(SEARCH("切替",C32)),NOT(ISNUMBER(H32))),"",IF(ISNUMBER(G32),G32/60*H32*④前提設定!$B$4,IF(AND(G32="",ISNUMBER(F32)),F32/60*H32*④前提設定!$B$4,""))) | N32: =IF(I32>0,M32/I32,"") | O32: =IF(AND(J32>0,ISNUMBER(M32)),M32/J32,"") | R32: ふわもちホテルロール３個 | S32: ふわもちホテルロール８個入 | T32: ふわもちホテルロール１６個 | U32: Ｓふわもちホテルロール８個 | V32: Ｓふわもちホテルロール１６ | W32: ホテルロールＫＩＴ ４０個 | X32: =COUNTA(R32:W32) | Y32: =IF(AND($X32>0,ISNUMBER($M32)),$M32/$X32,"") | Z32: =IF($X32=0,"",IF(COUNTIF(⑳商品別1食労務費!$C$5:$C$124,$R32)+COUNTIF(⑳商品別1食労務費!$C$5:$C$124,$S32)+COUNTIF(⑳商品別1食労務費!$C$5:$C$124,$T32)+COUNTIF(⑳商品別1食労務費!$C$5:$C$124,$U32)+COUNTIF(⑳商品別1食労務費!$C$5:$C$124,$V32)+COUNTIF(⑳商品別1食労務費!$C$5:$C$124,$W32)=$X32,"OK","⑳に無い商品名")) | AA32: =SUMIF(⑳商品別1食労務費!$C$5:$C$124,$R32,⑳商品別1食労務費!$F$5:$F$124)+SUMIF(⑳商品別1食労務費!$C$5:$C$124,$S32,⑳商品別1食労務費!$F$5:$F$124)+SUMIF(⑳商品別1食労務費!$C$5:$C$124,$T32,⑳商品別1食労務費!$F$5:$F$124)+SUMIF(⑳商品別1食労務費!$C$5:$C$124,$U32,⑳商品別1食労務費!$F$5:$F$124)+SUMIF(⑳商品別1食労務費!$C$5:$C$124,$V32,⑳商品別1食労務費!$F$5:$F$124)+SUMIF(⑳商品別1食労務費!$C$5:$C$124,$W32,⑳商品別1食労務費!$F$5:$F$124) | AB32: =IF(ISNUMBER($M32),$M32,0) | AD32: =IF($R32="",0,IF($AA32>0,$AB32*SUMIF(⑳商品別1食労務費!$C$5:$C$124,$R32,⑳商品別1食労務費!$F$5:$F$124)/$AA32,$AB32/$X32)) | AE32: =IF($S32="",0,IF($AA32>0,$AB32*SUMIF(⑳商品別1食労務費!$C$5:$C$124,$S32,⑳商品別1食労務費!$F$5:$F$124)/$AA32,$AB32/$X32)) | AF32: =IF($T32="",0,IF($AA32>0,$AB32*SUMIF(⑳商品別1食労務費!$C$5:$C$124,$T32,⑳商品別1食労務費!$F$5:$F$124)/$AA32,$AB32/$X32)) | AG32: =IF($U32="",0,IF($AA32>0,$AB32*SUMIF(⑳商品別1食労務費!$C$5:$C$124,$U32,⑳商品別1食労務費!$F$5:$F$124)/$AA32,$AB32/$X32)) | AH32: =IF($V32="",0,IF($AA32>0,$AB32*SUMIF(⑳商品別1食労務費!$C$5:$C$124,$V32,⑳商品別1食労務費!$F$5:$F$124)/$AA32,$AB32/$X32)) | AI32: =IF($W32="",0,IF($AA32>0,$AB32*SUMIF(⑳商品別1食労務費!$C$5:$C$124,$W32,⑳商品別1食労務費!$F$5:$F$124)/$AA32,$AB32/$X32))
A33: 29 | B33: 釜製造 | C33: ホテルロール | D33: 0.20555556 | E33: 0.21944444 | F33: 5 | G33: 15 | H33: 1 | I33: 16 | K33: =IF(F33>0,I33/(F33/60),0) | L33: =IF(AND(ISNUMBER(F33),J33>0),J33/(F33/60),"") | M33: =IF(OR(ISNUMBER(SEARCH("サニテーション",C33)),ISNUMBER(SEARCH("客注",C33)),ISNUMBER(SEARCH("切り替え",C33)),ISNUMBER(SEARCH("切替",C33)),NOT(ISNUMBER(H33))),"",IF(ISNUMBER(G33),G33/60*H33*④前提設定!$B$4,IF(AND(G33="",ISNUMBER(F33)),F33/60*H33*④前提設定!$B$4,""))) | N33: =IF(I33>0,M33/I33,"") | O33: =IF(AND(J33>0,ISNUMBER(M33)),M33/J33,"") | R33: ふわもちホテルロール３個 | S33: ふわもちホテルロール８個入 | T33: ふわもちホテルロール１６個 | U33: Ｓふわもちホテルロール８個 | V33: Ｓふわもちホテルロール１６ | W33: ホテルロールＫＩＴ ４０個 | X33: =COUNTA(R33:W33) | Y33: =IF(AND($X33>0,ISNUMBER($M33)),$M33/$X33,"") | Z33: =IF($X33=0,"",IF(COUNTIF(⑳商品別1食労務費!$C$5:$C$124,$R33)+COUNTIF(⑳商品別1食労務費!$C$5:$C$124,$S33)+COUNTIF(⑳商品別1食労務費!$C$5:$C$124,$T33)+COUNTIF(⑳商品別1食労務費!$C$5:$C$124,$U33)+COUNTIF(⑳商品別1食労務費!$C$5:$C$124,$V33)+COUNTIF(⑳商品別1食労務費!$C$5:$C$124,$W33)=$X33,"OK","⑳に無い商品名")) | AA33: =SUMIF(⑳商品別1食労務費!$C$5:$C$124,$R33,⑳商品別1食労務費!$F$5:$F$124)+SUMIF(⑳商品別1食労務費!$C$5:$C$124,$S33,⑳商品別1食労務費!$F$5:$F$124)+SUMIF(⑳商品別1食労務費!$C$5:$C$124,$T33,⑳商品別1食労務費!$F$5:$F$124)+SUMIF(⑳商品別1食労務費!$C$5:$C$124,$U33,⑳商品別1食労務費!$F$5:$F$124)+SUMIF(⑳商品別1食労務費!$C$5:$C$124,$V33,⑳商品別1食労務費!$F$5:$F$124)+SUMIF(⑳商品別1食労務費!$C$5:$C$124,$W33,⑳商品別1食労務費!$F$5:$F$124) | AB33: =IF(ISNUMBER($M33),$M33,0) | AD33: =IF($R33="",0,IF($AA33>0,$AB33*SUMIF(⑳商品別1食労務費!$C$5:$C$124,$R33,⑳商品別1食労務費!$F$5:$F$124)/$AA33,$AB33/$X33)) | AE33: =IF($S33="",0,IF($AA33>0,$AB33*SUMIF(⑳商品別1食労務費!$C$5:$C$124,$S33,⑳商品別1食労務費!$F$5:$F$124)/$AA33,$AB33/$X33)) | AF33: =IF($T33="",0,IF($AA33>0,$AB33*SUMIF(⑳商品別1食労務費!$C$5:$C$124,$T33,⑳商品別1食労務費!$F$5:$F$124)/$AA33,$AB33/$X33)) | AG33: =IF($U33="",0,IF($AA33>0,$AB33*SUMIF(⑳商品別1食労務費!$C$5:$C$124,$U33,⑳商品別1食労務費!$F$5:$F$124)/$AA33,$AB33/$X33)) | AH33: =IF($V33="",0,IF($AA33>0,$AB33*SUMIF(⑳商品別1食労務費!$C$5:$C$124,$V33,⑳商品別1食労務費!$F$5:$F$124)/$AA33,$AB33/$X33)) | AI33: =IF($W33="",0,IF($AA33>0,$AB33*SUMIF(⑳商品別1食労務費!$C$5:$C$124,$W33,⑳商品別1食労務費!$F$5:$F$124)/$AA33,$AB33/$X33))
A34: 30 | B34: 釜製造 | C34: ホテルロール | D34: 0.21944444 | E34: 0.23333333 | F34: 5 | G34: 15 | H34: 1 | I34: 16 | K34: =IF(F34>0,I34/(F34/60),0) | L34: =IF(AND(ISNUMBER(F34),J34>0),J34/(F34/60),"") | M34: =IF(OR(ISNUMBER(SEARCH("サニテーション",C34)),ISNUMBER(SEARCH("客注",C34)),ISNUMBER(SEARCH("切り替え",C34)),ISNUMBER(SEARCH("切替",C34)),NOT(ISNUMBER(H34))),"",IF(ISNUMBER(G34),G34/60*H34*④前提設定!$B$4,IF(AND(G34="",ISNUMBER(F34)),F34/60*H34*④前提設定!$B$4,""))) | N34: =IF(I34>0,M34/I34,"") | O34: =IF(AND(J34>0,ISNUMBER(M34)),M34/J34,"") | R34: ふわもちホテルロール３個 | S34: ふわもちホテルロール８個入 | T34: ふわもちホテルロール１６個 | U34: Ｓふわもちホテルロール８個 | V34: Ｓふわもちホテルロール１６ | W34: ホテルロールＫＩＴ ４０個 | X34: =COUNTA(R34:W34) | Y34: =IF(AND($X34>0,ISNUMBER($M34)),$M34/$X34,"") | Z34: =IF($X34=0,"",IF(COUNTIF(⑳商品別1食労務費!$C$5:$C$124,$R34)+COUNTIF(⑳商品別1食労務費!$C$5:$C$124,$S34)+COUNTIF(⑳商品別1食労務費!$C$5:$C$124,$T34)+COUNTIF(⑳商品別1食労務費!$C$5:$C$124,$U34)+COUNTIF(⑳商品別1食労務費!$C$5:$C$124,$V34)+COUNTIF(⑳商品別1食労務費!$C$5:$C$124,$W34)=$X34,"OK","⑳に無い商品名")) | AA34: =SUMIF(⑳商品別1食労務費!$C$5:$C$124,$R34,⑳商品別1食労務費!$F$5:$F$124)+SUMIF(⑳商品別1食労務費!$C$5:$C$124,$S34,⑳商品別1食労務費!$F$5:$F$124)+SUMIF(⑳商品別1食労務費!$C$5:$C$124,$T34,⑳商品別1食労務費!$F$5:$F$124)+SUMIF(⑳商品別1食労務費!$C$5:$C$124,$U34,⑳商品別1食労務費!$F$5:$F$124)+SUMIF(⑳商品別1食労務費!$C$5:$C$124,$V34,⑳商品別1食労務費!$F$5:$F$124)+SUMIF(⑳商品別1食労務費!$C$5:$C$124,$W34,⑳商品別1食労務費!$F$5:$F$124) | AB34: =IF(ISNUMBER($M34),$M34,0) | AD34: =IF($R34="",0,IF($AA34>0,$AB34*SUMIF(⑳商品別1食労務費!$C$5:$C$124,$R34,⑳商品別1食労務費!$F$5:$F$124)/$AA34,$AB34/$X34)) | AE34: =IF($S34="",0,IF($AA34>0,$AB34*SUMIF(⑳商品別1食労務費!$C$5:$C$124,$S34,⑳商品別1食労務費!$F$5:$F$124)/$AA34,$AB34/$X34)) | AF34: =IF($T34="",0,IF($AA34>0,$AB34*SUMIF(⑳商品別1食労務費!$C$5:$C$124,$T34,⑳商品別1食労務費!$F$5:$F$124)/$AA34,$AB34/$X34)) | AG34: =IF($U34="",0,IF($AA34>0,$AB34*SUMIF(⑳商品別1食労務費!$C$5:$C$124,$U34,⑳商品別1食労務費!$F$5:$F$124)/$AA34,$AB34/$X34)) | AH34: =IF($V34="",0,IF($AA34>0,$AB34*SUMIF(⑳商品別1食労務費!$C$5:$C$124,$V34,⑳商品別1食労務費!$F$5:$F$124)/$AA34,$AB34/$X34)) | AI34: =IF($W34="",0,IF($AA34>0,$AB34*SUMIF(⑳商品別1食労務費!$C$5:$C$124,$W34,⑳商品別1食労務費!$F$5:$F$124)/$AA34,$AB34/$X34))
A35: 31 | B35: 釜製造 | C35: ホテルロール | D35: 0.23333333 | E35: 0.24722222 | F35: 5 | G35: 15 | H35: 1 | I35: 16 | K35: =IF(F35>0,I35/(F35/60),0) | L35: =IF(AND(ISNUMBER(F35),J35>0),J35/(F35/60),"") | M35: =IF(OR(ISNUMBER(SEARCH("サニテーション",C35)),ISNUMBER(SEARCH("客注",C35)),ISNUMBER(SEARCH("切り替え",C35)),ISNUMBER(SEARCH("切替",C35)),NOT(ISNUMBER(H35))),"",IF(ISNUMBER(G35),G35/60*H35*④前提設定!$B$4,IF(AND(G35="",ISNUMBER(F35)),F35/60*H35*④前提設定!$B$4,""))) | N35: =IF(I35>0,M35/I35,"") | O35: =IF(AND(J35>0,ISNUMBER(M35)),M35/J35,"") | R35: ふわもちホテルロール３個 | S35: ふわもちホテルロール８個入 | T35: ふわもちホテルロール１６個 | U35: Ｓふわもちホテルロール８個 | V35: Ｓふわもちホテルロール１６ | W35: ホテルロールＫＩＴ ４０個 | X35: =COUNTA(R35:W35) | Y35: =IF(AND($X35>0,ISNUMBER($M35)),$M35/$X35,"") | Z35: =IF($X35=0,"",IF(COUNTIF(⑳商品別1食労務費!$C$5:$C$124,$R35)+COUNTIF(⑳商品別1食労務費!$C$5:$C$124,$S35)+COUNTIF(⑳商品別1食労務費!$C$5:$C$124,$T35)+COUNTIF(⑳商品別1食労務費!$C$5:$C$124,$U35)+COUNTIF(⑳商品別1食労務費!$C$5:$C$124,$V35)+COUNTIF(⑳商品別1食労務費!$C$5:$C$124,$W35)=$X35,"OK","⑳に無い商品名")) | AA35: =SUMIF(⑳商品別1食労務費!$C$5:$C$124,$R35,⑳商品別1食労務費!$F$5:$F$124)+SUMIF(⑳商品別1食労務費!$C$5:$C$124,$S35,⑳商品別1食労務費!$F$5:$F$124)+SUMIF(⑳商品別1食労務費!$C$5:$C$124,$T35,⑳商品別1食労務費!$F$5:$F$124)+SUMIF(⑳商品別1食労務費!$C$5:$C$124,$U35,⑳商品別1食労務費!$F$5:$F$124)+SUMIF(⑳商品別1食労務費!$C$5:$C$124,$V35,⑳商品別1食労務費!$F$5:$F$124)+SUMIF(⑳商品別1食労務費!$C$5:$C$124,$W35,⑳商品別1食労務費!$F$5:$F$124) | AB35: =IF(ISNUMBER($M35),$M35,0) | AD35: =IF($R35="",0,IF($AA35>0,$AB35*SUMIF(⑳商品別1食労務費!$C$5:$C$124,$R35,⑳商品別1食労務費!$F$5:$F$124)/$AA35,$AB35/$X35)) | AE35: =IF($S35="",0,IF($AA35>0,$AB35*SUMIF(⑳商品別1食労務費!$C$5:$C$124,$S35,⑳商品別1食労務費!$F$5:$F$124)/$AA35,$AB35/$X35)) | AF35: =IF($T35="",0,IF($AA35>0,$AB35*SUMIF(⑳商品別1食労務費!$C$5:$C$124,$T35,⑳商品別1食労務費!$F$5:$F$124)/$AA35,$AB35/$X35)) | AG35: =IF($U35="",0,IF($AA35>0,$AB35*SUMIF(⑳商品別1食労務費!$C$5:$C$124,$U35,⑳商品別1食労務費!$F$5:$F$124)/$AA35,$AB35/$X35)) | AH35: =IF($V35="",0,IF($AA35>0,$AB35*SUMIF(⑳商品別1食労務費!$C$5:$C$124,$V35,⑳商品別1食労務費!$F$5:$F$124)/$AA35,$AB35/$X35)) | AI35: =IF($W35="",0,IF($AA35>0,$AB35*SUMIF(⑳商品別1食労務費!$C$5:$C$124,$W35,⑳商品別1食労務費!$F$5:$F$124)/$AA35,$AB35/$X35))
A36: 32 | B36: 釜製造 | C36: ホテルロール | D36: 0.24722222 | E36: 0.26111111 | F36: 5 | G36: 15 | H36: 1 | I36: 16 | K36: =IF(F36>0,I36/(F36/60),0) | L36: =IF(AND(ISNUMBER(F36),J36>0),J36/(F36/60),"") | M36: =IF(OR(ISNUMBER(SEARCH("サニテーション",C36)),ISNUMBER(SEARCH("客注",C36)),ISNUMBER(SEARCH("切り替え",C36)),ISNUMBER(SEARCH("切替",C36)),NOT(ISNUMBER(H36))),"",IF(ISNUMBER(G36),G36/60*H36*④前提設定!$B$4,IF(AND(G36="",ISNUMBER(F36)),F36/60*H36*④前提設定!$B$4,""))) | N36: =IF(I36>0,M36/I36,"") | O36: =IF(AND(J36>0,ISNUMBER(M36)),M36/J36,"") | R36: ふわもちホテルロール３個 | S36: ふわもちホテルロール８個入 | T36: ふわもちホテルロール１６個 | U36: Ｓふわもちホテルロール８個 | V36: Ｓふわもちホテルロール１６ | W36: ホテルロールＫＩＴ ４０個 | X36: =COUNTA(R36:W36) | Y36: =IF(AND($X36>0,ISNUMBER($M36)),$M36/$X36,"") | Z36: =IF($X36=0,"",IF(COUNTIF(⑳商品別1食労務費!$C$5:$C$124,$R36)+COUNTIF(⑳商品別1食労務費!$C$5:$C$124,$S36)+COUNTIF(⑳商品別1食労務費!$C$5:$C$124,$T36)+COUNTIF(⑳商品別1食労務費!$C$5:$C$124,$U36)+COUNTIF(⑳商品別1食労務費!$C$5:$C$124,$V36)+COUNTIF(⑳商品別1食労務費!$C$5:$C$124,$W36)=$X36,"OK","⑳に無い商品名")) | AA36: =SUMIF(⑳商品別1食労務費!$C$5:$C$124,$R36,⑳商品別1食労務費!$F$5:$F$124)+SUMIF(⑳商品別1食労務費!$C$5:$C$124,$S36,⑳商品別1食労務費!$F$5:$F$124)+SUMIF(⑳商品別1食労務費!$C$5:$C$124,$T36,⑳商品別1食労務費!$F$5:$F$124)+SUMIF(⑳商品別1食労務費!$C$5:$C$124,$U36,⑳商品別1食労務費!$F$5:$F$124)+SUMIF(⑳商品別1食労務費!$C$5:$C$124,$V36,⑳商品別1食労務費!$F$5:$F$124)+SUMIF(⑳商品別1食労務費!$C$5:$C$124,$W36,⑳商品別1食労務費!$F$5:$F$124) | AB36: =IF(ISNUMBER($M36),$M36,0) | AD36: =IF($R36="",0,IF($AA36>0,$AB36*SUMIF(⑳商品別1食労務費!$C$5:$C$124,$R36,⑳商品別1食労務費!$F$5:$F$124)/$AA36,$AB36/$X36)) | AE36: =IF($S36="",0,IF($AA36>0,$AB36*SUMIF(⑳商品別1食労務費!$C$5:$C$124,$S36,⑳商品別1食労務費!$F$5:$F$124)/$AA36,$AB36/$X36)) | AF36: =IF($T36="",0,IF($AA36>0,$AB36*SUMIF(⑳商品別1食労務費!$C$5:$C$124,$T36,⑳商品別1食労務費!$F$5:$F$124)/$AA36,$AB36/$X36)) | AG36: =IF($U36="",0,IF($AA36>0,$AB36*SUMIF(⑳商品別1食労務費!$C$5:$C$124,$U36,⑳商品別1食労務費!$F$5:$F$124)/$AA36,$AB36/$X36)) | AH36: =IF($V36="",0,IF($AA36>0,$AB36*SUMIF(⑳商品別1食労務費!$C$5:$C$124,$V36,⑳商品別1食労務費!$F$5:$F$124)/$AA36,$AB36/$X36)) | AI36: =IF($W36="",0,IF($AA36>0,$AB36*SUMIF(⑳商品別1食労務費!$C$5:$C$124,$W36,⑳商品別1食労務費!$F$5:$F$124)/$AA36,$AB36/$X36))
A37: 33 | B37: 釜製造 | C37: ホテルロール | D37: 0.26111111 | E37: 0.275 | F37: 5 | G37: 15 | H37: 1 | I37: 16 | K37: =IF(F37>0,I37/(F37/60),0) | L37: =IF(AND(ISNUMBER(F37),J37>0),J37/(F37/60),"") | M37: =IF(OR(ISNUMBER(SEARCH("サニテーション",C37)),ISNUMBER(SEARCH("客注",C37)),ISNUMBER(SEARCH("切り替え",C37)),ISNUMBER(SEARCH("切替",C37)),NOT(ISNUMBER(H37))),"",IF(ISNUMBER(G37),G37/60*H37*④前提設定!$B$4,IF(AND(G37="",ISNUMBER(F37)),F37/60*H37*④前提設定!$B$4,""))) | N37: =IF(I37>0,M37/I37,"") | O37: =IF(AND(J37>0,ISNUMBER(M37)),M37/J37,"") | R37: ふわもちホテルロール３個 | S37: ふわもちホテルロール８個入 | T37: ふわもちホテルロール１６個 | U37: Ｓふわもちホテルロール８個 | V37: Ｓふわもちホテルロール１６ | W37: ホテルロールＫＩＴ ４０個 | X37: =COUNTA(R37:W37) | Y37: =IF(AND($X37>0,ISNUMBER($M37)),$M37/$X37,"") | Z37: =IF($X37=0,"",IF(COUNTIF(⑳商品別1食労務費!$C$5:$C$124,$R37)+COUNTIF(⑳商品別1食労務費!$C$5:$C$124,$S37)+COUNTIF(⑳商品別1食労務費!$C$5:$C$124,$T37)+COUNTIF(⑳商品別1食労務費!$C$5:$C$124,$U37)+COUNTIF(⑳商品別1食労務費!$C$5:$C$124,$V37)+COUNTIF(⑳商品別1食労務費!$C$5:$C$124,$W37)=$X37,"OK","⑳に無い商品名")) | AA37: =SUMIF(⑳商品別1食労務費!$C$5:$C$124,$R37,⑳商品別1食労務費!$F$5:$F$124)+SUMIF(⑳商品別1食労務費!$C$5:$C$124,$S37,⑳商品別1食労務費!$F$5:$F$124)+SUMIF(⑳商品別1食労務費!$C$5:$C$124,$T37,⑳商品別1食労務費!$F$5:$F$124)+SUMIF(⑳商品別1食労務費!$C$5:$C$124,$U37,⑳商品別1食労務費!$F$5:$F$124)+SUMIF(⑳商品別1食労務費!$C$5:$C$124,$V37,⑳商品別1食労務費!$F$5:$F$124)+SUMIF(⑳商品別1食労務費!$C$5:$C$124,$W37,⑳商品別1食労務費!$F$5:$F$124) | AB37: =IF(ISNUMBER($M37),$M37,0) | AD37: =IF($R37="",0,IF($AA37>0,$AB37*SUMIF(⑳商品別1食労務費!$C$5:$C$124,$R37,⑳商品別1食労務費!$F$5:$F$124)/$AA37,$AB37/$X37)) | AE37: =IF($S37="",0,IF($AA37>0,$AB37*SUMIF(⑳商品別1食労務費!$C$5:$C$124,$S37,⑳商品別1食労務費!$F$5:$F$124)/$AA37,$AB37/$X37)) | AF37: =IF($T37="",0,IF($AA37>0,$AB37*SUMIF(⑳商品別1食労務費!$C$5:$C$124,$T37,⑳商品別1食労務費!$F$5:$F$124)/$AA37,$AB37/$X37)) | AG37: =IF($U37="",0,IF($AA37>0,$AB37*SUMIF(⑳商品別1食労務費!$C$5:$C$124,$U37,⑳商品別1食労務費!$F$5:$F$124)/$AA37,$AB37/$X37)) | AH37: =IF($V37="",0,IF($AA37>0,$AB37*SUMIF(⑳商品別1食労務費!$C$5:$C$124,$V37,⑳商品別1食労務費!$F$5:$F$124)/$AA37,$AB37/$X37)) | AI37: =IF($W37="",0,IF($AA37>0,$AB37*SUMIF(⑳商品別1食労務費!$C$5:$C$124,$W37,⑳商品別1食労務費!$F$5:$F$124)/$AA37,$AB37/$X37))
A38: 34 | B38: 釜製造 | C38: ホテルロール | D38: 0.275 | E38: 0.28888889 | F38: 5 | G38: 15 | H38: 1 | I38: 16 | K38: =IF(F38>0,I38/(F38/60),0) | L38: =IF(AND(ISNUMBER(F38),J38>0),J38/(F38/60),"") | M38: =IF(OR(ISNUMBER(SEARCH("サニテーション",C38)),ISNUMBER(SEARCH("客注",C38)),ISNUMBER(SEARCH("切り替え",C38)),ISNUMBER(SEARCH("切替",C38)),NOT(ISNUMBER(H38))),"",IF(ISNUMBER(G38),G38/60*H38*④前提設定!$B$4,IF(AND(G38="",ISNUMBER(F38)),F38/60*H38*④前提設定!$B$4,""))) | N38: =IF(I38>0,M38/I38,"") | O38: =IF(AND(J38>0,ISNUMBER(M38)),M38/J38,"") | R38: ふわもちホテルロール３個 | S38: ふわもちホテルロール８個入 | T38: ふわもちホテルロール１６個 | U38: Ｓふわもちホテルロール８個 | V38: Ｓふわもちホテルロール１６ | W38: ホテルロールＫＩＴ ４０個 | X38: =COUNTA(R38:W38) | Y38: =IF(AND($X38>0,ISNUMBER($M38)),$M38/$X38,"") | Z38: =IF($X38=0,"",IF(COUNTIF(⑳商品別1食労務費!$C$5:$C$124,$R38)+COUNTIF(⑳商品別1食労務費!$C$5:$C$124,$S38)+COUNTIF(⑳商品別1食労務費!$C$5:$C$124,$T38)+COUNTIF(⑳商品別1食労務費!$C$5:$C$124,$U38)+COUNTIF(⑳商品別1食労務費!$C$5:$C$124,$V38)+COUNTIF(⑳商品別1食労務費!$C$5:$C$124,$W38)=$X38,"OK","⑳に無い商品名")) | AA38: =SUMIF(⑳商品別1食労務費!$C$5:$C$124,$R38,⑳商品別1食労務費!$F$5:$F$124)+SUMIF(⑳商品別1食労務費!$C$5:$C$124,$S38,⑳商品別1食労務費!$F$5:$F$124)+SUMIF(⑳商品別1食労務費!$C$5:$C$124,$T38,⑳商品別1食労務費!$F$5:$F$124)+SUMIF(⑳商品別1食労務費!$C$5:$C$124,$U38,⑳商品別1食労務費!$F$5:$F$124)+SUMIF(⑳商品別1食労務費!$C$5:$C$124,$V38,⑳商品別1食労務費!$F$5:$F$124)+SUMIF(⑳商品別1食労務費!$C$5:$C$124,$W38,⑳商品別1食労務費!$F$5:$F$124) | AB38: =IF(ISNUMBER($M38),$M38,0) | AD38: =IF($R38="",0,IF($AA38>0,$AB38*SUMIF(⑳商品別1食労務費!$C$5:$C$124,$R38,⑳商品別1食労務費!$F$5:$F$124)/$AA38,$AB38/$X38)) | AE38: =IF($S38="",0,IF($AA38>0,$AB38*SUMIF(⑳商品別1食労務費!$C$5:$C$124,$S38,⑳商品別1食労務費!$F$5:$F$124)/$AA38,$AB38/$X38)) | AF38: =IF($T38="",0,IF($AA38>0,$AB38*SUMIF(⑳商品別1食労務費!$C$5:$C$124,$T38,⑳商品別1食労務費!$F$5:$F$124)/$AA38,$AB38/$X38)) | AG38: =IF($U38="",0,IF($AA38>0,$AB38*SUMIF(⑳商品別1食労務費!$C$5:$C$124,$U38,⑳商品別1食労務費!$F$5:$F$124)/$AA38,$AB38/$X38)) | AH38: =IF($V38="",0,IF($AA38>0,$AB38*SUMIF(⑳商品別1食労務費!$C$5:$C$124,$V38,⑳商品別1食労務費!$F$5:$F$124)/$AA38,$AB38/$X38)) | AI38: =IF($W38="",0,IF($AA38>0,$AB38*SUMIF(⑳商品別1食労務費!$C$5:$C$124,$W38,⑳商品別1食労務費!$F$5:$F$124)/$AA38,$AB38/$X38))
A39: 35 | B39: 釜製造 | C39: ホテルロール | D39: 0.28888889 | E39: 0.30277778 | F39: 5 | G39: 15 | H39: 1 | I39: 16 | K39: =IF(F39>0,I39/(F39/60),0) | L39: =IF(AND(ISNUMBER(F39),J39>0),J39/(F39/60),"") | M39: =IF(OR(ISNUMBER(SEARCH("サニテーション",C39)),ISNUMBER(SEARCH("客注",C39)),ISNUMBER(SEARCH("切り替え",C39)),ISNUMBER(SEARCH("切替",C39)),NOT(ISNUMBER(H39))),"",IF(ISNUMBER(G39),G39/60*H39*④前提設定!$B$4,IF(AND(G39="",ISNUMBER(F39)),F39/60*H39*④前提設定!$B$4,""))) | N39: =IF(I39>0,M39/I39,"") | O39: =IF(AND(J39>0,ISNUMBER(M39)),M39/J39,"") | R39: ふわもちホテルロール３個 | S39: ふわもちホテルロール８個入 | T39: ふわもちホテルロール１６個 | U39: Ｓふわもちホテルロール８個 | V39: Ｓふわもちホテルロール１６ | W39: ホテルロールＫＩＴ ４０個 | X39: =COUNTA(R39:W39) | Y39: =IF(AND($X39>0,ISNUMBER($M39)),$M39/$X39,"") | Z39: =IF($X39=0,"",IF(COUNTIF(⑳商品別1食労務費!$C$5:$C$124,$R39)+COUNTIF(⑳商品別1食労務費!$C$5:$C$124,$S39)+COUNTIF(⑳商品別1食労務費!$C$5:$C$124,$T39)+COUNTIF(⑳商品別1食労務費!$C$5:$C$124,$U39)+COUNTIF(⑳商品別1食労務費!$C$5:$C$124,$V39)+COUNTIF(⑳商品別1食労務費!$C$5:$C$124,$W39)=$X39,"OK","⑳に無い商品名")) | AA39: =SUMIF(⑳商品別1食労務費!$C$5:$C$124,$R39,⑳商品別1食労務費!$F$5:$F$124)+SUMIF(⑳商品別1食労務費!$C$5:$C$124,$S39,⑳商品別1食労務費!$F$5:$F$124)+SUMIF(⑳商品別1食労務費!$C$5:$C$124,$T39,⑳商品別1食労務費!$F$5:$F$124)+SUMIF(⑳商品別1食労務費!$C$5:$C$124,$U39,⑳商品別1食労務費!$F$5:$F$124)+SUMIF(⑳商品別1食労務費!$C$5:$C$124,$V39,⑳商品別1食労務費!$F$5:$F$124)+SUMIF(⑳商品別1食労務費!$C$5:$C$124,$W39,⑳商品別1食労務費!$F$5:$F$124) | AB39: =IF(ISNUMBER($M39),$M39,0) | AD39: =IF($R39="",0,IF($AA39>0,$AB39*SUMIF(⑳商品別1食労務費!$C$5:$C$124,$R39,⑳商品別1食労務費!$F$5:$F$124)/$AA39,$AB39/$X39)) | AE39: =IF($S39="",0,IF($AA39>0,$AB39*SUMIF(⑳商品別1食労務費!$C$5:$C$124,$S39,⑳商品別1食労務費!$F$5:$F$124)/$AA39,$AB39/$X39)) | AF39: =IF($T39="",0,IF($AA39>0,$AB39*SUMIF(⑳商品別1食労務費!$C$5:$C$124,$T39,⑳商品別1食労務費!$F$5:$F$124)/$AA39,$AB39/$X39)) | AG39: =IF($U39="",0,IF($AA39>0,$AB39*SUMIF(⑳商品別1食労務費!$C$5:$C$124,$U39,⑳商品別1食労務費!$F$5:$F$124)/$AA39,$AB39/$X39)) | AH39: =IF($V39="",0,IF($AA39>0,$AB39*SUMIF(⑳商品別1食労務費!$C$5:$C$124,$V39,⑳商品別1食労務費!$F$5:$F$124)/$AA39,$AB39/$X39)) | AI39: =IF($W39="",0,IF($AA39>0,$AB39*SUMIF(⑳商品別1食労務費!$C$5:$C$124,$W39,⑳商品別1食労務費!$F$5:$F$124)/$AA39,$AB39/$X39))
... A44: 40 | B44: 釜製造 | C44: 塩パン | D44: 0.35833333 | E44: 0.37222222 | F44: 5 | G44: 15 | H44: 1 | I44: 16 | K44: =IF(F44>0,I44/(F44/60),0) | L44: =IF(AND(ISNUMBER(F44),J44>0),J44/(F44/60),"") | M44: =IF(OR(ISNUMBER(SEARCH("サニテーション",C44)),ISNUMBER(SEARCH("客注",C44)),ISNUMBER(SEARCH("切り替え",C44)),ISNUMBER(SEARCH("切替",C44)),NOT(ISNUMBER(H44))),"",IF(ISNUMBER(G44),G44/60*H44*④前提設定!$B$4,IF(AND(G44="",ISNUMBER(F44)),F44/60*H44*④前提設定!$B$4,""))) | N44: =IF(I44>0,M44/I44,"") | O44: =IF(AND(J44>0,ISNUMBER(M44)),M44/J44,"") | R44: 塩パン２個 | S44: 塩パンＫＩＴ | T44: メロン塩パン２個入 | U44: Ｓメロン塩パン２個入 | V44: メロン塩パンＫＩＴ | W44: チーズ塩パン２個 | X44: =COUNTA(R44:W44) | Y44: =IF(AND($X44>0,ISNUMBER($M44)),$M44/$X44,"") | Z44: =IF($X44=0,"",IF(COUNTIF(⑳商品別1食労務費!$C$5:$C$124,$R44)+COUNTIF(⑳商品別1食労務費!$C$5:$C$124,$S44)+COUNTIF(⑳商品別1食労務費!$C$5:$C$124,$T44)+COUNTIF(⑳商品別1食労務費!$C$5:$C$124,$U44)+COUNTIF(⑳商品別1食労務費!$C$5:$C$124,$V44)+COUNTIF(⑳商品別1食労務費!$C$5:$C$124,$W44)=$X44,"OK","⑳に無い商品名")) | AA44: =SUMIF(⑳商品別1食労務費!$C$5:$C$124,$R44,⑳商品別1食労務費!$F$5:$F$124)+SUMIF(⑳商品別1食労務費!$C$5:$C$124,$S44,⑳商品別1食労務費!$F$5:$F$124)+SUMIF(⑳商品別1食労務費!$C$5:$C$124,$T44,⑳商品別1食労務費!$F$5:$F$124)+SUMIF(⑳商品別1食労務費!$C$5:$C$124,$U44,⑳商品別1食労務費!$F$5:$F$124)+SUMIF(⑳商品別1食労務費!$C$5:$C$124,$V44,⑳商品別1食労務費!$F$5:$F$124)+SUMIF(⑳商品別1食労務費!$C$5:$C$124,$W44,⑳商品別1食労務費!$F$5:$F$124) | AB44: =IF(ISNUMBER($M44),$M44,0) | AD44: =IF($R44="",0,IF($AA44>0,$AB44*SUMIF(⑳商品別1食労務費!$C$5:$C$124,$R44,⑳商品別1食労務費!$F$5:$F$124)/$AA44,$AB44/$X44)) | AE44: =IF($S44="",0,IF($AA44>0,$AB44*SUMIF(⑳商品別1食労務費!$C$5:$C$124,$S44,⑳商品別1食労務費!$F$5:$F$124)/$AA44,$AB44/$X44)) | AF44: =IF($T44="",0,IF($AA44>0,$AB44*SUMIF(⑳商品別1食労務費!$C$5:$C$124,$T44,⑳商品別1食労務費!$F$5:$F$124)/$AA44,$AB44/$X44)) | AG44: =IF($U44="",0,IF($AA44>0,$AB44*SUMIF(⑳商品別1食労務費!$C$5:$C$124,$U44,⑳商品別1食労務費!$F$5:$F$124)/$AA44,$AB44/$X44)) | AH44: =IF($V44="",0,IF($AA44>0,$AB44*SUMIF(⑳商品別1食労務費!$C$5:$C$124,$V44,⑳商品別1食労務費!$F$5:$F$124)/$AA44,$AB44/$X44)) | AI44: =IF($W44="",0,IF($AA44>0,$AB44*SUMIF(⑳商品別1食労務費!$C$5:$C$124,$W44,⑳商品別1食労務費!$F$5:$F$124)/$AA44,$AB44/$X44))
A45: 41 | B45: 釜製造 | C45: 塩パン | D45: 0.37222222 | E45: 0.38611111 | F45: 5 | G45: 15 | H45: 1 | I45: 16 | K45: - | L45: =IF(AND(ISNUMBER(F45),J45>0),J45/(F45/60),"") | M45: =IF(OR(ISNUMBER(SEARCH("サニテーション",C45)),ISNUMBER(SEARCH("客注",C45)),ISNUMBER(SEARCH("切り替え",C45)),ISNUMBER(SEARCH("切替",C45)),NOT(ISNUMBER(H45))),"",IF(ISNUMBER(G45),G45/60*H45*④前提設定!$B$4,IF(AND(G45="",ISNUMBER(F45)),F45/60*H45*④前提設定!$B$4,""))) | N45: - | O45: =IF(AND(J45>0,ISNUMBER(M45)),M45/J45,"") | R45: 塩パン２個 | S45: 塩パンＫＩＴ | T45: メロン塩パン２個入 | U45: Ｓメロン塩パン２個入 | V45: メロン塩パンＫＩＴ | W45: チーズ塩パン２個 | X45: =COUNTA(R45:W45) | Y45: =IF(AND($X45>0,ISNUMBER($M45)),$M45/$X45,"") | Z45: =IF($X45=0,"",IF(COUNTIF(⑳商品別1食労務費!$C$5:$C$124,$R45)+COUNTIF(⑳商品別1食労務費!$C$5:$C$124,$S45)+COUNTIF(⑳商品別1食労務費!$C$5:$C$124,$T45)+COUNTIF(⑳商品別1食労務費!$C$5:$C$124,$U45)+COUNTIF(⑳商品別1食労務費!$C$5:$C$124,$V45)+COUNTIF(⑳商品別1食労務費!$C$5:$C$124,$W45)=$X45,"OK","⑳に無い商品名")) | AA45: =SUMIF(⑳商品別1食労務費!$C$5:$C$124,$R45,⑳商品別1食労務費!$F$5:$F$124)+SUMIF(⑳商品別1食労務費!$C$5:$C$124,$S45,⑳商品別1食労務費!$F$5:$F$124)+SUMIF(⑳商品別1食労務費!$C$5:$C$124,$T45,⑳商品別1食労務費!$F$5:$F$124)+SUMIF(⑳商品別1食労務費!$C$5:$C$124,$U45,⑳商品別1食労務費!$F$5:$F$124)+SUMIF(⑳商品別1食労務費!$C$5:$C$124,$V45,⑳商品別1食労務費!$F$5:$F$124)+SUMIF(⑳商品別1食労務費!$C$5:$C$124,$W45,⑳商品別1食労務費!$F$5:$F$124) | AB45: =IF(ISNUMBER($M45),$M45,0) | AD45: =IF($R45="",0,IF($AA45>0,$AB45*SUMIF(⑳商品別1食労務費!$C$5:$C$124,$R45,⑳商品別1食労務費!$F$5:$F$124)/$AA45,$AB45/$X45)) | AE45: =IF($S45="",0,IF($AA45>0,$AB45*SUMIF(⑳商品別1食労務費!$C$5:$C$124,$S45,⑳商品別1食労務費!$F$5:$F$124)/$AA45,$AB45/$X45)) | AF45: =IF($T45="",0,IF($AA45>0,$AB45*SUMIF(⑳商品別1食労務費!$C$5:$C$124,$T45,⑳商品別1食労務費!$F$5:$F$124)/$AA45,$AB45/$X45)) | AG45: =IF($U45="",0,IF($AA45>0,$AB45*SUMIF(⑳商品別1食労務費!$C$5:$C$124,$U45,⑳商品別1食労務費!$F$5:$F$124)/$AA45,$AB45/$X45)) | AH45: =IF($V45="",0,IF($AA45>0,$AB45*SUMIF(⑳商品別1食労務費!$C$5:$C$124,$V45,⑳商品別1食労務費!$F$5:$F$124)/$AA45,$AB45/$X45)) | AI45: =IF($W45="",0,IF($AA45>0,$AB45*SUMIF(⑳商品別1食労務費!$C$5:$C$124,$W45,⑳商品別1食労務費!$F$5:$F$124)/$AA45,$AB45/$X45))
A46: 42 | B46: 釜製造 | C46: 塩パン | D46: 0.38611111 | E46: 0.4 | F46: 5 | G46: 15 | H46: 1 | I46: 16 | K46: =IF(F46>0,I46/(F46/60),0) | L46: =IF(AND(ISNUMBER(F46),J46>0),J46/(F46/60),"") | M46: =IF(OR(ISNUMBER(SEARCH("サニテーション",C46)),ISNUMBER(SEARCH("客注",C46)),ISNUMBER(SEARCH("切り替え",C46)),ISNUMBER(SEARCH("切替",C46)),NOT(ISNUMBER(H46))),"",IF(ISNUMBER(G46),G46/60*H46*④前提設定!$B$4,IF(AND(G46="",ISNUMBER(F46)),F46/60*H46*④前提設定!$B$4,""))) | N46: =IF(I46>0,M46/I46,"") | O46: =IF(AND(J46>0,ISNUMBER(M46)),M46/J46,"") | R46: 塩パン２個 | S46: 塩パンＫＩＴ | T46: メロン塩パン２個入 | U46: Ｓメロン塩パン２個入 | V46: メロン塩パンＫＩＴ | W46: チーズ塩パン２個 | X46: =COUNTA(R46:W46) | Y46: =IF(AND($X46>0,ISNUMBER($M46)),$M46/$X46,"") | Z46: =IF($X46=0,"",IF(COUNTIF(⑳商品別1食労務費!$C$5:$C$124,$R46)+COUNTIF(⑳商品別1食労務費!$C$5:$C$124,$S46)+COUNTIF(⑳商品別1食労務費!$C$5:$C$124,$T46)+COUNTIF(⑳商品別1食労務費!$C$5:$C$124,$U46)+COUNTIF(⑳商品別1食労務費!$C$5:$C$124,$V46)+COUNTIF(⑳商品別1食労務費!$C$5:$C$124,$W46)=$X46,"OK","⑳に無い商品名")) | AA46: =SUMIF(⑳商品別1食労務費!$C$5:$C$124,$R46,⑳商品別1食労務費!$F$5:$F$124)+SUMIF(⑳商品別1食労務費!$C$5:$C$124,$S46,⑳商品別1食労務費!$F$5:$F$124)+SUMIF(⑳商品別1食労務費!$C$5:$C$124,$T46,⑳商品別1食労務費!$F$5:$F$124)+SUMIF(⑳商品別1食労務費!$C$5:$C$124,$U46,⑳商品別1食労務費!$F$5:$F$124)+SUMIF(⑳商品別1食労務費!$C$5:$C$124,$V46,⑳商品別1食労務費!$F$5:$F$124)+SUMIF(⑳商品別1食労務費!$C$5:$C$124,$W46,⑳商品別1食労務費!$F$5:$F$124) | AB46: =IF(ISNUMBER($M46),$M46,0) | AD46: =IF($R46="",0,IF($AA46>0,$AB46*SUMIF(⑳商品別1食労務費!$C$5:$C$124,$R46,⑳商品別1食労務費!$F$5:$F$124)/$AA46,$AB46/$X46)) | AE46: =IF($S46="",0,IF($AA46>0,$AB46*SUMIF(⑳商品別1食労務費!$C$5:$C$124,$S46,⑳商品別1食労務費!$F$5:$F$124)/$AA46,$AB46/$X46)) | AF46: =IF($T46="",0,IF($AA46>0,$AB46*SUMIF(⑳商品別1食労務費!$C$5:$C$124,$T46,⑳商品別1食労務費!$F$5:$F$124)/$AA46,$AB46/$X46)) | AG46: =IF($U46="",0,IF($AA46>0,$AB46*SUMIF(⑳商品別1食労務費!$C$5:$C$124,$U46,⑳商品別1食労務費!$F$5:$F$124)/$AA46,$AB46/$X46)) | AH46: =IF($V46="",0,IF($AA46>0,$AB46*SUMIF(⑳商品別1食労務費!$C$5:$C$124,$V46,⑳商品別1食労務費!$F$5:$F$124)/$AA46,$AB46/$X46)) | AI46: =IF($W46="",0,IF($AA46>0,$AB46*SUMIF(⑳商品別1食労務費!$C$5:$C$124,$W46,⑳商品別1食労務費!$F$5:$F$124)/$AA46,$AB46/$X46))
A47: 43 | B47: 釜製造 | C47: 塩パン | D47: 0.4 | E47: 0.41388889 | F47: 5 | G47: 15 | H47: 1 | I47: 16 | K47: =IF(F47>0,I47/(F47/60),0) | L47: =IF(AND(ISNUMBER(F47),J47>0),J47/(F47/60),"") | M47: =IF(OR(ISNUMBER(SEARCH("サニテーション",C47)),ISNUMBER(SEARCH("客注",C47)),ISNUMBER(SEARCH("切り替え",C47)),ISNUMBER(SEARCH("切替",C47)),NOT(ISNUMBER(H47))),"",IF(ISNUMBER(G47),G47/60*H47*④前提設定!$B$4,IF(AND(G47="",ISNUMBER(F47)),F47/60*H47*④前提設定!$B$4,""))) | N47: =IF(I47>0,M47/I47,"") | O47: =IF(AND(J47>0,ISNUMBER(M47)),M47/J47,"") | R47: 塩パン２個 | S47: 塩パンＫＩＴ | T47: メロン塩パン２個入 | U47: Ｓメロン塩パン２個入 | V47: メロン塩パンＫＩＴ | W47: チーズ塩パン２個 | X47: =COUNTA(R47:W47) | Y47: =IF(AND($X47>0,ISNUMBER($M47)),$M47/$X47,"") | Z47: =IF($X47=0,"",IF(COUNTIF(⑳商品別1食労務費!$C$5:$C$124,$R47)+COUNTIF(⑳商品別1食労務費!$C$5:$C$124,$S47)+COUNTIF(⑳商品別1食労務費!$C$5:$C$124,$T47)+COUNTIF(⑳商品別1食労務費!$C$5:$C$124,$U47)+COUNTIF(⑳商品別1食労務費!$C$5:$C$124,$V47)+COUNTIF(⑳商品別1食労務費!$C$5:$C$124,$W47)=$X47,"OK","⑳に無い商品名")) | AA47: =SUMIF(⑳商品別1食労務費!$C$5:$C$124,$R47,⑳商品別1食労務費!$F$5:$F$124)+SUMIF(⑳商品別1食労務費!$C$5:$C$124,$S47,⑳商品別1食労務費!$F$5:$F$124)+SUMIF(⑳商品別1食労務費!$C$5:$C$124,$T47,⑳商品別1食労務費!$F$5:$F$124)+SUMIF(⑳商品別1食労務費!$C$5:$C$124,$U47,⑳商品別1食労務費!$F$5:$F$124)+SUMIF(⑳商品別1食労務費!$C$5:$C$124,$V47,⑳商品別1食労務費!$F$5:$F$124)+SUMIF(⑳商品別1食労務費!$C$5:$C$124,$W47,⑳商品別1食労務費!$F$5:$F$124) | AB47: =IF(ISNUMBER($M47),$M47,0) | AD47: =IF($R47="",0,IF($AA47>0,$AB47*SUMIF(⑳商品別1食労務費!$C$5:$C$124,$R47,⑳商品別1食労務費!$F$5:$F$124)/$AA47,$AB47/$X47)) | AE47: =IF($S47="",0,IF($AA47>0,$AB47*SUMIF(⑳商品別1食労務費!$C$5:$C$124,$S47,⑳商品別1食労務費!$F$5:$F$124)/$AA47,$AB47/$X47)) | AF47: =IF($T47="",0,IF($AA47>0,$AB47*SUMIF(⑳商品別1食労務費!$C$5:$C$124,$T47,⑳商品別1食労務費!$F$5:$F$124)/$AA47,$AB47/$X47)) | AG47: =IF($U47="",0,IF($AA47>0,$AB47*SUMIF(⑳商品別1食労務費!$C$5:$C$124,$U47,⑳商品別1食労務費!$F$5:$F$124)/$AA47,$AB47/$X47)) | AH47: =IF($V47="",0,IF($AA47>0,$AB47*SUMIF(⑳商品別1食労務費!$C$5:$C$124,$V47,⑳商品別1食労務費!$F$5:$F$124)/$AA47,$AB47/$X47)) | AI47: =IF($W47="",0,IF($AA47>0,$AB47*SUMIF(⑳商品別1食労務費!$C$5:$C$124,$W47,⑳商品別1食労務費!$F$5:$F$124)/$AA47,$AB47/$X47))
A48: 44 | B48: 釜製造 | C48: 塩パン | D48: 0.41388889 | E48: 0.42777778 | F48: 5 | G48: 15 | H48: 1 | I48: 16 | K48: =IF(F48>0,I48/(F48/60),0) | L48: =IF(AND(ISNUMBER(F48),J48>0),J48/(F48/60),"") | M48: =IF(OR(ISNUMBER(SEARCH("サニテーション",C48)),ISNUMBER(SEARCH("客注",C48)),ISNUMBER(SEARCH("切り替え",C48)),ISNUMBER(SEARCH("切替",C48)),NOT(ISNUMBER(H48))),"",IF(ISNUMBER(G48),G48/60*H48*④前提設定!$B$4,IF(AND(G48="",ISNUMBER(F48)),F48/60*H48*④前提設定!$B$4,""))) | N48: =IF(I48>0,M48/I48,"") | O48: =IF(AND(J48>0,ISNUMBER(M48)),M48/J48,"") | R48: 塩パン２個 | S48: 塩パンＫＩＴ | T48: メロン塩パン２個入 | U48: Ｓメロン塩パン２個入 | V48: メロン塩パンＫＩＴ | W48: チーズ塩パン２個 | X48: =COUNTA(R48:W48) | Y48: =IF(AND($X48>0,ISNUMBER($M48)),$M48/$X48,"") | Z48: =IF($X48=0,"",IF(COUNTIF(⑳商品別1食労務費!$C$5:$C$124,$R48)+COUNTIF(⑳商品別1食労務費!$C$5:$C$124,$S48)+COUNTIF(⑳商品別1食労務費!$C$5:$C$124,$T48)+COUNTIF(⑳商品別1食労務費!$C$5:$C$124,$U48)+COUNTIF(⑳商品別1食労務費!$C$5:$C$124,$V48)+COUNTIF(⑳商品別1食労務費!$C$5:$C$124,$W48)=$X48,"OK","⑳に無い商品名")) | AA48: =SUMIF(⑳商品別1食労務費!$C$5:$C$124,$R48,⑳商品別1食労務費!$F$5:$F$124)+SUMIF(⑳商品別1食労務費!$C$5:$C$124,$S48,⑳商品別1食労務費!$F$5:$F$124)+SUMIF(⑳商品別1食労務費!$C$5:$C$124,$T48,⑳商品別1食労務費!$F$5:$F$124)+SUMIF(⑳商品別1食労務費!$C$5:$C$124,$U48,⑳商品別1食労務費!$F$5:$F$124)+SUMIF(⑳商品別1食労務費!$C$5:$C$124,$V48,⑳商品別1食労務費!$F$5:$F$124)+SUMIF(⑳商品別1食労務費!$C$5:$C$124,$W48,⑳商品別1食労務費!$F$5:$F$124) | AB48: =IF(ISNUMBER($M48),$M48,0) | AD48: =IF($R48="",0,IF($AA48>0,$AB48*SUMIF(⑳商品別1食労務費!$C$5:$C$124,$R48,⑳商品別1食労務費!$F$5:$F$124)/$AA48,$AB48/$X48)) | AE48: =IF($S48="",0,IF($AA48>0,$AB48*SUMIF(⑳商品別1食労務費!$C$5:$C$124,$S48,⑳商品別1食労務費!$F$5:$F$124)/$AA48,$AB48/$X48)) | AF48: =IF($T48="",0,IF($AA48>0,$AB48*SUMIF(⑳商品別1食労務費!$C$5:$C$124,$T48,⑳商品別1食労務費!$F$5:$F$124)/$AA48,$AB48/$X48)) | AG48: =IF($U48="",0,IF($AA48>0,$AB48*SUMIF(⑳商品別1食労務費!$C$5:$C$124,$U48,⑳商品別1食労務費!$F$5:$F$124)/$AA48,$AB48/$X48)) | AH48: =IF($V48="",0,IF($AA48>0,$AB48*SUMIF(⑳商品別1食労務費!$C$5:$C$124,$V48,⑳商品別1食労務費!$F$5:$F$124)/$AA48,$AB48/$X48)) | AI48: =IF($W48="",0,IF($AA48>0,$AB48*SUMIF(⑳商品別1食労務費!$C$5:$C$124,$W48,⑳商品別1食労務費!$F$5:$F$124)/$AA48,$AB48/$X48))
A49: 45 | B49: 釜製造 | C49: 塩パン | D49: 0.42777778 | E49: 0.44166667 | F49: 5 | G49: 15 | H49: 1 | I49: 16 | K49: =IF(F49>0,I49/(F49/60),0) | L49: =IF(AND(ISNUMBER(F49),J49>0),J49/(F49/60),"") | M49: =IF(OR(ISNUMBER(SEARCH("サニテーション",C49)),ISNUMBER(SEARCH("客注",C49)),ISNUMBER(SEARCH("切り替え",C49)),ISNUMBER(SEARCH("切替",C49)),NOT(ISNUMBER(H49))),"",IF(ISNUMBER(G49),G49/60*H49*④前提設定!$B$4,IF(AND(G49="",ISNUMBER(F49)),F49/60*H49*④前提設定!$B$4,""))) | N49: =IF(I49>0,M49/I49,"") | O49: =IF(AND(J49>0,ISNUMBER(M49)),M49/J49,"") | R49: 塩パン２個 | S49: 塩パンＫＩＴ | T49: メロン塩パン２個入 | U49: Ｓメロン塩パン２個入 | V49: メロン塩パンＫＩＴ | W49: チーズ塩パン２個 | X49: =COUNTA(R49:W49) | Y49: =IF(AND($X49>0,ISNUMBER($M49)),$M49/$X49,"") | Z49: =IF($X49=0,"",IF(COUNTIF(⑳商品別1食労務費!$C$5:$C$124,$R49)+COUNTIF(⑳商品別1食労務費!$C$5:$C$124,$S49)+COUNTIF(⑳商品別1食労務費!$C$5:$C$124,$T49)+COUNTIF(⑳商品別1食労務費!$C$5:$C$124,$U49)+COUNTIF(⑳商品別1食労務費!$C$5:$C$124,$V49)+COUNTIF(⑳商品別1食労務費!$C$5:$C$124,$W49)=$X49,"OK","⑳に無い商品名")) | AA49: =SUMIF(⑳商品別1食労務費!$C$5:$C$124,$R49,⑳商品別1食労務費!$F$5:$F$124)+SUMIF(⑳商品別1食労務費!$C$5:$C$124,$S49,⑳商品別1食労務費!$F$5:$F$124)+SUMIF(⑳商品別1食労務費!$C$5:$C$124,$T49,⑳商品別1食労務費!$F$5:$F$124)+SUMIF(⑳商品別1食労務費!$C$5:$C$124,$U49,⑳商品別1食労務費!$F$5:$F$124)+SUMIF(⑳商品別1食労務費!$C$5:$C$124,$V49,⑳商品別1食労務費!$F$5:$F$124)+SUMIF(⑳商品別1食労務費!$C$5:$C$124,$W49,⑳商品別1食労務費!$F$5:$F$124) | AB49: =IF(ISNUMBER($M49),$M49,0) | AD49: =IF($R49="",0,IF($AA49>0,$AB49*SUMIF(⑳商品別1食労務費!$C$5:$C$124,$R49,⑳商品別1食労務費!$F$5:$F$124)/$AA49,$AB49/$X49)) | AE49: =IF($S49="",0,IF($AA49>0,$AB49*SUMIF(⑳商品別1食労務費!$C$5:$C$124,$S49,⑳商品別1食労務費!$F$5:$F$124)/$AA49,$AB49/$X49)) | AF49: =IF($T49="",0,IF($AA49>0,$AB49*SUMIF(⑳商品別1食労務費!$C$5:$C$124,$T49,⑳商品別1食労務費!$F$5:$F$124)/$AA49,$AB49/$X49)) | AG49: =IF($U49="",0,IF($AA49>0,$AB49*SUMIF(⑳商品別1食労務費!$C$5:$C$124,$U49,⑳商品別1食労務費!$F$5:$F$124)/$AA49,$AB49/$X49)) | AH49: =IF($V49="",0,IF($AA49>0,$AB49*SUMIF(⑳商品別1食労務費!$C$5:$C$124,$V49,⑳商品別1食労務費!$F$5:$F$124)/$AA49,$AB49/$X49)) | AI49: =IF($W49="",0,IF($AA49>0,$AB49*SUMIF(⑳商品別1食労務費!$C$5:$C$124,$W49,⑳商品別1食労務費!$F$5:$F$124)/$AA49,$AB49/$X49))
A50: 46 | B50: 釜製造 | C50: 塩パン | D50: 0.44166667 | E50: 0.45555556 | F50: 5 | G50: 15 | H50: 1 | I50: 16 | K50: =IF(F50>0,I50/(F50/60),0) | L50: =IF(AND(ISNUMBER(F50),J50>0),J50/(F50/60),"") | M50: =IF(OR(ISNUMBER(SEARCH("サニテーション",C50)),ISNUMBER(SEARCH("客注",C50)),ISNUMBER(SEARCH("切り替え",C50)),ISNUMBER(SEARCH("切替",C50)),NOT(ISNUMBER(H50))),"",IF(ISNUMBER(G50),G50/60*H50*④前提設定!$B$4,IF(AND(G50="",ISNUMBER(F50)),F50/60*H50*④前提設定!$B$4,""))) | N50: =IF(I50>0,M50/I50,"") | O50: =IF(AND(J50>0,ISNUMBER(M50)),M50/J50,"") | R50: 塩パン２個 | S50: 塩パンＫＩＴ | T50: メロン塩パン２個入 | U50: Ｓメロン塩パン２個入 | V50: メロン塩パンＫＩＴ | W50: チーズ塩パン２個 | X50: =COUNTA(R50:W50) | Y50: =IF(AND($X50>0,ISNUMBER($M50)),$M50/$X50,"") | Z50: =IF($X50=0,"",IF(COUNTIF(⑳商品別1食労務費!$C$5:$C$124,$R50)+COUNTIF(⑳商品別1食労務費!$C$5:$C$124,$S50)+COUNTIF(⑳商品別1食労務費!$C$5:$C$124,$T50)+COUNTIF(⑳商品別1食労務費!$C$5:$C$124,$U50)+COUNTIF(⑳商品別1食労務費!$C$5:$C$124,$V50)+COUNTIF(⑳商品別1食労務費!$C$5:$C$124,$W50)=$X50,"OK","⑳に無い商品名")) | AA50: =SUMIF(⑳商品別1食労務費!$C$5:$C$124,$R50,⑳商品別1食労務費!$F$5:$F$124)+SUMIF(⑳商品別1食労務費!$C$5:$C$124,$S50,⑳商品別1食労務費!$F$5:$F$124)+SUMIF(⑳商品別1食労務費!$C$5:$C$124,$T50,⑳商品別1食労務費!$F$5:$F$124)+SUMIF(⑳商品別1食労務費!$C$5:$C$124,$U50,⑳商品別1食労務費!$F$5:$F$124)+SUMIF(⑳商品別1食労務費!$C$5:$C$124,$V50,⑳商品別1食労務費!$F$5:$F$124)+SUMIF(⑳商品別1食労務費!$C$5:$C$124,$W50,⑳商品別1食労務費!$F$5:$F$124) | AB50: =IF(ISNUMBER($M50),$M50,0) | AD50: =IF($R50="",0,IF($AA50>0,$AB50*SUMIF(⑳商品別1食労務費!$C$5:$C$124,$R50,⑳商品別1食労務費!$F$5:$F$124)/$AA50,$AB50/$X50)) | AE50: =IF($S50="",0,IF($AA50>0,$AB50*SUMIF(⑳商品別1食労務費!$C$5:$C$124,$S50,⑳商品別1食労務費!$F$5:$F$124)/$AA50,$AB50/$X50)) | AF50: =IF($T50="",0,IF($AA50>0,$AB50*SUMIF(⑳商品別1食労務費!$C$5:$C$124,$T50,⑳商品別1食労務費!$F$5:$F$124)/$AA50,$AB50/$X50)) | AG50: =IF($U50="",0,IF($AA50>0,$AB50*SUMIF(⑳商品別1食労務費!$C$5:$C$124,$U50,⑳商品別1食労務費!$F$5:$F$124)/$AA50,$AB50/$X50)) | AH50: =IF($V50="",0,IF($AA50>0,$AB50*SUMIF(⑳商品別1食労務費!$C$5:$C$124,$V50,⑳商品別1食労務費!$F$5:$F$124)/$AA50,$AB50/$X50)) | AI50: =IF($W50="",0,IF($AA50>0,$AB50*SUMIF(⑳商品別1食労務費!$C$5:$C$124,$W50,⑳商品別1食労務費!$F$5:$F$124)/$AA50,$AB50/$X50))
A51: 47 | B51: 釜製造 | C51: 塩パン | D51: 0.45555556 | E51: 0.46944444 | F51: 5 | G51: 15 | H51: 1 | I51: 16 | K51: =IF(F51>0,I51/(F51/60),0) | L51: =IF(AND(ISNUMBER(F51),J51>0),J51/(F51/60),"") | M51: =IF(OR(ISNUMBER(SEARCH("サニテーション",C51)),ISNUMBER(SEARCH("客注",C51)),ISNUMBER(SEARCH("切り替え",C51)),ISNUMBER(SEARCH("切替",C51)),NOT(ISNUMBER(H51))),"",IF(ISNUMBER(G51),G51/60*H51*④前提設定!$B$4,IF(AND(G51="",ISNUMBER(F51)),F51/60*H51*④前提設定!$B$4,""))) | N51: =IF(I51>0,M51/I51,"") | O51: =IF(AND(J51>0,ISNUMBER(M51)),M51/J51,"") | R51: 塩パン２個 | S51: 塩パンＫＩＴ | T51: メロン塩パン２個入 | U51: Ｓメロン塩パン２個入 | V51: メロン塩パンＫＩＴ | W51: チーズ塩パン２個 | X51: =COUNTA(R51:W51) | Y51: =IF(AND($X51>0,ISNUMBER($M51)),$M51/$X51,"") | Z51: =IF($X51=0,"",IF(COUNTIF(⑳商品別1食労務費!$C$5:$C$124,$R51)+COUNTIF(⑳商品別1食労務費!$C$5:$C$124,$S51)+COUNTIF(⑳商品別1食労務費!$C$5:$C$124,$T51)+COUNTIF(⑳商品別1食労務費!$C$5:$C$124,$U51)+COUNTIF(⑳商品別1食労務費!$C$5:$C$124,$V51)+COUNTIF(⑳商品別1食労務費!$C$5:$C$124,$W51)=$X51,"OK","⑳に無い商品名")) | AA51: =SUMIF(⑳商品別1食労務費!$C$5:$C$124,$R51,⑳商品別1食労務費!$F$5:$F$124)+SUMIF(⑳商品別1食労務費!$C$5:$C$124,$S51,⑳商品別1食労務費!$F$5:$F$124)+SUMIF(⑳商品別1食労務費!$C$5:$C$124,$T51,⑳商品別1食労務費!$F$5:$F$124)+SUMIF(⑳商品別1食労務費!$C$5:$C$124,$U51,⑳商品別1食労務費!$F$5:$F$124)+SUMIF(⑳商品別1食労務費!$C$5:$C$124,$V51,⑳商品別1食労務費!$F$5:$F$124)+SUMIF(⑳商品別1食労務費!$C$5:$C$124,$W51,⑳商品別1食労務費!$F$5:$F$124) | AB51: =IF(ISNUMBER($M51),$M51,0) | AD51: =IF($R51="",0,IF($AA51>0,$AB51*SUMIF(⑳商品別1食労務費!$C$5:$C$124,$R51,⑳商品別1食労務費!$F$5:$F$124)/$AA51,$AB51/$X51)) | AE51: =IF($S51="",0,IF($AA51>0,$AB51*SUMIF(⑳商品別1食労務費!$C$5:$C$124,$S51,⑳商品別1食労務費!$F$5:$F$124)/$AA51,$AB51/$X51)) | AF51: =IF($T51="",0,IF($AA51>0,$AB51*SUMIF(⑳商品別1食労務費!$C$5:$C$124,$T51,⑳商品別1食労務費!$F$5:$F$124)/$AA51,$AB51/$X51)) | AG51: =IF($U51="",0,IF($AA51>0,$AB51*SUMIF(⑳商品別1食労務費!$C$5:$C$124,$U51,⑳商品別1食労務費!$F$5:$F$124)/$AA51,$AB51/$X51)) | AH51: =IF($V51="",0,IF($AA51>0,$AB51*SUMIF(⑳商品別1食労務費!$C$5:$C$124,$V51,⑳商品別1食労務費!$F$5:$F$124)/$AA51,$AB51/$X51)) | AI51: =IF($W51="",0,IF($AA51>0,$AB51*SUMIF(⑳商品別1食労務費!$C$5:$C$124,$W51,⑳商品別1食労務費!$F$5:$F$124)/$AA51,$AB51/$X51))
A52: 48 | B52: 釜製造 | C52: 塩パン | D52: 0.46944444 | E52: 0.48333333 | F52: 5 | G52: 15 | H52: 1 | I52: 16 | K52: =IF(F52>0,I52/(F52/60),0) | L52: =IF(AND(ISNUMBER(F52),J52>0),J52/(F52/60),"") | M52: =IF(OR(ISNUMBER(SEARCH("サニテーション",C52)),ISNUMBER(SEARCH("客注",C52)),ISNUMBER(SEARCH("切り替え",C52)),ISNUMBER(SEARCH("切替",C52)),NOT(ISNUMBER(H52))),"",IF(ISNUMBER(G52),G52/60*H52*④前提設定!$B$4,IF(AND(G52="",ISNUMBER(F52)),F52/60*H52*④前提設定!$B$4,""))) | N52: =IF(I52>0,M52/I52,"") | O52: =IF(AND(J52>0,ISNUMBER(M52)),M52/J52,"") | R52: 塩パン２個 | S52: 塩パンＫＩＴ | T52: メロン塩パン２個入 | U52: Ｓメロン塩パン２個入 | V52: メロン塩パンＫＩＴ | W52: チーズ塩パン２個 | X52: =COUNTA(R52:W52) | Y52: =IF(AND($X52>0,ISNUMBER($M52)),$M52/$X52,"") | Z52: =IF($X52=0,"",IF(COUNTIF(⑳商品別1食労務費!$C$5:$C$124,$R52)+COUNTIF(⑳商品別1食労務費!$C$5:$C$124,$S52)+COUNTIF(⑳商品別1食労務費!$C$5:$C$124,$T52)+COUNTIF(⑳商品別1食労務費!$C$5:$C$124,$U52)+COUNTIF(⑳商品別1食労務費!$C$5:$C$124,$V52)+COUNTIF(⑳商品別1食労務費!$C$5:$C$124,$W52)=$X52,"OK","⑳に無い商品名")) | AA52: =SUMIF(⑳商品別1食労務費!$C$5:$C$124,$R52,⑳商品別1食労務費!$F$5:$F$124)+SUMIF(⑳商品別1食労務費!$C$5:$C$124,$S52,⑳商品別1食労務費!$F$5:$F$124)+SUMIF(⑳商品別1食労務費!$C$5:$C$124,$T52,⑳商品別1食労務費!$F$5:$F$124)+SUMIF(⑳商品別1食労務費!$C$5:$C$124,$U52,⑳商品別1食労務費!$F$5:$F$124)+SUMIF(⑳商品別1食労務費!$C$5:$C$124,$V52,⑳商品別1食労務費!$F$5:$F$124)+SUMIF(⑳商品別1食労務費!$C$5:$C$124,$W52,⑳商品別1食労務費!$F$5:$F$124) | AB52: =IF(ISNUMBER($M52),$M52,0) | AD52: =IF($R52="",0,IF($AA52>0,$AB52*SUMIF(⑳商品別1食労務費!$C$5:$C$124,$R52,⑳商品別1食労務費!$F$5:$F$124)/$AA52,$AB52/$X52)) | AE52: =IF($S52="",0,IF($AA52>0,$AB52*SUMIF(⑳商品別1食労務費!$C$5:$C$124,$S52,⑳商品別1食労務費!$F$5:$F$124)/$AA52,$AB52/$X52)) | AF52: =IF($T52="",0,IF($AA52>0,$AB52*SUMIF(⑳商品別1食労務費!$C$5:$C$124,$T52,⑳商品別1食労務費!$F$5:$F$124)/$AA52,$AB52/$X52)) | AG52: =IF($U52="",0,IF($AA52>0,$AB52*SUMIF(⑳商品別1食労務費!$C$5:$C$124,$U52,⑳商品別1食労務費!$F$5:$F$124)/$AA52,$AB52/$X52)) | AH52: =IF($V52="",0,IF($AA52>0,$AB52*SUMIF(⑳商品別1食労務費!$C$5:$C$124,$V52,⑳商品別1食労務費!$F$5:$F$124)/$AA52,$AB52/$X52)) | AI52: =IF($W52="",0,IF($AA52>0,$AB52*SUMIF(⑳商品別1食労務費!$C$5:$C$124,$W52,⑳商品別1食労務費!$F$5:$F$124)/$AA52,$AB52/$X52))
A53: 49 | B53: 釜製造 | C53: 塩パン | D53: 0.48333333 | E53: 0.49722222 | F53: 5 | G53: 15 | H53: 1 | I53: 16 | K53: =IF(F53>0,I53/(F53/60),0) | L53: =IF(AND(ISNUMBER(F53),J53>0),J53/(F53/60),"") | M53: =IF(OR(ISNUMBER(SEARCH("サニテーション",C53)),ISNUMBER(SEARCH("客注",C53)),ISNUMBER(SEARCH("切り替え",C53)),ISNUMBER(SEARCH("切替",C53)),NOT(ISNUMBER(H53))),"",IF(ISNUMBER(G53),G53/60*H53*④前提設定!$B$4,IF(AND(G53="",ISNUMBER(F53)),F53/60*H53*④前提設定!$B$4,""))) | N53: =IF(I53>0,M53/I53,"") | O53: =IF(AND(J53>0,ISNUMBER(M53)),M53/J53,"") | R53: 塩パン２個 | S53: 塩パンＫＩＴ | T53: メロン塩パン２個入 | U53: Ｓメロン塩パン２個入 | V53: メロン塩パンＫＩＴ | W53: チーズ塩パン２個 | X53: =COUNTA(R53:W53) | Y53: =IF(AND($X53>0,ISNUMBER($M53)),$M53/$X53,"") | Z53: =IF($X53=0,"",IF(COUNTIF(⑳商品別1食労務費!$C$5:$C$124,$R53)+COUNTIF(⑳商品別1食労務費!$C$5:$C$124,$S53)+COUNTIF(⑳商品別1食労務費!$C$5:$C$124,$T53)+COUNTIF(⑳商品別1食労務費!$C$5:$C$124,$U53)+COUNTIF(⑳商品別1食労務費!$C$5:$C$124,$V53)+COUNTIF(⑳商品別1食労務費!$C$5:$C$124,$W53)=$X53,"OK","⑳に無い商品名")) | AA53: =SUMIF(⑳商品別1食労務費!$C$5:$C$124,$R53,⑳商品別1食労務費!$F$5:$F$124)+SUMIF(⑳商品別1食労務費!$C$5:$C$124,$S53,⑳商品別1食労務費!$F$5:$F$124)+SUMIF(⑳商品別1食労務費!$C$5:$C$124,$T53,⑳商品別1食労務費!$F$5:$F$124)+SUMIF(⑳商品別1食労務費!$C$5:$C$124,$U53,⑳商品別1食労務費!$F$5:$F$124)+SUMIF(⑳商品別1食労務費!$C$5:$C$124,$V53,⑳商品別1食労務費!$F$5:$F$124)+SUMIF(⑳商品別1食労務費!$C$5:$C$124,$W53,⑳商品別1食労務費!$F$5:$F$124) | AB53: =IF(ISNUMBER($M53),$M53,0) | AD53: =IF($R53="",0,IF($AA53>0,$AB53*SUMIF(⑳商品別1食労務費!$C$5:$C$124,$R53,⑳商品別1食労務費!$F$5:$F$124)/$AA53,$AB53/$X53)) | AE53: =IF($S53="",0,IF($AA53>0,$AB53*SUMIF(⑳商品別1食労務費!$C$5:$C$124,$S53,⑳商品別1食労務費!$F$5:$F$124)/$AA53,$AB53/$X53)) | AF53: =IF($T53="",0,IF($AA53>0,$AB53*SUMIF(⑳商品別1食労務費!$C$5:$C$124,$T53,⑳商品別1食労務費!$F$5:$F$124)/$AA53,$AB53/$X53)) | AG53: =IF($U53="",0,IF($AA53>0,$AB53*SUMIF(⑳商品別1食労務費!$C$5:$C$124,$U53,⑳商品別1食労務費!$F$5:$F$124)/$AA53,$AB53/$X53)) | AH53: =IF($V53="",0,IF($AA53>0,$AB53*SUMIF(⑳商品別1食労務費!$C$5:$C$124,$V53,⑳商品別1食労務費!$F$5:$F$124)/$AA53,$AB53/$X53)) | AI53: =IF($W53="",0,IF($AA53>0,$AB53*SUMIF(⑳商品別1食労務費!$C$5:$C$124,$W53,⑳商品別1食労務費!$F$5:$F$124)/$AA53,$AB53/$X53))
A54: 50 | B54: 釜製造 | C54: 塩パン | D54: 0.49722222 | E54: 0.51111111 | F54: 5 | G54: 15 | H54: 1 | I54: 16 | K54: =IF(F54>0,I54/(F54/60),0) | L54: =IF(AND(ISNUMBER(F54),J54>0),J54/(F54/60),"") | M54: =IF(OR(ISNUMBER(SEARCH("サニテーション",C54)),ISNUMBER(SEARCH("客注",C54)),ISNUMBER(SEARCH("切り替え",C54)),ISNUMBER(SEARCH("切替",C54)),NOT(ISNUMBER(H54))),"",IF(ISNUMBER(G54),G54/60*H54*④前提設定!$B$4,IF(AND(G54="",ISNUMBER(F54)),F54/60*H54*④前提設定!$B$4,""))) | N54: =IF(I54>0,M54/I54,"") | O54: =IF(AND(J54>0,ISNUMBER(M54)),M54/J54,"") | R54: 塩パン２個 | S54: 塩パンＫＩＴ | T54: メロン塩パン２個入 | U54: Ｓメロン塩パン２個入 | V54: メロン塩パンＫＩＴ | W54: チーズ塩パン２個 | X54: =COUNTA(R54:W54) | Y54: =IF(AND($X54>0,ISNUMBER($M54)),$M54/$X54,"") | Z54: =IF($X54=0,"",IF(COUNTIF(⑳商品別1食労務費!$C$5:$C$124,$R54)+COUNTIF(⑳商品別1食労務費!$C$5:$C$124,$S54)+COUNTIF(⑳商品別1食労務費!$C$5:$C$124,$T54)+COUNTIF(⑳商品別1食労務費!$C$5:$C$124,$U54)+COUNTIF(⑳商品別1食労務費!$C$5:$C$124,$V54)+COUNTIF(⑳商品別1食労務費!$C$5:$C$124,$W54)=$X54,"OK","⑳に無い商品名")) | AA54: =SUMIF(⑳商品別1食労務費!$C$5:$C$124,$R54,⑳商品別1食労務費!$F$5:$F$124)+SUMIF(⑳商品別1食労務費!$C$5:$C$124,$S54,⑳商品別1食労務費!$F$5:$F$124)+SUMIF(⑳商品別1食労務費!$C$5:$C$124,$T54,⑳商品別1食労務費!$F$5:$F$124)+SUMIF(⑳商品別1食労務費!$C$5:$C$124,$U54,⑳商品別1食労務費!$F$5:$F$124)+SUMIF(⑳商品別1食労務費!$C$5:$C$124,$V54,⑳商品別1食労務費!$F$5:$F$124)+SUMIF(⑳商品別1食労務費!$C$5:$C$124,$W54,⑳商品別1食労務費!$F$5:$F$124) | AB54: =IF(ISNUMBER($M54),$M54,0) | AD54: =IF($R54="",0,IF($AA54>0,$AB54*SUMIF(⑳商品別1食労務費!$C$5:$C$124,$R54,⑳商品別1食労務費!$F$5:$F$124)/$AA54,$AB54/$X54)) | AE54: =IF($S54="",0,IF($AA54>0,$AB54*SUMIF(⑳商品別1食労務費!$C$5:$C$124,$S54,⑳商品別1食労務費!$F$5:$F$124)/$AA54,$AB54/$X54)) | AF54: =IF($T54="",0,IF($AA54>0,$AB54*SUMIF(⑳商品別1食労務費!$C$5:$C$124,$T54,⑳商品別1食労務費!$F$5:$F$124)/$AA54,$AB54/$X54)) | AG54: =IF($U54="",0,IF($AA54>0,$AB54*SUMIF(⑳商品別1食労務費!$C$5:$C$124,$U54,⑳商品別1食労務費!$F$5:$F$124)/$AA54,$AB54/$X54)) | AH54: =IF($V54="",0,IF($AA54>0,$AB54*SUMIF(⑳商品別1食労務費!$C$5:$C$124,$V54,⑳商品別1食労務費!$F$5:$F$124)/$AA54,$AB54/$X54)) | AI54: =IF($W54="",0,IF($AA54>0,$AB54*SUMIF(⑳商品別1食労務費!$C$5:$C$124,$W54,⑳商品別1食労務費!$F$5:$F$124)/$AA54,$AB54/$X54))
A55: 51 | B55: 釜製造 | C55: ホテルブレッド | D55: 0.51111111 | E55: 0.525 | F55: 5 | G55: 15 | H55: 1 | I55: 16 | K55: =IF(F55>0,I55/(F55/60),0) | L55: =IF(AND(ISNUMBER(F55),J55>0),J55/(F55/60),"") | M55: =IF(OR(ISNUMBER(SEARCH("サニテーション",C55)),ISNUMBER(SEARCH("客注",C55)),ISNUMBER(SEARCH("切り替え",C55)),ISNUMBER(SEARCH("切替",C55)),NOT(ISNUMBER(H55))),"",IF(ISNUMBER(G55),G55/60*H55*④前提設定!$B$4,IF(AND(G55="",ISNUMBER(F55)),F55/60*H55*④前提設定!$B$4,""))) | N55: =IF(I55>0,M55/I55,"") | O55: =IF(AND(J55>0,ISNUMBER(M55)),M55/J55,"") | R55: ホテルブレッド生地ＫＩＴ | S55: ホテルブレッド生地ＫＩＴ２ | X55: =COUNTA(R55:W55) | Y55: =IF(AND($X55>0,ISNUMBER($M55)),$M55/$X55,"") | Z55: =IF($X55=0,"",IF(COUNTIF(⑳商品別1食労務費!$C$5:$C$124,$R55)+COUNTIF(⑳商品別1食労務費!$C$5:$C$124,$S55)+COUNTIF(⑳商品別1食労務費!$C$5:$C$124,$T55)+COUNTIF(⑳商品別1食労務費!$C$5:$C$124,$U55)+COUNTIF(⑳商品別1食労務費!$C$5:$C$124,$V55)+COUNTIF(⑳商品別1食労務費!$C$5:$C$124,$W55)=$X55,"OK","⑳に無い商品名")) | AA55: =SUMIF(⑳商品別1食労務費!$C$5:$C$124,$R55,⑳商品別1食労務費!$F$5:$F$124)+SUMIF(⑳商品別1食労務費!$C$5:$C$124,$S55,⑳商品別1食労務費!$F$5:$F$124)+SUMIF(⑳商品別1食労務費!$C$5:$C$124,$T55,⑳商品別1食労務費!$F$5:$F$124)+SUMIF(⑳商品別1食労務費!$C$5:$C$124,$U55,⑳商品別1食労務費!$F$5:$F$124)+SUMIF(⑳商品別1食労務費!$C$5:$C$124,$V55,⑳商品別1食労務費!$F$5:$F$124)+SUMIF(⑳商品別1食労務費!$C$5:$C$124,$W55,⑳商品別1食労務費!$F$5:$F$124) | AB55: =IF(ISNUMBER($M55),$M55,0) | AD55: =IF($R55="",0,IF($AA55>0,$AB55*SUMIF(⑳商品別1食労務費!$C$5:$C$124,$R55,⑳商品別1食労務費!$F$5:$F$124)/$AA55,$AB55/$X55)) | AE55: =IF($S55="",0,IF($AA55>0,$AB55*SUMIF(⑳商品別1食労務費!$C$5:$C$124,$S55,⑳商品別1食労務費!$F$5:$F$124)/$AA55,$AB55/$X55)) | AF55: =IF($T55="",0,IF($AA55>0,$AB55*SUMIF(⑳商品別1食労務費!$C$5:$C$124,$T55,⑳商品別1食労務費!$F$5:$F$124)/$AA55,$AB55/$X55)) | AG55: =IF($U55="",0,IF($AA55>0,$AB55*SUMIF(⑳商品別1食労務費!$C$5:$C$124,$U55,⑳商品別1食労務費!$F$5:$F$124)/$AA55,$AB55/$X55)) | AH55: =IF($V55="",0,IF($AA55>0,$AB55*SUMIF(⑳商品別1食労務費!$C$5:$C$124,$V55,⑳商品別1食労務費!$F$5:$F$124)/$AA55,$AB55/$X55)) | AI55: =IF($W55="",0,IF($AA55>0,$AB55*SUMIF(⑳商品別1食労務費!$C$5:$C$124,$W55,⑳商品別1食労務費!$F$5:$F$124)/$AA55,$AB55/$X55))
A56: 52 | B56: 釜製造 | C56: ホテルブレッド | D56: 0.525 | E56: 0.53888889 | F56: 5 | G56: 15 | H56: 1 | I56: 16 | K56: =IF(F56>0,I56/(F56/60),0) | L56: =IF(AND(ISNUMBER(F56),J56>0),J56/(F56/60),"") | M56: =IF(OR(ISNUMBER(SEARCH("サニテーション",C56)),ISNUMBER(SEARCH("客注",C56)),ISNUMBER(SEARCH("切り替え",C56)),ISNUMBER(SEARCH("切替",C56)),NOT(ISNUMBER(H56))),"",IF(ISNUMBER(G56),G56/60*H56*④前提設定!$B$4,IF(AND(G56="",ISNUMBER(F56)),F56/60*H56*④前提設定!$B$4,""))) | N56: =IF(I56>0,M56/I56,"") | O56: =IF(AND(J56>0,ISNUMBER(M56)),M56/J56,"") | R56: ホテルブレッド生地ＫＩＴ | S56: ホテルブレッド生地ＫＩＴ２ | X56: =COUNTA(R56:W56) | Y56: =IF(AND($X56>0,ISNUMBER($M56)),$M56/$X56,"") | Z56: =IF($X56=0,"",IF(COUNTIF(⑳商品別1食労務費!$C$5:$C$124,$R56)+COUNTIF(⑳商品別1食労務費!$C$5:$C$124,$S56)+COUNTIF(⑳商品別1食労務費!$C$5:$C$124,$T56)+COUNTIF(⑳商品別1食労務費!$C$5:$C$124,$U56)+COUNTIF(⑳商品別1食労務費!$C$5:$C$124,$V56)+COUNTIF(⑳商品別1食労務費!$C$5:$C$124,$W56)=$X56,"OK","⑳に無い商品名")) | AA56: =SUMIF(⑳商品別1食労務費!$C$5:$C$124,$R56,⑳商品別1食労務費!$F$5:$F$124)+SUMIF(⑳商品別1食労務費!$C$5:$C$124,$S56,⑳商品別1食労務費!$F$5:$F$124)+SUMIF(⑳商品別1食労務費!$C$5:$C$124,$T56,⑳商品別1食労務費!$F$5:$F$124)+SUMIF(⑳商品別1食労務費!$C$5:$C$124,$U56,⑳商品別1食労務費!$F$5:$F$124)+SUMIF(⑳商品別1食労務費!$C$5:$C$124,$V56,⑳商品別1食労務費!$F$5:$F$124)+SUMIF(⑳商品別1食労務費!$C$5:$C$124,$W56,⑳商品別1食労務費!$F$5:$F$124) | AB56: =IF(ISNUMBER($M56),$M56,0) | AD56: =IF($R56="",0,IF($AA56>0,$AB56*SUMIF(⑳商品別1食労務費!$C$5:$C$124,$R56,⑳商品別1食労務費!$F$5:$F$124)/$AA56,$AB56/$X56)) | AE56: =IF($S56="",0,IF($AA56>0,$AB56*SUMIF(⑳商品別1食労務費!$C$5:$C$124,$S56,⑳商品別1食労務費!$F$5:$F$124)/$AA56,$AB56/$X56)) | AF56: =IF($T56="",0,IF($AA56>0,$AB56*SUMIF(⑳商品別1食労務費!$C$5:$C$124,$T56,⑳商品別1食労務費!$F$5:$F$124)/$AA56,$AB56/$X56)) | AG56: =IF($U56="",0,IF($AA56>0,$AB56*SUMIF(⑳商品別1食労務費!$C$5:$C$124,$U56,⑳商品別1食労務費!$F$5:$F$124)/$AA56,$AB56/$X56)) | AH56: =IF($V56="",0,IF($AA56>0,$AB56*SUMIF(⑳商品別1食労務費!$C$5:$C$124,$V56,⑳商品別1食労務費!$F$5:$F$124)/$AA56,$AB56/$X56)) | AI56: =IF($W56="",0,IF($AA56>0,$AB56*SUMIF(⑳商品別1食労務費!$C$5:$C$124,$W56,⑳商品別1食労務費!$F$5:$F$124)/$AA56,$AB56/$X56))
A57: 53 | B57: 釜製造 | C57: ホテルブレッド | D57: 0.53888889 | E57: 0.55277778 | F57: 5 | G57: 15 | H57: 1 | I57: 16 | K57: - | L57: =IF(AND(ISNUMBER(F57),J57>0),J57/(F57/60),"") | M57: =IF(OR(ISNUMBER(SEARCH("サニテーション",C57)),ISNUMBER(SEARCH("客注",C57)),ISNUMBER(SEARCH("切り替え",C57)),ISNUMBER(SEARCH("切替",C57)),NOT(ISNUMBER(H57))),"",IF(ISNUMBER(G57),G57/60*H57*④前提設定!$B$4,IF(AND(G57="",ISNUMBER(F57)),F57/60*H57*④前提設定!$B$4,""))) | N57: - | O57: =IF(AND(J57>0,ISNUMBER(M57)),M57/J57,"") | R57: ホテルブレッド生地ＫＩＴ | S57: ホテルブレッド生地ＫＩＴ２ | X57: =COUNTA(R57:W57) | Y57: =IF(AND($X57>0,ISNUMBER($M57)),$M57/$X57,"") | Z57: =IF($X57=0,"",IF(COUNTIF(⑳商品別1食労務費!$C$5:$C$124,$R57)+COUNTIF(⑳商品別1食労務費!$C$5:$C$124,$S57)+COUNTIF(⑳商品別1食労務費!$C$5:$C$124,$T57)+COUNTIF(⑳商品別1食労務費!$C$5:$C$124,$U57)+COUNTIF(⑳商品別1食労務費!$C$5:$C$124,$V57)+COUNTIF(⑳商品別1食労務費!$C$5:$C$124,$W57)=$X57,"OK","⑳に無い商品名")) | AA57: =SUMIF(⑳商品別1食労務費!$C$5:$C$124,$R57,⑳商品別1食労務費!$F$5:$F$124)+SUMIF(⑳商品別1食労務費!$C$5:$C$124,$S57,⑳商品別1食労務費!$F$5:$F$124)+SUMIF(⑳商品別1食労務費!$C$5:$C$124,$T57,⑳商品別1食労務費!$F$5:$F$124)+SUMIF(⑳商品別1食労務費!$C$5:$C$124,$U57,⑳商品別1食労務費!$F$5:$F$124)+SUMIF(⑳商品別1食労務費!$C$5:$C$124,$V57,⑳商品別1食労務費!$F$5:$F$124)+SUMIF(⑳商品別1食労務費!$C$5:$C$124,$W57,⑳商品別1食労務費!$F$5:$F$124) | AB57: =IF(ISNUMBER($M57),$M57,0) | AD57: =IF($R57="",0,IF($AA57>0,$AB57*SUMIF(⑳商品別1食労務費!$C$5:$C$124,$R57,⑳商品別1食労務費!$F$5:$F$124)/$AA57,$AB57/$X57)) | AE57: =IF($S57="",0,IF($AA57>0,$AB57*SUMIF(⑳商品別1食労務費!$C$5:$C$124,$S57,⑳商品別1食労務費!$F$5:$F$124)/$AA57,$AB57/$X57)) | AF57: =IF($T57="",0,IF($AA57>0,$AB57*SUMIF(⑳商品別1食労務費!$C$5:$C$124,$T57,⑳商品別1食労務費!$F$5:$F$124)/$AA57,$AB57/$X57)) | AG57: =IF($U57="",0,IF($AA57>0,$AB57*SUMIF(⑳商品別1食労務費!$C$5:$C$124,$U57,⑳商品別1食労務費!$F$5:$F$124)/$AA57,$AB57/$X57)) | AH57: =IF($V57="",0,IF($AA57>0,$AB57*SUMIF(⑳商品別1食労務費!$C$5:$C$124,$V57,⑳商品別1食労務費!$F$5:$F$124)/$AA57,$AB57/$X57)) | AI57: =IF($W57="",0,IF($AA57>0,$AB57*SUMIF(⑳商品別1食労務費!$C$5:$C$124,$W57,⑳商品別1食労務費!$F$5:$F$124)/$AA57,$AB57/$X57))
A58: 54 | B58: 釜製造 | C58: ホテルブレッド | D58: 0.55277778 | E58: 0.56666667 | F58: 5 | G58: 15 | H58: 1 | I58: 16 | K58: - | L58: =IF(AND(ISNUMBER(F58),J58>0),J58/(F58/60),"") | M58: =IF(OR(ISNUMBER(SEARCH("サニテーション",C58)),ISNUMBER(SEARCH("客注",C58)),ISNUMBER(SEARCH("切り替え",C58)),ISNUMBER(SEARCH("切替",C58)),NOT(ISNUMBER(H58))),"",IF(ISNUMBER(G58),G58/60*H58*④前提設定!$B$4,IF(AND(G58="",ISNUMBER(F58)),F58/60*H58*④前提設定!$B$4,""))) | N58: - | O58: =IF(AND(J58>0,ISNUMBER(M58)),M58/J58,"") | R58: ホテルブレッド生地ＫＩＴ | S58: ホテルブレッド生地ＫＩＴ２ | X58: =COUNTA(R58:W58) | Y58: =IF(AND($X58>0,ISNUMBER($M58)),$M58/$X58,"") | Z58: =IF($X58=0,"",IF(COUNTIF(⑳商品別1食労務費!$C$5:$C$124,$R58)+COUNTIF(⑳商品別1食労務費!$C$5:$C$124,$S58)+COUNTIF(⑳商品別1食労務費!$C$5:$C$124,$T58)+COUNTIF(⑳商品別1食労務費!$C$5:$C$124,$U58)+COUNTIF(⑳商品別1食労務費!$C$5:$C$124,$V58)+COUNTIF(⑳商品別1食労務費!$C$5:$C$124,$W58)=$X58,"OK","⑳に無い商品名")) | AA58: =SUMIF(⑳商品別1食労務費!$C$5:$C$124,$R58,⑳商品別1食労務費!$F$5:$F$124)+SUMIF(⑳商品別1食労務費!$C$5:$C$124,$S58,⑳商品別1食労務費!$F$5:$F$124)+SUMIF(⑳商品別1食労務費!$C$5:$C$124,$T58,⑳商品別1食労務費!$F$5:$F$124)+SUMIF(⑳商品別1食労務費!$C$5:$C$124,$U58,⑳商品別1食労務費!$F$5:$F$124)+SUMIF(⑳商品別1食労務費!$C$5:$C$124,$V58,⑳商品別1食労務費!$F$5:$F$124)+SUMIF(⑳商品別1食労務費!$C$5:$C$124,$W58,⑳商品別1食労務費!$F$5:$F$124) | AB58: =IF(ISNUMBER($M58),$M58,0) | AD58: =IF($R58="",0,IF($AA58>0,$AB58*SUMIF(⑳商品別1食労務費!$C$5:$C$124,$R58,⑳商品別1食労務費!$F$5:$F$124)/$AA58,$AB58/$X58)) | AE58: =IF($S58="",0,IF($AA58>0,$AB58*SUMIF(⑳商品別1食労務費!$C$5:$C$124,$S58,⑳商品別1食労務費!$F$5:$F$124)/$AA58,$AB58/$X58)) | AF58: =IF($T58="",0,IF($AA58>0,$AB58*SUMIF(⑳商品別1食労務費!$C$5:$C$124,$T58,⑳商品別1食労務費!$F$5:$F$124)/$AA58,$AB58/$X58)) | AG58: =IF($U58="",0,IF($AA58>0,$AB58*SUMIF(⑳商品別1食労務費!$C$5:$C$124,$U58,⑳商品別1食労務費!$F$5:$F$124)/$AA58,$AB58/$X58)) | AH58: =IF($V58="",0,IF($AA58>0,$AB58*SUMIF(⑳商品別1食労務費!$C$5:$C$124,$V58,⑳商品別1食労務費!$F$5:$F$124)/$AA58,$AB58/$X58)) | AI58: =IF($W58="",0,IF($AA58>0,$AB58*SUMIF(⑳商品別1食労務費!$C$5:$C$124,$W58,⑳商品別1食労務費!$F$5:$F$124)/$AA58,$AB58/$X58))
A59: 55 | B59: 釜製造 | C59: 【PC加工用】 | K59: =IF(F59>0,I59/(F59/60),0) | L59: =IF(AND(ISNUMBER(F59),J59>0),J59/(F59/60),"") | M59: =IF(OR(ISNUMBER(SEARCH("サニテーション",C59)),ISNUMBER(SEARCH("客注",C59)),ISNUMBER(SEARCH("切り替え",C59)),ISNUMBER(SEARCH("切替",C59)),NOT(ISNUMBER(H59))),"",IF(ISNUMBER(G59),G59/60*H59*④前提設定!$B$4,IF(AND(G59="",ISNUMBER(F59)),F59/60*H59*④前提設定!$B$4,""))) | N59: =IF(I59>0,M59/I59,"") | O59: =IF(AND(J59>0,ISNUMBER(M59)),M59/J59,"") | X59: =COUNTA(R59:W59) | Y59: =IF(AND($X59>0,ISNUMBER($M59)),$M59/$X59,"") | Z59: =IF($X59=0,"",IF(COUNTIF(⑳商品別1食労務費!$C$5:$C$124,$R59)+COUNTIF(⑳商品別1食労務費!$C$5:$C$124,$S59)+COUNTIF(⑳商品別1食労務費!$C$5:$C$124,$T59)+COUNTIF(⑳商品別1食労務費!$C$5:$C$124,$U59)+COUNTIF(⑳商品別1食労務費!$C$5:$C$124,$V59)+COUNTIF(⑳商品別1食労務費!$C$5:$C$124,$W59)=$X59,"OK","⑳に無い商品名")) | AA59: =SUMIF(⑳商品別1食労務費!$C$5:$C$124,$R59,⑳商品別1食労務費!$F$5:$F$124)+SUMIF(⑳商品別1食労務費!$C$5:$C$124,$S59,⑳商品別1食労務費!$F$5:$F$124)+SUMIF(⑳商品別1食労務費!$C$5:$C$124,$T59,⑳商品別1食労務費!$F$5:$F$124)+SUMIF(⑳商品別1食労務費!$C$5:$C$124,$U59,⑳商品別1食労務費!$F$5:$F$124)+SUMIF(⑳商品別1食労務費!$C$5:$C$124,$V59,⑳商品別1食労務費!$F$5:$F$124)+SUMIF(⑳商品別1食労務費!$C$5:$C$124,$W59,⑳商品別1食労務費!$F$5:$F$124) | AB59: =IF(ISNUMBER($M59),$M59,0) | AD59: =IF($R59="",0,IF($AA59>0,$AB59*SUMIF(⑳商品別1食労務費!$C$5:$C$124,$R59,⑳商品別1食労務費!$F$5:$F$124)/$AA59,$AB59/$X59)) | AE59: =IF($S59="",0,IF($AA59>0,$AB59*SUMIF(⑳商品別1食労務費!$C$5:$C$124,$S59,⑳商品別1食労務費!$F$5:$F$124)/$AA59,$AB59/$X59)) | AF59: =IF($T59="",0,IF($AA59>0,$AB59*SUMIF(⑳商品別1食労務費!$C$5:$C$124,$T59,⑳商品別1食労務費!$F$5:$F$124)/$AA59,$AB59/$X59)) | AG59: =IF($U59="",0,IF($AA59>0,$AB59*SUMIF(⑳商品別1食労務費!$C$5:$C$124,$U59,⑳商品別1食労務費!$F$5:$F$124)/$AA59,$AB59/$X59)) | AH59: =IF($V59="",0,IF($AA59>0,$AB59*SUMIF(⑳商品別1食労務費!$C$5:$C$124,$V59,⑳商品別1食労務費!$F$5:$F$124)/$AA59,$AB59/$X59)) | AI59: =IF($W59="",0,IF($AA59>0,$AB59*SUMIF(⑳商品別1食労務費!$C$5:$C$124,$W59,⑳商品別1食労務費!$F$5:$F$124)/$AA59,$AB59/$X59))
A60: 56 | B60: 釜製造 | C60: バナナロール | K60: =IF(F60>0,I60/(F60/60),0) | L60: =IF(AND(ISNUMBER(F60),J60>0),J60/(F60/60),"") | M60: =IF(OR(ISNUMBER(SEARCH("サニテーション",C60)),ISNUMBER(SEARCH("客注",C60)),ISNUMBER(SEARCH("切り替え",C60)),ISNUMBER(SEARCH("切替",C60)),NOT(ISNUMBER(H60))),"",IF(ISNUMBER(G60),G60/60*H60*④前提設定!$B$4,IF(AND(G60="",ISNUMBER(F60)),F60/60*H60*④前提設定!$B$4,""))) | N60: =IF(I60>0,M60/I60,"") | O60: =IF(AND(J60>0,ISNUMBER(M60)),M60/J60,"") | R60: バナナのふんわりロール２ | S60: Ｓバナナのふんわりロール２ | X60: =COUNTA(R60:W60) | Y60: =IF(AND($X60>0,ISNUMBER($M60)),$M60/$X60,"") | Z60: =IF($X60=0,"",IF(COUNTIF(⑳商品別1食労務費!$C$5:$C$124,$R60)+COUNTIF(⑳商品別1食労務費!$C$5:$C$124,$S60)+COUNTIF(⑳商品別1食労務費!$C$5:$C$124,$T60)+COUNTIF(⑳商品別1食労務費!$C$5:$C$124,$U60)+COUNTIF(⑳商品別1食労務費!$C$5:$C$124,$V60)+COUNTIF(⑳商品別1食労務費!$C$5:$C$124,$W60)=$X60,"OK","⑳に無い商品名")) | AA60: =SUMIF(⑳商品別1食労務費!$C$5:$C$124,$R60,⑳商品別1食労務費!$F$5:$F$124)+SUMIF(⑳商品別1食労務費!$C$5:$C$124,$S60,⑳商品別1食労務費!$F$5:$F$124)+SUMIF(⑳商品別1食労務費!$C$5:$C$124,$T60,⑳商品別1食労務費!$F$5:$F$124)+SUMIF(⑳商品別1食労務費!$C$5:$C$124,$U60,⑳商品別1食労務費!$F$5:$F$124)+SUMIF(⑳商品別1食労務費!$C$5:$C$124,$V60,⑳商品別1食労務費!$F$5:$F$124)+SUMIF(⑳商品別1食労務費!$C$5:$C$124,$W60,⑳商品別1食労務費!$F$5:$F$124) | AB60: =IF(ISNUMBER($M60),$M60,0) | AD60: =IF($R60="",0,IF($AA60>0,$AB60*SUMIF(⑳商品別1食労務費!$C$5:$C$124,$R60,⑳商品別1食労務費!$F$5:$F$124)/$AA60,$AB60/$X60)) | AE60: =IF($S60="",0,IF($AA60>0,$AB60*SUMIF(⑳商品別1食労務費!$C$5:$C$124,$S60,⑳商品別1食労務費!$F$5:$F$124)/$AA60,$AB60/$X60)) | AF60: =IF($T60="",0,IF($AA60>0,$AB60*SUMIF(⑳商品別1食労務費!$C$5:$C$124,$T60,⑳商品別1食労務費!$F$5:$F$124)/$AA60,$AB60/$X60)) | AG60: =IF($U60="",0,IF($AA60>0,$AB60*SUMIF(⑳商品別1食労務費!$C$5:$C$124,$U60,⑳商品別1食労務費!$F$5:$F$124)/$AA60,$AB60/$X60)) | AH60: =IF($V60="",0,IF($AA60>0,$AB60*SUMIF(⑳商品別1食労務費!$C$5:$C$124,$V60,⑳商品別1食労務費!$F$5:$F$124)/$AA60,$AB60/$X60)) | AI60: =IF($W60="",0,IF($AA60>0,$AB60*SUMIF(⑳商品別1食労務費!$C$5:$C$124,$W60,⑳商品別1食労務費!$F$5:$F$124)/$AA60,$AB60/$X60))
A61: 57 | B61: 釜製造 | C61: バナナロールカット | K61: =IF(F61>0,I61/(F61/60),0) | L61: =IF(AND(ISNUMBER(F61),J61>0),J61/(F61/60),"") | M61: =IF(OR(ISNUMBER(SEARCH("サニテーション",C61)),ISNUMBER(SEARCH("客注",C61)),ISNUMBER(SEARCH("切り替え",C61)),ISNUMBER(SEARCH("切替",C61)),NOT(ISNUMBER(H61))),"",IF(ISNUMBER(G61),G61/60*H61*④前提設定!$B$4,IF(AND(G61="",ISNUMBER(F61)),F61/60*H61*④前提設定!$B$4,""))) | N61: =IF(I61>0,M61/I61,"") | O61: =IF(AND(J61>0,ISNUMBER(M61)),M61/J61,"") | R61: バナナのふんわりロール２ | S61: Ｓバナナのふんわりロール２ | X61: =COUNTA(R61:W61) | Y61: =IF(AND($X61>0,ISNUMBER($M61)),$M61/$X61,"") | Z61: =IF($X61=0,"",IF(COUNTIF(⑳商品別1食労務費!$C$5:$C$124,$R61)+COUNTIF(⑳商品別1食労務費!$C$5:$C$124,$S61)+COUNTIF(⑳商品別1食労務費!$C$5:$C$124,$T61)+COUNTIF(⑳商品別1食労務費!$C$5:$C$124,$U61)+COUNTIF(⑳商品別1食労務費!$C$5:$C$124,$V61)+COUNTIF(⑳商品別1食労務費!$C$5:$C$124,$W61)=$X61,"OK","⑳に無い商品名")) | AA61: =SUMIF(⑳商品別1食労務費!$C$5:$C$124,$R61,⑳商品別1食労務費!$F$5:$F$124)+SUMIF(⑳商品別1食労務費!$C$5:$C$124,$S61,⑳商品別1食労務費!$F$5:$F$124)+SUMIF(⑳商品別1食労務費!$C$5:$C$124,$T61,⑳商品別1食労務費!$F$5:$F$124)+SUMIF(⑳商品別1食労務費!$C$5:$C$124,$U61,⑳商品別1食労務費!$F$5:$F$124)+SUMIF(⑳商品別1食労務費!$C$5:$C$124,$V61,⑳商品別1食労務費!$F$5:$F$124)+SUMIF(⑳商品別1食労務費!$C$5:$C$124,$W61,⑳商品別1食労務費!$F$5:$F$124) | AB61: =IF(ISNUMBER($M61),$M61,0) | AD61: =IF($R61="",0,IF($AA61>0,$AB61*SUMIF(⑳商品別1食労務費!$C$5:$C$124,$R61,⑳商品別1食労務費!$F$5:$F$124)/$AA61,$AB61/$X61)) | AE61: =IF($S61="",0,IF($AA61>0,$AB61*SUMIF(⑳商品別1食労務費!$C$5:$C$124,$S61,⑳商品別1食労務費!$F$5:$F$124)/$AA61,$AB61/$X61)) | AF61: =IF($T61="",0,IF($AA61>0,$AB61*SUMIF(⑳商品別1食労務費!$C$5:$C$124,$T61,⑳商品別1食労務費!$F$5:$F$124)/$AA61,$AB61/$X61)) | AG61: =IF($U61="",0,IF($AA61>0,$AB61*SUMIF(⑳商品別1食労務費!$C$5:$C$124,$U61,⑳商品別1食労務費!$F$5:$F$124)/$AA61,$AB61/$X61)) | AH61: =IF($V61="",0,IF($AA61>0,$AB61*SUMIF(⑳商品別1食労務費!$C$5:$C$124,$V61,⑳商品別1食労務費!$F$5:$F$124)/$AA61,$AB61/$X61)) | AI61: =IF($W61="",0,IF($AA61>0,$AB61*SUMIF(⑳商品別1食労務費!$C$5:$C$124,$W61,⑳商品別1食労務費!$F$5:$F$124)/$AA61,$AB61/$X61))
A62: 58 | B62: 釜製造 | C62: バナナ処理 | K62: =IF(F62>0,I62/(F62/60),0) | L62: =IF(AND(ISNUMBER(F62),J62>0),J62/(F62/60),"") | M62: =IF(OR(ISNUMBER(SEARCH("サニテーション",C62)),ISNUMBER(SEARCH("客注",C62)),ISNUMBER(SEARCH("切り替え",C62)),ISNUMBER(SEARCH("切替",C62)),NOT(ISNUMBER(H62))),"",IF(ISNUMBER(G62),G62/60*H62*④前提設定!$B$4,IF(AND(G62="",ISNUMBER(F62)),F62/60*H62*④前提設定!$B$4,""))) | N62: =IF(I62>0,M62/I62,"") | O62: =IF(AND(J62>0,ISNUMBER(M62)),M62/J62,"") | R62: バナナのふんわりロール２ | X62: =COUNTA(R62:W62) | Y62: =IF(AND($X62>0,ISNUMBER($M62)),$M62/$X62,"") | Z62: =IF($X62=0,"",IF(COUNTIF(⑳商品別1食労務費!$C$5:$C$124,$R62)+COUNTIF(⑳商品別1食労務費!$C$5:$C$124,$S62)+COUNTIF(⑳商品別1食労務費!$C$5:$C$124,$T62)+COUNTIF(⑳商品別1食労務費!$C$5:$C$124,$U62)+COUNTIF(⑳商品別1食労務費!$C$5:$C$124,$V62)+COUNTIF(⑳商品別1食労務費!$C$5:$C$124,$W62)=$X62,"OK","⑳に無い商品名")) | AA62: =SUMIF(⑳商品別1食労務費!$C$5:$C$124,$R62,⑳商品別1食労務費!$F$5:$F$124)+SUMIF(⑳商品別1食労務費!$C$5:$C$124,$S62,⑳商品別1食労務費!$F$5:$F$124)+SUMIF(⑳商品別1食労務費!$C$5:$C$124,$T62,⑳商品別1食労務費!$F$5:$F$124)+SUMIF(⑳商品別1食労務費!$C$5:$C$124,$U62,⑳商品別1食労務費!$F$5:$F$124)+SUMIF(⑳商品別1食労務費!$C$5:$C$124,$V62,⑳商品別1食労務費!$F$5:$F$124)+SUMIF(⑳商品別1食労務費!$C$5:$C$124,$W62,⑳商品別1食労務費!$F$5:$F$124) | AB62: =IF(ISNUMBER($M62),$M62,0) | AD62: =IF($R62="",0,IF($AA62>0,$AB62*SUMIF(⑳商品別1食労務費!$C$5:$C$124,$R62,⑳商品別1食労務費!$F$5:$F$124)/$AA62,$AB62/$X62)) | AE62: =IF($S62="",0,IF($AA62>0,$AB62*SUMIF(⑳商品別1食労務費!$C$5:$C$124,$S62,⑳商品別1食労務費!$F$5:$F$124)/$AA62,$AB62/$X62)) | AF62: =IF($T62="",0,IF($AA62>0,$AB62*SUMIF(⑳商品別1食労務費!$C$5:$C$124,$T62,⑳商品別1食労務費!$F$5:$F$124)/$AA62,$AB62/$X62)) | AG62: =IF($U62="",0,IF($AA62>0,$AB62*SUMIF(⑳商品別1食労務費!$C$5:$C$124,$U62,⑳商品別1食労務費!$F$5:$F$124)/$AA62,$AB62/$X62)) | AH62: =IF($V62="",0,IF($AA62>0,$AB62*SUMIF(⑳商品別1食労務費!$C$5:$C$124,$V62,⑳商品別1食労務費!$F$5:$F$124)/$AA62,$AB62/$X62)) | AI62: =IF($W62="",0,IF($AA62>0,$AB62*SUMIF(⑳商品別1食労務費!$C$5:$C$124,$W62,⑳商品別1食労務費!$F$5:$F$124)/$AA62,$AB62/$X62))
A63: 59 | B63: 釜製造 | C63: バナナロール生地 | K63: =IF(F63>0,I63/(F63/60),0) | L63: =IF(AND(ISNUMBER(F63),J63>0),J63/(F63/60),"") | M63: =IF(OR(ISNUMBER(SEARCH("サニテーション",C63)),ISNUMBER(SEARCH("客注",C63)),ISNUMBER(SEARCH("切り替え",C63)),ISNUMBER(SEARCH("切替",C63)),NOT(ISNUMBER(H63))),"",IF(ISNUMBER(G63),G63/60*H63*④前提設定!$B$4,IF(AND(G63="",ISNUMBER(F63)),F63/60*H63*④前提設定!$B$4,""))) | N63: =IF(I63>0,M63/I63,"") | O63: =IF(AND(J63>0,ISNUMBER(M63)),M63/J63,"") | R63: バナナのふんわりロール２ | S63: Ｓバナナのふんわりロール２ | X63: =COUNTA(R63:W63) | Y63: =IF(AND($X63>0,ISNUMBER($M63)),$M63/$X63,"") | Z63: =IF($X63=0,"",IF(COUNTIF(⑳商品別1食労務費!$C$5:$C$124,$R63)+COUNTIF(⑳商品別1食労務費!$C$5:$C$124,$S63)+COUNTIF(⑳商品別1食労務費!$C$5:$C$124,$T63)+COUNTIF(⑳商品別1食労務費!$C$5:$C$124,$U63)+COUNTIF(⑳商品別1食労務費!$C$5:$C$124,$V63)+COUNTIF(⑳商品別1食労務費!$C$5:$C$124,$W63)=$X63,"OK","⑳に無い商品名")) | AA63: =SUMIF(⑳商品別1食労務費!$C$5:$C$124,$R63,⑳商品別1食労務費!$F$5:$F$124)+SUMIF(⑳商品別1食労務費!$C$5:$C$124,$S63,⑳商品別1食労務費!$F$5:$F$124)+SUMIF(⑳商品別1食労務費!$C$5:$C$124,$T63,⑳商品別1食労務費!$F$5:$F$124)+SUMIF(⑳商品別1食労務費!$C$5:$C$124,$U63,⑳商品別1食労務費!$F$5:$F$124)+SUMIF(⑳商品別1食労務費!$C$5:$C$124,$V63,⑳商品別1食労務費!$F$5:$F$124)+SUMIF(⑳商品別1食労務費!$C$5:$C$124,$W63,⑳商品別1食労務費!$F$5:$F$124) | AB63: =IF(ISNUMBER($M63),$M63,0) | AD63: =IF($R63="",0,IF($AA63>0,$AB63*SUMIF(⑳商品別1食労務費!$C$5:$C$124,$R63,⑳商品別1食労務費!$F$5:$F$124)/$AA63,$AB63/$X63)) | AE63: =IF($S63="",0,IF($AA63>0,$AB63*SUMIF(⑳商品別1食労務費!$C$5:$C$124,$S63,⑳商品別1食労務費!$F$5:$F$124)/$AA63,$AB63/$X63)) | AF63: =IF($T63="",0,IF($AA63>0,$AB63*SUMIF(⑳商品別1食労務費!$C$5:$C$124,$T63,⑳商品別1食労務費!$F$5:$F$124)/$AA63,$AB63/$X63)) | AG63: =IF($U63="",0,IF($AA63>0,$AB63*SUMIF(⑳商品別1食労務費!$C$5:$C$124,$U63,⑳商品別1食労務費!$F$5:$F$124)/$AA63,$AB63/$X63)) | AH63: =IF($V63="",0,IF($AA63>0,$AB63*SUMIF(⑳商品別1食労務費!$C$5:$C$124,$V63,⑳商品別1食労務費!$F$5:$F$124)/$AA63,$AB63/$X63)) | AI63: =IF($W63="",0,IF($AA63>0,$AB63*SUMIF(⑳商品別1食労務費!$C$5:$C$124,$W63,⑳商品別1食労務費!$F$5:$F$124)/$AA63,$AB63/$X63))
A64: 60 | B64: 釜製造 | C64: 抹茶わらび餅 | K64: =IF(F64>0,I64/(F64/60),0) | L64: =IF(AND(ISNUMBER(F64),J64>0),J64/(F64/60),"") | M64: =IF(OR(ISNUMBER(SEARCH("サニテーション",C64)),ISNUMBER(SEARCH("客注",C64)),ISNUMBER(SEARCH("切り替え",C64)),ISNUMBER(SEARCH("切替",C64)),NOT(ISNUMBER(H64))),"",IF(ISNUMBER(G64),G64/60*H64*④前提設定!$B$4,IF(AND(G64="",ISNUMBER(F64)),F64/60*H64*④前提設定!$B$4,""))) | N64: =IF(I64>0,M64/I64,"") | O64: =IF(AND(J64>0,ISNUMBER(M64)),M64/J64,"") | R64: お箸でつまんでわらび餅小 | S64: Ｓお箸でつまんでわらび餅小 | X64: =COUNTA(R64:W64) | Y64: =IF(AND($X64>0,ISNUMBER($M64)),$M64/$X64,"") | Z64: =IF($X64=0,"",IF(COUNTIF(⑳商品別1食労務費!$C$5:$C$124,$R64)+COUNTIF(⑳商品別1食労務費!$C$5:$C$124,$S64)+COUNTIF(⑳商品別1食労務費!$C$5:$C$124,$T64)+COUNTIF(⑳商品別1食労務費!$C$5:$C$124,$U64)+COUNTIF(⑳商品別1食労務費!$C$5:$C$124,$V64)+COUNTIF(⑳商品別1食労務費!$C$5:$C$124,$W64)=$X64,"OK","⑳に無い商品名")) | AA64: =SUMIF(⑳商品別1食労務費!$C$5:$C$124,$R64,⑳商品別1食労務費!$F$5:$F$124)+SUMIF(⑳商品別1食労務費!$C$5:$C$124,$S64,⑳商品別1食労務費!$F$5:$F$124)+SUMIF(⑳商品別1食労務費!$C$5:$C$124,$T64,⑳商品別1食労務費!$F$5:$F$124)+SUMIF(⑳商品別1食労務費!$C$5:$C$124,$U64,⑳商品別1食労務費!$F$5:$F$124)+SUMIF(⑳商品別1食労務費!$C$5:$C$124,$V64,⑳商品別1食労務費!$F$5:$F$124)+SUMIF(⑳商品別1食労務費!$C$5:$C$124,$W64,⑳商品別1食労務費!$F$5:$F$124) | AB64: =IF(ISNUMBER($M64),$M64,0) | AD64: =IF($R64="",0,IF($AA64>0,$AB64*SUMIF(⑳商品別1食労務費!$C$5:$C$124,$R64,⑳商品別1食労務費!$F$5:$F$124)/$AA64,$AB64/$X64)) | AE64: =IF($S64="",0,IF($AA64>0,$AB64*SUMIF(⑳商品別1食労務費!$C$5:$C$124,$S64,⑳商品別1食労務費!$F$5:$F$124)/$AA64,$AB64/$X64)) | AF64: =IF($T64="",0,IF($AA64>0,$AB64*SUMIF(⑳商品別1食労務費!$C$5:$C$124,$T64,⑳商品別1食労務費!$F$5:$F$124)/$AA64,$AB64/$X64)) | AG64: =IF($U64="",0,IF($AA64>0,$AB64*SUMIF(⑳商品別1食労務費!$C$5:$C$124,$U64,⑳商品別1食労務費!$F$5:$F$124)/$AA64,$AB64/$X64)) | AH64: =IF($V64="",0,IF($AA64>0,$AB64*SUMIF(⑳商品別1食労務費!$C$5:$C$124,$V64,⑳商品別1食労務費!$F$5:$F$124)/$AA64,$AB64/$X64)) | AI64: =IF($W64="",0,IF($AA64>0,$AB64*SUMIF(⑳商品別1食労務費!$C$5:$C$124,$W64,⑳商品別1食労務費!$F$5:$F$124)/$AA64,$AB64/$X64))
A65: 61 | B65: 釜製造 | C65: 抹茶きなこ | K65: - | L65: =IF(AND(ISNUMBER(F65),J65>0),J65/(F65/60),"") | M65: =IF(OR(ISNUMBER(SEARCH("サニテーション",C65)),ISNUMBER(SEARCH("客注",C65)),ISNUMBER(SEARCH("切り替え",C65)),ISNUMBER(SEARCH("切替",C65)),NOT(ISNUMBER(H65))),"",IF(ISNUMBER(G65),G65/60*H65*④前提設定!$B$4,IF(AND(G65="",ISNUMBER(F65)),F65/60*H65*④前提設定!$B$4,""))) | N65: - | O65: =IF(AND(J65>0,ISNUMBER(M65)),M65/J65,"") | R65: Ｓお箸でつまんでわらび餅小 | S65: お箸でつまんでわらび餅小 | X65: =COUNTA(R65:W65) | Y65: =IF(AND($X65>0,ISNUMBER($M65)),$M65/$X65,"") | Z65: =IF($X65=0,"",IF(COUNTIF(⑳商品別1食労務費!$C$5:$C$124,$R65)+COUNTIF(⑳商品別1食労務費!$C$5:$C$124,$S65)+COUNTIF(⑳商品別1食労務費!$C$5:$C$124,$T65)+COUNTIF(⑳商品別1食労務費!$C$5:$C$124,$U65)+COUNTIF(⑳商品別1食労務費!$C$5:$C$124,$V65)+COUNTIF(⑳商品別1食労務費!$C$5:$C$124,$W65)=$X65,"OK","⑳に無い商品名")) | AA65: =SUMIF(⑳商品別1食労務費!$C$5:$C$124,$R65,⑳商品別1食労務費!$F$5:$F$124)+SUMIF(⑳商品別1食労務費!$C$5:$C$124,$S65,⑳商品別1食労務費!$F$5:$F$124)+SUMIF(⑳商品別1食労務費!$C$5:$C$124,$T65,⑳商品別1食労務費!$F$5:$F$124)+SUMIF(⑳商品別1食労務費!$C$5:$C$124,$U65,⑳商品別1食労務費!$F$5:$F$124)+SUMIF(⑳商品別1食労務費!$C$5:$C$124,$V65,⑳商品別1食労務費!$F$5:$F$124)+SUMIF(⑳商品別1食労務費!$C$5:$C$124,$W65,⑳商品別1食労務費!$F$5:$F$124) | AB65: =IF(ISNUMBER($M65),$M65,0) | AD65: =IF($R65="",0,IF($AA65>0,$AB65*SUMIF(⑳商品別1食労務費!$C$5:$C$124,$R65,⑳商品別1食労務費!$F$5:$F$124)/$AA65,$AB65/$X65)) | AE65: =IF($S65="",0,IF($AA65>0,$AB65*SUMIF(⑳商品別1食労務費!$C$5:$C$124,$S65,⑳商品別1食労務費!$F$5:$F$124)/$AA65,$AB65/$X65)) | AF65: =IF($T65="",0,IF($AA65>0,$AB65*SUMIF(⑳商品別1食労務費!$C$5:$C$124,$T65,⑳商品別1食労務費!$F$5:$F$124)/$AA65,$AB65/$X65)) | AG65: =IF($U65="",0,IF($AA65>0,$AB65*SUMIF(⑳商品別1食労務費!$C$5:$C$124,$U65,⑳商品別1食労務費!$F$5:$F$124)/$AA65,$AB65/$X65)) | AH65: =IF($V65="",0,IF($AA65>0,$AB65*SUMIF(⑳商品別1食労務費!$C$5:$C$124,$V65,⑳商品別1食労務費!$F$5:$F$124)/$AA65,$AB65/$X65)) | AI65: =IF($W65="",0,IF($AA65>0,$AB65*SUMIF(⑳商品別1食労務費!$C$5:$C$124,$W65,⑳商品別1食労務費!$F$5:$F$124)/$AA65,$AB65/$X65))
A66: 62 | B66: 釜製造 | C66: 抹茶わらび餅加熱 | K66: =IF(F66>0,I66/(F66/60),0) | L66: =IF(AND(ISNUMBER(F66),J66>0),J66/(F66/60),"") | M66: =IF(OR(ISNUMBER(SEARCH("サニテーション",C66)),ISNUMBER(SEARCH("客注",C66)),ISNUMBER(SEARCH("切り替え",C66)),ISNUMBER(SEARCH("切替",C66)),NOT(ISNUMBER(H66))),"",IF(ISNUMBER(G66),G66/60*H66*④前提設定!$B$4,IF(AND(G66="",ISNUMBER(F66)),F66/60*H66*④前提設定!$B$4,""))) | N66: =IF(I66>0,M66/I66,"") | O66: =IF(AND(J66>0,ISNUMBER(M66)),M66/J66,"") | R66: お箸でつまんでわらび餅小 | S66: Ｓお箸でつまんでわらび餅小 | X66: =COUNTA(R66:W66) | Y66: =IF(AND($X66>0,ISNUMBER($M66)),$M66/$X66,"") | Z66: =IF($X66=0,"",IF(COUNTIF(⑳商品別1食労務費!$C$5:$C$124,$R66)+COUNTIF(⑳商品別1食労務費!$C$5:$C$124,$S66)+COUNTIF(⑳商品別1食労務費!$C$5:$C$124,$T66)+COUNTIF(⑳商品別1食労務費!$C$5:$C$124,$U66)+COUNTIF(⑳商品別1食労務費!$C$5:$C$124,$V66)+COUNTIF(⑳商品別1食労務費!$C$5:$C$124,$W66)=$X66,"OK","⑳に無い商品名")) | AA66: =SUMIF(⑳商品別1食労務費!$C$5:$C$124,$R66,⑳商品別1食労務費!$F$5:$F$124)+SUMIF(⑳商品別1食労務費!$C$5:$C$124,$S66,⑳商品別1食労務費!$F$5:$F$124)+SUMIF(⑳商品別1食労務費!$C$5:$C$124,$T66,⑳商品別1食労務費!$F$5:$F$124)+SUMIF(⑳商品別1食労務費!$C$5:$C$124,$U66,⑳商品別1食労務費!$F$5:$F$124)+SUMIF(⑳商品別1食労務費!$C$5:$C$124,$V66,⑳商品別1食労務費!$F$5:$F$124)+SUMIF(⑳商品別1食労務費!$C$5:$C$124,$W66,⑳商品別1食労務費!$F$5:$F$124) | AB66: =IF(ISNUMBER($M66),$M66,0) | AD66: =IF($R66="",0,IF($AA66>0,$AB66*SUMIF(⑳商品別1食労務費!$C$5:$C$124,$R66,⑳商品別1食労務費!$F$5:$F$124)/$AA66,$AB66/$X66)) | AE66: =IF($S66="",0,IF($AA66>0,$AB66*SUMIF(⑳商品別1食労務費!$C$5:$C$124,$S66,⑳商品別1食労務費!$F$5:$F$124)/$AA66,$AB66/$X66)) | AF66: =IF($T66="",0,IF($AA66>0,$AB66*SUMIF(⑳商品別1食労務費!$C$5:$C$124,$T66,⑳商品別1食労務費!$F$5:$F$124)/$AA66,$AB66/$X66)) | AG66: =IF($U66="",0,IF($AA66>0,$AB66*SUMIF(⑳商品別1食労務費!$C$5:$C$124,$U66,⑳商品別1食労務費!$F$5:$F$124)/$AA66,$AB66/$X66)) | AH66: =IF($V66="",0,IF($AA66>0,$AB66*SUMIF(⑳商品別1食労務費!$C$5:$C$124,$V66,⑳商品別1食労務費!$F$5:$F$124)/$AA66,$AB66/$X66)) | AI66: =IF($W66="",0,IF($AA66>0,$AB66*SUMIF(⑳商品別1食労務費!$C$5:$C$124,$W66,⑳商品別1食労務費!$F$5:$F$124)/$AA66,$AB66/$X66))
A67: 63 | B67: 釜製造 | C67: 自社製ホイップの卵プリン | K67: =IF(F67>0,I67/(F67/60),0) | L67: =IF(AND(ISNUMBER(F67),J67>0),J67/(F67/60),"") | M67: =IF(OR(ISNUMBER(SEARCH("サニテーション",C67)),ISNUMBER(SEARCH("客注",C67)),ISNUMBER(SEARCH("切り替え",C67)),ISNUMBER(SEARCH("切替",C67)),NOT(ISNUMBER(H67))),"",IF(ISNUMBER(G67),G67/60*H67*④前提設定!$B$4,IF(AND(G67="",ISNUMBER(F67)),F67/60*H67*④前提設定!$B$4,""))) | N67: =IF(I67>0,M67/I67,"") | O67: =IF(AND(J67>0,ISNUMBER(M67)),M67/J67,"") | R67: 自社製ホイップの卵プリン | S67: Ｓホイップの卵プリン | T67: ホイップの卵プリン | X67: =COUNTA(R67:W67) | Y67: =IF(AND($X67>0,ISNUMBER($M67)),$M67/$X67,"") | Z67: =IF($X67=0,"",IF(COUNTIF(⑳商品別1食労務費!$C$5:$C$124,$R67)+COUNTIF(⑳商品別1食労務費!$C$5:$C$124,$S67)+COUNTIF(⑳商品別1食労務費!$C$5:$C$124,$T67)+COUNTIF(⑳商品別1食労務費!$C$5:$C$124,$U67)+COUNTIF(⑳商品別1食労務費!$C$5:$C$124,$V67)+COUNTIF(⑳商品別1食労務費!$C$5:$C$124,$W67)=$X67,"OK","⑳に無い商品名")) | AA67: =SUMIF(⑳商品別1食労務費!$C$5:$C$124,$R67,⑳商品別1食労務費!$F$5:$F$124)+SUMIF(⑳商品別1食労務費!$C$5:$C$124,$S67,⑳商品別1食労務費!$F$5:$F$124)+SUMIF(⑳商品別1食労務費!$C$5:$C$124,$T67,⑳商品別1食労務費!$F$5:$F$124)+SUMIF(⑳商品別1食労務費!$C$5:$C$124,$U67,⑳商品別1食労務費!$F$5:$F$124)+SUMIF(⑳商品別1食労務費!$C$5:$C$124,$V67,⑳商品別1食労務費!$F$5:$F$124)+SUMIF(⑳商品別1食労務費!$C$5:$C$124,$W67,⑳商品別1食労務費!$F$5:$F$124) | AB67: =IF(ISNUMBER($M67),$M67,0) | AD67: =IF($R67="",0,IF($AA67>0,$AB67*SUMIF(⑳商品別1食労務費!$C$5:$C$124,$R67,⑳商品別1食労務費!$F$5:$F$124)/$AA67,$AB67/$X67)) | AE67: =IF($S67="",0,IF($AA67>0,$AB67*SUMIF(⑳商品別1食労務費!$C$5:$C$124,$S67,⑳商品別1食労務費!$F$5:$F$124)/$AA67,$AB67/$X67)) | AF67: =IF($T67="",0,IF($AA67>0,$AB67*SUMIF(⑳商品別1食労務費!$C$5:$C$124,$T67,⑳商品別1食労務費!$F$5:$F$124)/$AA67,$AB67/$X67)) | AG67: =IF($U67="",0,IF($AA67>0,$AB67*SUMIF(⑳商品別1食労務費!$C$5:$C$124,$U67,⑳商品別1食労務費!$F$5:$F$124)/$AA67,$AB67/$X67)) | AH67: =IF($V67="",0,IF($AA67>0,$AB67*SUMIF(⑳商品別1食労務費!$C$5:$C$124,$V67,⑳商品別1食労務費!$F$5:$F$124)/$AA67,$AB67/$X67)) | AI67: =IF($W67="",0,IF($AA67>0,$AB67*SUMIF(⑳商品別1食労務費!$C$5:$C$124,$W67,⑳商品別1食労務費!$F$5:$F$124)/$AA67,$AB67/$X67))
A68: 64 | B68: 釜製造 | C68: 内製ホイップ | K68: =IF(F68>0,I68/(F68/60),0) | L68: =IF(AND(ISNUMBER(F68),J68>0),J68/(F68/60),"") | M68: =IF(OR(ISNUMBER(SEARCH("サニテーション",C68)),ISNUMBER(SEARCH("客注",C68)),ISNUMBER(SEARCH("切り替え",C68)),ISNUMBER(SEARCH("切替",C68)),NOT(ISNUMBER(H68))),"",IF(ISNUMBER(G68),G68/60*H68*④前提設定!$B$4,IF(AND(G68="",ISNUMBER(F68)),F68/60*H68*④前提設定!$B$4,""))) | N68: =IF(I68>0,M68/I68,"") | O68: =IF(AND(J68>0,ISNUMBER(M68)),M68/J68,"") | R68: 自社製ホイップの卵プリン | S68: Ｓホイップの卵プリン | T68: Ｓカスタード＆ホイップシュ | U68: ホイップの卵プリン | X68: =COUNTA(R68:W68) | Y68: =IF(AND($X68>0,ISNUMBER($M68)),$M68/$X68,"") | Z68: =IF($X68=0,"",IF(COUNTIF(⑳商品別1食労務費!$C$5:$C$124,$R68)+COUNTIF(⑳商品別1食労務費!$C$5:$C$124,$S68)+COUNTIF(⑳商品別1食労務費!$C$5:$C$124,$T68)+COUNTIF(⑳商品別1食労務費!$C$5:$C$124,$U68)+COUNTIF(⑳商品別1食労務費!$C$5:$C$124,$V68)+COUNTIF(⑳商品別1食労務費!$C$5:$C$124,$W68)=$X68,"OK","⑳に無い商品名")) | AA68: =SUMIF(⑳商品別1食労務費!$C$5:$C$124,$R68,⑳商品別1食労務費!$F$5:$F$124)+SUMIF(⑳商品別1食労務費!$C$5:$C$124,$S68,⑳商品別1食労務費!$F$5:$F$124)+SUMIF(⑳商品別1食労務費!$C$5:$C$124,$T68,⑳商品別1食労務費!$F$5:$F$124)+SUMIF(⑳商品別1食労務費!$C$5:$C$124,$U68,⑳商品別1食労務費!$F$5:$F$124)+SUMIF(⑳商品別1食労務費!$C$5:$C$124,$V68,⑳商品別1食労務費!$F$5:$F$124)+SUMIF(⑳商品別1食労務費!$C$5:$C$124,$W68,⑳商品別1食労務費!$F$5:$F$124) | AB68: =IF(ISNUMBER($M68),$M68,0) | AD68: =IF($R68="",0,IF($AA68>0,$AB68*SUMIF(⑳商品別1食労務費!$C$5:$C$124,$R68,⑳商品別1食労務費!$F$5:$F$124)/$AA68,$AB68/$X68)) | AE68: =IF($S68="",0,IF($AA68>0,$AB68*SUMIF(⑳商品別1食労務費!$C$5:$C$124,$S68,⑳商品別1食労務費!$F$5:$F$124)/$AA68,$AB68/$X68)) | AF68: =IF($T68="",0,IF($AA68>0,$AB68*SUMIF(⑳商品別1食労務費!$C$5:$C$124,$T68,⑳商品別1食労務費!$F$5:$F$124)/$AA68,$AB68/$X68)) | AG68: =IF($U68="",0,IF($AA68>0,$AB68*SUMIF(⑳商品別1食労務費!$C$5:$C$124,$U68,⑳商品別1食労務費!$F$5:$F$124)/$AA68,$AB68/$X68)) | AH68: =IF($V68="",0,IF($AA68>0,$AB68*SUMIF(⑳商品別1食労務費!$C$5:$C$124,$V68,⑳商品別1食労務費!$F$5:$F$124)/$AA68,$AB68/$X68)) | AI68: =IF($W68="",0,IF($AA68>0,$AB68*SUMIF(⑳商品別1食労務費!$C$5:$C$124,$W68,⑳商品別1食労務費!$F$5:$F$124)/$AA68,$AB68/$X68))
A69: 65 | B69: 釜製造 | C69: 卵プリン液 | K69: =IF(F69>0,I69/(F69/60),0) | L69: =IF(AND(ISNUMBER(F69),J69>0),J69/(F69/60),"") | M69: =IF(OR(ISNUMBER(SEARCH("サニテーション",C69)),ISNUMBER(SEARCH("客注",C69)),ISNUMBER(SEARCH("切り替え",C69)),ISNUMBER(SEARCH("切替",C69)),NOT(ISNUMBER(H69))),"",IF(ISNUMBER(G69),G69/60*H69*④前提設定!$B$4,IF(AND(G69="",ISNUMBER(F69)),F69/60*H69*④前提設定!$B$4,""))) | N69: =IF(I69>0,M69/I69,"") | O69: =IF(AND(J69>0,ISNUMBER(M69)),M69/J69,"") | R69: Ｓホイップの卵プリン | S69: 自社製ホイップの卵プリン | T69: ホイップの卵プリン | X69: =COUNTA(R69:W69) | Y69: =IF(AND($X69>0,ISNUMBER($M69)),$M69/$X69,"") | Z69: =IF($X69=0,"",IF(COUNTIF(⑳商品別1食労務費!$C$5:$C$124,$R69)+COUNTIF(⑳商品別1食労務費!$C$5:$C$124,$S69)+COUNTIF(⑳商品別1食労務費!$C$5:$C$124,$T69)+COUNTIF(⑳商品別1食労務費!$C$5:$C$124,$U69)+COUNTIF(⑳商品別1食労務費!$C$5:$C$124,$V69)+COUNTIF(⑳商品別1食労務費!$C$5:$C$124,$W69)=$X69,"OK","⑳に無い商品名")) | AA69: =SUMIF(⑳商品別1食労務費!$C$5:$C$124,$R69,⑳商品別1食労務費!$F$5:$F$124)+SUMIF(⑳商品別1食労務費!$C$5:$C$124,$S69,⑳商品別1食労務費!$F$5:$F$124)+SUMIF(⑳商品別1食労務費!$C$5:$C$124,$T69,⑳商品別1食労務費!$F$5:$F$124)+SUMIF(⑳商品別1食労務費!$C$5:$C$124,$U69,⑳商品別1食労務費!$F$5:$F$124)+SUMIF(⑳商品別1食労務費!$C$5:$C$124,$V69,⑳商品別1食労務費!$F$5:$F$124)+SUMIF(⑳商品別1食労務費!$C$5:$C$124,$W69,⑳商品別1食労務費!$F$5:$F$124) | AB69: =IF(ISNUMBER($M69),$M69,0) | AD69: =IF($R69="",0,IF($AA69>0,$AB69*SUMIF(⑳商品別1食労務費!$C$5:$C$124,$R69,⑳商品別1食労務費!$F$5:$F$124)/$AA69,$AB69/$X69)) | AE69: =IF($S69="",0,IF($AA69>0,$AB69*SUMIF(⑳商品別1食労務費!$C$5:$C$124,$S69,⑳商品別1食労務費!$F$5:$F$124)/$AA69,$AB69/$X69)) | AF69: =IF($T69="",0,IF($AA69>0,$AB69*SUMIF(⑳商品別1食労務費!$C$5:$C$124,$T69,⑳商品別1食労務費!$F$5:$F$124)/$AA69,$AB69/$X69)) | AG69: =IF($U69="",0,IF($AA69>0,$AB69*SUMIF(⑳商品別1食労務費!$C$5:$C$124,$U69,⑳商品別1食労務費!$F$5:$F$124)/$AA69,$AB69/$X69)) | AH69: =IF($V69="",0,IF($AA69>0,$AB69*SUMIF(⑳商品別1食労務費!$C$5:$C$124,$V69,⑳商品別1食労務費!$F$5:$F$124)/$AA69,$AB69/$X69)) | AI69: =IF($W69="",0,IF($AA69>0,$AB69*SUMIF(⑳商品別1食労務費!$C$5:$C$124,$W69,⑳商品別1食労務費!$F$5:$F$124)/$AA69,$AB69/$X69))
A70: 66 | B70: 釜製造 | C70: プリンソース | K70: =IF(F70>0,I70/(F70/60),0) | L70: =IF(AND(ISNUMBER(F70),J70>0),J70/(F70/60),"") | M70: =IF(OR(ISNUMBER(SEARCH("サニテーション",C70)),ISNUMBER(SEARCH("客注",C70)),ISNUMBER(SEARCH("切り替え",C70)),ISNUMBER(SEARCH("切替",C70)),NOT(ISNUMBER(H70))),"",IF(ISNUMBER(G70),G70/60*H70*④前提設定!$B$4,IF(AND(G70="",ISNUMBER(F70)),F70/60*H70*④前提設定!$B$4,""))) | N70: =IF(I70>0,M70/I70,"") | O70: =IF(AND(J70>0,ISNUMBER(M70)),M70/J70,"") | R70: Ｓホイップの卵プリン | S70: ホイップの卵プリン | X70: =COUNTA(R70:W70) | Y70: =IF(AND($X70>0,ISNUMBER($M70)),$M70/$X70,"") | Z70: =IF($X70=0,"",IF(COUNTIF(⑳商品別1食労務費!$C$5:$C$124,$R70)+COUNTIF(⑳商品別1食労務費!$C$5:$C$124,$S70)+COUNTIF(⑳商品別1食労務費!$C$5:$C$124,$T70)+COUNTIF(⑳商品別1食労務費!$C$5:$C$124,$U70)+COUNTIF(⑳商品別1食労務費!$C$5:$C$124,$V70)+COUNTIF(⑳商品別1食労務費!$C$5:$C$124,$W70)=$X70,"OK","⑳に無い商品名")) | AA70: =SUMIF(⑳商品別1食労務費!$C$5:$C$124,$R70,⑳商品別1食労務費!$F$5:$F$124)+SUMIF(⑳商品別1食労務費!$C$5:$C$124,$S70,⑳商品別1食労務費!$F$5:$F$124)+SUMIF(⑳商品別1食労務費!$C$5:$C$124,$T70,⑳商品別1食労務費!$F$5:$F$124)+SUMIF(⑳商品別1食労務費!$C$5:$C$124,$U70,⑳商品別1食労務費!$F$5:$F$124)+SUMIF(⑳商品別1食労務費!$C$5:$C$124,$V70,⑳商品別1食労務費!$F$5:$F$124)+SUMIF(⑳商品別1食労務費!$C$5:$C$124,$W70,⑳商品別1食労務費!$F$5:$F$124) | AB70: =IF(ISNUMBER($M70),$M70,0) | AD70: =IF($R70="",0,IF($AA70>0,$AB70*SUMIF(⑳商品別1食労務費!$C$5:$C$124,$R70,⑳商品別1食労務費!$F$5:$F$124)/$AA70,$AB70/$X70)) | AE70: =IF($S70="",0,IF($AA70>0,$AB70*SUMIF(⑳商品別1食労務費!$C$5:$C$124,$S70,⑳商品別1食労務費!$F$5:$F$124)/$AA70,$AB70/$X70)) | AF70: =IF($T70="",0,IF($AA70>0,$AB70*SUMIF(⑳商品別1食労務費!$C$5:$C$124,$T70,⑳商品別1食労務費!$F$5:$F$124)/$AA70,$AB70/$X70)) | AG70: =IF($U70="",0,IF($AA70>0,$AB70*SUMIF(⑳商品別1食労務費!$C$5:$C$124,$U70,⑳商品別1食労務費!$F$5:$F$124)/$AA70,$AB70/$X70)) | AH70: =IF($V70="",0,IF($AA70>0,$AB70*SUMIF(⑳商品別1食労務費!$C$5:$C$124,$V70,⑳商品別1食労務費!$F$5:$F$124)/$AA70,$AB70/$X70)) | AI70: =IF($W70="",0,IF($AA70>0,$AB70*SUMIF(⑳商品別1食労務費!$C$5:$C$124,$W70,⑳商品別1食労務費!$F$5:$F$124)/$AA70,$AB70/$X70))
A71: 67 | B71: 釜製造 | C71: みかん牛乳寒天 | K71: =IF(F71>0,I71/(F71/60),0) | L71: =IF(AND(ISNUMBER(F71),J71>0),J71/(F71/60),"") | M71: =IF(OR(ISNUMBER(SEARCH("サニテーション",C71)),ISNUMBER(SEARCH("客注",C71)),ISNUMBER(SEARCH("切り替え",C71)),ISNUMBER(SEARCH("切替",C71)),NOT(ISNUMBER(H71))),"",IF(ISNUMBER(G71),G71/60*H71*④前提設定!$B$4,IF(AND(G71="",ISNUMBER(F71)),F71/60*H71*④前提設定!$B$4,""))) | N71: =IF(I71>0,M71/I71,"") | O71: =IF(AND(J71>0,ISNUMBER(M71)),M71/J71,"") | R71: みかんの牛乳寒天２ | S71: みかんの牛乳寒天 小 | T71: Ｓみかんの牛乳寒天 小 | X71: =COUNTA(R71:W71) | Y71: =IF(AND($X71>0,ISNUMBER($M71)),$M71/$X71,"") | Z71: =IF($X71=0,"",IF(COUNTIF(⑳商品別1食労務費!$C$5:$C$124,$R71)+COUNTIF(⑳商品別1食労務費!$C$5:$C$124,$S71)+COUNTIF(⑳商品別1食労務費!$C$5:$C$124,$T71)+COUNTIF(⑳商品別1食労務費!$C$5:$C$124,$U71)+COUNTIF(⑳商品別1食労務費!$C$5:$C$124,$V71)+COUNTIF(⑳商品別1食労務費!$C$5:$C$124,$W71)=$X71,"OK","⑳に無い商品名")) | AA71: =SUMIF(⑳商品別1食労務費!$C$5:$C$124,$R71,⑳商品別1食労務費!$F$5:$F$124)+SUMIF(⑳商品別1食労務費!$C$5:$C$124,$S71,⑳商品別1食労務費!$F$5:$F$124)+SUMIF(⑳商品別1食労務費!$C$5:$C$124,$T71,⑳商品別1食労務費!$F$5:$F$124)+SUMIF(⑳商品別1食労務費!$C$5:$C$124,$U71,⑳商品別1食労務費!$F$5:$F$124)+SUMIF(⑳商品別1食労務費!$C$5:$C$124,$V71,⑳商品別1食労務費!$F$5:$F$124)+SUMIF(⑳商品別1食労務費!$C$5:$C$124,$W71,⑳商品別1食労務費!$F$5:$F$124) | AB71: =IF(ISNUMBER($M71),$M71,0) | AD71: =IF($R71="",0,IF($AA71>0,$AB71*SUMIF(⑳商品別1食労務費!$C$5:$C$124,$R71,⑳商品別1食労務費!$F$5:$F$124)/$AA71,$AB71/$X71)) | AE71: =IF($S71="",0,IF($AA71>0,$AB71*SUMIF(⑳商品別1食労務費!$C$5:$C$124,$S71,⑳商品別1食労務費!$F$5:$F$124)/$AA71,$AB71/$X71)) | AF71: =IF($T71="",0,IF($AA71>0,$AB71*SUMIF(⑳商品別1食労務費!$C$5:$C$124,$T71,⑳商品別1食労務費!$F$5:$F$124)/$AA71,$AB71/$X71)) | AG71: =IF($U71="",0,IF($AA71>0,$AB71*SUMIF(⑳商品別1食労務費!$C$5:$C$124,$U71,⑳商品別1食労務費!$F$5:$F$124)/$AA71,$AB71/$X71)) | AH71: =IF($V71="",0,IF($AA71>0,$AB71*SUMIF(⑳商品別1食労務費!$C$5:$C$124,$V71,⑳商品別1食労務費!$F$5:$F$124)/$AA71,$AB71/$X71)) | AI71: =IF($W71="",0,IF($AA71>0,$AB71*SUMIF(⑳商品別1食労務費!$C$5:$C$124,$W71,⑳商品別1食労務費!$F$5:$F$124)/$AA71,$AB71/$X71))
A72: 68 | B72: 釜製造 | C72: みかん牛乳寒天液 | K72: =IF(F72>0,I72/(F72/60),0) | L72: =IF(AND(ISNUMBER(F72),J72>0),J72/(F72/60),"") | M72: =IF(OR(ISNUMBER(SEARCH("サニテーション",C72)),ISNUMBER(SEARCH("客注",C72)),ISNUMBER(SEARCH("切り替え",C72)),ISNUMBER(SEARCH("切替",C72)),NOT(ISNUMBER(H72))),"",IF(ISNUMBER(G72),G72/60*H72*④前提設定!$B$4,IF(AND(G72="",ISNUMBER(F72)),F72/60*H72*④前提設定!$B$4,""))) | N72: =IF(I72>0,M72/I72,"") | O72: =IF(AND(J72>0,ISNUMBER(M72)),M72/J72,"") | R72: みかんの牛乳寒天２ | S72: みかんの牛乳寒天 小 | T72: Ｓみかんの牛乳寒天 小 | X72: =COUNTA(R72:W72) | Y72: =IF(AND($X72>0,ISNUMBER($M72)),$M72/$X72,"") | Z72: =IF($X72=0,"",IF(COUNTIF(⑳商品別1食労務費!$C$5:$C$124,$R72)+COUNTIF(⑳商品別1食労務費!$C$5:$C$124,$S72)+COUNTIF(⑳商品別1食労務費!$C$5:$C$124,$T72)+COUNTIF(⑳商品別1食労務費!$C$5:$C$124,$U72)+COUNTIF(⑳商品別1食労務費!$C$5:$C$124,$V72)+COUNTIF(⑳商品別1食労務費!$C$5:$C$124,$W72)=$X72,"OK","⑳に無い商品名")) | AA72: =SUMIF(⑳商品別1食労務費!$C$5:$C$124,$R72,⑳商品別1食労務費!$F$5:$F$124)+SUMIF(⑳商品別1食労務費!$C$5:$C$124,$S72,⑳商品別1食労務費!$F$5:$F$124)+SUMIF(⑳商品別1食労務費!$C$5:$C$124,$T72,⑳商品別1食労務費!$F$5:$F$124)+SUMIF(⑳商品別1食労務費!$C$5:$C$124,$U72,⑳商品別1食労務費!$F$5:$F$124)+SUMIF(⑳商品別1食労務費!$C$5:$C$124,$V72,⑳商品別1食労務費!$F$5:$F$124)+SUMIF(⑳商品別1食労務費!$C$5:$C$124,$W72,⑳商品別1食労務費!$F$5:$F$124) | AB72: =IF(ISNUMBER($M72),$M72,0) | AD72: =IF($R72="",0,IF($AA72>0,$AB72*SUMIF(⑳商品別1食労務費!$C$5:$C$124,$R72,⑳商品別1食労務費!$F$5:$F$124)/$AA72,$AB72/$X72)) | AE72: =IF($S72="",0,IF($AA72>0,$AB72*SUMIF(⑳商品別1食労務費!$C$5:$C$124,$S72,⑳商品別1食労務費!$F$5:$F$124)/$AA72,$AB72/$X72)) | AF72: =IF($T72="",0,IF($AA72>0,$AB72*SUMIF(⑳商品別1食労務費!$C$5:$C$124,$T72,⑳商品別1食労務費!$F$5:$F$124)/$AA72,$AB72/$X72)) | AG72: =IF($U72="",0,IF($AA72>0,$AB72*SUMIF(⑳商品別1食労務費!$C$5:$C$124,$U72,⑳商品別1食労務費!$F$5:$F$124)/$AA72,$AB72/$X72)) | AH72: =IF($V72="",0,IF($AA72>0,$AB72*SUMIF(⑳商品別1食労務費!$C$5:$C$124,$V72,⑳商品別1食労務費!$F$5:$F$124)/$AA72,$AB72/$X72)) | AI72: =IF($W72="",0,IF($AA72>0,$AB72*SUMIF(⑳商品別1食労務費!$C$5:$C$124,$W72,⑳商品別1食労務費!$F$5:$F$124)/$AA72,$AB72/$X72))
A73: 69 | B73: 釜製造 | C73: みかん缶 | K73: =IF(F73>0,I73/(F73/60),0) | L73: =IF(AND(ISNUMBER(F73),J73>0),J73/(F73/60),"") | M73: =IF(OR(ISNUMBER(SEARCH("サニテーション",C73)),ISNUMBER(SEARCH("客注",C73)),ISNUMBER(SEARCH("切り替え",C73)),ISNUMBER(SEARCH("切替",C73)),NOT(ISNUMBER(H73))),"",IF(ISNUMBER(G73),G73/60*H73*④前提設定!$B$4,IF(AND(G73="",ISNUMBER(F73)),F73/60*H73*④前提設定!$B$4,""))) | N73: =IF(I73>0,M73/I73,"") | O73: =IF(AND(J73>0,ISNUMBER(M73)),M73/J73,"") | R73: みかんの牛乳寒天２ | S73: みかんの牛乳寒天 小 | T73: Ｓみかんの牛乳寒天 小 | X73: =COUNTA(R73:W73) | Y73: =IF(AND($X73>0,ISNUMBER($M73)),$M73/$X73,"") | Z73: =IF($X73=0,"",IF(COUNTIF(⑳商品別1食労務費!$C$5:$C$124,$R73)+COUNTIF(⑳商品別1食労務費!$C$5:$C$124,$S73)+COUNTIF(⑳商品別1食労務費!$C$5:$C$124,$T73)+COUNTIF(⑳商品別1食労務費!$C$5:$C$124,$U73)+COUNTIF(⑳商品別1食労務費!$C$5:$C$124,$V73)+COUNTIF(⑳商品別1食労務費!$C$5:$C$124,$W73)=$X73,"OK","⑳に無い商品名")) | AA73: =SUMIF(⑳商品別1食労務費!$C$5:$C$124,$R73,⑳商品別1食労務費!$F$5:$F$124)+SUMIF(⑳商品別1食労務費!$C$5:$C$124,$S73,⑳商品別1食労務費!$F$5:$F$124)+SUMIF(⑳商品別1食労務費!$C$5:$C$124,$T73,⑳商品別1食労務費!$F$5:$F$124)+SUMIF(⑳商品別1食労務費!$C$5:$C$124,$U73,⑳商品別1食労務費!$F$5:$F$124)+SUMIF(⑳商品別1食労務費!$C$5:$C$124,$V73,⑳商品別1食労務費!$F$5:$F$124)+SUMIF(⑳商品別1食労務費!$C$5:$C$124,$W73,⑳商品別1食労務費!$F$5:$F$124) | AB73: =IF(ISNUMBER($M73),$M73,0) | AD73: =IF($R73="",0,IF($AA73>0,$AB73*SUMIF(⑳商品別1食労務費!$C$5:$C$124,$R73,⑳商品別1食労務費!$F$5:$F$124)/$AA73,$AB73/$X73)) | AE73: =IF($S73="",0,IF($AA73>0,$AB73*SUMIF(⑳商品別1食労務費!$C$5:$C$124,$S73,⑳商品別1食労務費!$F$5:$F$124)/$AA73,$AB73/$X73)) | AF73: =IF($T73="",0,IF($AA73>0,$AB73*SUMIF(⑳商品別1食労務費!$C$5:$C$124,$T73,⑳商品別1食労務費!$F$5:$F$124)/$AA73,$AB73/$X73)) | AG73: =IF($U73="",0,IF($AA73>0,$AB73*SUMIF(⑳商品別1食労務費!$C$5:$C$124,$U73,⑳商品別1食労務費!$F$5:$F$124)/$AA73,$AB73/$X73)) | AH73: =IF($V73="",0,IF($AA73>0,$AB73*SUMIF(⑳商品別1食労務費!$C$5:$C$124,$V73,⑳商品別1食労務費!$F$5:$F$124)/$AA73,$AB73/$X73)) | AI73: =IF($W73="",0,IF($AA73>0,$AB73*SUMIF(⑳商品別1食労務費!$C$5:$C$124,$W73,⑳商品別1食労務費!$F$5:$F$124)/$AA73,$AB73/$X73))
A74: 70 | B74: 釜製造 | C74: プリンロール | K74: - | L74: =IF(AND(ISNUMBER(F74),J74>0),J74/(F74/60),"") | M74: =IF(OR(ISNUMBER(SEARCH("サニテーション",C74)),ISNUMBER(SEARCH("客注",C74)),ISNUMBER(SEARCH("切り替え",C74)),ISNUMBER(SEARCH("切替",C74)),NOT(ISNUMBER(H74))),"",IF(ISNUMBER(G74),G74/60*H74*④前提設定!$B$4,IF(AND(G74="",ISNUMBER(F74)),F74/60*H74*④前提設定!$B$4,""))) | N74: - | O74: =IF(AND(J74>0,ISNUMBER(M74)),M74/J74,"") | R74: Ｓホイップの卵プリン | S74: ホイップの卵プリン | X74: =COUNTA(R74:W74) | Y74: =IF(AND($X74>0,ISNUMBER($M74)),$M74/$X74,"") | Z74: =IF($X74=0,"",IF(COUNTIF(⑳商品別1食労務費!$C$5:$C$124,$R74)+COUNTIF(⑳商品別1食労務費!$C$5:$C$124,$S74)+COUNTIF(⑳商品別1食労務費!$C$5:$C$124,$T74)+COUNTIF(⑳商品別1食労務費!$C$5:$C$124,$U74)+COUNTIF(⑳商品別1食労務費!$C$5:$C$124,$V74)+COUNTIF(⑳商品別1食労務費!$C$5:$C$124,$W74)=$X74,"OK","⑳に無い商品名")) | AA74: =SUMIF(⑳商品別1食労務費!$C$5:$C$124,$R74,⑳商品別1食労務費!$F$5:$F$124)+SUMIF(⑳商品別1食労務費!$C$5:$C$124,$S74,⑳商品別1食労務費!$F$5:$F$124)+SUMIF(⑳商品別1食労務費!$C$5:$C$124,$T74,⑳商品別1食労務費!$F$5:$F$124)+SUMIF(⑳商品別1食労務費!$C$5:$C$124,$U74,⑳商品別1食労務費!$F$5:$F$124)+SUMIF(⑳商品別1食労務費!$C$5:$C$124,$V74,⑳商品別1食労務費!$F$5:$F$124)+SUMIF(⑳商品別1食労務費!$C$5:$C$124,$W74,⑳商品別1食労務費!$F$5:$F$124) | AB74: =IF(ISNUMBER($M74),$M74,0) | AD74: =IF($R74="",0,IF($AA74>0,$AB74*SUMIF(⑳商品別1食労務費!$C$5:$C$124,$R74,⑳商品別1食労務費!$F$5:$F$124)/$AA74,$AB74/$X74)) | AE74: =IF($S74="",0,IF($AA74>0,$AB74*SUMIF(⑳商品別1食労務費!$C$5:$C$124,$S74,⑳商品別1食労務費!$F$5:$F$124)/$AA74,$AB74/$X74)) | AF74: =IF($T74="",0,IF($AA74>0,$AB74*SUMIF(⑳商品別1食労務費!$C$5:$C$124,$T74,⑳商品別1食労務費!$F$5:$F$124)/$AA74,$AB74/$X74)) | AG74: =IF($U74="",0,IF($AA74>0,$AB74*SUMIF(⑳商品別1食労務費!$C$5:$C$124,$U74,⑳商品別1食労務費!$F$5:$F$124)/$AA74,$AB74/$X74)) | AH74: =IF($V74="",0,IF($AA74>0,$AB74*SUMIF(⑳商品別1食労務費!$C$5:$C$124,$V74,⑳商品別1食労務費!$F$5:$F$124)/$AA74,$AB74/$X74)) | AI74: =IF($W74="",0,IF($AA74>0,$AB74*SUMIF(⑳商品別1食労務費!$C$5:$C$124,$W74,⑳商品別1食労務費!$F$5:$F$124)/$AA74,$AB74/$X74))
A75: 71 | B75: 釜製造 | C75: プリンロール内製ホイップ | K75: =IF(F75>0,I75/(F75/60),0) | L75: =IF(AND(ISNUMBER(F75),J75>0),J75/(F75/60),"") | M75: =IF(OR(ISNUMBER(SEARCH("サニテーション",C75)),ISNUMBER(SEARCH("客注",C75)),ISNUMBER(SEARCH("切り替え",C75)),ISNUMBER(SEARCH("切替",C75)),NOT(ISNUMBER(H75))),"",IF(ISNUMBER(G75),G75/60*H75*④前提設定!$B$4,IF(AND(G75="",ISNUMBER(F75)),F75/60*H75*④前提設定!$B$4,""))) | N75: =IF(I75>0,M75/I75,"") | O75: =IF(AND(J75>0,ISNUMBER(M75)),M75/J75,"") | R75: 自社製ホイップの卵プリン | S75: Ｓホイップの卵プリン | T75: ホイップの卵プリン | X75: =COUNTA(R75:W75) | Y75: =IF(AND($X75>0,ISNUMBER($M75)),$M75/$X75,"") | Z75: =IF($X75=0,"",IF(COUNTIF(⑳商品別1食労務費!$C$5:$C$124,$R75)+COUNTIF(⑳商品別1食労務費!$C$5:$C$124,$S75)+COUNTIF(⑳商品別1食労務費!$C$5:$C$124,$T75)+COUNTIF(⑳商品別1食労務費!$C$5:$C$124,$U75)+COUNTIF(⑳商品別1食労務費!$C$5:$C$124,$V75)+COUNTIF(⑳商品別1食労務費!$C$5:$C$124,$W75)=$X75,"OK","⑳に無い商品名")) | AA75: =SUMIF(⑳商品別1食労務費!$C$5:$C$124,$R75,⑳商品別1食労務費!$F$5:$F$124)+SUMIF(⑳商品別1食労務費!$C$5:$C$124,$S75,⑳商品別1食労務費!$F$5:$F$124)+SUMIF(⑳商品別1食労務費!$C$5:$C$124,$T75,⑳商品別1食労務費!$F$5:$F$124)+SUMIF(⑳商品別1食労務費!$C$5:$C$124,$U75,⑳商品別1食労務費!$F$5:$F$124)+SUMIF(⑳商品別1食労務費!$C$5:$C$124,$V75,⑳商品別1食労務費!$F$5:$F$124)+SUMIF(⑳商品別1食労務費!$C$5:$C$124,$W75,⑳商品別1食労務費!$F$5:$F$124) | AB75: =IF(ISNUMBER($M75),$M75,0) | AD75: =IF($R75="",0,IF($AA75>0,$AB75*SUMIF(⑳商品別1食労務費!$C$5:$C$124,$R75,⑳商品別1食労務費!$F$5:$F$124)/$AA75,$AB75/$X75)) | AE75: =IF($S75="",0,IF($AA75>0,$AB75*SUMIF(⑳商品別1食労務費!$C$5:$C$124,$S75,⑳商品別1食労務費!$F$5:$F$124)/$AA75,$AB75/$X75)) | AF75: =IF($T75="",0,IF($AA75>0,$AB75*SUMIF(⑳商品別1食労務費!$C$5:$C$124,$T75,⑳商品別1食労務費!$F$5:$F$124)/$AA75,$AB75/$X75)) | AG75: =IF($U75="",0,IF($AA75>0,$AB75*SUMIF(⑳商品別1食労務費!$C$5:$C$124,$U75,⑳商品別1食労務費!$F$5:$F$124)/$AA75,$AB75/$X75)) | AH75: =IF($V75="",0,IF($AA75>0,$AB75*SUMIF(⑳商品別1食労務費!$C$5:$C$124,$V75,⑳商品別1食労務費!$F$5:$F$124)/$AA75,$AB75/$X75)) | AI75: =IF($W75="",0,IF($AA75>0,$AB75*SUMIF(⑳商品別1食労務費!$C$5:$C$124,$W75,⑳商品別1食労務費!$F$5:$F$124)/$AA75,$AB75/$X75))
A76: 72 | B76: 釜製造 | C76: プリンロール（ロール生地作成） | K76: =IF(F76>0,I76/(F76/60),0) | L76: =IF(AND(ISNUMBER(F76),J76>0),J76/(F76/60),"") | M76: =IF(OR(ISNUMBER(SEARCH("サニテーション",C76)),ISNUMBER(SEARCH("客注",C76)),ISNUMBER(SEARCH("切り替え",C76)),ISNUMBER(SEARCH("切替",C76)),NOT(ISNUMBER(H76))),"",IF(ISNUMBER(G76),G76/60*H76*④前提設定!$B$4,IF(AND(G76="",ISNUMBER(F76)),F76/60*H76*④前提設定!$B$4,""))) | N76: =IF(I76>0,M76/I76,"") | O76: =IF(AND(J76>0,ISNUMBER(M76)),M76/J76,"") | R76: Ｓクリーム爆盛ロールケキ小 | S76: クリーム爆盛ロールケーキ大 | X76: =COUNTA(R76:W76) | Y76: =IF(AND($X76>0,ISNUMBER($M76)),$M76/$X76,"") | Z76: =IF($X76=0,"",IF(COUNTIF(⑳商品別1食労務費!$C$5:$C$124,$R76)+COUNTIF(⑳商品別1食労務費!$C$5:$C$124,$S76)+COUNTIF(⑳商品別1食労務費!$C$5:$C$124,$T76)+COUNTIF(⑳商品別1食労務費!$C$5:$C$124,$U76)+COUNTIF(⑳商品別1食労務費!$C$5:$C$124,$V76)+COUNTIF(⑳商品別1食労務費!$C$5:$C$124,$W76)=$X76,"OK","⑳に無い商品名")) | AA76: =SUMIF(⑳商品別1食労務費!$C$5:$C$124,$R76,⑳商品別1食労務費!$F$5:$F$124)+SUMIF(⑳商品別1食労務費!$C$5:$C$124,$S76,⑳商品別1食労務費!$F$5:$F$124)+SUMIF(⑳商品別1食労務費!$C$5:$C$124,$T76,⑳商品別1食労務費!$F$5:$F$124)+SUMIF(⑳商品別1食労務費!$C$5:$C$124,$U76,⑳商品別1食労務費!$F$5:$F$124)+SUMIF(⑳商品別1食労務費!$C$5:$C$124,$V76,⑳商品別1食労務費!$F$5:$F$124)+SUMIF(⑳商品別1食労務費!$C$5:$C$124,$W76,⑳商品別1食労務費!$F$5:$F$124) | AB76: =IF(ISNUMBER($M76),$M76,0) | AD76: =IF($R76="",0,IF($AA76>0,$AB76*SUMIF(⑳商品別1食労務費!$C$5:$C$124,$R76,⑳商品別1食労務費!$F$5:$F$124)/$AA76,$AB76/$X76)) | AE76: =IF($S76="",0,IF($AA76>0,$AB76*SUMIF(⑳商品別1食労務費!$C$5:$C$124,$S76,⑳商品別1食労務費!$F$5:$F$124)/$AA76,$AB76/$X76)) | AF76: =IF($T76="",0,IF($AA76>0,$AB76*SUMIF(⑳商品別1食労務費!$C$5:$C$124,$T76,⑳商品別1食労務費!$F$5:$F$124)/$AA76,$AB76/$X76)) | AG76: =IF($U76="",0,IF($AA76>0,$AB76*SUMIF(⑳商品別1食労務費!$C$5:$C$124,$U76,⑳商品別1食労務費!$F$5:$F$124)/$AA76,$AB76/$X76)) | AH76: =IF($V76="",0,IF($AA76>0,$AB76*SUMIF(⑳商品別1食労務費!$C$5:$C$124,$V76,⑳商品別1食労務費!$F$5:$F$124)/$AA76,$AB76/$X76)) | AI76: =IF($W76="",0,IF($AA76>0,$AB76*SUMIF(⑳商品別1食労務費!$C$5:$C$124,$W76,⑳商品別1食労務費!$F$5:$F$124)/$AA76,$AB76/$X76))
A77: 73 | B77: 釜製造 | C77: プリンタブレット加熱 | K77: =IF(F77>0,I77/(F77/60),0) | L77: =IF(AND(ISNUMBER(F77),J77>0),J77/(F77/60),"") | M77: =IF(OR(ISNUMBER(SEARCH("サニテーション",C77)),ISNUMBER(SEARCH("客注",C77)),ISNUMBER(SEARCH("切り替え",C77)),ISNUMBER(SEARCH("切替",C77)),NOT(ISNUMBER(H77))),"",IF(ISNUMBER(G77),G77/60*H77*④前提設定!$B$4,IF(AND(G77="",ISNUMBER(F77)),F77/60*H77*④前提設定!$B$4,""))) | N77: =IF(I77>0,M77/I77,"") | O77: =IF(AND(J77>0,ISNUMBER(M77)),M77/J77,"") | R77: Ｓホイップの卵プリン | S77: 自社製ホイップの卵プリン | T77: ホイップの卵プリン | X77: =COUNTA(R77:W77) | Y77: =IF(AND($X77>0,ISNUMBER($M77)),$M77/$X77,"") | Z77: =IF($X77=0,"",IF(COUNTIF(⑳商品別1食労務費!$C$5:$C$124,$R77)+COUNTIF(⑳商品別1食労務費!$C$5:$C$124,$S77)+COUNTIF(⑳商品別1食労務費!$C$5:$C$124,$T77)+COUNTIF(⑳商品別1食労務費!$C$5:$C$124,$U77)+COUNTIF(⑳商品別1食労務費!$C$5:$C$124,$V77)+COUNTIF(⑳商品別1食労務費!$C$5:$C$124,$W77)=$X77,"OK","⑳に無い商品名")) | AA77: =SUMIF(⑳商品別1食労務費!$C$5:$C$124,$R77,⑳商品別1食労務費!$F$5:$F$124)+SUMIF(⑳商品別1食労務費!$C$5:$C$124,$S77,⑳商品別1食労務費!$F$5:$F$124)+SUMIF(⑳商品別1食労務費!$C$5:$C$124,$T77,⑳商品別1食労務費!$F$5:$F$124)+SUMIF(⑳商品別1食労務費!$C$5:$C$124,$U77,⑳商品別1食労務費!$F$5:$F$124)+SUMIF(⑳商品別1食労務費!$C$5:$C$124,$V77,⑳商品別1食労務費!$F$5:$F$124)+SUMIF(⑳商品別1食労務費!$C$5:$C$124,$W77,⑳商品別1食労務費!$F$5:$F$124) | AB77: =IF(ISNUMBER($M77),$M77,0) | AD77: =IF($R77="",0,IF($AA77>0,$AB77*SUMIF(⑳商品別1食労務費!$C$5:$C$124,$R77,⑳商品別1食労務費!$F$5:$F$124)/$AA77,$AB77/$X77)) | AE77: =IF($S77="",0,IF($AA77>0,$AB77*SUMIF(⑳商品別1食労務費!$C$5:$C$124,$S77,⑳商品別1食労務費!$F$5:$F$124)/$AA77,$AB77/$X77)) | AF77: =IF($T77="",0,IF($AA77>0,$AB77*SUMIF(⑳商品別1食労務費!$C$5:$C$124,$T77,⑳商品別1食労務費!$F$5:$F$124)/$AA77,$AB77/$X77)) | AG77: =IF($U77="",0,IF($AA77>0,$AB77*SUMIF(⑳商品別1食労務費!$C$5:$C$124,$U77,⑳商品別1食労務費!$F$5:$F$124)/$AA77,$AB77/$X77)) | AH77: =IF($V77="",0,IF($AA77>0,$AB77*SUMIF(⑳商品別1食労務費!$C$5:$C$124,$V77,⑳商品別1食労務費!$F$5:$F$124)/$AA77,$AB77/$X77)) | AI77: =IF($W77="",0,IF($AA77>0,$AB77*SUMIF(⑳商品別1食労務費!$C$5:$C$124,$W77,⑳商品別1食労務費!$F$5:$F$124)/$AA77,$AB77/$X77))
A78: 74 | B78: 釜製造 | C78: プリン液加熱 | K78: =IF(F78>0,I78/(F78/60),0) | L78: =IF(AND(ISNUMBER(F78),J78>0),J78/(F78/60),"") | M78: =IF(OR(ISNUMBER(SEARCH("サニテーション",C78)),ISNUMBER(SEARCH("客注",C78)),ISNUMBER(SEARCH("切り替え",C78)),ISNUMBER(SEARCH("切替",C78)),NOT(ISNUMBER(H78))),"",IF(ISNUMBER(G78),G78/60*H78*④前提設定!$B$4,IF(AND(G78="",ISNUMBER(F78)),F78/60*H78*④前提設定!$B$4,""))) | N78: =IF(I78>0,M78/I78,"") | O78: =IF(AND(J78>0,ISNUMBER(M78)),M78/J78,"") | R78: Ｓホイップの卵プリン | S78: ホイップの卵プリン | X78: =COUNTA(R78:W78) | Y78: =IF(AND($X78>0,ISNUMBER($M78)),$M78/$X78,"") | Z78: =IF($X78=0,"",IF(COUNTIF(⑳商品別1食労務費!$C$5:$C$124,$R78)+COUNTIF(⑳商品別1食労務費!$C$5:$C$124,$S78)+COUNTIF(⑳商品別1食労務費!$C$5:$C$124,$T78)+COUNTIF(⑳商品別1食労務費!$C$5:$C$124,$U78)+COUNTIF(⑳商品別1食労務費!$C$5:$C$124,$V78)+COUNTIF(⑳商品別1食労務費!$C$5:$C$124,$W78)=$X78,"OK","⑳に無い商品名")) | AA78: =SUMIF(⑳商品別1食労務費!$C$5:$C$124,$R78,⑳商品別1食労務費!$F$5:$F$124)+SUMIF(⑳商品別1食労務費!$C$5:$C$124,$S78,⑳商品別1食労務費!$F$5:$F$124)+SUMIF(⑳商品別1食労務費!$C$5:$C$124,$T78,⑳商品別1食労務費!$F$5:$F$124)+SUMIF(⑳商品別1食労務費!$C$5:$C$124,$U78,⑳商品別1食労務費!$F$5:$F$124)+SUMIF(⑳商品別1食労務費!$C$5:$C$124,$V78,⑳商品別1食労務費!$F$5:$F$124)+SUMIF(⑳商品別1食労務費!$C$5:$C$124,$W78,⑳商品別1食労務費!$F$5:$F$124) | AB78: =IF(ISNUMBER($M78),$M78,0) | AD78: =IF($R78="",0,IF($AA78>0,$AB78*SUMIF(⑳商品別1食労務費!$C$5:$C$124,$R78,⑳商品別1食労務費!$F$5:$F$124)/$AA78,$AB78/$X78)) | AE78: =IF($S78="",0,IF($AA78>0,$AB78*SUMIF(⑳商品別1食労務費!$C$5:$C$124,$S78,⑳商品別1食労務費!$F$5:$F$124)/$AA78,$AB78/$X78)) | AF78: =IF($T78="",0,IF($AA78>0,$AB78*SUMIF(⑳商品別1食労務費!$C$5:$C$124,$T78,⑳商品別1食労務費!$F$5:$F$124)/$AA78,$AB78/$X78)) | AG78: =IF($U78="",0,IF($AA78>0,$AB78*SUMIF(⑳商品別1食労務費!$C$5:$C$124,$U78,⑳商品別1食労務費!$F$5:$F$124)/$AA78,$AB78/$X78)) | AH78: =IF($V78="",0,IF($AA78>0,$AB78*SUMIF(⑳商品別1食労務費!$C$5:$C$124,$V78,⑳商品別1食労務費!$F$5:$F$124)/$AA78,$AB78/$X78)) | AI78: =IF($W78="",0,IF($AA78>0,$AB78*SUMIF(⑳商品別1食労務費!$C$5:$C$124,$W78,⑳商品別1食労務費!$F$5:$F$124)/$AA78,$AB78/$X78))
A79: 75 | B79: 釜製造 | C79: まっしろミルクプリン | K79: =IF(F79>0,I79/(F79/60),0) | L79: =IF(AND(ISNUMBER(F79),J79>0),J79/(F79/60),"") | M79: =IF(OR(ISNUMBER(SEARCH("サニテーション",C79)),ISNUMBER(SEARCH("客注",C79)),ISNUMBER(SEARCH("切り替え",C79)),ISNUMBER(SEARCH("切替",C79)),NOT(ISNUMBER(H79))),"",IF(ISNUMBER(G79),G79/60*H79*④前提設定!$B$4,IF(AND(G79="",ISNUMBER(F79)),F79/60*H79*④前提設定!$B$4,""))) | N79: =IF(I79>0,M79/I79,"") | O79: =IF(AND(J79>0,ISNUMBER(M79)),M79/J79,"") | R79: まっしろミルクプリン３ | S79: Ｓまっしろミルクプリン小３ | X79: =COUNTA(R79:W79) | Y79: =IF(AND($X79>0,ISNUMBER($M79)),$M79/$X79,"") | Z79: =IF($X79=0,"",IF(COUNTIF(⑳商品別1食労務費!$C$5:$C$124,$R79)+COUNTIF(⑳商品別1食労務費!$C$5:$C$124,$S79)+COUNTIF(⑳商品別1食労務費!$C$5:$C$124,$T79)+COUNTIF(⑳商品別1食労務費!$C$5:$C$124,$U79)+COUNTIF(⑳商品別1食労務費!$C$5:$C$124,$V79)+COUNTIF(⑳商品別1食労務費!$C$5:$C$124,$W79)=$X79,"OK","⑳に無い商品名")) | AA79: =SUMIF(⑳商品別1食労務費!$C$5:$C$124,$R79,⑳商品別1食労務費!$F$5:$F$124)+SUMIF(⑳商品別1食労務費!$C$5:$C$124,$S79,⑳商品別1食労務費!$F$5:$F$124)+SUMIF(⑳商品別1食労務費!$C$5:$C$124,$T79,⑳商品別1食労務費!$F$5:$F$124)+SUMIF(⑳商品別1食労務費!$C$5:$C$124,$U79,⑳商品別1食労務費!$F$5:$F$124)+SUMIF(⑳商品別1食労務費!$C$5:$C$124,$V79,⑳商品別1食労務費!$F$5:$F$124)+SUMIF(⑳商品別1食労務費!$C$5:$C$124,$W79,⑳商品別1食労務費!$F$5:$F$124) | AB79: =IF(ISNUMBER($M79),$M79,0) | AD79: =IF($R79="",0,IF($AA79>0,$AB79*SUMIF(⑳商品別1食労務費!$C$5:$C$124,$R79,⑳商品別1食労務費!$F$5:$F$124)/$AA79,$AB79/$X79)) | AE79: =IF($S79="",0,IF($AA79>0,$AB79*SUMIF(⑳商品別1食労務費!$C$5:$C$124,$S79,⑳商品別1食労務費!$F$5:$F$124)/$AA79,$AB79/$X79)) | AF79: =IF($T79="",0,IF($AA79>0,$AB79*SUMIF(⑳商品別1食労務費!$C$5:$C$124,$T79,⑳商品別1食労務費!$F$5:$F$124)/$AA79,$AB79/$X79)) | AG79: =IF($U79="",0,IF($AA79>0,$AB79*SUMIF(⑳商品別1食労務費!$C$5:$C$124,$U79,⑳商品別1食労務費!$F$5:$F$124)/$AA79,$AB79/$X79)) | AH79: =IF($V79="",0,IF($AA79>0,$AB79*SUMIF(⑳商品別1食労務費!$C$5:$C$124,$V79,⑳商品別1食労務費!$F$5:$F$124)/$AA79,$AB79/$X79)) | AI79: =IF($W79="",0,IF($AA79>0,$AB79*SUMIF(⑳商品別1食労務費!$C$5:$C$124,$W79,⑳商品別1食労務費!$F$5:$F$124)/$AA79,$AB79/$X79))
A80: 76 | B80: 釜製造 | C80: まっしろミルクプリン | K80: =IF(F80>0,I80/(F80/60),0) | L80: =IF(AND(ISNUMBER(F80),J80>0),J80/(F80/60),"") | M80: =IF(OR(ISNUMBER(SEARCH("サニテーション",C80)),ISNUMBER(SEARCH("客注",C80)),ISNUMBER(SEARCH("切り替え",C80)),ISNUMBER(SEARCH("切替",C80)),NOT(ISNUMBER(H80))),"",IF(ISNUMBER(G80),G80/60*H80*④前提設定!$B$4,IF(AND(G80="",ISNUMBER(F80)),F80/60*H80*④前提設定!$B$4,""))) | N80: =IF(I80>0,M80/I80,"") | O80: =IF(AND(J80>0,ISNUMBER(M80)),M80/J80,"") | R80: まっしろミルクプリン３ | S80: Ｓまっしろミルクプリン小３ | X80: =COUNTA(R80:W80) | Y80: =IF(AND($X80>0,ISNUMBER($M80)),$M80/$X80,"") | Z80: =IF($X80=0,"",IF(COUNTIF(⑳商品別1食労務費!$C$5:$C$124,$R80)+COUNTIF(⑳商品別1食労務費!$C$5:$C$124,$S80)+COUNTIF(⑳商品別1食労務費!$C$5:$C$124,$T80)+COUNTIF(⑳商品別1食労務費!$C$5:$C$124,$U80)+COUNTIF(⑳商品別1食労務費!$C$5:$C$124,$V80)+COUNTIF(⑳商品別1食労務費!$C$5:$C$124,$W80)=$X80,"OK","⑳に無い商品名")) | AA80: =SUMIF(⑳商品別1食労務費!$C$5:$C$124,$R80,⑳商品別1食労務費!$F$5:$F$124)+SUMIF(⑳商品別1食労務費!$C$5:$C$124,$S80,⑳商品別1食労務費!$F$5:$F$124)+SUMIF(⑳商品別1食労務費!$C$5:$C$124,$T80,⑳商品別1食労務費!$F$5:$F$124)+SUMIF(⑳商品別1食労務費!$C$5:$C$124,$U80,⑳商品別1食労務費!$F$5:$F$124)+SUMIF(⑳商品別1食労務費!$C$5:$C$124,$V80,⑳商品別1食労務費!$F$5:$F$124)+SUMIF(⑳商品別1食労務費!$C$5:$C$124,$W80,⑳商品別1食労務費!$F$5:$F$124) | AB80: =IF(ISNUMBER($M80),$M80,0) | AD80: =IF($R80="",0,IF($AA80>0,$AB80*SUMIF(⑳商品別1食労務費!$C$5:$C$124,$R80,⑳商品別1食労務費!$F$5:$F$124)/$AA80,$AB80/$X80)) | AE80: =IF($S80="",0,IF($AA80>0,$AB80*SUMIF(⑳商品別1食労務費!$C$5:$C$124,$S80,⑳商品別1食労務費!$F$5:$F$124)/$AA80,$AB80/$X80)) | AF80: =IF($T80="",0,IF($AA80>0,$AB80*SUMIF(⑳商品別1食労務費!$C$5:$C$124,$T80,⑳商品別1食労務費!$F$5:$F$124)/$AA80,$AB80/$X80)) | AG80: =IF($U80="",0,IF($AA80>0,$AB80*SUMIF(⑳商品別1食労務費!$C$5:$C$124,$U80,⑳商品別1食労務費!$F$5:$F$124)/$AA80,$AB80/$X80)) | AH80: =IF($V80="",0,IF($AA80>0,$AB80*SUMIF(⑳商品別1食労務費!$C$5:$C$124,$V80,⑳商品別1食労務費!$F$5:$F$124)/$AA80,$AB80/$X80)) | AI80: =IF($W80="",0,IF($AA80>0,$AB80*SUMIF(⑳商品別1食労務費!$C$5:$C$124,$W80,⑳商品別1食労務費!$F$5:$F$124)/$AA80,$AB80/$X80))
A81: 77 | B81: 釜製造 | C81: 内製ホイップ | K81: =IF(F81>0,I81/(F81/60),0) | L81: =IF(AND(ISNUMBER(F81),J81>0),J81/(F81/60),"") | M81: =IF(OR(ISNUMBER(SEARCH("サニテーション",C81)),ISNUMBER(SEARCH("客注",C81)),ISNUMBER(SEARCH("切り替え",C81)),ISNUMBER(SEARCH("切替",C81)),NOT(ISNUMBER(H81))),"",IF(ISNUMBER(G81),G81/60*H81*④前提設定!$B$4,IF(AND(G81="",ISNUMBER(F81)),F81/60*H81*④前提設定!$B$4,""))) | N81: =IF(I81>0,M81/I81,"") | O81: =IF(AND(J81>0,ISNUMBER(M81)),M81/J81,"") | R81: 自社製ホイップの卵プリン | S81: Ｓホイップの卵プリン | T81: Ｓカスタード＆ホイップシュ | U81: ホイップの卵プリン | X81: =COUNTA(R81:W81) | Y81: =IF(AND($X81>0,ISNUMBER($M81)),$M81/$X81,"") | Z81: =IF($X81=0,"",IF(COUNTIF(⑳商品別1食労務費!$C$5:$C$124,$R81)+COUNTIF(⑳商品別1食労務費!$C$5:$C$124,$S81)+COUNTIF(⑳商品別1食労務費!$C$5:$C$124,$T81)+COUNTIF(⑳商品別1食労務費!$C$5:$C$124,$U81)+COUNTIF(⑳商品別1食労務費!$C$5:$C$124,$V81)+COUNTIF(⑳商品別1食労務費!$C$5:$C$124,$W81)=$X81,"OK","⑳に無い商品名")) | AA81: =SUMIF(⑳商品別1食労務費!$C$5:$C$124,$R81,⑳商品別1食労務費!$F$5:$F$124)+SUMIF(⑳商品別1食労務費!$C$5:$C$124,$S81,⑳商品別1食労務費!$F$5:$F$124)+SUMIF(⑳商品別1食労務費!$C$5:$C$124,$T81,⑳商品別1食労務費!$F$5:$F$124)+SUMIF(⑳商品別1食労務費!$C$5:$C$124,$U81,⑳商品別1食労務費!$F$5:$F$124)+SUMIF(⑳商品別1食労務費!$C$5:$C$124,$V81,⑳商品別1食労務費!$F$5:$F$124)+SUMIF(⑳商品別1食労務費!$C$5:$C$124,$W81,⑳商品別1食労務費!$F$5:$F$124) | AB81: =IF(ISNUMBER($M81),$M81,0) | AD81: =IF($R81="",0,IF($AA81>0,$AB81*SUMIF(⑳商品別1食労務費!$C$5:$C$124,$R81,⑳商品別1食労務費!$F$5:$F$124)/$AA81,$AB81/$X81)) | AE81: =IF($S81="",0,IF($AA81>0,$AB81*SUMIF(⑳商品別1食労務費!$C$5:$C$124,$S81,⑳商品別1食労務費!$F$5:$F$124)/$AA81,$AB81/$X81)) | AF81: =IF($T81="",0,IF($AA81>0,$AB81*SUMIF(⑳商品別1食労務費!$C$5:$C$124,$T81,⑳商品別1食労務費!$F$5:$F$124)/$AA81,$AB81/$X81)) | AG81: =IF($U81="",0,IF($AA81>0,$AB81*SUMIF(⑳商品別1食労務費!$C$5:$C$124,$U81,⑳商品別1食労務費!$F$5:$F$124)/$AA81,$AB81/$X81)) | AH81: =IF($V81="",0,IF($AA81>0,$AB81*SUMIF(⑳商品別1食労務費!$C$5:$C$124,$V81,⑳商品別1食労務費!$F$5:$F$124)/$AA81,$AB81/$X81)) | AI81: =IF($W81="",0,IF($AA81>0,$AB81*SUMIF(⑳商品別1食労務費!$C$5:$C$124,$W81,⑳商品別1食労務費!$F$5:$F$124)/$AA81,$AB81/$X81))
A82: 78 | B82: 釜製造 | C82: 大人のコーヒーゼリー | K82: - | L82: =IF(AND(ISNUMBER(F82),J82>0),J82/(F82/60),"") | M82: =IF(OR(ISNUMBER(SEARCH("サニテーション",C82)),ISNUMBER(SEARCH("客注",C82)),ISNUMBER(SEARCH("切り替え",C82)),ISNUMBER(SEARCH("切替",C82)),NOT(ISNUMBER(H82))),"",IF(ISNUMBER(G82),G82/60*H82*④前提設定!$B$4,IF(AND(G82="",ISNUMBER(F82)),F82/60*H82*④前提設定!$B$4,""))) | N82: - | O82: =IF(AND(J82>0,ISNUMBER(M82)),M82/J82,"") | R82: 大人のコーヒーゼリー４ | S82: Ｓ大人のコーヒーゼリー４ | T82: 大人のコーヒーゼリー小４ | U82: Ｓ大人のコーヒーゼリー小４ | X82: =COUNTA(R82:W82) | Y82: =IF(AND($X82>0,ISNUMBER($M82)),$M82/$X82,"") | Z82: =IF($X82=0,"",IF(COUNTIF(⑳商品別1食労務費!$C$5:$C$124,$R82)+COUNTIF(⑳商品別1食労務費!$C$5:$C$124,$S82)+COUNTIF(⑳商品別1食労務費!$C$5:$C$124,$T82)+COUNTIF(⑳商品別1食労務費!$C$5:$C$124,$U82)+COUNTIF(⑳商品別1食労務費!$C$5:$C$124,$V82)+COUNTIF(⑳商品別1食労務費!$C$5:$C$124,$W82)=$X82,"OK","⑳に無い商品名")) | AA82: =SUMIF(⑳商品別1食労務費!$C$5:$C$124,$R82,⑳商品別1食労務費!$F$5:$F$124)+SUMIF(⑳商品別1食労務費!$C$5:$C$124,$S82,⑳商品別1食労務費!$F$5:$F$124)+SUMIF(⑳商品別1食労務費!$C$5:$C$124,$T82,⑳商品別1食労務費!$F$5:$F$124)+SUMIF(⑳商品別1食労務費!$C$5:$C$124,$U82,⑳商品別1食労務費!$F$5:$F$124)+SUMIF(⑳商品別1食労務費!$C$5:$C$124,$V82,⑳商品別1食労務費!$F$5:$F$124)+SUMIF(⑳商品別1食労務費!$C$5:$C$124,$W82,⑳商品別1食労務費!$F$5:$F$124) | AB82: =IF(ISNUMBER($M82),$M82,0) | AD82: =IF($R82="",0,IF($AA82>0,$AB82*SUMIF(⑳商品別1食労務費!$C$5:$C$124,$R82,⑳商品別1食労務費!$F$5:$F$124)/$AA82,$AB82/$X82)) | AE82: =IF($S82="",0,IF($AA82>0,$AB82*SUMIF(⑳商品別1食労務費!$C$5:$C$124,$S82,⑳商品別1食労務費!$F$5:$F$124)/$AA82,$AB82/$X82)) | AF82: =IF($T82="",0,IF($AA82>0,$AB82*SUMIF(⑳商品別1食労務費!$C$5:$C$124,$T82,⑳商品別1食労務費!$F$5:$F$124)/$AA82,$AB82/$X82)) | AG82: =IF($U82="",0,IF($AA82>0,$AB82*SUMIF(⑳商品別1食労務費!$C$5:$C$124,$U82,⑳商品別1食労務費!$F$5:$F$124)/$AA82,$AB82/$X82)) | AH82: =IF($V82="",0,IF($AA82>0,$AB82*SUMIF(⑳商品別1食労務費!$C$5:$C$124,$V82,⑳商品別1食労務費!$F$5:$F$124)/$AA82,$AB82/$X82)) | AI82: =IF($W82="",0,IF($AA82>0,$AB82*SUMIF(⑳商品別1食労務費!$C$5:$C$124,$W82,⑳商品別1食労務費!$F$5:$F$124)/$AA82,$AB82/$X82))
A83: 79 | B83: 釜製造 | C83: 大人のコーヒーゼリー | K83: =IF(F83>0,I83/(F83/60),0) | L83: =IF(AND(ISNUMBER(F83),J83>0),J83/(F83/60),"") | M83: =IF(OR(ISNUMBER(SEARCH("サニテーション",C83)),ISNUMBER(SEARCH("客注",C83)),ISNUMBER(SEARCH("切り替え",C83)),ISNUMBER(SEARCH("切替",C83)),NOT(ISNUMBER(H83))),"",IF(ISNUMBER(G83),G83/60*H83*④前提設定!$B$4,IF(AND(G83="",ISNUMBER(F83)),F83/60*H83*④前提設定!$B$4,""))) | N83: =IF(I83>0,M83/I83,"") | O83: =IF(AND(J83>0,ISNUMBER(M83)),M83/J83,"") | R83: 大人のコーヒーゼリー４ | S83: Ｓ大人のコーヒーゼリー４ | T83: 大人のコーヒーゼリー小４ | U83: Ｓ大人のコーヒーゼリー小４ | X83: =COUNTA(R83:W83) | Y83: =IF(AND($X83>0,ISNUMBER($M83)),$M83/$X83,"") | Z83: =IF($X83=0,"",IF(COUNTIF(⑳商品別1食労務費!$C$5:$C$124,$R83)+COUNTIF(⑳商品別1食労務費!$C$5:$C$124,$S83)+COUNTIF(⑳商品別1食労務費!$C$5:$C$124,$T83)+COUNTIF(⑳商品別1食労務費!$C$5:$C$124,$U83)+COUNTIF(⑳商品別1食労務費!$C$5:$C$124,$V83)+COUNTIF(⑳商品別1食労務費!$C$5:$C$124,$W83)=$X83,"OK","⑳に無い商品名")) | AA83: =SUMIF(⑳商品別1食労務費!$C$5:$C$124,$R83,⑳商品別1食労務費!$F$5:$F$124)+SUMIF(⑳商品別1食労務費!$C$5:$C$124,$S83,⑳商品別1食労務費!$F$5:$F$124)+SUMIF(⑳商品別1食労務費!$C$5:$C$124,$T83,⑳商品別1食労務費!$F$5:$F$124)+SUMIF(⑳商品別1食労務費!$C$5:$C$124,$U83,⑳商品別1食労務費!$F$5:$F$124)+SUMIF(⑳商品別1食労務費!$C$5:$C$124,$V83,⑳商品別1食労務費!$F$5:$F$124)+SUMIF(⑳商品別1食労務費!$C$5:$C$124,$W83,⑳商品別1食労務費!$F$5:$F$124) | AB83: =IF(ISNUMBER($M83),$M83,0) | AD83: =IF($R83="",0,IF($AA83>0,$AB83*SUMIF(⑳商品別1食労務費!$C$5:$C$124,$R83,⑳商品別1食労務費!$F$5:$F$124)/$AA83,$AB83/$X83)) | AE83: =IF($S83="",0,IF($AA83>0,$AB83*SUMIF(⑳商品別1食労務費!$C$5:$C$124,$S83,⑳商品別1食労務費!$F$5:$F$124)/$AA83,$AB83/$X83)) | AF83: =IF($T83="",0,IF($AA83>0,$AB83*SUMIF(⑳商品別1食労務費!$C$5:$C$124,$T83,⑳商品別1食労務費!$F$5:$F$124)/$AA83,$AB83/$X83)) | AG83: =IF($U83="",0,IF($AA83>0,$AB83*SUMIF(⑳商品別1食労務費!$C$5:$C$124,$U83,⑳商品別1食労務費!$F$5:$F$124)/$AA83,$AB83/$X83)) | AH83: =IF($V83="",0,IF($AA83>0,$AB83*SUMIF(⑳商品別1食労務費!$C$5:$C$124,$V83,⑳商品別1食労務費!$F$5:$F$124)/$AA83,$AB83/$X83)) | AI83: =IF($W83="",0,IF($AA83>0,$AB83*SUMIF(⑳商品別1食労務費!$C$5:$C$124,$W83,⑳商品別1食労務費!$F$5:$F$124)/$AA83,$AB83/$X83))
A84: 80 | B84: 釜製造 | C84: 蜜いもスイートポテト | K84: =IF(F84>0,I84/(F84/60),0) | L84: =IF(AND(ISNUMBER(F84),J84>0),J84/(F84/60),"") | M84: =IF(OR(ISNUMBER(SEARCH("サニテーション",C84)),ISNUMBER(SEARCH("客注",C84)),ISNUMBER(SEARCH("切り替え",C84)),ISNUMBER(SEARCH("切替",C84)),NOT(ISNUMBER(H84))),"",IF(ISNUMBER(G84),G84/60*H84*④前提設定!$B$4,IF(AND(G84="",ISNUMBER(F84)),F84/60*H84*④前提設定!$B$4,""))) | N84: =IF(I84>0,M84/I84,"") | O84: =IF(AND(J84>0,ISNUMBER(M84)),M84/J84,"") | R84: 蜜いもスイートポテト | S84: Ｓ蜜いもスイートポテト | T84: Ｓ蜜いもスイートポテト小 | X84: =COUNTA(R84:W84) | Y84: =IF(AND($X84>0,ISNUMBER($M84)),$M84/$X84,"") | Z84: =IF($X84=0,"",IF(COUNTIF(⑳商品別1食労務費!$C$5:$C$124,$R84)+COUNTIF(⑳商品別1食労務費!$C$5:$C$124,$S84)+COUNTIF(⑳商品別1食労務費!$C$5:$C$124,$T84)+COUNTIF(⑳商品別1食労務費!$C$5:$C$124,$U84)+COUNTIF(⑳商品別1食労務費!$C$5:$C$124,$V84)+COUNTIF(⑳商品別1食労務費!$C$5:$C$124,$W84)=$X84,"OK","⑳に無い商品名")) | AA84: =SUMIF(⑳商品別1食労務費!$C$5:$C$124,$R84,⑳商品別1食労務費!$F$5:$F$124)+SUMIF(⑳商品別1食労務費!$C$5:$C$124,$S84,⑳商品別1食労務費!$F$5:$F$124)+SUMIF(⑳商品別1食労務費!$C$5:$C$124,$T84,⑳商品別1食労務費!$F$5:$F$124)+SUMIF(⑳商品別1食労務費!$C$5:$C$124,$U84,⑳商品別1食労務費!$F$5:$F$124)+SUMIF(⑳商品別1食労務費!$C$5:$C$124,$V84,⑳商品別1食労務費!$F$5:$F$124)+SUMIF(⑳商品別1食労務費!$C$5:$C$124,$W84,⑳商品別1食労務費!$F$5:$F$124) | AB84: =IF(ISNUMBER($M84),$M84,0) | AD84: =IF($R84="",0,IF($AA84>0,$AB84*SUMIF(⑳商品別1食労務費!$C$5:$C$124,$R84,⑳商品別1食労務費!$F$5:$F$124)/$AA84,$AB84/$X84)) | AE84: =IF($S84="",0,IF($AA84>0,$AB84*SUMIF(⑳商品別1食労務費!$C$5:$C$124,$S84,⑳商品別1食労務費!$F$5:$F$124)/$AA84,$AB84/$X84)) | AF84: =IF($T84="",0,IF($AA84>0,$AB84*SUMIF(⑳商品別1食労務費!$C$5:$C$124,$T84,⑳商品別1食労務費!$F$5:$F$124)/$AA84,$AB84/$X84)) | AG84: =IF($U84="",0,IF($AA84>0,$AB84*SUMIF(⑳商品別1食労務費!$C$5:$C$124,$U84,⑳商品別1食労務費!$F$5:$F$124)/$AA84,$AB84/$X84)) | AH84: =IF($V84="",0,IF($AA84>0,$AB84*SUMIF(⑳商品別1食労務費!$C$5:$C$124,$V84,⑳商品別1食労務費!$F$5:$F$124)/$AA84,$AB84/$X84)) | AI84: =IF($W84="",0,IF($AA84>0,$AB84*SUMIF(⑳商品別1食労務費!$C$5:$C$124,$W84,⑳商品別1食労務費!$F$5:$F$124)/$AA84,$AB84/$X84))
A85: 81 | B85: 釜製造 | C85: 蜜いもスイートポテト | K85: =IF(F85>0,I85/(F85/60),0) | L85: =IF(AND(ISNUMBER(F85),J85>0),J85/(F85/60),"") | M85: =IF(OR(ISNUMBER(SEARCH("サニテーション",C85)),ISNUMBER(SEARCH("客注",C85)),ISNUMBER(SEARCH("切り替え",C85)),ISNUMBER(SEARCH("切替",C85)),NOT(ISNUMBER(H85))),"",IF(ISNUMBER(G85),G85/60*H85*④前提設定!$B$4,IF(AND(G85="",ISNUMBER(F85)),F85/60*H85*④前提設定!$B$4,""))) | N85: =IF(I85>0,M85/I85,"") | O85: =IF(AND(J85>0,ISNUMBER(M85)),M85/J85,"") | R85: 蜜いもスイートポテト | S85: Ｓ蜜いもスイートポテト | T85: Ｓ蜜いもスイートポテト小 | X85: =COUNTA(R85:W85) | Y85: =IF(AND($X85>0,ISNUMBER($M85)),$M85/$X85,"") | Z85: =IF($X85=0,"",IF(COUNTIF(⑳商品別1食労務費!$C$5:$C$124,$R85)+COUNTIF(⑳商品別1食労務費!$C$5:$C$124,$S85)+COUNTIF(⑳商品別1食労務費!$C$5:$C$124,$T85)+COUNTIF(⑳商品別1食労務費!$C$5:$C$124,$U85)+COUNTIF(⑳商品別1食労務費!$C$5:$C$124,$V85)+COUNTIF(⑳商品別1食労務費!$C$5:$C$124,$W85)=$X85,"OK","⑳に無い商品名")) | AA85: =SUMIF(⑳商品別1食労務費!$C$5:$C$124,$R85,⑳商品別1食労務費!$F$5:$F$124)+SUMIF(⑳商品別1食労務費!$C$5:$C$124,$S85,⑳商品別1食労務費!$F$5:$F$124)+SUMIF(⑳商品別1食労務費!$C$5:$C$124,$T85,⑳商品別1食労務費!$F$5:$F$124)+SUMIF(⑳商品別1食労務費!$C$5:$C$124,$U85,⑳商品別1食労務費!$F$5:$F$124)+SUMIF(⑳商品別1食労務費!$C$5:$C$124,$V85,⑳商品別1食労務費!$F$5:$F$124)+SUMIF(⑳商品別1食労務費!$C$5:$C$124,$W85,⑳商品別1食労務費!$F$5:$F$124) | AB85: =IF(ISNUMBER($M85),$M85,0) | AD85: =IF($R85="",0,IF($AA85>0,$AB85*SUMIF(⑳商品別1食労務費!$C$5:$C$124,$R85,⑳商品別1食労務費!$F$5:$F$124)/$AA85,$AB85/$X85)) | AE85: =IF($S85="",0,IF($AA85>0,$AB85*SUMIF(⑳商品別1食労務費!$C$5:$C$124,$S85,⑳商品別1食労務費!$F$5:$F$124)/$AA85,$AB85/$X85)) | AF85: =IF($T85="",0,IF($AA85>0,$AB85*SUMIF(⑳商品別1食労務費!$C$5:$C$124,$T85,⑳商品別1食労務費!$F$5:$F$124)/$AA85,$AB85/$X85)) | AG85: =IF($U85="",0,IF($AA85>0,$AB85*SUMIF(⑳商品別1食労務費!$C$5:$C$124,$U85,⑳商品別1食労務費!$F$5:$F$124)/$AA85,$AB85/$X85)) | AH85: =IF($V85="",0,IF($AA85>0,$AB85*SUMIF(⑳商品別1食労務費!$C$5:$C$124,$V85,⑳商品別1食労務費!$F$5:$F$124)/$AA85,$AB85/$X85)) | AI85: =IF($W85="",0,IF($AA85>0,$AB85*SUMIF(⑳商品別1食労務費!$C$5:$C$124,$W85,⑳商品別1食労務費!$F$5:$F$124)/$AA85,$AB85/$X85))
A86: 82 | K86: =IF(F86>0,I86/(F86/60),0) | L86: =IF(AND(ISNUMBER(F86),J86>0),J86/(F86/60),"") | M86: =IF(OR(ISNUMBER(SEARCH("サニテーション",C86)),ISNUMBER(SEARCH("客注",C86)),ISNUMBER(SEARCH("切り替え",C86)),ISNUMBER(SEARCH("切替",C86)),NOT(ISNUMBER(H86))),"",IF(ISNUMBER(G86),G86/60*H86*④前提設定!$B$4,IF(AND(G86="",ISNUMBER(F86)),F86/60*H86*④前提設定!$B$4,""))) | N86: =IF(I86>0,M86/I86,"") | O86: =IF(AND(J86>0,ISNUMBER(M86)),M86/J86,"") | X86: =COUNTA(R86:W86) | Y86: =IF(AND($X86>0,ISNUMBER($M86)),$M86/$X86,"") | Z86: =IF($X86=0,"",IF(COUNTIF(⑳商品別1食労務費!$C$5:$C$124,$R86)+COUNTIF(⑳商品別1食労務費!$C$5:$C$124,$S86)+COUNTIF(⑳商品別1食労務費!$C$5:$C$124,$T86)+COUNTIF(⑳商品別1食労務費!$C$5:$C$124,$U86)+COUNTIF(⑳商品別1食労務費!$C$5:$C$124,$V86)+COUNTIF(⑳商品別1食労務費!$C$5:$C$124,$W86)=$X86,"OK","⑳に無い商品名")) | AA86: =SUMIF(⑳商品別1食労務費!$C$5:$C$124,$R86,⑳商品別1食労務費!$F$5:$F$124)+SUMIF(⑳商品別1食労務費!$C$5:$C$124,$S86,⑳商品別1食労務費!$F$5:$F$124)+SUMIF(⑳商品別1食労務費!$C$5:$C$124,$T86,⑳商品別1食労務費!$F$5:$F$124)+SUMIF(⑳商品別1食労務費!$C$5:$C$124,$U86,⑳商品別1食労務費!$F$5:$F$124)+SUMIF(⑳商品別1食労務費!$C$5:$C$124,$V86,⑳商品別1食労務費!$F$5:$F$124)+SUMIF(⑳商品別1食労務費!$C$5:$C$124,$W86,⑳商品別1食労務費!$F$5:$F$124) | AB86: =IF(ISNUMBER($M86),$M86,0) | AD86: =IF($R86="",0,IF($AA86>0,$AB86*SUMIF(⑳商品別1食労務費!$C$5:$C$124,$R86,⑳商品別1食労務費!$F$5:$F$124)/$AA86,$AB86/$X86)) | AE86: =IF($S86="",0,IF($AA86>0,$AB86*SUMIF(⑳商品別1食労務費!$C$5:$C$124,$S86,⑳商品別1食労務費!$F$5:$F$124)/$AA86,$AB86/$X86)) | AF86: =IF($T86="",0,IF($AA86>0,$AB86*SUMIF(⑳商品別1食労務費!$C$5:$C$124,$T86,⑳商品別1食労務費!$F$5:$F$124)/$AA86,$AB86/$X86)) | AG86: =IF($U86="",0,IF($AA86>0,$AB86*SUMIF(⑳商品別1食労務費!$C$5:$C$124,$U86,⑳商品別1食労務費!$F$5:$F$124)/$AA86,$AB86/$X86)) | AH86: =IF($V86="",0,IF($AA86>0,$AB86*SUMIF(⑳商品別1食労務費!$C$5:$C$124,$V86,⑳商品別1食労務費!$F$5:$F$124)/$AA86,$AB86/$X86)) | AI86: =IF($W86="",0,IF($AA86>0,$AB86*SUMIF(⑳商品別1食労務費!$C$5:$C$124,$W86,⑳商品別1食労務費!$F$5:$F$124)/$AA86,$AB86/$X86))
A87: 83 | K87: =IF(F87>0,I87/(F87/60),0) | L87: =IF(AND(ISNUMBER(F87),J87>0),J87/(F87/60),"") | M87: =IF(OR(ISNUMBER(SEARCH("サニテーション",C87)),ISNUMBER(SEARCH("客注",C87)),ISNUMBER(SEARCH("切り替え",C87)),ISNUMBER(SEARCH("切替",C87)),NOT(ISNUMBER(H87))),"",IF(ISNUMBER(G87),G87/60*H87*④前提設定!$B$4,IF(AND(G87="",ISNUMBER(F87)),F87/60*H87*④前提設定!$B$4,""))) | N87: =IF(I87>0,M87/I87,"") | O87: =IF(AND(J87>0,ISNUMBER(M87)),M87/J87,"") | X87: =COUNTA(R87:W87) | Y87: =IF(AND($X87>0,ISNUMBER($M87)),$M87/$X87,"") | Z87: =IF($X87=0,"",IF(COUNTIF(⑳商品別1食労務費!$C$5:$C$124,$R87)+COUNTIF(⑳商品別1食労務費!$C$5:$C$124,$S87)+COUNTIF(⑳商品別1食労務費!$C$5:$C$124,$T87)+COUNTIF(⑳商品別1食労務費!$C$5:$C$124,$U87)+COUNTIF(⑳商品別1食労務費!$C$5:$C$124,$V87)+COUNTIF(⑳商品別1食労務費!$C$5:$C$124,$W87)=$X87,"OK","⑳に無い商品名")) | AA87: =SUMIF(⑳商品別1食労務費!$C$5:$C$124,$R87,⑳商品別1食労務費!$F$5:$F$124)+SUMIF(⑳商品別1食労務費!$C$5:$C$124,$S87,⑳商品別1食労務費!$F$5:$F$124)+SUMIF(⑳商品別1食労務費!$C$5:$C$124,$T87,⑳商品別1食労務費!$F$5:$F$124)+SUMIF(⑳商品別1食労務費!$C$5:$C$124,$U87,⑳商品別1食労務費!$F$5:$F$124)+SUMIF(⑳商品別1食労務費!$C$5:$C$124,$V87,⑳商品別1食労務費!$F$5:$F$124)+SUMIF(⑳商品別1食労務費!$C$5:$C$124,$W87,⑳商品別1食労務費!$F$5:$F$124) | AB87: =IF(ISNUMBER($M87),$M87,0) | AD87: =IF($R87="",0,IF($AA87>0,$AB87*SUMIF(⑳商品別1食労務費!$C$5:$C$124,$R87,⑳商品別1食労務費!$F$5:$F$124)/$AA87,$AB87/$X87)) | AE87: =IF($S87="",0,IF($AA87>0,$AB87*SUMIF(⑳商品別1食労務費!$C$5:$C$124,$S87,⑳商品別1食労務費!$F$5:$F$124)/$AA87,$AB87/$X87)) | AF87: =IF($T87="",0,IF($AA87>0,$AB87*SUMIF(⑳商品別1食労務費!$C$5:$C$124,$T87,⑳商品別1食労務費!$F$5:$F$124)/$AA87,$AB87/$X87)) | AG87: =IF($U87="",0,IF($AA87>0,$AB87*SUMIF(⑳商品別1食労務費!$C$5:$C$124,$U87,⑳商品別1食労務費!$F$5:$F$124)/$AA87,$AB87/$X87)) | AH87: =IF($V87="",0,IF($AA87>0,$AB87*SUMIF(⑳商品別1食労務費!$C$5:$C$124,$V87,⑳商品別1食労務費!$F$5:$F$124)/$AA87,$AB87/$X87)) | AI87: =IF($W87="",0,IF($AA87>0,$AB87*SUMIF(⑳商品別1食労務費!$C$5:$C$124,$W87,⑳商品別1食労務費!$F$5:$F$124)/$AA87,$AB87/$X87))
A88: 84 | K88: =IF(F88>0,I88/(F88/60),0) | L88: =IF(AND(ISNUMBER(F88),J88>0),J88/(F88/60),"") | M88: =IF(OR(ISNUMBER(SEARCH("サニテーション",C88)),ISNUMBER(SEARCH("客注",C88)),ISNUMBER(SEARCH("切り替え",C88)),ISNUMBER(SEARCH("切替",C88)),NOT(ISNUMBER(H88))),"",IF(ISNUMBER(G88),G88/60*H88*④前提設定!$B$4,IF(AND(G88="",ISNUMBER(F88)),F88/60*H88*④前提設定!$B$4,""))) | N88: =IF(I88>0,M88/I88,"") | O88: =IF(AND(J88>0,ISNUMBER(M88)),M88/J88,"") | X88: =COUNTA(R88:W88) | Y88: =IF(AND($X88>0,ISNUMBER($M88)),$M88/$X88,"") | Z88: =IF($X88=0,"",IF(COUNTIF(⑳商品別1食労務費!$C$5:$C$124,$R88)+COUNTIF(⑳商品別1食労務費!$C$5:$C$124,$S88)+COUNTIF(⑳商品別1食労務費!$C$5:$C$124,$T88)+COUNTIF(⑳商品別1食労務費!$C$5:$C$124,$U88)+COUNTIF(⑳商品別1食労務費!$C$5:$C$124,$V88)+COUNTIF(⑳商品別1食労務費!$C$5:$C$124,$W88)=$X88,"OK","⑳に無い商品名")) | AA88: =SUMIF(⑳商品別1食労務費!$C$5:$C$124,$R88,⑳商品別1食労務費!$F$5:$F$124)+SUMIF(⑳商品別1食労務費!$C$5:$C$124,$S88,⑳商品別1食労務費!$F$5:$F$124)+SUMIF(⑳商品別1食労務費!$C$5:$C$124,$T88,⑳商品別1食労務費!$F$5:$F$124)+SUMIF(⑳商品別1食労務費!$C$5:$C$124,$U88,⑳商品別1食労務費!$F$5:$F$124)+SUMIF(⑳商品別1食労務費!$C$5:$C$124,$V88,⑳商品別1食労務費!$F$5:$F$124)+SUMIF(⑳商品別1食労務費!$C$5:$C$124,$W88,⑳商品別1食労務費!$F$5:$F$124) | AB88: =IF(ISNUMBER($M88),$M88,0) | AD88: =IF($R88="",0,IF($AA88>0,$AB88*SUMIF(⑳商品別1食労務費!$C$5:$C$124,$R88,⑳商品別1食労務費!$F$5:$F$124)/$AA88,$AB88/$X88)) | AE88: =IF($S88="",0,IF($AA88>0,$AB88*SUMIF(⑳商品別1食労務費!$C$5:$C$124,$S88,⑳商品別1食労務費!$F$5:$F$124)/$AA88,$AB88/$X88)) | AF88: =IF($T88="",0,IF($AA88>0,$AB88*SUMIF(⑳商品別1食労務費!$C$5:$C$124,$T88,⑳商品別1食労務費!$F$5:$F$124)/$AA88,$AB88/$X88)) | AG88: =IF($U88="",0,IF($AA88>0,$AB88*SUMIF(⑳商品別1食労務費!$C$5:$C$124,$U88,⑳商品別1食労務費!$F$5:$F$124)/$AA88,$AB88/$X88)) | AH88: =IF($V88="",0,IF($AA88>0,$AB88*SUMIF(⑳商品別1食労務費!$C$5:$C$124,$V88,⑳商品別1食労務費!$F$5:$F$124)/$AA88,$AB88/$X88)) | AI88: =IF($W88="",0,IF($AA88>0,$AB88*SUMIF(⑳商品別1食労務費!$C$5:$C$124,$W88,⑳商品別1食労務費!$F$5:$F$124)/$AA88,$AB88/$X88))
A89: 85 | K89: =IF(F89>0,I89/(F89/60),0) | L89: =IF(AND(ISNUMBER(F89),J89>0),J89/(F89/60),"") | M89: =IF(OR(ISNUMBER(SEARCH("サニテーション",C89)),ISNUMBER(SEARCH("客注",C89)),ISNUMBER(SEARCH("切り替え",C89)),ISNUMBER(SEARCH("切替",C89)),NOT(ISNUMBER(H89))),"",IF(ISNUMBER(G89),G89/60*H89*④前提設定!$B$4,IF(AND(G89="",ISNUMBER(F89)),F89/60*H89*④前提設定!$B$4,""))) | N89: =IF(I89>0,M89/I89,"") | O89: =IF(AND(J89>0,ISNUMBER(M89)),M89/J89,"") | X89: =COUNTA(R89:W89) | Y89: =IF(AND($X89>0,ISNUMBER($M89)),$M89/$X89,"") | Z89: =IF($X89=0,"",IF(COUNTIF(⑳商品別1食労務費!$C$5:$C$124,$R89)+COUNTIF(⑳商品別1食労務費!$C$5:$C$124,$S89)+COUNTIF(⑳商品別1食労務費!$C$5:$C$124,$T89)+COUNTIF(⑳商品別1食労務費!$C$5:$C$124,$U89)+COUNTIF(⑳商品別1食労務費!$C$5:$C$124,$V89)+COUNTIF(⑳商品別1食労務費!$C$5:$C$124,$W89)=$X89,"OK","⑳に無い商品名")) | AA89: =SUMIF(⑳商品別1食労務費!$C$5:$C$124,$R89,⑳商品別1食労務費!$F$5:$F$124)+SUMIF(⑳商品別1食労務費!$C$5:$C$124,$S89,⑳商品別1食労務費!$F$5:$F$124)+SUMIF(⑳商品別1食労務費!$C$5:$C$124,$T89,⑳商品別1食労務費!$F$5:$F$124)+SUMIF(⑳商品別1食労務費!$C$5:$C$124,$U89,⑳商品別1食労務費!$F$5:$F$124)+SUMIF(⑳商品別1食労務費!$C$5:$C$124,$V89,⑳商品別1食労務費!$F$5:$F$124)+SUMIF(⑳商品別1食労務費!$C$5:$C$124,$W89,⑳商品別1食労務費!$F$5:$F$124) | AB89: =IF(ISNUMBER($M89),$M89,0) | AD89: =IF($R89="",0,IF($AA89>0,$AB89*SUMIF(⑳商品別1食労務費!$C$5:$C$124,$R89,⑳商品別1食労務費!$F$5:$F$124)/$AA89,$AB89/$X89)) | AE89: =IF($S89="",0,IF($AA89>0,$AB89*SUMIF(⑳商品別1食労務費!$C$5:$C$124,$S89,⑳商品別1食労務費!$F$5:$F$124)/$AA89,$AB89/$X89)) | AF89: =IF($T89="",0,IF($AA89>0,$AB89*SUMIF(⑳商品別1食労務費!$C$5:$C$124,$T89,⑳商品別1食労務費!$F$5:$F$124)/$AA89,$AB89/$X89)) | AG89: =IF($U89="",0,IF($AA89>0,$AB89*SUMIF(⑳商品別1食労務費!$C$5:$C$124,$U89,⑳商品別1食労務費!$F$5:$F$124)/$AA89,$AB89/$X89)) | AH89: =IF($V89="",0,IF($AA89>0,$AB89*SUMIF(⑳商品別1食労務費!$C$5:$C$124,$V89,⑳商品別1食労務費!$F$5:$F$124)/$AA89,$AB89/$X89)) | AI89: =IF($W89="",0,IF($AA89>0,$AB89*SUMIF(⑳商品別1食労務費!$C$5:$C$124,$W89,⑳商品別1食労務費!$F$5:$F$124)/$AA89,$AB89/$X89))
A90: 86 | K90: =IF(F90>0,I90/(F90/60),0) | L90: =IF(AND(ISNUMBER(F90),J90>0),J90/(F90/60),"") | M90: =IF(OR(ISNUMBER(SEARCH("サニテーション",C90)),ISNUMBER(SEARCH("客注",C90)),ISNUMBER(SEARCH("切り替え",C90)),ISNUMBER(SEARCH("切替",C90)),NOT(ISNUMBER(H90))),"",IF(ISNUMBER(G90),G90/60*H90*④前提設定!$B$4,IF(AND(G90="",ISNUMBER(F90)),F90/60*H90*④前提設定!$B$4,""))) | N90: =IF(I90>0,M90/I90,"") | O90: =IF(AND(J90>0,ISNUMBER(M90)),M90/J90,"") | X90: =COUNTA(R90:W90) | Y90: =IF(AND($X90>0,ISNUMBER($M90)),$M90/$X90,"") | Z90: =IF($X90=0,"",IF(COUNTIF(⑳商品別1食労務費!$C$5:$C$124,$R90)+COUNTIF(⑳商品別1食労務費!$C$5:$C$124,$S90)+COUNTIF(⑳商品別1食労務費!$C$5:$C$124,$T90)+COUNTIF(⑳商品別1食労務費!$C$5:$C$124,$U90)+COUNTIF(⑳商品別1食労務費!$C$5:$C$124,$V90)+COUNTIF(⑳商品別1食労務費!$C$5:$C$124,$W90)=$X90,"OK","⑳に無い商品名")) | AA90: =SUMIF(⑳商品別1食労務費!$C$5:$C$124,$R90,⑳商品別1食労務費!$F$5:$F$124)+SUMIF(⑳商品別1食労務費!$C$5:$C$124,$S90,⑳商品別1食労務費!$F$5:$F$124)+SUMIF(⑳商品別1食労務費!$C$5:$C$124,$T90,⑳商品別1食労務費!$F$5:$F$124)+SUMIF(⑳商品別1食労務費!$C$5:$C$124,$U90,⑳商品別1食労務費!$F$5:$F$124)+SUMIF(⑳商品別1食労務費!$C$5:$C$124,$V90,⑳商品別1食労務費!$F$5:$F$124)+SUMIF(⑳商品別1食労務費!$C$5:$C$124,$W90,⑳商品別1食労務費!$F$5:$F$124) | AB90: =IF(ISNUMBER($M90),$M90,0) | AD90: =IF($R90="",0,IF($AA90>0,$AB90*SUMIF(⑳商品別1食労務費!$C$5:$C$124,$R90,⑳商品別1食労務費!$F$5:$F$124)/$AA90,$AB90/$X90)) | AE90: =IF($S90="",0,IF($AA90>0,$AB90*SUMIF(⑳商品別1食労務費!$C$5:$C$124,$S90,⑳商品別1食労務費!$F$5:$F$124)/$AA90,$AB90/$X90)) | AF90: =IF($T90="",0,IF($AA90>0,$AB90*SUMIF(⑳商品別1食労務費!$C$5:$C$124,$T90,⑳商品別1食労務費!$F$5:$F$124)/$AA90,$AB90/$X90)) | AG90: =IF($U90="",0,IF($AA90>0,$AB90*SUMIF(⑳商品別1食労務費!$C$5:$C$124,$U90,⑳商品別1食労務費!$F$5:$F$124)/$AA90,$AB90/$X90)) | AH90: =IF($V90="",0,IF($AA90>0,$AB90*SUMIF(⑳商品別1食労務費!$C$5:$C$124,$V90,⑳商品別1食労務費!$F$5:$F$124)/$AA90,$AB90/$X90)) | AI90: =IF($W90="",0,IF($AA90>0,$AB90*SUMIF(⑳商品別1食労務費!$C$5:$C$124,$W90,⑳商品別1食労務費!$F$5:$F$124)/$AA90,$AB90/$X90))
A91: 87 | K91: - | L91: =IF(AND(ISNUMBER(F91),J91>0),J91/(F91/60),"") | M91: =IF(OR(ISNUMBER(SEARCH("サニテーション",C91)),ISNUMBER(SEARCH("客注",C91)),ISNUMBER(SEARCH("切り替え",C91)),ISNUMBER(SEARCH("切替",C91)),NOT(ISNUMBER(H91))),"",IF(ISNUMBER(G91),G91/60*H91*④前提設定!$B$4,IF(AND(G91="",ISNUMBER(F91)),F91/60*H91*④前提設定!$B$4,""))) | N91: - | O91: =IF(AND(J91>0,ISNUMBER(M91)),M91/J91,"") | X91: =COUNTA(R91:W91) | Y91: =IF(AND($X91>0,ISNUMBER($M91)),$M91/$X91,"") | Z91: =IF($X91=0,"",IF(COUNTIF(⑳商品別1食労務費!$C$5:$C$124,$R91)+COUNTIF(⑳商品別1食労務費!$C$5:$C$124,$S91)+COUNTIF(⑳商品別1食労務費!$C$5:$C$124,$T91)+COUNTIF(⑳商品別1食労務費!$C$5:$C$124,$U91)+COUNTIF(⑳商品別1食労務費!$C$5:$C$124,$V91)+COUNTIF(⑳商品別1食労務費!$C$5:$C$124,$W91)=$X91,"OK","⑳に無い商品名")) | AA91: =SUMIF(⑳商品別1食労務費!$C$5:$C$124,$R91,⑳商品別1食労務費!$F$5:$F$124)+SUMIF(⑳商品別1食労務費!$C$5:$C$124,$S91,⑳商品別1食労務費!$F$5:$F$124)+SUMIF(⑳商品別1食労務費!$C$5:$C$124,$T91,⑳商品別1食労務費!$F$5:$F$124)+SUMIF(⑳商品別1食労務費!$C$5:$C$124,$U91,⑳商品別1食労務費!$F$5:$F$124)+SUMIF(⑳商品別1食労務費!$C$5:$C$124,$V91,⑳商品別1食労務費!$F$5:$F$124)+SUMIF(⑳商品別1食労務費!$C$5:$C$124,$W91,⑳商品別1食労務費!$F$5:$F$124) | AB91: =IF(ISNUMBER($M91),$M91,0) | AD91: =IF($R91="",0,IF($AA91>0,$AB91*SUMIF(⑳商品別1食労務費!$C$5:$C$124,$R91,⑳商品別1食労務費!$F$5:$F$124)/$AA91,$AB91/$X91)) | AE91: =IF($S91="",0,IF($AA91>0,$AB91*SUMIF(⑳商品別1食労務費!$C$5:$C$124,$S91,⑳商品別1食労務費!$F$5:$F$124)/$AA91,$AB91/$X91)) | AF91: =IF($T91="",0,IF($AA91>0,$AB91*SUMIF(⑳商品別1食労務費!$C$5:$C$124,$T91,⑳商品別1食労務費!$F$5:$F$124)/$AA91,$AB91/$X91)) | AG91: =IF($U91="",0,IF($AA91>0,$AB91*SUMIF(⑳商品別1食労務費!$C$5:$C$124,$U91,⑳商品別1食労務費!$F$5:$F$124)/$AA91,$AB91/$X91)) | AH91: =IF($V91="",0,IF($AA91>0,$AB91*SUMIF(⑳商品別1食労務費!$C$5:$C$124,$V91,⑳商品別1食労務費!$F$5:$F$124)/$AA91,$AB91/$X91)) | AI91: =IF($W91="",0,IF($AA91>0,$AB91*SUMIF(⑳商品別1食労務費!$C$5:$C$124,$W91,⑳商品別1食労務費!$F$5:$F$124)/$AA91,$AB91/$X91))
A92: 88 | K92: =IF(F92>0,I92/(F92/60),0) | L92: =IF(AND(ISNUMBER(F92),J92>0),J92/(F92/60),"") | M92: =IF(OR(ISNUMBER(SEARCH("サニテーション",C92)),ISNUMBER(SEARCH("客注",C92)),ISNUMBER(SEARCH("切り替え",C92)),ISNUMBER(SEARCH("切替",C92)),NOT(ISNUMBER(H92))),"",IF(ISNUMBER(G92),G92/60*H92*④前提設定!$B$4,IF(AND(G92="",ISNUMBER(F92)),F92/60*H92*④前提設定!$B$4,""))) | N92: =IF(I92>0,M92/I92,"") | O92: =IF(AND(J92>0,ISNUMBER(M92)),M92/J92,"") | X92: =COUNTA(R92:W92) | Y92: =IF(AND($X92>0,ISNUMBER($M92)),$M92/$X92,"") | Z92: =IF($X92=0,"",IF(COUNTIF(⑳商品別1食労務費!$C$5:$C$124,$R92)+COUNTIF(⑳商品別1食労務費!$C$5:$C$124,$S92)+COUNTIF(⑳商品別1食労務費!$C$5:$C$124,$T92)+COUNTIF(⑳商品別1食労務費!$C$5:$C$124,$U92)+COUNTIF(⑳商品別1食労務費!$C$5:$C$124,$V92)+COUNTIF(⑳商品別1食労務費!$C$5:$C$124,$W92)=$X92,"OK","⑳に無い商品名")) | AA92: =SUMIF(⑳商品別1食労務費!$C$5:$C$124,$R92,⑳商品別1食労務費!$F$5:$F$124)+SUMIF(⑳商品別1食労務費!$C$5:$C$124,$S92,⑳商品別1食労務費!$F$5:$F$124)+SUMIF(⑳商品別1食労務費!$C$5:$C$124,$T92,⑳商品別1食労務費!$F$5:$F$124)+SUMIF(⑳商品別1食労務費!$C$5:$C$124,$U92,⑳商品別1食労務費!$F$5:$F$124)+SUMIF(⑳商品別1食労務費!$C$5:$C$124,$V92,⑳商品別1食労務費!$F$5:$F$124)+SUMIF(⑳商品別1食労務費!$C$5:$C$124,$W92,⑳商品別1食労務費!$F$5:$F$124) | AB92: =IF(ISNUMBER($M92),$M92,0) | AD92: =IF($R92="",0,IF($AA92>0,$AB92*SUMIF(⑳商品別1食労務費!$C$5:$C$124,$R92,⑳商品別1食労務費!$F$5:$F$124)/$AA92,$AB92/$X92)) | AE92: =IF($S92="",0,IF($AA92>0,$AB92*SUMIF(⑳商品別1食労務費!$C$5:$C$124,$S92,⑳商品別1食労務費!$F$5:$F$124)/$AA92,$AB92/$X92)) | AF92: =IF($T92="",0,IF($AA92>0,$AB92*SUMIF(⑳商品別1食労務費!$C$5:$C$124,$T92,⑳商品別1食労務費!$F$5:$F$124)/$AA92,$AB92/$X92)) | AG92: =IF($U92="",0,IF($AA92>0,$AB92*SUMIF(⑳商品別1食労務費!$C$5:$C$124,$U92,⑳商品別1食労務費!$F$5:$F$124)/$AA92,$AB92/$X92)) | AH92: =IF($V92="",0,IF($AA92>0,$AB92*SUMIF(⑳商品別1食労務費!$C$5:$C$124,$V92,⑳商品別1食労務費!$F$5:$F$124)/$AA92,$AB92/$X92)) | AI92: =IF($W92="",0,IF($AA92>0,$AB92*SUMIF(⑳商品別1食労務費!$C$5:$C$124,$W92,⑳商品別1食労務費!$F$5:$F$124)/$AA92,$AB92/$X92))
A93: 89 | K93: =IF(F93>0,I93/(F93/60),0) | L93: =IF(AND(ISNUMBER(F93),J93>0),J93/(F93/60),"") | M93: =IF(OR(ISNUMBER(SEARCH("サニテーション",C93)),ISNUMBER(SEARCH("客注",C93)),ISNUMBER(SEARCH("切り替え",C93)),ISNUMBER(SEARCH("切替",C93)),NOT(ISNUMBER(H93))),"",IF(ISNUMBER(G93),G93/60*H93*④前提設定!$B$4,IF(AND(G93="",ISNUMBER(F93)),F93/60*H93*④前提設定!$B$4,""))) | N93: =IF(I93>0,M93/I93,"") | O93: =IF(AND(J93>0,ISNUMBER(M93)),M93/J93,"") | X93: =COUNTA(R93:W93) | Y93: =IF(AND($X93>0,ISNUMBER($M93)),$M93/$X93,"") | Z93: =IF($X93=0,"",IF(COUNTIF(⑳商品別1食労務費!$C$5:$C$124,$R93)+COUNTIF(⑳商品別1食労務費!$C$5:$C$124,$S93)+COUNTIF(⑳商品別1食労務費!$C$5:$C$124,$T93)+COUNTIF(⑳商品別1食労務費!$C$5:$C$124,$U93)+COUNTIF(⑳商品別1食労務費!$C$5:$C$124,$V93)+COUNTIF(⑳商品別1食労務費!$C$5:$C$124,$W93)=$X93,"OK","⑳に無い商品名")) | AA93: =SUMIF(⑳商品別1食労務費!$C$5:$C$124,$R93,⑳商品別1食労務費!$F$5:$F$124)+SUMIF(⑳商品別1食労務費!$C$5:$C$124,$S93,⑳商品別1食労務費!$F$5:$F$124)+SUMIF(⑳商品別1食労務費!$C$5:$C$124,$T93,⑳商品別1食労務費!$F$5:$F$124)+SUMIF(⑳商品別1食労務費!$C$5:$C$124,$U93,⑳商品別1食労務費!$F$5:$F$124)+SUMIF(⑳商品別1食労務費!$C$5:$C$124,$V93,⑳商品別1食労務費!$F$5:$F$124)+SUMIF(⑳商品別1食労務費!$C$5:$C$124,$W93,⑳商品別1食労務費!$F$5:$F$124) | AB93: =IF(ISNUMBER($M93),$M93,0) | AD93: =IF($R93="",0,IF($AA93>0,$AB93*SUMIF(⑳商品別1食労務費!$C$5:$C$124,$R93,⑳商品別1食労務費!$F$5:$F$124)/$AA93,$AB93/$X93)) | AE93: =IF($S93="",0,IF($AA93>0,$AB93*SUMIF(⑳商品別1食労務費!$C$5:$C$124,$S93,⑳商品別1食労務費!$F$5:$F$124)/$AA93,$AB93/$X93)) | AF93: =IF($T93="",0,IF($AA93>0,$AB93*SUMIF(⑳商品別1食労務費!$C$5:$C$124,$T93,⑳商品別1食労務費!$F$5:$F$124)/$AA93,$AB93/$X93)) | AG93: =IF($U93="",0,IF($AA93>0,$AB93*SUMIF(⑳商品別1食労務費!$C$5:$C$124,$U93,⑳商品別1食労務費!$F$5:$F$124)/$AA93,$AB93/$X93)) | AH93: =IF($V93="",0,IF($AA93>0,$AB93*SUMIF(⑳商品別1食労務費!$C$5:$C$124,$V93,⑳商品別1食労務費!$F$5:$F$124)/$AA93,$AB93/$X93)) | AI93: =IF($W93="",0,IF($AA93>0,$AB93*SUMIF(⑳商品別1食労務費!$C$5:$C$124,$W93,⑳商品別1食労務費!$F$5:$F$124)/$AA93,$AB93/$X93))
A94: 90 | K94: =IF(F94>0,I94/(F94/60),0) | L94: =IF(AND(ISNUMBER(F94),J94>0),J94/(F94/60),"") | M94: =IF(OR(ISNUMBER(SEARCH("サニテーション",C94)),ISNUMBER(SEARCH("客注",C94)),ISNUMBER(SEARCH("切り替え",C94)),ISNUMBER(SEARCH("切替",C94)),NOT(ISNUMBER(H94))),"",IF(ISNUMBER(G94),G94/60*H94*④前提設定!$B$4,IF(AND(G94="",ISNUMBER(F94)),F94/60*H94*④前提設定!$B$4,""))) | N94: =IF(I94>0,M94/I94,"") | O94: =IF(AND(J94>0,ISNUMBER(M94)),M94/J94,"") | X94: =COUNTA(R94:W94) | Y94: =IF(AND($X94>0,ISNUMBER($M94)),$M94/$X94,"") | Z94: =IF($X94=0,"",IF(COUNTIF(⑳商品別1食労務費!$C$5:$C$124,$R94)+COUNTIF(⑳商品別1食労務費!$C$5:$C$124,$S94)+COUNTIF(⑳商品別1食労務費!$C$5:$C$124,$T94)+COUNTIF(⑳商品別1食労務費!$C$5:$C$124,$U94)+COUNTIF(⑳商品別1食労務費!$C$5:$C$124,$V94)+COUNTIF(⑳商品別1食労務費!$C$5:$C$124,$W94)=$X94,"OK","⑳に無い商品名")) | AA94: =SUMIF(⑳商品別1食労務費!$C$5:$C$124,$R94,⑳商品別1食労務費!$F$5:$F$124)+SUMIF(⑳商品別1食労務費!$C$5:$C$124,$S94,⑳商品別1食労務費!$F$5:$F$124)+SUMIF(⑳商品別1食労務費!$C$5:$C$124,$T94,⑳商品別1食労務費!$F$5:$F$124)+SUMIF(⑳商品別1食労務費!$C$5:$C$124,$U94,⑳商品別1食労務費!$F$5:$F$124)+SUMIF(⑳商品別1食労務費!$C$5:$C$124,$V94,⑳商品別1食労務費!$F$5:$F$124)+SUMIF(⑳商品別1食労務費!$C$5:$C$124,$W94,⑳商品別1食労務費!$F$5:$F$124) | AB94: =IF(ISNUMBER($M94),$M94,0) | AD94: =IF($R94="",0,IF($AA94>0,$AB94*SUMIF(⑳商品別1食労務費!$C$5:$C$124,$R94,⑳商品別1食労務費!$F$5:$F$124)/$AA94,$AB94/$X94)) | AE94: =IF($S94="",0,IF($AA94>0,$AB94*SUMIF(⑳商品別1食労務費!$C$5:$C$124,$S94,⑳商品別1食労務費!$F$5:$F$124)/$AA94,$AB94/$X94)) | AF94: =IF($T94="",0,IF($AA94>0,$AB94*SUMIF(⑳商品別1食労務費!$C$5:$C$124,$T94,⑳商品別1食労務費!$F$5:$F$124)/$AA94,$AB94/$X94)) | AG94: =IF($U94="",0,IF($AA94>0,$AB94*SUMIF(⑳商品別1食労務費!$C$5:$C$124,$U94,⑳商品別1食労務費!$F$5:$F$124)/$AA94,$AB94/$X94)) | AH94: =IF($V94="",0,IF($AA94>0,$AB94*SUMIF(⑳商品別1食労務費!$C$5:$C$124,$V94,⑳商品別1食労務費!$F$5:$F$124)/$AA94,$AB94/$X94)) | AI94: =IF($W94="",0,IF($AA94>0,$AB94*SUMIF(⑳商品別1食労務費!$C$5:$C$124,$W94,⑳商品別1食労務費!$F$5:$F$124)/$AA94,$AB94/$X94))
A95: 91 | K95: =IF(F95>0,I95/(F95/60),0) | L95: =IF(AND(ISNUMBER(F95),J95>0),J95/(F95/60),"") | M95: =IF(OR(ISNUMBER(SEARCH("サニテーション",C95)),ISNUMBER(SEARCH("客注",C95)),ISNUMBER(SEARCH("切り替え",C95)),ISNUMBER(SEARCH("切替",C95)),NOT(ISNUMBER(H95))),"",IF(ISNUMBER(G95),G95/60*H95*④前提設定!$B$4,IF(AND(G95="",ISNUMBER(F95)),F95/60*H95*④前提設定!$B$4,""))) | N95: =IF(I95>0,M95/I95,"") | O95: =IF(AND(J95>0,ISNUMBER(M95)),M95/J95,"") | X95: =COUNTA(R95:W95) | Y95: =IF(AND($X95>0,ISNUMBER($M95)),$M95/$X95,"") | Z95: =IF($X95=0,"",IF(COUNTIF(⑳商品別1食労務費!$C$5:$C$124,$R95)+COUNTIF(⑳商品別1食労務費!$C$5:$C$124,$S95)+COUNTIF(⑳商品別1食労務費!$C$5:$C$124,$T95)+COUNTIF(⑳商品別1食労務費!$C$5:$C$124,$U95)+COUNTIF(⑳商品別1食労務費!$C$5:$C$124,$V95)+COUNTIF(⑳商品別1食労務費!$C$5:$C$124,$W95)=$X95,"OK","⑳に無い商品名")) | AA95: =SUMIF(⑳商品別1食労務費!$C$5:$C$124,$R95,⑳商品別1食労務費!$F$5:$F$124)+SUMIF(⑳商品別1食労務費!$C$5:$C$124,$S95,⑳商品別1食労務費!$F$5:$F$124)+SUMIF(⑳商品別1食労務費!$C$5:$C$124,$T95,⑳商品別1食労務費!$F$5:$F$124)+SUMIF(⑳商品別1食労務費!$C$5:$C$124,$U95,⑳商品別1食労務費!$F$5:$F$124)+SUMIF(⑳商品別1食労務費!$C$5:$C$124,$V95,⑳商品別1食労務費!$F$5:$F$124)+SUMIF(⑳商品別1食労務費!$C$5:$C$124,$W95,⑳商品別1食労務費!$F$5:$F$124) | AB95: =IF(ISNUMBER($M95),$M95,0) | AD95: =IF($R95="",0,IF($AA95>0,$AB95*SUMIF(⑳商品別1食労務費!$C$5:$C$124,$R95,⑳商品別1食労務費!$F$5:$F$124)/$AA95,$AB95/$X95)) | AE95: =IF($S95="",0,IF($AA95>0,$AB95*SUMIF(⑳商品別1食労務費!$C$5:$C$124,$S95,⑳商品別1食労務費!$F$5:$F$124)/$AA95,$AB95/$X95)) | AF95: =IF($T95="",0,IF($AA95>0,$AB95*SUMIF(⑳商品別1食労務費!$C$5:$C$124,$T95,⑳商品別1食労務費!$F$5:$F$124)/$AA95,$AB95/$X95)) | AG95: =IF($U95="",0,IF($AA95>0,$AB95*SUMIF(⑳商品別1食労務費!$C$5:$C$124,$U95,⑳商品別1食労務費!$F$5:$F$124)/$AA95,$AB95/$X95)) | AH95: =IF($V95="",0,IF($AA95>0,$AB95*SUMIF(⑳商品別1食労務費!$C$5:$C$124,$V95,⑳商品別1食労務費!$F$5:$F$124)/$AA95,$AB95/$X95)) | AI95: =IF($W95="",0,IF($AA95>0,$AB95*SUMIF(⑳商品別1食労務費!$C$5:$C$124,$W95,⑳商品別1食労務費!$F$5:$F$124)/$AA95,$AB95/$X95))
A96: 92 | K96: =IF(F96>0,I96/(F96/60),0) | L96: =IF(AND(ISNUMBER(F96),J96>0),J96/(F96/60),"") | M96: =IF(OR(ISNUMBER(SEARCH("サニテーション",C96)),ISNUMBER(SEARCH("客注",C96)),ISNUMBER(SEARCH("切り替え",C96)),ISNUMBER(SEARCH("切替",C96)),NOT(ISNUMBER(H96))),"",IF(ISNUMBER(G96),G96/60*H96*④前提設定!$B$4,IF(AND(G96="",ISNUMBER(F96)),F96/60*H96*④前提設定!$B$4,""))) | N96: =IF(I96>0,M96/I96,"") | O96: =IF(AND(J96>0,ISNUMBER(M96)),M96/J96,"") | X96: =COUNTA(R96:W96) | Y96: =IF(AND($X96>0,ISNUMBER($M96)),$M96/$X96,"") | Z96: =IF($X96=0,"",IF(COUNTIF(⑳商品別1食労務費!$C$5:$C$124,$R96)+COUNTIF(⑳商品別1食労務費!$C$5:$C$124,$S96)+COUNTIF(⑳商品別1食労務費!$C$5:$C$124,$T96)+COUNTIF(⑳商品別1食労務費!$C$5:$C$124,$U96)+COUNTIF(⑳商品別1食労務費!$C$5:$C$124,$V96)+COUNTIF(⑳商品別1食労務費!$C$5:$C$124,$W96)=$X96,"OK","⑳に無い商品名")) | AA96: =SUMIF(⑳商品別1食労務費!$C$5:$C$124,$R96,⑳商品別1食労務費!$F$5:$F$124)+SUMIF(⑳商品別1食労務費!$C$5:$C$124,$S96,⑳商品別1食労務費!$F$5:$F$124)+SUMIF(⑳商品別1食労務費!$C$5:$C$124,$T96,⑳商品別1食労務費!$F$5:$F$124)+SUMIF(⑳商品別1食労務費!$C$5:$C$124,$U96,⑳商品別1食労務費!$F$5:$F$124)+SUMIF(⑳商品別1食労務費!$C$5:$C$124,$V96,⑳商品別1食労務費!$F$5:$F$124)+SUMIF(⑳商品別1食労務費!$C$5:$C$124,$W96,⑳商品別1食労務費!$F$5:$F$124) | AB96: =IF(ISNUMBER($M96),$M96,0) | AD96: =IF($R96="",0,IF($AA96>0,$AB96*SUMIF(⑳商品別1食労務費!$C$5:$C$124,$R96,⑳商品別1食労務費!$F$5:$F$124)/$AA96,$AB96/$X96)) | AE96: =IF($S96="",0,IF($AA96>0,$AB96*SUMIF(⑳商品別1食労務費!$C$5:$C$124,$S96,⑳商品別1食労務費!$F$5:$F$124)/$AA96,$AB96/$X96)) | AF96: =IF($T96="",0,IF($AA96>0,$AB96*SUMIF(⑳商品別1食労務費!$C$5:$C$124,$T96,⑳商品別1食労務費!$F$5:$F$124)/$AA96,$AB96/$X96)) | AG96: =IF($U96="",0,IF($AA96>0,$AB96*SUMIF(⑳商品別1食労務費!$C$5:$C$124,$U96,⑳商品別1食労務費!$F$5:$F$124)/$AA96,$AB96/$X96)) | AH96: =IF($V96="",0,IF($AA96>0,$AB96*SUMIF(⑳商品別1食労務費!$C$5:$C$124,$V96,⑳商品別1食労務費!$F$5:$F$124)/$AA96,$AB96/$X96)) | AI96: =IF($W96="",0,IF($AA96>0,$AB96*SUMIF(⑳商品別1食労務費!$C$5:$C$124,$W96,⑳商品別1食労務費!$F$5:$F$124)/$AA96,$AB96/$X96))
A97: 93 | K97: =IF(F97>0,I97/(F97/60),0) | L97: =IF(AND(ISNUMBER(F97),J97>0),J97/(F97/60),"") | M97: =IF(OR(ISNUMBER(SEARCH("サニテーション",C97)),ISNUMBER(SEARCH("客注",C97)),ISNUMBER(SEARCH("切り替え",C97)),ISNUMBER(SEARCH("切替",C97)),NOT(ISNUMBER(H97))),"",IF(ISNUMBER(G97),G97/60*H97*④前提設定!$B$4,IF(AND(G97="",ISNUMBER(F97)),F97/60*H97*④前提設定!$B$4,""))) | N97: =IF(I97>0,M97/I97,"") | O97: =IF(AND(J97>0,ISNUMBER(M97)),M97/J97,"") | X97: =COUNTA(R97:W97) | Y97: =IF(AND($X97>0,ISNUMBER($M97)),$M97/$X97,"") | Z97: =IF($X97=0,"",IF(COUNTIF(⑳商品別1食労務費!$C$5:$C$124,$R97)+COUNTIF(⑳商品別1食労務費!$C$5:$C$124,$S97)+COUNTIF(⑳商品別1食労務費!$C$5:$C$124,$T97)+COUNTIF(⑳商品別1食労務費!$C$5:$C$124,$U97)+COUNTIF(⑳商品別1食労務費!$C$5:$C$124,$V97)+COUNTIF(⑳商品別1食労務費!$C$5:$C$124,$W97)=$X97,"OK","⑳に無い商品名")) | AA97: =SUMIF(⑳商品別1食労務費!$C$5:$C$124,$R97,⑳商品別1食労務費!$F$5:$F$124)+SUMIF(⑳商品別1食労務費!$C$5:$C$124,$S97,⑳商品別1食労務費!$F$5:$F$124)+SUMIF(⑳商品別1食労務費!$C$5:$C$124,$T97,⑳商品別1食労務費!$F$5:$F$124)+SUMIF(⑳商品別1食労務費!$C$5:$C$124,$U97,⑳商品別1食労務費!$F$5:$F$124)+SUMIF(⑳商品別1食労務費!$C$5:$C$124,$V97,⑳商品別1食労務費!$F$5:$F$124)+SUMIF(⑳商品別1食労務費!$C$5:$C$124,$W97,⑳商品別1食労務費!$F$5:$F$124) | AB97: =IF(ISNUMBER($M97),$M97,0) | AD97: =IF($R97="",0,IF($AA97>0,$AB97*SUMIF(⑳商品別1食労務費!$C$5:$C$124,$R97,⑳商品別1食労務費!$F$5:$F$124)/$AA97,$AB97/$X97)) | AE97: =IF($S97="",0,IF($AA97>0,$AB97*SUMIF(⑳商品別1食労務費!$C$5:$C$124,$S97,⑳商品別1食労務費!$F$5:$F$124)/$AA97,$AB97/$X97)) | AF97: =IF($T97="",0,IF($AA97>0,$AB97*SUMIF(⑳商品別1食労務費!$C$5:$C$124,$T97,⑳商品別1食労務費!$F$5:$F$124)/$AA97,$AB97/$X97)) | AG97: =IF($U97="",0,IF($AA97>0,$AB97*SUMIF(⑳商品別1食労務費!$C$5:$C$124,$U97,⑳商品別1食労務費!$F$5:$F$124)/$AA97,$AB97/$X97)) | AH97: =IF($V97="",0,IF($AA97>0,$AB97*SUMIF(⑳商品別1食労務費!$C$5:$C$124,$V97,⑳商品別1食労務費!$F$5:$F$124)/$AA97,$AB97/$X97)) | AI97: =IF($W97="",0,IF($AA97>0,$AB97*SUMIF(⑳商品別1食労務費!$C$5:$C$124,$W97,⑳商品別1食労務費!$F$5:$F$124)/$AA97,$AB97/$X97))
A98: 94 | K98: =IF(F98>0,I98/(F98/60),0) | L98: =IF(AND(ISNUMBER(F98),J98>0),J98/(F98/60),"") | M98: =IF(OR(ISNUMBER(SEARCH("サニテーション",C98)),ISNUMBER(SEARCH("客注",C98)),ISNUMBER(SEARCH("切り替え",C98)),ISNUMBER(SEARCH("切替",C98)),NOT(ISNUMBER(H98))),"",IF(ISNUMBER(G98),G98/60*H98*④前提設定!$B$4,IF(AND(G98="",ISNUMBER(F98)),F98/60*H98*④前提設定!$B$4,""))) | N98: =IF(I98>0,M98/I98,"") | O98: =IF(AND(J98>0,ISNUMBER(M98)),M98/J98,"") | X98: =COUNTA(R98:W98) | Y98: =IF(AND($X98>0,ISNUMBER($M98)),$M98/$X98,"") | Z98: =IF($X98=0,"",IF(COUNTIF(⑳商品別1食労務費!$C$5:$C$124,$R98)+COUNTIF(⑳商品別1食労務費!$C$5:$C$124,$S98)+COUNTIF(⑳商品別1食労務費!$C$5:$C$124,$T98)+COUNTIF(⑳商品別1食労務費!$C$5:$C$124,$U98)+COUNTIF(⑳商品別1食労務費!$C$5:$C$124,$V98)+COUNTIF(⑳商品別1食労務費!$C$5:$C$124,$W98)=$X98,"OK","⑳に無い商品名")) | AA98: =SUMIF(⑳商品別1食労務費!$C$5:$C$124,$R98,⑳商品別1食労務費!$F$5:$F$124)+SUMIF(⑳商品別1食労務費!$C$5:$C$124,$S98,⑳商品別1食労務費!$F$5:$F$124)+SUMIF(⑳商品別1食労務費!$C$5:$C$124,$T98,⑳商品別1食労務費!$F$5:$F$124)+SUMIF(⑳商品別1食労務費!$C$5:$C$124,$U98,⑳商品別1食労務費!$F$5:$F$124)+SUMIF(⑳商品別1食労務費!$C$5:$C$124,$V98,⑳商品別1食労務費!$F$5:$F$124)+SUMIF(⑳商品別1食労務費!$C$5:$C$124,$W98,⑳商品別1食労務費!$F$5:$F$124) | AB98: =IF(ISNUMBER($M98),$M98,0) | AD98: =IF($R98="",0,IF($AA98>0,$AB98*SUMIF(⑳商品別1食労務費!$C$5:$C$124,$R98,⑳商品別1食労務費!$F$5:$F$124)/$AA98,$AB98/$X98)) | AE98: =IF($S98="",0,IF($AA98>0,$AB98*SUMIF(⑳商品別1食労務費!$C$5:$C$124,$S98,⑳商品別1食労務費!$F$5:$F$124)/$AA98,$AB98/$X98)) | AF98: =IF($T98="",0,IF($AA98>0,$AB98*SUMIF(⑳商品別1食労務費!$C$5:$C$124,$T98,⑳商品別1食労務費!$F$5:$F$124)/$AA98,$AB98/$X98)) | AG98: =IF($U98="",0,IF($AA98>0,$AB98*SUMIF(⑳商品別1食労務費!$C$5:$C$124,$U98,⑳商品別1食労務費!$F$5:$F$124)/$AA98,$AB98/$X98)) | AH98: =IF($V98="",0,IF($AA98>0,$AB98*SUMIF(⑳商品別1食労務費!$C$5:$C$124,$V98,⑳商品別1食労務費!$F$5:$F$124)/$AA98,$AB98/$X98)) | AI98: =IF($W98="",0,IF($AA98>0,$AB98*SUMIF(⑳商品別1食労務費!$C$5:$C$124,$W98,⑳商品別1食労務費!$F$5:$F$124)/$AA98,$AB98/$X98))
A99: 95 | K99: =IF(F99>0,I99/(F99/60),0) | L99: =IF(AND(ISNUMBER(F99),J99>0),J99/(F99/60),"") | M99: =IF(OR(ISNUMBER(SEARCH("サニテーション",C99)),ISNUMBER(SEARCH("客注",C99)),ISNUMBER(SEARCH("切り替え",C99)),ISNUMBER(SEARCH("切替",C99)),NOT(ISNUMBER(H99))),"",IF(ISNUMBER(G99),G99/60*H99*④前提設定!$B$4,IF(AND(G99="",ISNUMBER(F99)),F99/60*H99*④前提設定!$B$4,""))) | N99: =IF(I99>0,M99/I99,"") | O99: =IF(AND(J99>0,ISNUMBER(M99)),M99/J99,"") | X99: =COUNTA(R99:W99) | Y99: =IF(AND($X99>0,ISNUMBER($M99)),$M99/$X99,"") | Z99: =IF($X99=0,"",IF(COUNTIF(⑳商品別1食労務費!$C$5:$C$124,$R99)+COUNTIF(⑳商品別1食労務費!$C$5:$C$124,$S99)+COUNTIF(⑳商品別1食労務費!$C$5:$C$124,$T99)+COUNTIF(⑳商品別1食労務費!$C$5:$C$124,$U99)+COUNTIF(⑳商品別1食労務費!$C$5:$C$124,$V99)+COUNTIF(⑳商品別1食労務費!$C$5:$C$124,$W99)=$X99,"OK","⑳に無い商品名")) | AA99: =SUMIF(⑳商品別1食労務費!$C$5:$C$124,$R99,⑳商品別1食労務費!$F$5:$F$124)+SUMIF(⑳商品別1食労務費!$C$5:$C$124,$S99,⑳商品別1食労務費!$F$5:$F$124)+SUMIF(⑳商品別1食労務費!$C$5:$C$124,$T99,⑳商品別1食労務費!$F$5:$F$124)+SUMIF(⑳商品別1食労務費!$C$5:$C$124,$U99,⑳商品別1食労務費!$F$5:$F$124)+SUMIF(⑳商品別1食労務費!$C$5:$C$124,$V99,⑳商品別1食労務費!$F$5:$F$124)+SUMIF(⑳商品別1食労務費!$C$5:$C$124,$W99,⑳商品別1食労務費!$F$5:$F$124) | AB99: =IF(ISNUMBER($M99),$M99,0) | AD99: =IF($R99="",0,IF($AA99>0,$AB99*SUMIF(⑳商品別1食労務費!$C$5:$C$124,$R99,⑳商品別1食労務費!$F$5:$F$124)/$AA99,$AB99/$X99)) | AE99: =IF($S99="",0,IF($AA99>0,$AB99*SUMIF(⑳商品別1食労務費!$C$5:$C$124,$S99,⑳商品別1食労務費!$F$5:$F$124)/$AA99,$AB99/$X99)) | AF99: =IF($T99="",0,IF($AA99>0,$AB99*SUMIF(⑳商品別1食労務費!$C$5:$C$124,$T99,⑳商品別1食労務費!$F$5:$F$124)/$AA99,$AB99/$X99)) | AG99: =IF($U99="",0,IF($AA99>0,$AB99*SUMIF(⑳商品別1食労務費!$C$5:$C$124,$U99,⑳商品別1食労務費!$F$5:$F$124)/$AA99,$AB99/$X99)) | AH99: =IF($V99="",0,IF($AA99>0,$AB99*SUMIF(⑳商品別1食労務費!$C$5:$C$124,$V99,⑳商品別1食労務費!$F$5:$F$124)/$AA99,$AB99/$X99)) | AI99: =IF($W99="",0,IF($AA99>0,$AB99*SUMIF(⑳商品別1食労務費!$C$5:$C$124,$W99,⑳商品別1食労務費!$F$5:$F$124)/$AA99,$AB99/$X99))
A100: 96 | K100: =IF(F100>0,I100/(F100/60),0) | L100: =IF(AND(ISNUMBER(F100),J100>0),J100/(F100/60),"") | M100: =IF(OR(ISNUMBER(SEARCH("サニテーション",C100)),ISNUMBER(SEARCH("客注",C100)),ISNUMBER(SEARCH("切り替え",C100)),ISNUMBER(SEARCH("切替",C100)),NOT(ISNUMBER(H100))),"",IF(ISNUMBER(G100),G100/60*H100*④前提設定!$B$4,IF(AND(G100="",ISNUMBER(F100)),F100/60*H100*④前提設定!$B$4,""))) | N100: =IF(I100>0,M100/I100,"") | O100: =IF(AND(J100>0,ISNUMBER(M100)),M100/J100,"") | X100: =COUNTA(R100:W100) | Y100: =IF(AND($X100>0,ISNUMBER($M100)),$M100/$X100,"") | Z100: =IF($X100=0,"",IF(COUNTIF(⑳商品別1食労務費!$C$5:$C$124,$R100)+COUNTIF(⑳商品別1食労務費!$C$5:$C$124,$S100)+COUNTIF(⑳商品別1食労務費!$C$5:$C$124,$T100)+COUNTIF(⑳商品別1食労務費!$C$5:$C$124,$U100)+COUNTIF(⑳商品別1食労務費!$C$5:$C$124,$V100)+COUNTIF(⑳商品別1食労務費!$C$5:$C$124,$W100)=$X100,"OK","⑳に無い商品名")) | AA100: =SUMIF(⑳商品別1食労務費!$C$5:$C$124,$R100,⑳商品別1食労務費!$F$5:$F$124)+SUMIF(⑳商品別1食労務費!$C$5:$C$124,$S100,⑳商品別1食労務費!$F$5:$F$124)+SUMIF(⑳商品別1食労務費!$C$5:$C$124,$T100,⑳商品別1食労務費!$F$5:$F$124)+SUMIF(⑳商品別1食労務費!$C$5:$C$124,$U100,⑳商品別1食労務費!$F$5:$F$124)+SUMIF(⑳商品別1食労務費!$C$5:$C$124,$V100,⑳商品別1食労務費!$F$5:$F$124)+SUMIF(⑳商品別1食労務費!$C$5:$C$124,$W100,⑳商品別1食労務費!$F$5:$F$124) | AB100: =IF(ISNUMBER($M100),$M100,0) | AD100: =IF($R100="",0,IF($AA100>0,$AB100*SUMIF(⑳商品別1食労務費!$C$5:$C$124,$R100,⑳商品別1食労務費!$F$5:$F$124)/$AA100,$AB100/$X100)) | AE100: =IF($S100="",0,IF($AA100>0,$AB100*SUMIF(⑳商品別1食労務費!$C$5:$C$124,$S100,⑳商品別1食労務費!$F$5:$F$124)/$AA100,$AB100/$X100)) | AF100: =IF($T100="",0,IF($AA100>0,$AB100*SUMIF(⑳商品別1食労務費!$C$5:$C$124,$T100,⑳商品別1食労務費!$F$5:$F$124)/$AA100,$AB100/$X100)) | AG100: =IF($U100="",0,IF($AA100>0,$AB100*SUMIF(⑳商品別1食労務費!$C$5:$C$124,$U100,⑳商品別1食労務費!$F$5:$F$124)/$AA100,$AB100/$X100)) | AH100: =IF($V100="",0,IF($AA100>0,$AB100*SUMIF(⑳商品別1食労務費!$C$5:$C$124,$V100,⑳商品別1食労務費!$F$5:$F$124)/$AA100,$AB100/$X100)) | AI100: =IF($W100="",0,IF($AA100>0,$AB100*SUMIF(⑳商品別1食労務費!$C$5:$C$124,$W100,⑳商品別1食労務費!$F$5:$F$124)/$AA100,$AB100/$X100))
A101: 97 | K101: =IF(F101>0,I101/(F101/60),0) | L101: =IF(AND(ISNUMBER(F101),J101>0),J101/(F101/60),"") | M101: =IF(OR(ISNUMBER(SEARCH("サニテーション",C101)),ISNUMBER(SEARCH("客注",C101)),ISNUMBER(SEARCH("切り替え",C101)),ISNUMBER(SEARCH("切替",C101)),NOT(ISNUMBER(H101))),"",IF(ISNUMBER(G101),G101/60*H101*④前提設定!$B$4,IF(AND(G101="",ISNUMBER(F101)),F101/60*H101*④前提設定!$B$4,""))) | N101: =IF(I101>0,M101/I101,"") | O101: =IF(AND(J101>0,ISNUMBER(M101)),M101/J101,"") | X101: =COUNTA(R101:W101) | Y101: =IF(AND($X101>0,ISNUMBER($M101)),$M101/$X101,"") | Z101: =IF($X101=0,"",IF(COUNTIF(⑳商品別1食労務費!$C$5:$C$124,$R101)+COUNTIF(⑳商品別1食労務費!$C$5:$C$124,$S101)+COUNTIF(⑳商品別1食労務費!$C$5:$C$124,$T101)+COUNTIF(⑳商品別1食労務費!$C$5:$C$124,$U101)+COUNTIF(⑳商品別1食労務費!$C$5:$C$124,$V101)+COUNTIF(⑳商品別1食労務費!$C$5:$C$124,$W101)=$X101,"OK","⑳に無い商品名")) | AA101: =SUMIF(⑳商品別1食労務費!$C$5:$C$124,$R101,⑳商品別1食労務費!$F$5:$F$124)+SUMIF(⑳商品別1食労務費!$C$5:$C$124,$S101,⑳商品別1食労務費!$F$5:$F$124)+SUMIF(⑳商品別1食労務費!$C$5:$C$124,$T101,⑳商品別1食労務費!$F$5:$F$124)+SUMIF(⑳商品別1食労務費!$C$5:$C$124,$U101,⑳商品別1食労務費!$F$5:$F$124)+SUMIF(⑳商品別1食労務費!$C$5:$C$124,$V101,⑳商品別1食労務費!$F$5:$F$124)+SUMIF(⑳商品別1食労務費!$C$5:$C$124,$W101,⑳商品別1食労務費!$F$5:$F$124) | AB101: =IF(ISNUMBER($M101),$M101,0) | AD101: =IF($R101="",0,IF($AA101>0,$AB101*SUMIF(⑳商品別1食労務費!$C$5:$C$124,$R101,⑳商品別1食労務費!$F$5:$F$124)/$AA101,$AB101/$X101)) | AE101: =IF($S101="",0,IF($AA101>0,$AB101*SUMIF(⑳商品別1食労務費!$C$5:$C$124,$S101,⑳商品別1食労務費!$F$5:$F$124)/$AA101,$AB101/$X101)) | AF101: =IF($T101="",0,IF($AA101>0,$AB101*SUMIF(⑳商品別1食労務費!$C$5:$C$124,$T101,⑳商品別1食労務費!$F$5:$F$124)/$AA101,$AB101/$X101)) | AG101: =IF($U101="",0,IF($AA101>0,$AB101*SUMIF(⑳商品別1食労務費!$C$5:$C$124,$U101,⑳商品別1食労務費!$F$5:$F$124)/$AA101,$AB101/$X101)) | AH101: =IF($V101="",0,IF($AA101>0,$AB101*SUMIF(⑳商品別1食労務費!$C$5:$C$124,$V101,⑳商品別1食労務費!$F$5:$F$124)/$AA101,$AB101/$X101)) | AI101: =IF($W101="",0,IF($AA101>0,$AB101*SUMIF(⑳商品別1食労務費!$C$5:$C$124,$W101,⑳商品別1食労務費!$F$5:$F$124)/$AA101,$AB101/$X101))
A102: 98 | K102: =IF(F102>0,I102/(F102/60),0) | L102: =IF(AND(ISNUMBER(F102),J102>0),J102/(F102/60),"") | M102: =IF(OR(ISNUMBER(SEARCH("サニテーション",C102)),ISNUMBER(SEARCH("客注",C102)),ISNUMBER(SEARCH("切り替え",C102)),ISNUMBER(SEARCH("切替",C102)),NOT(ISNUMBER(H102))),"",IF(ISNUMBER(G102),G102/60*H102*④前提設定!$B$4,IF(AND(G102="",ISNUMBER(F102)),F102/60*H102*④前提設定!$B$4,""))) | N102: =IF(I102>0,M102/I102,"") | O102: =IF(AND(J102>0,ISNUMBER(M102)),M102/J102,"") | X102: =COUNTA(R102:W102) | Y102: =IF(AND($X102>0,ISNUMBER($M102)),$M102/$X102,"") | Z102: =IF($X102=0,"",IF(COUNTIF(⑳商品別1食労務費!$C$5:$C$124,$R102)+COUNTIF(⑳商品別1食労務費!$C$5:$C$124,$S102)+COUNTIF(⑳商品別1食労務費!$C$5:$C$124,$T102)+COUNTIF(⑳商品別1食労務費!$C$5:$C$124,$U102)+COUNTIF(⑳商品別1食労務費!$C$5:$C$124,$V102)+COUNTIF(⑳商品別1食労務費!$C$5:$C$124,$W102)=$X102,"OK","⑳に無い商品名")) | AA102: =SUMIF(⑳商品別1食労務費!$C$5:$C$124,$R102,⑳商品別1食労務費!$F$5:$F$124)+SUMIF(⑳商品別1食労務費!$C$5:$C$124,$S102,⑳商品別1食労務費!$F$5:$F$124)+SUMIF(⑳商品別1食労務費!$C$5:$C$124,$T102,⑳商品別1食労務費!$F$5:$F$124)+SUMIF(⑳商品別1食労務費!$C$5:$C$124,$U102,⑳商品別1食労務費!$F$5:$F$124)+SUMIF(⑳商品別1食労務費!$C$5:$C$124,$V102,⑳商品別1食労務費!$F$5:$F$124)+SUMIF(⑳商品別1食労務費!$C$5:$C$124,$W102,⑳商品別1食労務費!$F$5:$F$124) | AB102: =IF(ISNUMBER($M102),$M102,0) | AD102: =IF($R102="",0,IF($AA102>0,$AB102*SUMIF(⑳商品別1食労務費!$C$5:$C$124,$R102,⑳商品別1食労務費!$F$5:$F$124)/$AA102,$AB102/$X102)) | AE102: =IF($S102="",0,IF($AA102>0,$AB102*SUMIF(⑳商品別1食労務費!$C$5:$C$124,$S102,⑳商品別1食労務費!$F$5:$F$124)/$AA102,$AB102/$X102)) | AF102: =IF($T102="",0,IF($AA102>0,$AB102*SUMIF(⑳商品別1食労務費!$C$5:$C$124,$T102,⑳商品別1食労務費!$F$5:$F$124)/$AA102,$AB102/$X102)) | AG102: =IF($U102="",0,IF($AA102>0,$AB102*SUMIF(⑳商品別1食労務費!$C$5:$C$124,$U102,⑳商品別1食労務費!$F$5:$F$124)/$AA102,$AB102/$X102)) | AH102: =IF($V102="",0,IF($AA102>0,$AB102*SUMIF(⑳商品別1食労務費!$C$5:$C$124,$V102,⑳商品別1食労務費!$F$5:$F$124)/$AA102,$AB102/$X102)) | AI102: =IF($W102="",0,IF($AA102>0,$AB102*SUMIF(⑳商品別1食労務費!$C$5:$C$124,$W102,⑳商品別1食労務費!$F$5:$F$124)/$AA102,$AB102/$X102))
A103: 99 | K103: - | L103: =IF(AND(ISNUMBER(F103),J103>0),J103/(F103/60),"") | M103: =IF(OR(ISNUMBER(SEARCH("サニテーション",C103)),ISNUMBER(SEARCH("客注",C103)),ISNUMBER(SEARCH("切り替え",C103)),ISNUMBER(SEARCH("切替",C103)),NOT(ISNUMBER(H103))),"",IF(ISNUMBER(G103),G103/60*H103*④前提設定!$B$4,IF(AND(G103="",ISNUMBER(F103)),F103/60*H103*④前提設定!$B$4,""))) | N103: - | O103: =IF(AND(J103>0,ISNUMBER(M103)),M103/J103,"") | X103: =COUNTA(R103:W103) | Y103: =IF(AND($X103>0,ISNUMBER($M103)),$M103/$X103,"") | Z103: =IF($X103=0,"",IF(COUNTIF(⑳商品別1食労務費!$C$5:$C$124,$R103)+COUNTIF(⑳商品別1食労務費!$C$5:$C$124,$S103)+COUNTIF(⑳商品別1食労務費!$C$5:$C$124,$T103)+COUNTIF(⑳商品別1食労務費!$C$5:$C$124,$U103)+COUNTIF(⑳商品別1食労務費!$C$5:$C$124,$V103)+COUNTIF(⑳商品別1食労務費!$C$5:$C$124,$W103)=$X103,"OK","⑳に無い商品名")) | AA103: =SUMIF(⑳商品別1食労務費!$C$5:$C$124,$R103,⑳商品別1食労務費!$F$5:$F$124)+SUMIF(⑳商品別1食労務費!$C$5:$C$124,$S103,⑳商品別1食労務費!$F$5:$F$124)+SUMIF(⑳商品別1食労務費!$C$5:$C$124,$T103,⑳商品別1食労務費!$F$5:$F$124)+SUMIF(⑳商品別1食労務費!$C$5:$C$124,$U103,⑳商品別1食労務費!$F$5:$F$124)+SUMIF(⑳商品別1食労務費!$C$5:$C$124,$V103,⑳商品別1食労務費!$F$5:$F$124)+SUMIF(⑳商品別1食労務費!$C$5:$C$124,$W103,⑳商品別1食労務費!$F$5:$F$124) | AB103: =IF(ISNUMBER($M103),$M103,0) | AD103: =IF($R103="",0,IF($AA103>0,$AB103*SUMIF(⑳商品別1食労務費!$C$5:$C$124,$R103,⑳商品別1食労務費!$F$5:$F$124)/$AA103,$AB103/$X103)) | AE103: =IF($S103="",0,IF($AA103>0,$AB103*SUMIF(⑳商品別1食労務費!$C$5:$C$124,$S103,⑳商品別1食労務費!$F$5:$F$124)/$AA103,$AB103/$X103)) | AF103: =IF($T103="",0,IF($AA103>0,$AB103*SUMIF(⑳商品別1食労務費!$C$5:$C$124,$T103,⑳商品別1食労務費!$F$5:$F$124)/$AA103,$AB103/$X103)) | AG103: =IF($U103="",0,IF($AA103>0,$AB103*SUMIF(⑳商品別1食労務費!$C$5:$C$124,$U103,⑳商品別1食労務費!$F$5:$F$124)/$AA103,$AB103/$X103)) | AH103: =IF($V103="",0,IF($AA103>0,$AB103*SUMIF(⑳商品別1食労務費!$C$5:$C$124,$V103,⑳商品別1食労務費!$F$5:$F$124)/$AA103,$AB103/$X103)) | AI103: =IF($W103="",0,IF($AA103>0,$AB103*SUMIF(⑳商品別1食労務費!$C$5:$C$124,$W103,⑳商品別1食労務費!$F$5:$F$124)/$AA103,$AB103/$X103))
A104: 100 | K104: =IF(F104>0,I104/(F104/60),0) | L104: =IF(AND(ISNUMBER(F104),J104>0),J104/(F104/60),"") | M104: =IF(OR(ISNUMBER(SEARCH("サニテーション",C104)),ISNUMBER(SEARCH("客注",C104)),ISNUMBER(SEARCH("切り替え",C104)),ISNUMBER(SEARCH("切替",C104)),NOT(ISNUMBER(H104))),"",IF(ISNUMBER(G104),G104/60*H104*④前提設定!$B$4,IF(AND(G104="",ISNUMBER(F104)),F104/60*H104*④前提設定!$B$4,""))) | N104: =IF(I104>0,M104/I104,"") | O104: =IF(AND(J104>0,ISNUMBER(M104)),M104/J104,"") | X104: =COUNTA(R104:W104) | Y104: =IF(AND($X104>0,ISNUMBER($M104)),$M104/$X104,"") | Z104: =IF($X104=0,"",IF(COUNTIF(⑳商品別1食労務費!$C$5:$C$124,$R104)+COUNTIF(⑳商品別1食労務費!$C$5:$C$124,$S104)+COUNTIF(⑳商品別1食労務費!$C$5:$C$124,$T104)+COUNTIF(⑳商品別1食労務費!$C$5:$C$124,$U104)+COUNTIF(⑳商品別1食労務費!$C$5:$C$124,$V104)+COUNTIF(⑳商品別1食労務費!$C$5:$C$124,$W104)=$X104,"OK","⑳に無い商品名")) | AA104: =SUMIF(⑳商品別1食労務費!$C$5:$C$124,$R104,⑳商品別1食労務費!$F$5:$F$124)+SUMIF(⑳商品別1食労務費!$C$5:$C$124,$S104,⑳商品別1食労務費!$F$5:$F$124)+SUMIF(⑳商品別1食労務費!$C$5:$C$124,$T104,⑳商品別1食労務費!$F$5:$F$124)+SUMIF(⑳商品別1食労務費!$C$5:$C$124,$U104,⑳商品別1食労務費!$F$5:$F$124)+SUMIF(⑳商品別1食労務費!$C$5:$C$124,$V104,⑳商品別1食労務費!$F$5:$F$124)+SUMIF(⑳商品別1食労務費!$C$5:$C$124,$W104,⑳商品別1食労務費!$F$5:$F$124) | AB104: =IF(ISNUMBER($M104),$M104,0) | AD104: =IF($R104="",0,IF($AA104>0,$AB104*SUMIF(⑳商品別1食労務費!$C$5:$C$124,$R104,⑳商品別1食労務費!$F$5:$F$124)/$AA104,$AB104/$X104)) | AE104: =IF($S104="",0,IF($AA104>0,$AB104*SUMIF(⑳商品別1食労務費!$C$5:$C$124,$S104,⑳商品別1食労務費!$F$5:$F$124)/$AA104,$AB104/$X104)) | AF104: =IF($T104="",0,IF($AA104>0,$AB104*SUMIF(⑳商品別1食労務費!$C$5:$C$124,$T104,⑳商品別1食労務費!$F$5:$F$124)/$AA104,$AB104/$X104)) | AG104: =IF($U104="",0,IF($AA104>0,$AB104*SUMIF(⑳商品別1食労務費!$C$5:$C$124,$U104,⑳商品別1食労務費!$F$5:$F$124)/$AA104,$AB104/$X104)) | AH104: =IF($V104="",0,IF($AA104>0,$AB104*SUMIF(⑳商品別1食労務費!$C$5:$C$124,$V104,⑳商品別1食労務費!$F$5:$F$124)/$AA104,$AB104/$X104)) | AI104: =IF($W104="",0,IF($AA104>0,$AB104*SUMIF(⑳商品別1食労務費!$C$5:$C$124,$W104,⑳商品別1食労務費!$F$5:$F$124)/$AA104,$AB104/$X104))
A105: 101 | K105: =IF(F105>0,I105/(F105/60),0) | L105: =IF(AND(ISNUMBER(F105),J105>0),J105/(F105/60),"") | M105: =IF(OR(ISNUMBER(SEARCH("サニテーション",C105)),ISNUMBER(SEARCH("客注",C105)),ISNUMBER(SEARCH("切り替え",C105)),ISNUMBER(SEARCH("切替",C105)),NOT(ISNUMBER(H105))),"",IF(ISNUMBER(G105),G105/60*H105*④前提設定!$B$4,IF(AND(G105="",ISNUMBER(F105)),F105/60*H105*④前提設定!$B$4,""))) | N105: =IF(I105>0,M105/I105,"") | O105: =IF(AND(J105>0,ISNUMBER(M105)),M105/J105,"") | X105: =COUNTA(R105:W105) | Y105: =IF(AND($X105>0,ISNUMBER($M105)),$M105/$X105,"") | Z105: =IF($X105=0,"",IF(COUNTIF(⑳商品別1食労務費!$C$5:$C$124,$R105)+COUNTIF(⑳商品別1食労務費!$C$5:$C$124,$S105)+COUNTIF(⑳商品別1食労務費!$C$5:$C$124,$T105)+COUNTIF(⑳商品別1食労務費!$C$5:$C$124,$U105)+COUNTIF(⑳商品別1食労務費!$C$5:$C$124,$V105)+COUNTIF(⑳商品別1食労務費!$C$5:$C$124,$W105)=$X105,"OK","⑳に無い商品名")) | AA105: =SUMIF(⑳商品別1食労務費!$C$5:$C$124,$R105,⑳商品別1食労務費!$F$5:$F$124)+SUMIF(⑳商品別1食労務費!$C$5:$C$124,$S105,⑳商品別1食労務費!$F$5:$F$124)+SUMIF(⑳商品別1食労務費!$C$5:$C$124,$T105,⑳商品別1食労務費!$F$5:$F$124)+SUMIF(⑳商品別1食労務費!$C$5:$C$124,$U105,⑳商品別1食労務費!$F$5:$F$124)+SUMIF(⑳商品別1食労務費!$C$5:$C$124,$V105,⑳商品別1食労務費!$F$5:$F$124)+SUMIF(⑳商品別1食労務費!$C$5:$C$124,$W105,⑳商品別1食労務費!$F$5:$F$124) | AB105: =IF(ISNUMBER($M105),$M105,0) | AD105: =IF($R105="",0,IF($AA105>0,$AB105*SUMIF(⑳商品別1食労務費!$C$5:$C$124,$R105,⑳商品別1食労務費!$F$5:$F$124)/$AA105,$AB105/$X105)) | AE105: =IF($S105="",0,IF($AA105>0,$AB105*SUMIF(⑳商品別1食労務費!$C$5:$C$124,$S105,⑳商品別1食労務費!$F$5:$F$124)/$AA105,$AB105/$X105)) | AF105: =IF($T105="",0,IF($AA105>0,$AB105*SUMIF(⑳商品別1食労務費!$C$5:$C$124,$T105,⑳商品別1食労務費!$F$5:$F$124)/$AA105,$AB105/$X105)) | AG105: =IF($U105="",0,IF($AA105>0,$AB105*SUMIF(⑳商品別1食労務費!$C$5:$C$124,$U105,⑳商品別1食労務費!$F$5:$F$124)/$AA105,$AB105/$X105)) | AH105: =IF($V105="",0,IF($AA105>0,$AB105*SUMIF(⑳商品別1食労務費!$C$5:$C$124,$V105,⑳商品別1食労務費!$F$5:$F$124)/$AA105,$AB105/$X105)) | AI105: =IF($W105="",0,IF($AA105>0,$AB105*SUMIF(⑳商品別1食労務費!$C$5:$C$124,$W105,⑳商品別1食労務費!$F$5:$F$124)/$AA105,$AB105/$X105))
...

Sheet ③スチコン工程入力
A1: スチコン工程入力台帳 毎週更新 | 黄色セル＝入力（商品名・重量・実作業分を更新）
A2: ● 青字・黄背景 = 毎週更新するセル 黒字・グレー = 自動計算（変更不要） | ★R列で中間品名を選ぶと、中間品JAN（S列）で⑱〜⑳に労務費がひもづきます
A4: No. | B4: 機器 | C4: 商品名★ | D4: 開始★ | E4: 終了★ | F4: 稼働(分) | G4: 実作業(分)★ | H4: 人数★ | I4: 重量kg★ | J4: 個数(個)★ 個入力欄 | K4: 生産性 (kg/h) | L4: 生産性 (個/h) | M4: 労務費 (円) | N4: 円/kg | O4: 円/個 | P4: 区分 | Q4: 備考 | R4: ★商品名① | S4: ★商品名② | T4: ★商品名③ | U4: ★商品名④ | V4: ★商品名⑤ | W4: ★商品名⑥ | X4: 振り分け数 自動 | Y4: 1商品あたり 労務費(等分・参考) | Z4: ひもづけ確認 | AA4: 選んだ商品の 食数合計 | AB4: 労務費(数値) | AD4: 配分額① (自動) | AE4: 配分額② (自動) | AF4: 配分額③ (自動) | AG4: 配分額④ (自動) | AH4: 配分額⑤ (自動) | AI4: 配分額⑥ (自動)
A5: 1 | B5: スチコン | C5: 黒クランブル | D5: 0.0625 | E5: 0.090277778 | F5: 40 | G5: 20 | H5: 1 | I5: 10 | K5: =IF(F5>0,I5/(F5/60),0) | L5: =IF(AND(ISNUMBER(F5),J5>0),J5/(F5/60),"") | M5: =IF(OR(ISNUMBER(SEARCH("サニテーション",C5)),ISNUMBER(SEARCH("客注",C5)),ISNUMBER(SEARCH("切り替え",C5)),ISNUMBER(SEARCH("切替",C5)),NOT(ISNUMBER(H5))),"",IF(ISNUMBER(G5),G5/60*H5*④前提設定!$B$4,IF(AND(G5="",ISNUMBER(F5)),F5/60*H5*④前提設定!$B$4,""))) | N5: =IF(I5>0,M5/I5,"") | O5: =IF(AND(J5>0,ISNUMBER(M5)),M5/J5,"") | R5: ２層仕立てのチーズケーキ | S5: Ｓ２層仕立てのチーズケーキ | X5: =COUNTA(R5:W5) | Y5: =IF(AND($X5>0,ISNUMBER($M5)),$M5/$X5,"") | Z5: =IF($X5=0,"",IF(COUNTIF(⑳商品別1食労務費!$C$5:$C$124,$R5)+COUNTIF(⑳商品別1食労務費!$C$5:$C$124,$S5)+COUNTIF(⑳商品別1食労務費!$C$5:$C$124,$T5)+COUNTIF(⑳商品別1食労務費!$C$5:$C$124,$U5)+COUNTIF(⑳商品別1食労務費!$C$5:$C$124,$V5)+COUNTIF(⑳商品別1食労務費!$C$5:$C$124,$W5)=$X5,"OK","⑳に無い商品名")) | AA5: =SUMIF(⑳商品別1食労務費!$C$5:$C$124,$R5,⑳商品別1食労務費!$F$5:$F$124)+SUMIF(⑳商品別1食労務費!$C$5:$C$124,$S5,⑳商品別1食労務費!$F$5:$F$124)+SUMIF(⑳商品別1食労務費!$C$5:$C$124,$T5,⑳商品別1食労務費!$F$5:$F$124)+SUMIF(⑳商品別1食労務費!$C$5:$C$124,$U5,⑳商品別1食労務費!$F$5:$F$124)+SUMIF(⑳商品別1食労務費!$C$5:$C$124,$V5,⑳商品別1食労務費!$F$5:$F$124)+SUMIF(⑳商品別1食労務費!$C$5:$C$124,$W5,⑳商品別1食労務費!$F$5:$F$124) | AB5: =IF(ISNUMBER($M5),$M5,0) | AD5: =IF($R5="",0,IF($AA5>0,$AB5*SUMIF(⑳商品別1食労務費!$C$5:$C$124,$R5,⑳商品別1食労務費!$F$5:$F$124)/$AA5,$AB5/$X5)) | AE5: =IF($S5="",0,IF($AA5>0,$AB5*SUMIF(⑳商品別1食労務費!$C$5:$C$124,$S5,⑳商品別1食労務費!$F$5:$F$124)/$AA5,$AB5/$X5)) | AF5: =IF($T5="",0,IF($AA5>0,$AB5*SUMIF(⑳商品別1食労務費!$C$5:$C$124,$T5,⑳商品別1食労務費!$F$5:$F$124)/$AA5,$AB5/$X5)) | AG5: =IF($U5="",0,IF($AA5>0,$AB5*SUMIF(⑳商品別1食労務費!$C$5:$C$124,$U5,⑳商品別1食労務費!$F$5:$F$124)/$AA5,$AB5/$X5)) | AH5: =IF($V5="",0,IF($AA5>0,$AB5*SUMIF(⑳商品別1食労務費!$C$5:$C$124,$V5,⑳商品別1食労務費!$F$5:$F$124)/$AA5,$AB5/$X5)) | AI5: =IF($W5="",0,IF($AA5>0,$AB5*SUMIF(⑳商品別1食労務費!$C$5:$C$124,$W5,⑳商品別1食労務費!$F$5:$F$124)/$AA5,$AB5/$X5))
A6: 2 | B6: スチコン | C6: 抹茶わらび餅(12分） | D6: 0.041666667 | E6: 0.097222222 | F6: 80 | G6: 30 | H6: 2 | I6: 60 | K6: =IF(F6>0,I6/(F6/60),0) | L6: =IF(AND(ISNUMBER(F6),J6>0),J6/(F6/60),"") | M6: =IF(OR(ISNUMBER(SEARCH("サニテーション",C6)),ISNUMBER(SEARCH("客注",C6)),ISNUMBER(SEARCH("切り替え",C6)),ISNUMBER(SEARCH("切替",C6)),NOT(ISNUMBER(H6))),"",IF(ISNUMBER(G6),G6/60*H6*④前提設定!$B$4,IF(AND(G6="",ISNUMBER(F6)),F6/60*H6*④前提設定!$B$4,""))) | N6: =IF(I6>0,M6/I6,"") | O6: =IF(AND(J6>0,ISNUMBER(M6)),M6/J6,"") | R6: お箸でつまんでわらび餅小 | S6: Ｓお箸でつまんでわらび餅小 | X6: =COUNTA(R6:W6) | Y6: =IF(AND($X6>0,ISNUMBER($M6)),$M6/$X6,"") | Z6: =IF($X6=0,"",IF(COUNTIF(⑳商品別1食労務費!$C$5:$C$124,$R6)+COUNTIF(⑳商品別1食労務費!$C$5:$C$124,$S6)+COUNTIF(⑳商品別1食労務費!$C$5:$C$124,$T6)+COUNTIF(⑳商品別1食労務費!$C$5:$C$124,$U6)+COUNTIF(⑳商品別1食労務費!$C$5:$C$124,$V6)+COUNTIF(⑳商品別1食労務費!$C$5:$C$124,$W6)=$X6,"OK","⑳に無い商品名")) | AA6: =SUMIF(⑳商品別1食労務費!$C$5:$C$124,$R6,⑳商品別1食労務費!$F$5:$F$124)+SUMIF(⑳商品別1食労務費!$C$5:$C$124,$S6,⑳商品別1食労務費!$F$5:$F$124)+SUMIF(⑳商品別1食労務費!$C$5:$C$124,$T6,⑳商品別1食労務費!$F$5:$F$124)+SUMIF(⑳商品別1食労務費!$C$5:$C$124,$U6,⑳商品別1食労務費!$F$5:$F$124)+SUMIF(⑳商品別1食労務費!$C$5:$C$124,$V6,⑳商品別1食労務費!$F$5:$F$124)+SUMIF(⑳商品別1食労務費!$C$5:$C$124,$W6,⑳商品別1食労務費!$F$5:$F$124) | AB6: =IF(ISNUMBER($M6),$M6,0) | AD6: =IF($R6="",0,IF($AA6>0,$AB6*SUMIF(⑳商品別1食労務費!$C$5:$C$124,$R6,⑳商品別1食労務費!$F$5:$F$124)/$AA6,$AB6/$X6)) | AE6: =IF($S6="",0,IF($AA6>0,$AB6*SUMIF(⑳商品別1食労務費!$C$5:$C$124,$S6,⑳商品別1食労務費!$F$5:$F$124)/$AA6,$AB6/$X6)) | AF6: =IF($T6="",0,IF($AA6>0,$AB6*SUMIF(⑳商品別1食労務費!$C$5:$C$124,$T6,⑳商品別1食労務費!$F$5:$F$124)/$AA6,$AB6/$X6)) | AG6: =IF($U6="",0,IF($AA6>0,$AB6*SUMIF(⑳商品別1食労務費!$C$5:$C$124,$U6,⑳商品別1食労務費!$F$5:$F$124)/$AA6,$AB6/$X6)) | AH6: =IF($V6="",0,IF($AA6>0,$AB6*SUMIF(⑳商品別1食労務費!$C$5:$C$124,$V6,⑳商品別1食労務費!$F$5:$F$124)/$AA6,$AB6/$X6)) | AI6: =IF($W6="",0,IF($AA6>0,$AB6*SUMIF(⑳商品別1食労務費!$C$5:$C$124,$W6,⑳商品別1食労務費!$F$5:$F$124)/$AA6,$AB6/$X6))
A7: 3 | B7: スチコン | C7: 抹茶わらび餅(1２分） | H7: 2 | K7: =IF(F7>0,I7/(F7/60),0) | L7: =IF(AND(ISNUMBER(F7),J7>0),J7/(F7/60),"") | M7: =IF(OR(ISNUMBER(SEARCH("サニテーション",C7)),ISNUMBER(SEARCH("客注",C7)),ISNUMBER(SEARCH("切り替え",C7)),ISNUMBER(SEARCH("切替",C7)),NOT(ISNUMBER(H7))),"",IF(ISNUMBER(G7),G7/60*H7*④前提設定!$B$4,IF(AND(G7="",ISNUMBER(F7)),F7/60*H7*④前提設定!$B$4,""))) | N7: =IF(I7>0,M7/I7,"") | O7: =IF(AND(J7>0,ISNUMBER(M7)),M7/J7,"") | R7: お箸でつまんでわらび餅小 | S7: Ｓお箸でつまんでわらび餅小 | X7: =COUNTA(R7:W7) | Y7: =IF(AND($X7>0,ISNUMBER($M7)),$M7/$X7,"") | Z7: =IF($X7=0,"",IF(COUNTIF(⑳商品別1食労務費!$C$5:$C$124,$R7)+COUNTIF(⑳商品別1食労務費!$C$5:$C$124,$S7)+COUNTIF(⑳商品別1食労務費!$C$5:$C$124,$T7)+COUNTIF(⑳商品別1食労務費!$C$5:$C$124,$U7)+COUNTIF(⑳商品別1食労務費!$C$5:$C$124,$V7)+COUNTIF(⑳商品別1食労務費!$C$5:$C$124,$W7)=$X7,"OK","⑳に無い商品名")) | AA7: =SUMIF(⑳商品別1食労務費!$C$5:$C$124,$R7,⑳商品別1食労務費!$F$5:$F$124)+SUMIF(⑳商品別1食労務費!$C$5:$C$124,$S7,⑳商品別1食労務費!$F$5:$F$124)+SUMIF(⑳商品別1食労務費!$C$5:$C$124,$T7,⑳商品別1食労務費!$F$5:$F$124)+SUMIF(⑳商品別1食労務費!$C$5:$C$124,$U7,⑳商品別1食労務費!$F$5:$F$124)+SUMIF(⑳商品別1食労務費!$C$5:$C$124,$V7,⑳商品別1食労務費!$F$5:$F$124)+SUMIF(⑳商品別1食労務費!$C$5:$C$124,$W7,⑳商品別1食労務費!$F$5:$F$124) | AB7: =IF(ISNUMBER($M7),$M7,0) | AD7: =IF($R7="",0,IF($AA7>0,$AB7*SUMIF(⑳商品別1食労務費!$C$5:$C$124,$R7,⑳商品別1食労務費!$F$5:$F$124)/$AA7,$AB7/$X7)) | AE7: =IF($S7="",0,IF($AA7>0,$AB7*SUMIF(⑳商品別1食労務費!$C$5:$C$124,$S7,⑳商品別1食労務費!$F$5:$F$124)/$AA7,$AB7/$X7)) | AF7: =IF($T7="",0,IF($AA7>0,$AB7*SUMIF(⑳商品別1食労務費!$C$5:$C$124,$T7,⑳商品別1食労務費!$F$5:$F$124)/$AA7,$AB7/$X7)) | AG7: =IF($U7="",0,IF($AA7>0,$AB7*SUMIF(⑳商品別1食労務費!$C$5:$C$124,$U7,⑳商品別1食労務費!$F$5:$F$124)/$AA7,$AB7/$X7)) | AH7: =IF($V7="",0,IF($AA7>0,$AB7*SUMIF(⑳商品別1食労務費!$C$5:$C$124,$V7,⑳商品別1食労務費!$F$5:$F$124)/$AA7,$AB7/$X7)) | AI7: =IF($W7="",0,IF($AA7>0,$AB7*SUMIF(⑳商品別1食労務費!$C$5:$C$124,$W7,⑳商品別1食労務費!$F$5:$F$124)/$AA7,$AB7/$X7))
A8: 4 | B8: スチコン | C8: わらび餅（１２分） | D8: 0.11111111 | E8: 0.20347222 | F8: 133 | G8: 55 | H8: 2 | I8: 60 | K8: =IF(F8>0,I8/(F8/60),0) | L8: =IF(AND(ISNUMBER(F8),J8>0),J8/(F8/60),"") | M8: =IF(OR(ISNUMBER(SEARCH("サニテーション",C8)),ISNUMBER(SEARCH("客注",C8)),ISNUMBER(SEARCH("切り替え",C8)),ISNUMBER(SEARCH("切替",C8)),NOT(ISNUMBER(H8))),"",IF(ISNUMBER(G8),G8/60*H8*④前提設定!$B$4,IF(AND(G8="",ISNUMBER(F8)),F8/60*H8*④前提設定!$B$4,""))) | N8: =IF(I8>0,M8/I8,"") | O8: =IF(AND(J8>0,ISNUMBER(M8)),M8/J8,"") | R8: お箸でつまんでわらび餅小 | S8: Ｓお箸でつまんでわらび餅小 | X8: =COUNTA(R8:W8) | Y8: =IF(AND($X8>0,ISNUMBER($M8)),$M8/$X8,"") | Z8: =IF($X8=0,"",IF(COUNTIF(⑳商品別1食労務費!$C$5:$C$124,$R8)+COUNTIF(⑳商品別1食労務費!$C$5:$C$124,$S8)+COUNTIF(⑳商品別1食労務費!$C$5:$C$124,$T8)+COUNTIF(⑳商品別1食労務費!$C$5:$C$124,$U8)+COUNTIF(⑳商品別1食労務費!$C$5:$C$124,$V8)+COUNTIF(⑳商品別1食労務費!$C$5:$C$124,$W8)=$X8,"OK","⑳に無い商品名")) | AA8: =SUMIF(⑳商品別1食労務費!$C$5:$C$124,$R8,⑳商品別1食労務費!$F$5:$F$124)+SUMIF(⑳商品別1食労務費!$C$5:$C$124,$S8,⑳商品別1食労務費!$F$5:$F$124)+SUMIF(⑳商品別1食労務費!$C$5:$C$124,$T8,⑳商品別1食労務費!$F$5:$F$124)+SUMIF(⑳商品別1食労務費!$C$5:$C$124,$U8,⑳商品別1食労務費!$F$5:$F$124)+SUMIF(⑳商品別1食労務費!$C$5:$C$124,$V8,⑳商品別1食労務費!$F$5:$F$124)+SUMIF(⑳商品別1食労務費!$C$5:$C$124,$W8,⑳商品別1食労務費!$F$5:$F$124) | AB8: =IF(ISNUMBER($M8),$M8,0) | AD8: =IF($R8="",0,IF($AA8>0,$AB8*SUMIF(⑳商品別1食労務費!$C$5:$C$124,$R8,⑳商品別1食労務費!$F$5:$F$124)/$AA8,$AB8/$X8)) | AE8: =IF($S8="",0,IF($AA8>0,$AB8*SUMIF(⑳商品別1食労務費!$C$5:$C$124,$S8,⑳商品別1食労務費!$F$5:$F$124)/$AA8,$AB8/$X8)) | AF8: =IF($T8="",0,IF($AA8>0,$AB8*SUMIF(⑳商品別1食労務費!$C$5:$C$124,$T8,⑳商品別1食労務費!$F$5:$F$124)/$AA8,$AB8/$X8)) | AG8: =IF($U8="",0,IF($AA8>0,$AB8*SUMIF(⑳商品別1食労務費!$C$5:$C$124,$U8,⑳商品別1食労務費!$F$5:$F$124)/$AA8,$AB8/$X8)) | AH8: =IF($V8="",0,IF($AA8>0,$AB8*SUMIF(⑳商品別1食労務費!$C$5:$C$124,$V8,⑳商品別1食労務費!$F$5:$F$124)/$AA8,$AB8/$X8)) | AI8: =IF($W8="",0,IF($AA8>0,$AB8*SUMIF(⑳商品別1食労務費!$C$5:$C$124,$W8,⑳商品別1食労務費!$F$5:$F$124)/$AA8,$AB8/$X8))
A9: 5 | B9: スチコン | C9: わらび餅（１２分） | H9: 2 | K9: =IF(F9>0,I9/(F9/60),0) | L9: =IF(AND(ISNUMBER(F9),J9>0),J9/(F9/60),"") | M9: =IF(OR(ISNUMBER(SEARCH("サニテーション",C9)),ISNUMBER(SEARCH("客注",C9)),ISNUMBER(SEARCH("切り替え",C9)),ISNUMBER(SEARCH("切替",C9)),NOT(ISNUMBER(H9))),"",IF(ISNUMBER(G9),G9/60*H9*④前提設定!$B$4,IF(AND(G9="",ISNUMBER(F9)),F9/60*H9*④前提設定!$B$4,""))) | N9: =IF(I9>0,M9/I9,"") | O9: =IF(AND(J9>0,ISNUMBER(M9)),M9/J9,"") | R9: お箸でつまんでわらび餅小 | S9: Ｓお箸でつまんでわらび餅小 | X9: =COUNTA(R9:W9) | Y9: =IF(AND($X9>0,ISNUMBER($M9)),$M9/$X9,"") | Z9: =IF($X9=0,"",IF(COUNTIF(⑳商品別1食労務費!$C$5:$C$124,$R9)+COUNTIF(⑳商品別1食労務費!$C$5:$C$124,$S9)+COUNTIF(⑳商品別1食労務費!$C$5:$C$124,$T9)+COUNTIF(⑳商品別1食労務費!$C$5:$C$124,$U9)+COUNTIF(⑳商品別1食労務費!$C$5:$C$124,$V9)+COUNTIF(⑳商品別1食労務費!$C$5:$C$124,$W9)=$X9,"OK","⑳に無い商品名")) | AA9: =SUMIF(⑳商品別1食労務費!$C$5:$C$124,$R9,⑳商品別1食労務費!$F$5:$F$124)+SUMIF(⑳商品別1食労務費!$C$5:$C$124,$S9,⑳商品別1食労務費!$F$5:$F$124)+SUMIF(⑳商品別1食労務費!$C$5:$C$124,$T9,⑳商品別1食労務費!$F$5:$F$124)+SUMIF(⑳商品別1食労務費!$C$5:$C$124,$U9,⑳商品別1食労務費!$F$5:$F$124)+SUMIF(⑳商品別1食労務費!$C$5:$C$124,$V9,⑳商品別1食労務費!$F$5:$F$124)+SUMIF(⑳商品別1食労務費!$C$5:$C$124,$W9,⑳商品別1食労務費!$F$5:$F$124) | AB9: =IF(ISNUMBER($M9),$M9,0) | AD9: =IF($R9="",0,IF($AA9>0,$AB9*SUMIF(⑳商品別1食労務費!$C$5:$C$124,$R9,⑳商品別1食労務費!$F$5:$F$124)/$AA9,$AB9/$X9)) | AE9: =IF($S9="",0,IF($AA9>0,$AB9*SUMIF(⑳商品別1食労務費!$C$5:$C$124,$S9,⑳商品別1食労務費!$F$5:$F$124)/$AA9,$AB9/$X9)) | AF9: =IF($T9="",0,IF($AA9>0,$AB9*SUMIF(⑳商品別1食労務費!$C$5:$C$124,$T9,⑳商品別1食労務費!$F$5:$F$124)/$AA9,$AB9/$X9)) | AG9: =IF($U9="",0,IF($AA9>0,$AB9*SUMIF(⑳商品別1食労務費!$C$5:$C$124,$U9,⑳商品別1食労務費!$F$5:$F$124)/$AA9,$AB9/$X9)) | AH9: =IF($V9="",0,IF($AA9>0,$AB9*SUMIF(⑳商品別1食労務費!$C$5:$C$124,$V9,⑳商品別1食労務費!$F$5:$F$124)/$AA9,$AB9/$X9)) | AI9: =IF($W9="",0,IF($AA9>0,$AB9*SUMIF(⑳商品別1食労務費!$C$5:$C$124,$W9,⑳商品別1食労務費!$F$5:$F$124)/$AA9,$AB9/$X9))
